rtl/top_level.sv


module top_level (
    input  logic       clk,

    // Channel A
    input  logic       rst_A,
    input  logic       valid_in_A,
    input  logic [7:0] a_A,
    input  logic [7:0] b_A,
    output logic [8:0] sum_async_A,
    output logic [8:0] sum_sync_A,

    // Channel B
    input  logic       rst_B,
    input  logic       valid_in_B,
    input  logic [7:0] a_B,
    input  logic [7:0] b_B,
    output logic [8:0] sum_async_B,
    output logic [8:0] sum_sync_B
);

    // Channel A synchronous accumulator
    always_ff @(posedge clk) begin
        if (rst_A)
            sum_sync_A <= '0;
        else if (valid_in_A)
            sum_sync_A <= sum_sync_A + b_A;
    end

    assign sum_async_A = a_A + b_A;

    // Channel B synchronous accumulator
    always_ff @(posedge clk) begin
        if (rst_B)
            sum_sync_B <= '0;
        else if (valid_in_B)
            sum_sync_B <= sum_sync_B + b_B;
    end

    assign sum_async_B = a_B + b_B;

    initial begin
        $display("Time | rst_A| valid_in_A | a_A | b_A |sum_async_A | sum_sync_A |rst_B | valid_in_B| a_B | b_B  | sum_async_B | sum_sync_B   ");
        $monitor("%4t  |  %b  |  %b        | %0d | %0d |    %0d     |   %0d      | %b   |    %b     | %0d | %0d  |    %0d      |   %0d ",
                 $time, rst_A, valid_in_A, a_A, b_A, sum_async_A,sum_sync_A, rst_B, valid_in_B, a_B, b_B, sum_async_B, sum_sync_B);
    end

    initial begin
        $dumpfile("dump.vcd");
        $dumpvars(1, top_level.sv);
    end

endmodule

rtl/dut_wrapper.sv
module dut_wrapper (
    input  logic       clk,

    // Channel A – cocotb drives these
    input  logic       rst_A,
    input  logic       valid_in_A,
    input  logic [7:0] a_A,
    input  logic [7:0] b_A,

    // DUT drives these
    output logic [8:0] sum_async_A,
    output logic [8:0] sum_sync_A,

    // Channel B (if needed)
    input  logic       rst_B,
    input  logic       valid_in_B,
    input  logic [7:0] a_B,
    input  logic [7:0] b_B,
    output logic [8:0] sum_async_B,
    output logic [8:0] sum_sync_B
);

    top_level u_top_level (
        .clk(clk),

        // Channel A
        .rst_A(rst_A),
        .valid_in_A(valid_in_A),
        .a_A(a_A),
        .b_A(b_A),
        .sum_async_A(sum_async_A),
        .sum_sync_A(sum_sync_A),

        // Channel B
        .rst_B(rst_B),
        .valid_in_B(valid_in_B),
        .a_B(a_B),
        .b_B(b_B),
        .sum_async_B(sum_async_B),
        .sum_sync_B(sum_sync_B)
    );

endmodule



// module dut_wrapper (
//     input  logic       clk,

//     // Channel A – exposed directly for cocotb
//     output logic       rst_A,
//     output logic       valid_in_A,
//     output logic [7:0] a_A,
//     output logic [7:0] b_A,
//     output logic [8:0] sum_async_A,
//     output logic [8:0] sum_sync_A,

//     // Channel B – exposed directly for cocotb
//     output logic       rst_B,
//     output logic       valid_in_B,
//     output logic [7:0] a_B,
//     output logic [7:0] b_B,
//     output logic [8:0] sum_async_B,
//     output logic [8:0] sum_sync_B
// );

//     // Internal wires driven by cocotb (use these as DUT inputs)
//     logic rst_A_int;
//     logic valid_in_A_int;
//     logic [7:0] a_A_int;
//     logic [7:0] b_A_int;

//     logic rst_B_int;
//     logic valid_in_B_int;
//     logic [7:0] a_B_int;
//     logic [7:0] b_B_int;

//     // Connect exposed ports to internal wires so cocotb can drive them
//     assign rst_A       = rst_A_int;
//     assign valid_in_A  = valid_in_A_int;
//     assign a_A         = a_A_int;
//     assign b_A         = b_A_int;

//     assign rst_B       = rst_B_int;
//     assign valid_in_B  = valid_in_B_int;
//     assign a_B         = a_B_int;
//     assign b_B         = b_B_int;

//     // DUT instance
//     top_level u_top_level (
//         .clk          (clk),

//         // Channel A
//         .rst_A        (rst_A_int),
//         .valid_in_A   (valid_in_A_int),
//         .a_A          (a_A_int),
//         .b_A          (b_A_int),
//         .sum_async_A  (sum_async_A),
//         .sum_sync_A   (sum_sync_A),

//         // Channel B
//         .rst_B        (rst_B_int),
//         .valid_in_B   (valid_in_B_int),
//         .a_B          (a_B_int),
//         .b_B          (b_B_int),
//         .sum_async_B  (sum_async_B),
//         .sum_sync_B   (sum_sync_B)
//     );

// endmodule

regression_results/waves_3.vcd
$version Generated by VerilatedVcd $end
$timescale 1ps $end
 $scope module $rootio $end
  $var wire 1 # clk $end
  $var wire 1 $ rst_A $end
  $var wire 1 % valid_in_A $end
  $var wire 8 & a_A [7:0] $end
  $var wire 8 ' b_A [7:0] $end
  $var wire 9 ( sum_async_A [8:0] $end
  $var wire 9 ) sum_sync_A [8:0] $end
  $var wire 1 * rst_B $end
  $var wire 1 + valid_in_B $end
  $var wire 8 , a_B [7:0] $end
  $var wire 8 - b_B [7:0] $end
  $var wire 9 . sum_async_B [8:0] $end
  $var wire 9 / sum_sync_B [8:0] $end
 $upscope $end
 $scope module dut_wrapper $end
  $var wire 1 0 clk $end
  $var wire 1 1 rst_A $end
  $var wire 1 2 valid_in_A $end
  $var wire 8 3 a_A [7:0] $end
  $var wire 8 4 b_A [7:0] $end
  $var wire 9 5 sum_async_A [8:0] $end
  $var wire 9 6 sum_sync_A [8:0] $end
  $var wire 1 7 rst_B $end
  $var wire 1 8 valid_in_B $end
  $var wire 8 9 a_B [7:0] $end
  $var wire 8 : b_B [7:0] $end
  $var wire 9 ; sum_async_B [8:0] $end
  $var wire 9 < sum_sync_B [8:0] $end
  $scope module u_top_level $end
   $var wire 1 = clk $end
   $var wire 1 > rst_A $end
   $var wire 1 ? valid_in_A $end
   $var wire 8 @ a_A [7:0] $end
   $var wire 8 A b_A [7:0] $end
   $var wire 9 B sum_async_A [8:0] $end
   $var wire 9 C sum_sync_A [8:0] $end
   $var wire 1 D rst_B $end
   $var wire 1 E valid_in_B $end
   $var wire 8 F a_B [7:0] $end
   $var wire 8 G b_B [7:0] $end
   $var wire 9 H sum_async_B [8:0] $end
   $var wire 9 I sum_sync_B [8:0] $end
  $upscope $end
 $upscope $end
$enddefinitions $end


#0
1#
1$
0%
b00000000 &
b00000000 '
b000000000 (
b000000000 )
1*
0+
b00000000 ,
b00000000 -
b000000000 .
b000000000 /
10
11
02
b00000000 3
b00000000 4
b000000000 5
b000000000 6
17
08
b00000000 9
b00000000 :
b000000000 ;
b000000000 <
1=
1>
0?
b00000000 @
b00000000 A
b000000000 B
b000000000 C
1D
0E
b00000000 F
b00000000 G
b000000000 H
b000000000 I
#5000
0#
00
0=
#10000
1#
10
1=
#15000
0#
00
0=
#20000
1#
0$
1%
b11111111 &
b011111111 (
0*
10
01
12
b11111111 3
b011111111 5
07
1=
0>
1?
b11111111 @
b011111111 B
0D
#25000
0#
00
0=
#30000
1#
10
1=
#31000
b11111111 '
b111111110 (
b11111111 4
b111111110 5
b11111111 A
b111111110 B
#35000
0#
00
0=
#40000
1#
b011111111 )
10
b011111111 6
1=
b011111111 C
#41000
1$
b00000000 &
b00000000 '
b000000000 (
11
b00000000 3
b00000000 4
b000000000 5
1>
b00000000 @
b00000000 A
b000000000 B
#45000
0#
00
0=
#50000
1#
b000000000 )
10
b000000000 6
1=
b000000000 C
#51000
b00000001 &
b00000001 '
b000000010 (
b00000001 3
b00000001 4
b000000010 5
b00000001 @
b00000001 A
b000000010 B
#55000
0#
00
0=
#60000
1#
10
1=
#61000
0$
b11111111 &
b100000000 (
01
b11111111 3
b100000000 5
0>
b11111111 @
b100000000 B
#65000
0#
00
0=
#70000
1#
b000000001 )
10
b000000001 6
1=
b000000001 C
#71000
b11001000 &
b01100100 '
b100101100 (
b11001000 3
b01100100 4
b100101100 5
b11001000 @
b01100100 A
b100101100 B
#75000
0#
00
0=
#80000
1#
b001100101 )
10
b001100101 6
1=
b001100101 C
#81000
b10000000 &
b11001000 '
b101001000 (
b10000000 3
b11001000 4
b101001000 5
b10000000 @
b11001000 A
b101001000 B
#85000
0#
00
0=
#90000
1#
b100101101 )
10
b100101101 6
1=
b100101101 C
#91000
b11111111 &
b11111111 '
b111111110 (
b11111111 3
b11111111 4
b111111110 5
b11111111 @
b11111111 A
b111111110 B
#95000
0#
00
0=
#100000
1#
b000101100 )
10
b000101100 6
1=
b000101100 C
#101000
0%
b00000000 &
b00000000 '
b000000000 (
02
b00000000 3
b00000000 4
b000000000 5
0?
b00000000 @
b00000000 A
b000000000 B
#105000
0#
00
0=
#110000
1#
10
1=
#111000
1%
b11111111 &
b011111111 (
12
b11111111 3
b011111111 5
1?
b11111111 @
b011111111 B
#115000
0#
00
0=
#120000
1#
10
1=
#121000
0%
b00000000 &
b000000000 (
02
b00000000 3
b000000000 5
0?
b00000000 @
b000000000 B
#125000
0#
00
0=
#130000
1#
10
1=
#131000
1%
b11111111 &
b11111111 '
b111111110 (
12
b11111111 3
b11111111 4
b111111110 5
1?
b11111111 @
b11111111 A
b111111110 B
#135000
0#
00
0=
#140000
1#
b100101011 )
10
b100101011 6
1=
b100101011 C
#141000
b01000010 &
b01000000 '
b010000010 (
b01000010 3
b01000000 4
b010000010 5
b01000010 @
b01000000 A
b010000010 B
#145000
0#
00
0=
#150000
1#
b101101011 )
10
b101101011 6
1=
b101101011 C
#151000
0%
1+
b11100110 ,
b01100010 -
b101001000 .
02
18
b11100110 9
b01100010 :
b101001000 ;
0?
1E
b11100110 F
b01100010 G
b101001000 H
#155000
0#
00
0=
#160000
1#
b001100010 /
10
b001100010 <
1=
b001100010 I
#161000
0+
08
0E
#162000
1%
b00001010 &
b01011001 '
b001100011 (
12
b00001010 3
b01011001 4
b001100011 5
1?
b00001010 @
b01011001 A
b001100011 B
#165000
0#
00
0=
#170000
1#
b111000100 )
10
b111000100 6
1=
b111000100 C
#171000
0%
1+
b00000001 ,
b00011001 -
b000011010 .
02
18
b00000001 9
b00011001 :
b000011010 ;
0?
1E
b00000001 F
b00011001 G
b000011010 H
#175000
0#
00
0=
#180000
1#
b001111011 /
10
b001111011 <
1=
b001111011 I
#181000
0+
08
0E
#182000
1%
b10011100 &
b01011111 '
b011111011 (
12
b10011100 3
b01011111 4
b011111011 5
1?
b10011100 @
b01011111 A
b011111011 B
#185000
0#
00
0=
#190000
1#
b000100011 )
10
b000100011 6
1=
b000100011 C
#191000
0%
1+
b01001001 ,
b00101011 -
b001110100 .
02
18
b01001001 9
b00101011 :
b001110100 ;
0?
1E
b01001001 F
b00101011 G
b001110100 H
#195000
0#
00
0=
#200000
1#
b010100110 /
10
b010100110 <
1=
b010100110 I
#201000
0+
08
0E
#202000
1%
b00101001 &
b11100011 '
b100001100 (
12
b00101001 3
b11100011 4
b100001100 5
1?
b00101001 @
b11100011 A
b100001100 B
#205000
0#
00
0=
#210000
1#
b100000110 )
10
b100000110 6
1=
b100000110 C
#211000
0%
1+
b10100110 ,
b00000010 -
b010101000 .
02
18
b10100110 9
b00000010 :
b010101000 ;
0?
1E
b10100110 F
b00000010 G
b010101000 H
#215000
0#
00
0=
#220000
1#
b010101000 /
10
b010101000 <
1=
b010101000 I
#221000
0+
08
0E
#222000
1%
b00010100 &
b01000001 '
b001010101 (
12
b00010100 3
b01000001 4
b001010101 5
1?
b00010100 @
b01000001 A
b001010101 B
#225000
0#
00
0=
#230000
1#
b101000111 )
10
b101000111 6
1=
b101000111 C
#231000
0%
1+
b10101001 ,
b00101110 -
b011010111 .
02
18
b10101001 9
b00101110 :
b011010111 ;
0?
1E
b10101001 F
b00101110 G
b011010111 H
#235000
0#
00
0=
#240000
1#
b011010110 /
10
b011010110 <
1=
b011010110 I
#241000
0+
08
0E
#242000
1%
b00100000 &
b11001010 '
b011101010 (
12
b00100000 3
b11001010 4
b011101010 5
1?
b00100000 @
b11001010 A
b011101010 B
#245000
0#
00
0=
#250000
1#
b000010001 )
10
b000010001 6
1=
b000010001 C
#251000
0%
1+
b00010101 ,
b10000000 -
b010010101 .
02
18
b00010101 9
b10000000 :
b010010101 ;
0?
1E
b00010101 F
b10000000 G
b010010101 H
#255000
0#
00
0=
#260000
1#
b101010110 /
10
b101010110 <
1=
b101010110 I
#261000
0+
08
0E
#262000
1%
b11111000 &
b10010010 '
b110001010 (
12
b11111000 3
b10010010 4
b110001010 5
1?
b11111000 @
b10010010 A
b110001010 B
#265000
0#
00
0=
#270000
1#
b010100011 )
10
b010100011 6
1=
b010100011 C
#271000
0%
1+
b01000111 ,
b00011100 -
b001100011 .
02
18
b01000111 9
b00011100 :
b001100011 ;
0?
1E
b01000111 F
b00011100 G
b001100011 H
#275000
0#
00
0=
#280000
1#
b101110010 /
10
b101110010 <
1=
b101110010 I
#281000
0+
08
0E
#282000
1%
b01011110 &
b11001100 '
b100101010 (
12
b01011110 3
b11001100 4
b100101010 5
1?
b01011110 @
b11001100 A
b100101010 B
#285000
0#
00
0=
#290000
1#
b101101111 )
10
b101101111 6
1=
b101101111 C
#291000
0%
1+
b10110100 ,
b11011110 -
b110010010 .
02
18
b10110100 9
b11011110 :
b110010010 ;
0?
1E
b10110100 F
b11011110 G
b110010010 H
#295000
0#
00
0=
#300000
1#
b001010000 /
10
b001010000 <
1=
b001010000 I
#301000
0+
08
0E
#302000
1%
b11111111 &
b01000001 '
b101000000 (
12
b11111111 3
b01000001 4
b101000000 5
1?
b11111111 @
b01000001 A
b101000000 B
#305000
0#
00
0=
#310000
1#
b110110000 )
10
b110110000 6
1=
b110110000 C
#311000
0%
1+
b10010010 ,
b00000111 -
b010011001 .
02
18
b10010010 9
b00000111 :
b010011001 ;
0?
1E
b10010010 F
b00000111 G
b010011001 H
#315000
0#
00
0=
#320000
1#
b001010111 /
10
b001010111 <
1=
b001010111 I
#321000
0+
08
0E
#322000
1%
b01100000 &
b10001111 '
b011101111 (
12
b01100000 3
b10001111 4
b011101111 5
1?
b01100000 @
b10001111 A
b011101111 B
#325000
0#
00
0=
#330000
1#
b000111111 )
10
b000111111 6
1=
b000111111 C
#331000
0%
1+
b00001101 ,
b10101100 -
b010111001 .
02
18
b00001101 9
b10101100 :
b010111001 ;
0?
1E
b00001101 F
b10101100 G
b010111001 H
#335000
0#
00
0=
#340000
1#
b100000011 /
10
b100000011 <
1=
b100000011 I
#341000
0+
08
0E
