rtl/top_level.sv


module top_level (
    input  logic       clk,

    // Channel A
    input  logic       rst_A,
    input  logic       valid_in_A,
    input  logic [7:0] a_A,
    input  logic [7:0] b_A,
    output logic [8:0] sum_async_A,
    output logic [8:0] sum_sync_A,

    // Channel B
    input  logic       rst_B,
    input  logic       valid_in_B,
    input  logic [7:0] a_B,
    input  logic [7:0] b_B,
    output logic [8:0] sum_async_B,
    output logic [8:0] sum_sync_B
);

    // Channel A synchronous accumulator
    always_ff @(posedge clk) begin
        if (rst_A)
            sum_sync_A <= '0;
        else if (valid_in_A)
            sum_sync_A <= sum_sync_A + b_A;
    end

    assign sum_async_A = a_A + b_A;

    // Channel B synchronous accumulator
    always_ff @(posedge clk) begin
        if (rst_B)
            sum_sync_B <= '0;
        else if (valid_in_B)
            sum_sync_B <= sum_sync_B + b_B;
    end

    assign sum_async_B = a_B + b_B;

    initial begin
        $display("Time | rst_A| valid_in_A | a_A | b_A |sum_async_A | sum_sync_A |rst_B | valid_in_B| a_B | b_B  | sum_async_B | sum_sync_B   ");
        $monitor("%4t  |  %b  |  %b        | %0d | %0d |    %0d     |   %0d      | %b   |    %b     | %0d | %0d  |    %0d      |   %0d ",
                 $time, rst_A, valid_in_A, a_A, b_A, sum_async_A,sum_sync_A, rst_B, valid_in_B, a_B, b_B, sum_async_B, sum_sync_B);
    end

    initial begin
        $dumpfile("dump.vcd");
        $dumpvars(1, top_level.sv);
    end

endmodule

rtl/dut_wrapper.sv
module dut_wrapper (
    input  logic       clk,

    // Channel A – cocotb drives these
    input  logic       rst_A,
    input  logic       valid_in_A,
    input  logic [7:0] a_A,
    input  logic [7:0] b_A,

    // DUT drives these
    output logic [8:0] sum_async_A,
    output logic [8:0] sum_sync_A,

    // Channel B (if needed)
    input  logic       rst_B,
    input  logic       valid_in_B,
    input  logic [7:0] a_B,
    input  logic [7:0] b_B,
    output logic [8:0] sum_async_B,
    output logic [8:0] sum_sync_B
);

    top_level u_top_level (
        .clk(clk),

        // Channel A
        .rst_A(rst_A),
        .valid_in_A(valid_in_A),
        .a_A(a_A),
        .b_A(b_A),
        .sum_async_A(sum_async_A),
        .sum_sync_A(sum_sync_A),

        // Channel B
        .rst_B(rst_B),
        .valid_in_B(valid_in_B),
        .a_B(a_B),
        .b_B(b_B),
        .sum_async_B(sum_async_B),
        .sum_sync_B(sum_sync_B)
    );

endmodule



// module dut_wrapper (
//     input  logic       clk,

//     // Channel A – exposed directly for cocotb
//     output logic       rst_A,
//     output logic       valid_in_A,
//     output logic [7:0] a_A,
//     output logic [7:0] b_A,
//     output logic [8:0] sum_async_A,
//     output logic [8:0] sum_sync_A,

//     // Channel B – exposed directly for cocotb
//     output logic       rst_B,
//     output logic       valid_in_B,
//     output logic [7:0] a_B,
//     output logic [7:0] b_B,
//     output logic [8:0] sum_async_B,
//     output logic [8:0] sum_sync_B
// );

//     // Internal wires driven by cocotb (use these as DUT inputs)
//     logic rst_A_int;
//     logic valid_in_A_int;
//     logic [7:0] a_A_int;
//     logic [7:0] b_A_int;

//     logic rst_B_int;
//     logic valid_in_B_int;
//     logic [7:0] a_B_int;
//     logic [7:0] b_B_int;

//     // Connect exposed ports to internal wires so cocotb can drive them
//     assign rst_A       = rst_A_int;
//     assign valid_in_A  = valid_in_A_int;
//     assign a_A         = a_A_int;
//     assign b_A         = b_A_int;

//     assign rst_B       = rst_B_int;
//     assign valid_in_B  = valid_in_B_int;
//     assign a_B         = a_B_int;
//     assign b_B         = b_B_int;

//     // DUT instance
//     top_level u_top_level (
//         .clk          (clk),

//         // Channel A
//         .rst_A        (rst_A_int),
//         .valid_in_A   (valid_in_A_int),
//         .a_A          (a_A_int),
//         .b_A          (b_A_int),
//         .sum_async_A  (sum_async_A),
//         .sum_sync_A   (sum_sync_A),

//         // Channel B
//         .rst_B        (rst_B_int),
//         .valid_in_B   (valid_in_B_int),
//         .a_B          (a_B_int),
//         .b_B          (b_B_int),
//         .sum_async_B  (sum_async_B),
//         .sum_sync_B   (sum_sync_B)
//     );

// endmodule

regression_results/waves_8.vcd
$version Generated by VerilatedVcd $end
$timescale 1ps $end
 $scope module $rootio $end
  $var wire 1 # clk $end
  $var wire 1 $ rst_A $end
  $var wire 1 % valid_in_A $end
  $var wire 8 & a_A [7:0] $end
  $var wire 8 ' b_A [7:0] $end
  $var wire 9 ( sum_async_A [8:0] $end
  $var wire 9 ) sum_sync_A [8:0] $end
  $var wire 1 * rst_B $end
  $var wire 1 + valid_in_B $end
  $var wire 8 , a_B [7:0] $end
  $var wire 8 - b_B [7:0] $end
  $var wire 9 . sum_async_B [8:0] $end
  $var wire 9 / sum_sync_B [8:0] $end
 $upscope $end
 $scope module dut_wrapper $end
  $var wire 1 0 clk $end
  $var wire 1 1 rst_A $end
  $var wire 1 2 valid_in_A $end
  $var wire 8 3 a_A [7:0] $end
  $var wire 8 4 b_A [7:0] $end
  $var wire 9 5 sum_async_A [8:0] $end
  $var wire 9 6 sum_sync_A [8:0] $end
  $var wire 1 7 rst_B $end
  $var wire 1 8 valid_in_B $end
  $var wire 8 9 a_B [7:0] $end
  $var wire 8 : b_B [7:0] $end
  $var wire 9 ; sum_async_B [8:0] $end
  $var wire 9 < sum_sync_B [8:0] $end
  $scope module u_top_level $end
   $var wire 1 = clk $end
   $var wire 1 > rst_A $end
   $var wire 1 ? valid_in_A $end
   $var wire 8 @ a_A [7:0] $end
   $var wire 8 A b_A [7:0] $end
   $var wire 9 B sum_async_A [8:0] $end
   $var wire 9 C sum_sync_A [8:0] $end
   $var wire 1 D rst_B $end
   $var wire 1 E valid_in_B $end
   $var wire 8 F a_B [7:0] $end
   $var wire 8 G b_B [7:0] $end
   $var wire 9 H sum_async_B [8:0] $end
   $var wire 9 I sum_sync_B [8:0] $end
  $upscope $end
 $upscope $end
$enddefinitions $end


#0
1#
1$
0%
b00000000 &
b00000000 '
b000000000 (
b000000000 )
1*
0+
b00000000 ,
b00000000 -
b000000000 .
b000000000 /
10
11
02
b00000000 3
b00000000 4
b000000000 5
b000000000 6
17
08
b00000000 9
b00000000 :
b000000000 ;
b000000000 <
1=
1>
0?
b00000000 @
b00000000 A
b000000000 B
b000000000 C
1D
0E
b00000000 F
b00000000 G
b000000000 H
b000000000 I
#10021000
0
0=
#10000
1#
10
1=
#15000
0#
00
0=
#20000
1#
0$
1%
b00100001 &
b11001110 '
b011101111 (
0*
10
01
12
b00100001 3
b11001110 4
b011101111 5
07
1=
0>
1?
b00100001 @
b11001110 A
b011101111 B
0D
#25000
0#
00
0=
#30000
1#
b011001110 )
10
b011001110 6
1=
b011001110 C
#31000
0%
1+
b01010101 ,
b00100110 -
b001111011 .
02
18
b01010101 9
b00100110 :
b001111011 ;
0?
1E
b01010101 F
b00100110 G
b001111011 H
#35000
0#
00
0=
#40000
1#
b000100110 /
10
b000100110 <
1=
b000100110 I
#41000
0+
08
0E
#42000
1%
b00110010 &
b11010011 '
b100000101 (
12
b00110010 3
b11010011 4
b100000101 5
1?
b00110010 @
b11010011 A
b100000101 B
#45000
0#
00
0=
#50000
1#
b110100001 )
10
b110100001 6
1=
b110100001 C
#51000
0%
1+
b11011101 ,
b00111001 -
b100010110 .
02
18
b11011101 9
b00111001 :
b100010110 ;
0?
1E
b11011101 F
b00111001 G
b100010110 H
#55000
0#
00
0=
#60000
1#
b001011111 /
10
b001011111 <
1=
b001011111 I
#61000
0+
08
0E
#62000
1%
b01110110 &
b10011111 '
b100010101 (
12
b01110110 3
b10011111 4
b100010101 5
1?
b01110110 @
b10011111 A
b100010101 B
#65000
0#
00
0=
#70000
1#
b001000000 )
10
b001000000 6
1=
b001000000 C
#71000
0%
1+
b01010010 ,
b01011111 -
b010110001 .
02
18
b01010010 9
b01011111 :
b010110001 ;
0?
1E
b01010010 F
b01011111 G
b010110001 H
#75000
0#
00
0=
#80000
1#
b010111110 /
10
b010111110 <
1=
b010111110 I
#81000
0+
08
0E
#82000
1%
b10001110 &
b00101100 '
b010111010 (
12
b10001110 3
b00101100 4
b010111010 5
1?
b10001110 @
b00101100 A
b010111010 B
#85000
0#
00
0=
#90000
1#
b001101100 )
10
b001101100 6
1=
b001101100 C
#91000
0%
1+
b01011010 ,
b01010111 -
02
18
b01011010 9
b01010111 :
0?
1E
b01011010 F
b01010111 G
#95000
0#
00
0=
#100000
1#
b100010101 /
10
b100010101 <
1=
b100010101 I
#101000
0+
08
0E
#102000
1%
b11100101 &
b10100101 '
b110001010 (
12
b11100101 3
b10100101 4
b110001010 5
1?
b11100101 @
b10100101 A
b110001010 B
#105000
0#
00
0=
#110000
1#
b100010001 )
10
b100010001 6
1=
b100010001 C
#111000
0%
1+
b01111011 ,
b11100010 -
b101011101 .
02
18
b01111011 9
b11100010 :
b101011101 ;
0?
1E
b01111011 F
b11100010 G
b101011101 H
#115000
0#
00
0=
#120000
1#
b111110111 /
10
b111110111 <
1=
b111110111 I
#121000
0+
08
0E
#122000
1%
b11000000 &
b00010111 '
b011010111 (
12
b11000000 3
b00010111 4
b011010111 5
1?
b11000000 @
b00010111 A
b011010111 B
#125000
0#
00
0=
#130000
1#
b100101000 )
10
b100101000 6
1=
b100101000 C
#131000
0%
1+
b11010111 ,
b10011101 -
b101110100 .
02
18
b11010111 9
b10011101 :
b101110100 ;
0?
1E
b11010111 F
b10011101 G
b101110100 H
#135000
0#
00
0=
#140000
1#
b010010100 /
10
b010010100 <
1=
b010010100 I
#141000
0+
08
0E
#142000
1%
b11100010 &
b10010011 '
b101110101 (
12
b11100010 3
b10010011 4
b101110101 5
1?
b11100010 @
b10010011 A
b101110101 B
#145000
0#
00
0=
#150000
1#
b110111011 )
10
b110111011 6
1=
b110111011 C
#151000
0%
1+
b10011000 ,
b00100100 -
b010111100 .
02
18
b10011000 9
b00100100 :
b010111100 ;
0?
1E
b10011000 F
b00100100 G
b010111100 H
#155000
0#
00
0=
#160000
1#
b010111000 /
10
b010111000 <
1=
b010111000 I
#161000
0+
08
0E
#162000
1%
b11101111 &
b00000100 '
b011110011 (
12
b11101111 3
b00000100 4
b011110011 5
1?
b11101111 @
b00000100 A
b011110011 B
#165000
0#
00
0=
#170000
1#
b110111111 )
10
b110111111 6
1=
b110111111 C
#171000
0%
1+
b01011011 ,
b01100111 -
b011000010 .
02
18
b01011011 9
b01100111 :
b011000010 ;
0?
1E
b01011011 F
b01100111 G
b011000010 H
#175000
0#
00
0=
#180000
1#
b100011111 /
10
b100011111 <
1=
b100011111 I
#181000
0+
08
0E
#182000
1%
b01011100 &
b00000011 '
b001011111 (
12
b01011100 3
b00000011 4
b001011111 5
1?
b01011100 @
b00000011 A
b001011111 B
#185000
0#
00
0=
#190000
1#
b111000010 )
10
b111000010 6
1=
b111000010 C
#191000
0%
1+
b00010011 ,
b00001000 -
b000011011 .
02
18
b00010011 9
b00001000 :
b000011011 ;
0?
1E
b00010011 F
b00001000 G
b000011011 H
#195000
0#
00
0=
#200000
1#
b100100111 /
10
b100100111 <
1=
b100100111 I
#201000
0+
08
0E
#202000
1%
b11110111 &
b00000110 '
b011111101 (
12
b11110111 3
b00000110 4
b011111101 5
1?
b11110111 @
b00000110 A
b011111101 B
#205000
0#
00
0=
#210000
1#
b111001000 )
10
b111001000 6
1=
b111001000 C
#211000
0%
1+
b01010010 ,
b01101101 -
b010111111 .
02
18
b01010010 9
b01101101 :
b010111111 ;
0?
1E
b01010010 F
b01101101 G
b010111111 H
#215000
0#
00
0=
#220000
1#
b110010100 /
10
b110010100 <
1=
b110010100 I
#221000
0+
08
0E
#222000
1%
b01001001 &
b01110010 '
b010111011 (
12
b01001001 3
b01110010 4
b010111011 5
1?
b01001001 @
b01110010 A
b010111011 B
#225000
0#
00
0=
#230000
1#
b000111010 )
10
b000111010 6
1=
b000111010 C
#231000
0%
1+
b01001111 ,
b10011000 -
b011100111 .
02
18
b01001111 9
b10011000 :
b011100111 ;
0?
1E
b01001111 F
b10011000 G
b011100111 H
#235000
0#
00
0=
#240000
1#
b000101100 /
10
b000101100 <
1=
b000101100 I
#241000
0+
08
0E
#242000
1%
b10100001 &
b00011010 '
12
b10100001 3
b00011010 4
1?
b10100001 @
b00011010 A
#245000
0#
00
0=
#250000
1#
b001010100 )
10
b001010100 6
1=
b001010100 C
#251000
0%
1+
b01011110 ,
b00100010 -
b010000000 .
02
18
b01011110 9
b00100010 :
b010000000 ;
0?
1E
b01011110 F
b00100010 G
b010000000 H
#255000
0#
00
0=
#260000
1#
b001001110 /
10
b001001110 <
1=
b001001110 I
#261000
0+
08
0E
#262000
1%
b01111101 &
b11001110 '
b101001011 (
12
b01111101 3
b11001110 4
b101001011 5
1?
b01111101 @
b11001110 A
b101001011 B
#265000
0#
00
0=
#270000
1#
b100100010 )
10
b100100010 6
1=
b100100010 C
#271000
0%
1+
b10110111 ,
b00001100 -
b011000011 .
02
18
b10110111 9
b00001100 :
b011000011 ;
0?
1E
b10110111 F
b00001100 G
b011000011 H
#275000
0#
00
0=
#280000
1#
b001011010 /
10
b001011010 <
1=
b001011010 I
#281000
0+
08
0E
#282000
1%
b00001001 &
b10100000 '
b010101001 (
12
b00001001 3
b10100000 4
b010101001 5
1?
b00001001 @
b10100000 A
b010101001 B
#285000
0#
00
0=
#290000
1#
b111000010 )
10
b111000010 6
1=
b111000010 C
#291000
0%
1+
b00010010 ,
b10001000 -
b010011010 .
02
18
b00010010 9
b10001000 :
b010011010 ;
0?
1E
b00010010 F
b10001000 G
b010011010 H
#295000
0#
00
0=
#300000
1#
b011100010 /
10
b011100010 <
1=
b011100010 I
#301000
0+
08
0E
#302000
1%
b10000100 &
b01100000 '
b011100100 (
12
b10000100 3
b01100000 4
b011100100 5
1?
b10000100 @
b01100000 A
b011100100 B
#305000
0#
00
0=
#310000
1#
b000100010 )
10
b000100010 6
1=
b000100010 C
#311000
0%
1+
b00111101 ,
b00010010 -
b001001111 .
02
18
b00111101 9
b00010010 :
b001001111 ;
0?
1E
b00111101 F
b00010010 G
b001001111 H
#315000
0#
00
0=
#320000
1#
b011110100 /
10
b011110100 <
1=
b011110100 I
#321000
0+
08
0E
#322000
1%
b01111110 &
b10100001 '
b100011111 (
12
b01111110 3
b10100001 4
b100011111 5
1?
b01111110 @
b10100001 A
b100011111 B
#325000
0#
00
0=
#330000
1#
b011000011 )
10
b011000011 6
1=
b011000011 C
#331000
0%
1+
b10010101 ,
b10011101 -
b100110010 .
02
18
b10010101 9
b10011101 :
b100110010 ;
0?
1E
b10010101 F
b10011101 G
b100110010 H
#335000
0#
00
0=
#340000
1#
b110010001 /
10
b110010001 <
1=
b110010001 I
#341000
0+
08
0E
#342000
1%
b10010011 &
b01101010 '
b011111101 (
12
b10010011 3
b01101010 4
b011111101 5
1?
b10010011 @
b01101010 A
b011111101 B
#345000
0#
00
0=
#350000
1#
b100101101 )
10
b100101101 6
1=
b100101101 C
#351000
0%
1+
b10011010 ,
b11010100 -
b101101110 .
02
18
b10011010 9
b11010100 :
b101101110 ;
0?
1E
b10011010 F
b11010100 G
b101101110 H
#355000
0#
00
0=
#360000
1#
b001100101 /
10
b001100101 <
1=
b001100101 I
#361000
0+
08
0E
#362000
1%
b01000010 &
b11010011 '
b100010101 (
12
b01000010 3
b11010011 4
b100010101 5
1?
b01000010 @
b11010011 A
b100010101 B
#365000
0#
00
0=
#370000
1#
b000000000 )
10
b000000000 6
1=
b000000000 C
#371000
0%
1+
b01010111 ,
b00111000 -
b010001111 .
02
18
b01010111 9
b00111000 :
b010001111 ;
0?
1E
b01010111 F
b00111000 G
b010001111 H
#375000
0#
00
0=
#380000
1#
b010011101 /
10
b010011101 <
1=
b010011101 I
#381000
0+
08
0E
#382000
1%
b10001001 &
b10011000 '
b100100001 (
12
b10001001 3
b10011000 4
b100100001 5
1?
b10001001 @
b10011000 A
b100100001 B
#385000
0#
00
0=
#390000
1#
b010011000 )
10
b010011000 6
1=
b010011000 C
#391000
0%
1+
b01111001 ,
b00000001 -
b001111010 .
02
18
b01111001 9
b00000001 :
b001111010 ;
0?
1E
b01111001 F
b00000001 G
b001111010 H
#395000
0#
00
0=
#400000
1#
b010011110 /
10
b010011110 <
1=
b010011110 I
#401000
0+
08
0E
#402000
1%
b01100110 &
b01000100 '
b010101010 (
12
b01100110 3
b01000100 4
b010101010 5
1?
b01100110 @
b01000100 A
b010101010 B
#405000
0#
00
0=
#410000
1#
b011011100 )
10
b011011100 6
1=
b011011100 C
#411000
0%
1+
b01101001 ,
b10000101 -
b011101110 .
02
18
b01101001 9
b10000101 :
b011101110 ;
0?
1E
b01101001 F
b10000101 G
b011101110 H
#415000
0#
00
0=
#420000
1#
b100100011 /
10
b100100011 <
1=
b100100011 I
#421000
0+
08
0E
#422000
1%
b00100101 &
b01000010 '
b001100111 (
12
b00100101 3
b01000010 4
b001100111 5
1?
b00100101 @
b01000010 A
b001100111 B
#425000
0#
00
0=
#430000
1#
b100011110 )
10
b100011110 6
1=
b100011110 C
#431000
0%
1+
b00001010 ,
b11110110 -
b100000000 .
02
18
b00001010 9
b11110110 :
b100000000 ;
0?
1E
b00001010 F
b11110110 G
b100000000 H
#435000
0#
00
0=
#440000
1#
b000011001 /
10
b000011001 <
1=
b000011001 I
#441000
0+
08
0E
#442000
1%
b10110000 &
b00011010 '
b011001010 (
12
b10110000 3
b00011010 4
b011001010 5
1?
b10110000 @
b00011010 A
b011001010 B
#445000
0#
00
0=
#450000
1#
b100111000 )
10
b100111000 6
1=
b100111000 C
#451000
0%
1+
b10110101 ,
b01100111 -
b100011100 .
02
18
b10110101 9
b01100111 :
b100011100 ;
0?
1E
b10110101 F
b01100111 G
b100011100 H
#455000
0#
00
0=
#460000
1#
b010000000 /
10
b010000000 <
1=
b010000000 I
#461000
0+
08
0E
#462000
1%
b01110111 &
b10001100 '
b100000011 (
12
b01110111 3
b10001100 4
b100000011 5
1?
b01110111 @
b10001100 A
b100000011 B
#465000
0#
00
0=
#470000
1#
b111000100 )
10
b111000100 6
1=
b111000100 C
#471000
0%
1+
b00011110 ,
b01101011 -
b010001001 .
02
18
b00011110 9
b01101011 :
b010001001 ;
0?
1E
b00011110 F
b01101011 G
b010001001 H
#475000
0#
00
0=
#480000
1#
b011101011 /
10
b011101011 <
1=
b011101011 I
#481000
0+
08
0E
#482000
1%
b10000101 &
b00001010 '
b010001111 (
12
b10000101 3
b00001010 4
b010001111 5
1?
b10000101 @
b00001010 A
b010001111 B
#485000
0#
00
0=
#490000
1#
b111001110 )
10
b111001110 6
1=
b111001110 C
#491000
0%
1+
b01001101 ,
b10001000 -
b011010101 .
02
18
b01001101 9
b10001000 :
b011010101 ;
0?
1E
b01001101 F
b10001000 G
b011010101 H
#495000
0#
00
0=
#500000
1#
b101110011 /
10
b101110011 <
1=
b101110011 I
#501000
0+
08
0E
#502000
1%
b11010001 &
b11100100 '
b110110101 (
12
b11010001 3
b11100100 4
b110110101 5
1?
b11010001 @
b11100100 A
b110110101 B
#505000
0#
00
0=
#510000
1#
b010110010 )
10
b010110010 6
1=
b010110010 C
#511000
0%
1+
b00101110 ,
b00011101 -
b001001011 .
02
18
b00101110 9
b00011101 :
b001001011 ;
0?
1E
b00101110 F
b00011101 G
b001001011 H
#515000
0#
00
0=
#520000
1#
b110010000 /
10
b110010000 <
1=
b110010000 I
#521000
0+
08
0E
#522000
1%
b00110011 &
b01011011 '
b010001110 (
12
b00110011 3
b01011011 4
b010001110 5
1?
b00110011 @
b01011011 A
b010001110 B
#525000
0#
00
0=
#530000
1#
b100001101 )
10
b100001101 6
1=
b100001101 C
#531000
0%
1+
b10011111 ,
b00100111 -
b011000110 .
02
18
b10011111 9
b00100111 :
b011000110 ;
0?
1E
b10011111 F
b00100111 G
b011000110 H
#535000
0#
00
0=
#540000
1#
b110110111 /
10
b110110111 <
1=
b110110111 I
#541000
0+
08
0E
#542000
1%
b11101011 &
b00111111 '
b100101010 (
12
b11101011 3
b00111111 4
b100101010 5
1?
b11101011 @
b00111111 A
b100101010 B
#545000
0#
00
0=
#550000
1#
b101001100 )
10
b101001100 6
1=
b101001100 C
#551000
0%
1+
b11000011 ,
b11111111 -
b111000010 .
02
18
b11000011 9
b11111111 :
b111000010 ;
0?
1E
b11000011 F
b11111111 G
b111000010 H
#555000
0#
00
0=
#560000
1#
b010110110 /
10
b010110110 <
1=
b010110110 I
#561000
0+
08
0E
#562000
1%
b11110011 &
b01011010 '
b101001101 (
12
b11110011 3
b01011010 4
b101001101 5
1?
b11110011 @
b01011010 A
b101001101 B
#565000
0#
00
0=
#570000
1#
b110100110 )
10
b110100110 6
1=
b110100110 C
#571000
0%
1+
b01110010 ,
b10100110 -
b100011000 .
02
18
b01110010 9
b10100110 :
b100011000 ;
0?
1E
b01110010 F
b10100110 G
b100011000 H
#575000
0#
00
0=
#580000
1#
b101011100 /
10
b101011100 <
1=
b101011100 I
#581000
0+
08
0E
#582000
1%
b11111010 &
b10111110 '
b110111000 (
12
b11111010 3
b10111110 4
b110111000 5
1?
b11111010 @
b10111110 A
b110111000 B
#585000
0#
00
0=
#590000
1#
b001100100 )
10
b001100100 6
1=
b001100100 C
#591000
0%
1+
b11011011 ,
b11111010 -
b111010101 .
02
18
b11011011 9
b11111010 :
b111010101 ;
0?
1E
b11011011 F
b11111010 G
b111010101 H
#595000
0#
00
0=
#600000
1#
b001010110 /
10
b001010110 <
1=
b001010110 I
#601000
0+
08
0E
#602000
1%
b11001101 &
b01111101 '
b101001010 (
12
b11001101 3
b01111101 4
b101001010 5
1?
b11001101 @
b01111101 A
b101001010 B
#605000
0#
00
0=
#610000
1#
b011100001 )
10
b011100001 6
1=
b011100001 C
#611000
0%
1+
b01001000 ,
b11000111 -
b100001111 .
02
18
b01001000 9
b11000111 :
b100001111 ;
0?
1E
b01001000 F
b11000111 G
b100001111 H
#615000
0#
00
0=
#620000
1#
b100011101 /
10
b100011101 <
1=
b100011101 I
#621000
0+
08
0E
#622000
1%
b10001010 &
b10000101 '
b100001111 (
12
b10001010 3
b10000101 4
b100001111 5
1?
b10001010 @
b10000101 A
b100001111 B
#625000
0#
00
0=
#630000
1#
b101100110 )
10
b101100110 6
1=
b101100110 C
#631000
0%
1+
b11110110 ,
b01010111 -
b101001101 .
02
18
b11110110 9
b01010111 :
b101001101 ;
0?
1E
b11110110 F
b01010111 G
b101001101 H
#635000
0#
00
0=
#640000
1#
b101110100 /
10
b101110100 <
1=
b101110100 I
#641000
0+
08
0E
#642000
1%
b10101011 &
b10000010 '
b100101101 (
12
b10101011 3
b10000010 4
b100101101 5
1?
b10101011 @
b10000010 A
b100101101 B
#645000
0#
00
0=
#650000
1#
b111101000 )
10
b111101000 6
1=
b111101000 C
#651000
0%
1+
b11110010 ,
b01100011 -
b101010101 .
02
18
b11110010 9
b01100011 :
b101010101 ;
0?
1E
b11110010 F
b01100011 G
b101010101 H
#655000
0#
00
0=
#660000
1#
b111010111 /
10
b111010111 <
1=
b111010111 I
#661000
0+
08
0E
#662000
1%
b01101010 &
b11101001 '
b101010011 (
12
b01101010 3
b11101001 4
b101010011 5
1?
b01101010 @
b11101001 A
b101010011 B
#665000
0#
00
0=
#670000
1#
b011010001 )
10
b011010001 6
1=
b011010001 C
#671000
0%
1+
b10101100 ,
b01011010 -
b100000110 .
02
18
b10101100 9
b01011010 :
b100000110 ;
0?
1E
b10101100 F
b01011010 G
b100000110 H
#675000
0#
00
0=
#680000
1#
b000110001 /
10
b000110001 <
1=
b000110001 I
#681000
0+
08
0E
#682000
1%
b01000100 &
b00110101 '
b001111001 (
12
b01000100 3
b00110101 4
b001111001 5
1?
b01000100 @
b00110101 A
b001111001 B
#685000
0#
00
0=
#690000
1#
b100000110 )
10
b100000110 6
1=
b100000110 C
#691000
0%
1+
b01010011 ,
b11101110 -
b101000001 .
02
18
b01010011 9
b11101110 :
b101000001 ;
0?
1E
b01010011 F
b11101110 G
b101000001 H
#695000
0#
00
0=
#700000
1#
b100011111 /
10
b100011111 <
1=
b100011111 I
#701000
0+
08
0E
#702000
1%
b10001100 &
b00010101 '
b010100001 (
12
b10001100 3
b00010101 4
b010100001 5
1?
b10001100 @
b00010101 A
b010100001 B
#705000
0#
00
0=
#710000
1#
b100011011 )
10
b100011011 6
1=
b100011011 C
#711000
0%
1+
b10100010 ,
b11010100 -
b101110110 .
02
18
b10100010 9
b11010100 :
b101110110 ;
0?
1E
b10100010 F
b11010100 G
b101110110 H
#715000
0#
00
0=
#720000
1#
b111110011 /
10
b111110011 <
1=
b111110011 I
#721000
0+
08
0E
#722000
1%
b10110111 &
b10110110 '
b101101101 (
12
b10110111 3
b10110110 4
b101101101 5
1?
b10110111 @
b10110110 A
b101101101 B
#725000
0#
00
0=
#730000
1#
b111010001 )
10
b111010001 6
1=
b111010001 C
#731000
0%
1+
b00100111 ,
b01100011 -
b010001010 .
02
18
b00100111 9
b01100011 :
b010001010 ;
0?
1E
b00100111 F
b01100011 G
b010001010 H
#735000
0#
00
0=
#740000
1#
b001010110 /
10
b001010110 <
1=
b001010110 I
#741000
0+
08
0E
#742000
1%
b11000001 &
b10111000 '
b101111001 (
12
b11000001 3
b10111000 4
b101111001 5
1?
b11000001 @
b10111000 A
b101111001 B
#745000
0#
00
0=
#750000
1#
b010001001 )
10
b010001001 6
1=
b010001001 C
#751000
0%
1+
b00011010 ,
b11000010 -
b011011100 .
02
18
b00011010 9
b11000010 :
b011011100 ;
0?
1E
b00011010 F
b11000010 G
b011011100 H
#755000
0#
00
0=
#760000
1#
b100011000 /
10
b100011000 <
1=
b100011000 I
#761000
0+
08
0E
#762000
1%
b10101000 &
b10011101 '
b101000101 (
12
b10101000 3
b10011101 4
b101000101 5
1?
b10101000 @
b10011101 A
b101000101 B
#765000
0#
00
0=
#770000
1#
b100100110 )
10
b100100110 6
1=
b100100110 C
#771000
0%
1+
b00010000 ,
b10101101 -
b010111101 .
02
18
b00010000 9
b10101101 :
b010111101 ;
0?
1E
b00010000 F
b10101101 G
b010111101 H
#775000
0#
00
0=
#780000
1#
b111000101 /
10
b111000101 <
1=
b111000101 I
#781000
0+
08
0E
#782000
1%
b01101001 &
b10010110 '
b011111111 (
12
b01101001 3
b10010110 4
b011111111 5
1?
b01101001 @
b10010110 A
b011111111 B
#785000
0#
00
0=
#790000
1#
b110111100 )
10
b110111100 6
1=
b110111100 C
#791000
0%
1+
b11000100 ,
b10001111 -
b101010011 .
02
18
b11000100 9
b10001111 :
b101010011 ;
0?
1E
b11000100 F
b10001111 G
b101010011 H
#795000
0#
00
0=
#800000
1#
b001010100 /
10
b001010100 <
1=
b001010100 I
#801000
0+
08
0E
#802000
1%
b00011111 &
b00111001 '
b001011000 (
12
b00011111 3
b00111001 4
b001011000 5
1?
b00011111 @
b00111001 A
b001011000 B
#805000
0#
00
0=
#810000
1#
b111110101 )
10
b111110101 6
1=
b111110101 C
#811000
0%
1+
b11001110 ,
b11000111 -
b110010101 .
02
18
b11001110 9
b11000111 :
b110010101 ;
0?
1E
b11001110 F
b11000111 G
b110010101 H
#815000
0#
00
0=
#820000
1#
b100011011 /
10
b100011011 <
1=
b100011011 I
#821000
0+
08
0E
#822000
1%
b10110101 &
b10111100 '
b101110001 (
12
b10110101 3
b10111100 4
b101110001 5
1?
b10110101 @
b10111100 A
b101110001 B
#825000
0#
00
0=
#830000
1#
b010110001 )
10
b010110001 6
1=
b010110001 C
#831000
0%
1+
b00011011 ,
b00001011 -
b000100110 .
02
18
b00011011 9
b00001011 :
b000100110 ;
0?
1E
b00011011 F
b00001011 G
b000100110 H
#835000
0#
00
0=
#840000
1#
b100100110 /
10
b100100110 <
1=
b100100110 I
#841000
0+
08
0E
#842000
1%
b11000001 &
b11000101 '
b110000110 (
12
b11000001 3
b11000101 4
b110000110 5
1?
b11000001 @
b11000101 A
b110000110 B
#845000
0#
00
0=
#850000
1#
b101110110 )
10
b101110110 6
1=
b101110110 C
#851000
0%
1+
b11001111 ,
b01001110 -
b100011101 .
02
18
b11001111 9
b01001110 :
b100011101 ;
0?
1E
b11001111 F
b01001110 G
b100011101 H
#855000
0#
00
0=
#860000
1#
b101110100 /
10
b101110100 <
1=
b101110100 I
#861000
0+
08
0E
#862000
1%
b01000101 &
b10101111 '
b011110100 (
12
b01000101 3
b10101111 4
b011110100 5
1?
b01000101 @
b10101111 A
b011110100 B
#865000
0#
00
0=
#870000
1#
b000100101 )
10
b000100101 6
1=
b000100101 C
#871000
0%
1+
b01110010 ,
b11100011 -
b101010101 .
02
18
b01110010 9
b11100011 :
b101010101 ;
0?
1E
b01110010 F
b11100011 G
b101010101 H
#875000
0#
00
0=
#880000
1#
b001010111 /
10
b001010111 <
1=
b001010111 I
#881000
0+
08
0E
#882000
1%
b00010000 &
b10010111 '
b010100111 (
12
b00010000 3
b10010111 4
b010100111 5
1?
b00010000 @
b10010111 A
b010100111 B
#885000
0#
00
0=
#890000
1#
b010111100 )
10
b010111100 6
1=
b010111100 C
#891000
0%
1+
b11110100 ,
b10010000 -
b110000100 .
02
18
b11110100 9
b10010000 :
b110000100 ;
0?
1E
b11110100 F
b10010000 G
b110000100 H
#895000
0#
00
0=
#900000
1#
b011100111 /
10
b011100111 <
1=
b011100111 I
#901000
0+
08
0E
#902000
1%
b01101110 &
b00011100 '
b010001010 (
12
b01101110 3
b00011100 4
b010001010 5
1?
b01101110 @
b00011100 A
b010001010 B
#905000
0#
00
0=
#910000
1#
b011011000 )
10
b011011000 6
1=
b011011000 C
#911000
0%
1+
b11011000 ,
b11000001 -
b110011001 .
02
18
b11011000 9
b11000001 :
b110011001 ;
0?
1E
b11011000 F
b11000001 G
b110011001 H
#915000
0#
00
0=
#920000
1#
b110101000 /
10
b110101000 <
1=
b110101000 I
#921000
0+
08
0E
