rtl/top_level.sv


module top_level (
    input  logic       clk,

    // Channel A
    input  logic       rst_A,
    input  logic       valid_in_A,
    input  logic [7:0] a_A,
    input  logic [7:0] b_A,
    output logic [8:0] sum_async_A,
    output logic [8:0] sum_sync_A,

    // Channel B
    input  logic       rst_B,
    input  logic       valid_in_B,
    input  logic [7:0] a_B,
    input  logic [7:0] b_B,
    output logic [8:0] sum_async_B,
    output logic [8:0] sum_sync_B
);

    // Channel A synchronous accumulator
    always_ff @(posedge clk) begin
        if (rst_A)
            sum_sync_A <= '0;
        else if (valid_in_A)
            sum_sync_A <= sum_sync_A + b_A;
    end

    assign sum_async_A = a_A + b_A;

    // Channel B synchronous accumulator
    always_ff @(posedge clk) begin
        if (rst_B)
            sum_sync_B <= '0;
        else if (valid_in_B)
            sum_sync_B <= sum_sync_B + b_B;
    end

    assign sum_async_B = a_B + b_B;

    // initial begin
    //     $display("Time | rst_A| valid_in_A | a_A | b_A |sum_async_A | sum_sync_A |rst_B | valid_in_B| a_B | b_B  | sum_async_B | sum_sync_B   ");
    //     $monitor("%9t  |  %b  |  %b        | %3d | %3d |    %3d     |   %3d      | %b   |    %b     | %3d | %3d  |    %3d      |   %3d ",
    //              $time, rst_A, valid_in_A, a_A, b_A, sum_async_A,sum_sync_A, rst_B, valid_in_B, a_B, b_B, sum_async_B, sum_sync_B);
    // end

    initial begin
        $dumpfile("dump.vcd");
        $dumpvars(1, top_level.sv);
    end

endmodule

rtl/dut_wrapper.sv
module dut_wrapper (
    input  logic       clk,

    // Channel A – cocotb drives these
    input  logic       rst_A,
    input  logic       valid_in_A,
    input  logic [7:0] a_A,
    input  logic [7:0] b_A,

    // DUT drives these
    output logic [8:0] sum_async_A,
    output logic [8:0] sum_sync_A,

    // Channel B (if needed)
    input  logic       rst_B,
    input  logic       valid_in_B,
    input  logic [7:0] a_B,
    input  logic [7:0] b_B,
    output logic [8:0] sum_async_B,
    output logic [8:0] sum_sync_B
);

    top_level u_top_level (
        .clk(clk),

        // Channel A
        .rst_A(rst_A),
        .valid_in_A(valid_in_A),
        .a_A(a_A),
        .b_A(b_A),
        .sum_async_A(sum_async_A),
        .sum_sync_A(sum_sync_A),

        // Channel B
        .rst_B(rst_B),
        .valid_in_B(valid_in_B),
        .a_B(a_B),
        .b_B(b_B),
        .sum_async_B(sum_async_B),
        .sum_sync_B(sum_sync_B)
    );

endmodule



// module dut_wrapper (
//     input  logic       clk,

//     // Channel A – exposed directly for cocotb
//     output logic       rst_A,
//     output logic       valid_in_A,
//     output logic [7:0] a_A,
//     output logic [7:0] b_A,
//     output logic [8:0] sum_async_A,
//     output logic [8:0] sum_sync_A,

//     // Channel B – exposed directly for cocotb
//     output logic       rst_B,
//     output logic       valid_in_B,
//     output logic [7:0] a_B,
//     output logic [7:0] b_B,
//     output logic [8:0] sum_async_B,
//     output logic [8:0] sum_sync_B
// );

//     // Internal wires driven by cocotb (use these as DUT inputs)
//     logic rst_A_int;
//     logic valid_in_A_int;
//     logic [7:0] a_A_int;
//     logic [7:0] b_A_int;

//     logic rst_B_int;
//     logic valid_in_B_int;
//     logic [7:0] a_B_int;
//     logic [7:0] b_B_int;

//     // Connect exposed ports to internal wires so cocotb can drive them
//     assign rst_A       = rst_A_int;
//     assign valid_in_A  = valid_in_A_int;
//     assign a_A         = a_A_int;
//     assign b_A         = b_A_int;

//     assign rst_B       = rst_B_int;
//     assign valid_in_B  = valid_in_B_int;
//     assign a_B         = a_B_int;
//     assign b_B         = b_B_int;

//     // DUT instance
//     top_level u_top_level (
//         .clk          (clk),

//         // Channel A
//         .rst_A        (rst_A_int),
//         .valid_in_A   (valid_in_A_int),
//         .a_A          (a_A_int),
//         .b_A          (b_A_int),
//         .sum_async_A  (sum_async_A),
//         .sum_sync_A   (sum_sync_A),

//         // Channel B
//         .rst_B        (rst_B_int),
//         .valid_in_B   (valid_in_B_int),
//         .a_B          (a_B_int),
//         .b_B          (b_B_int),
//         .sum_async_B  (sum_async_B),
//         .sum_sync_B   (sum_sync_B)
//     );

// endmodule

regression_results/waves_7.vcd
$version Generated by VerilatedVcd $end
$timescale 1ps $end
 $scope module $rootio $end
  $var wire 1 # clk $end
  $var wire 1 $ rst_A $end
  $var wire 1 % valid_in_A $end
  $var wire 8 & a_A [7:0] $end
  $var wire 8 ' b_A [7:0] $end
  $var wire 9 ( sum_async_A [8:0] $end
  $var wire 9 ) sum_sync_A [8:0] $end
  $var wire 1 * rst_B $end
  $var wire 1 + valid_in_B $end
  $var wire 8 , a_B [7:0] $end
  $var wire 8 - b_B [7:0] $end
  $var wire 9 . sum_async_B [8:0] $end
  $var wire 9 / sum_sync_B [8:0] $end
 $upscope $end
 $scope module dut_wrapper $end
  $var wire 1 0 clk $end
  $var wire 1 1 rst_A $end
  $var wire 1 2 valid_in_A $end
  $var wire 8 3 a_A [7:0] $end
  $var wire 8 4 b_A [7:0] $end
  $var wire 9 5 sum_async_A [8:0] $end
  $var wire 9 6 sum_sync_A [8:0] $end
  $var wire 1 7 rst_B $end
  $var wire 1 8 valid_in_B $end
  $var wire 8 9 a_B [7:0] $end
  $var wire 8 : b_B [7:0] $end
  $var wire 9 ; sum_async_B [8:0] $end
  $var wire 9 < sum_sync_B [8:0] $end
  $scope module u_top_level $end
   $var wire 1 = clk $end
   $var wire 1 > rst_A $end
   $var wire 1 ? valid_in_A $end
   $var wire 8 @ a_A [7:0] $end
   $var wire 8 A b_A [7:0] $end
   $var wire 9 B sum_async_A [8:0] $end
   $var wire 9 C sum_sync_A [8:0] $end
   $var wire 1 D rst_B $end
   $var wire 1 E valid_in_B $end
   $var wire 8 F a_B [7:0] $end
   $var wire 8 G b_B [7:0] $end
   $var wire 9 H sum_async_B [8:0] $end
   $var wire 9 I sum_sync_B [8:0] $end
  $upscope $end
 $upscope $end
$enddefinitions $end


#0
1#
0$
1%
b00001000 &
b00001100 '
b000010100 (
b000000000 )
0*
0+
b00000000 ,
b00000000 -
b000000000 .
b000000000 /
10
01
12
b00001000 3
b00001100 4
b000010100 5
b000000000 6
07
08
b00000000 9
b00000000 :
b000000000 ;
b000000000 <
1=
0>
1?
b00001000 @
b00001100 A
b000010100 B
b000000000 C
0D
0E
b00000000 F
b00000000 G
b000000000 H
b000000000 I
#150020000

0=
#10000
1#
0%
b000001100 )
10
02
b000001100 6
1=
0?
b000001100 C
#15000
0#
00
0=
#20000
1#
10
1=
#25000
0#
00
0=
#30000
1#
1%
b00011101 &
b00011100 '
b000111001 (
10
12
b00011101 3
b00011100 4
b000111001 5
1=
1?
b00011101 @
b00011100 A
b000111001 B
#35000
0#
00
0=
#40000
1#
0%
b000101000 )
10
02
b000101000 6
1=
0?
b000101000 C
#45000
0#
00
0=
#50000
1#
10
1=
#55000
0#
00
0=
#60000
1#
1%
b00100100 &
b00110101 '
b001011001 (
10
12
b00100100 3
b00110101 4
b001011001 5
1=
1?
b00100100 @
b00110101 A
b001011001 B
#65000
0#
00
0=
#70000
1#
0%
b001011101 )
10
02
b001011101 6
1=
0?
b001011101 C
#75000
0#
00
0=
#80000
1#
10
1=
#85000
0#
00
0=
#90000
1#
1%
b01010000 &
b01010100 '
b010100100 (
10
12
b01010000 3
b01010100 4
b010100100 5
1=
1?
b01010000 @
b01010100 A
b010100100 B
#95000
0#
00
0=
#100000
1#
0%
b010110001 )
10
02
b010110001 6
1=
0?
b010110001 C
#105000
0#
00
0=
#110000
1#
10
1=
#115000
0#
00
0=
#120000
1#
1%
b11100000 &
b10001101 '
b101101101 (
10
12
b11100000 3
b10001101 4
b101101101 5
1=
1?
b11100000 @
b10001101 A
b101101101 B
#125000
0#
00
0=
#130000
1#
0%
b100111110 )
10
02
b100111110 6
1=
0?
b100111110 C
#135000
0#
00
0=
#140000
1#
10
1=
#145000
0#
00
0=
#150000
1#
1%
b00001110 &
b00001000 '
b000010110 (
10
12
b00001110 3
b00001000 4
b000010110 5
1=
1?
b00001110 @
b00001000 A
b000010110 B
#155000
0#
00
0=
#160000
1#
0%
b101000110 )
10
02
b101000110 6
1=
0?
b101000110 C
#165000
0#
00
0=
#170000
1#
10
1=
#175000
0#
00
0=
#180000
1#
1%
b00010101 &
b00010100 '
b000101001 (
10
12
b00010101 3
b00010100 4
b000101001 5
1=
1?
b00010101 @
b00010100 A
b000101001 B
#185000
0#
00
0=
#190000
1#
0%
b101011010 )
10
02
b101011010 6
1=
0?
b101011010 C
#195000
0#
00
0=
#200000
1#
10
1=
#205000
0#
00
0=
#210000
1#
1%
b00110110 &
b00111010 '
b001110000 (
10
12
b00110110 3
b00111010 4
b001110000 5
1=
1?
b00110110 @
b00111010 A
b001110000 B
#215000
0#
00
0=
#220000
1#
0%
b110010100 )
10
02
b110010100 6
1=
0?
b110010100 C
#225000
0#
00
0=
#230000
1#
10
1=
#235000
0#
00
0=
#240000
1#
1%
b01011001 &
b01110101 '
b011001110 (
10
12
b01011001 3
b01110101 4
b011001110 5
1=
1?
b01011001 @
b01110101 A
b011001110 B
#245000
0#
00
0=
#250000
1#
0%
b000001001 )
10
02
b000001001 6
1=
0?
b000001001 C
#255000
0#
00
0=
#260000
1#
10
1=
#265000
0#
00
0=
#270000
1#
1%
b11010001 &
b11000110 '
b110010111 (
10
12
b11010001 3
b11000110 4
b110010111 5
1=
1?
b11010001 @
b11000110 A
b110010111 B
#275000
0#
00
0=
#280000
1#
0%
b011001111 )
10
02
b011001111 6
1=
0?
b011001111 C
#285000
0#
00
0=
#290000
1#
10
1=
#295000
0#
00
0=
#300000
1#
1%
b00000111 &
b00000000 '
b000000111 (
10
12
b00000111 3
b00000000 4
b000000111 5
1=
1?
b00000111 @
b00000000 A
b000000111 B
#305000
0#
00
0=
#310000
1#
0%
10
02
1=
0?
#315000
0#
00
0=
#320000
1#
10
1=
#325000
0#
00
0=
#330000
1#
1%
b00010110 &
b00011011 '
b000110001 (
10
12
b00010110 3
b00011011 4
b000110001 5
1=
1?
b00010110 @
b00011011 A
b000110001 B
#335000
0#
00
0=
#340000
1#
0%
b011101010 )
10
02
b011101010 6
1=
0?
b011101010 C
#345000
0#
00
0=
#350000
1#
10
1=
#355000
0#
00
0=
#360000
1#
1%
b00111111 &
b00101000 '
b001100111 (
10
12
b00111111 3
b00101000 4
b001100111 5
1=
1?
b00111111 @
b00101000 A
b001100111 B
#365000
0#
00
0=
#370000
1#
0%
b100010010 )
10
02
b100010010 6
1=
0?
b100010010 C
#375000
0#
00
0=
#380000
1#
10
1=
#385000
0#
00
0=
#390000
1#
1%
b01011101 &
b01010001 '
b010101110 (
10
12
b01011101 3
b01010001 4
b010101110 5
1=
1?
b01011101 @
b01010001 A
b010101110 B
#395000
0#
00
0=
#400000
1#
0%
b101100011 )
10
02
b101100011 6
1=
0?
b101100011 C
#405000
0#
00
0=
#410000
1#
10
1=
#415000
0#
00
0=
#420000
1#
1%
b11111111 &
b10101000 '
b110100111 (
10
12
b11111111 3
b10101000 4
b110100111 5
1=
1?
b11111111 @
b10101000 A
b110100111 B
#425000
0#
00
0=
#430000
1#
0%
b000001011 )
10
02
b000001011 6
1=
0?
b000001011 C
#435000
0#
00
0=
#440000
1#
10
1=
#445000
0#
00
0=
#450000
1#
1%
b00000001 &
b00000000 '
b000000001 (
10
12
b00000001 3
b00000000 4
b000000001 5
1=
1?
b00000001 @
b00000000 A
b000000001 B
#455000
0#
00
0=
#460000
1#
0%
10
02
1=
0?
#465000
0#
00
0=
#470000
1#
10
1=
#475000
0#
00
0=
#480000
1#
1%
b00011000 &
b00011110 '
b000110110 (
10
12
b00011000 3
b00011110 4
b000110110 5
1=
1?
b00011000 @
b00011110 A
b000110110 B
#485000
0#
00
0=
#490000
1#
0%
b000101001 )
10
02
b000101001 6
1=
0?
b000101001 C
#495000
0#
00
0=
#500000
1#
10
1=
#505000
0#
00
0=
#510000
1#
1%
b00111111 &
b00111011 '
b001111010 (
10
12
b00111111 3
b00111011 4
b001111010 5
1=
1?
b00111111 @
b00111011 A
b001111010 B
#515000
0#
00
0=
#520000
1#
0%
b001100100 )
10
02
b001100100 6
1=
0?
b001100100 C
#525000
0#
00
0=
#530000
1#
10
1=
#535000
0#
00
0=
#540000
1#
1%
b01110000 &
b01111001 '
b011101001 (
10
12
b01110000 3
b01111001 4
b011101001 5
1=
1?
b01110000 @
b01111001 A
b011101001 B
#545000
0#
00
0=
#550000
1#
0%
b011011101 )
10
02
b011011101 6
1=
0?
b011011101 C
#555000
0#
00
0=
#560000
1#
10
1=
#565000
0#
00
0=
#570000
1#
1%
b11011011 &
b11011100 '
b110110111 (
10
12
b11011011 3
b11011100 4
b110110111 5
1=
1?
b11011011 @
b11011100 A
b110110111 B
#575000
0#
00
0=
#580000
1#
0%
b110111001 )
10
02
b110111001 6
1=
0?
b110111001 C
#585000
0#
00
0=
#590000
1#
10
1=
#595000
0#
00
0=
#600000
1#
1%
b00000000 &
b00001000 '
b000001000 (
10
12
b00000000 3
b00001000 4
b000001000 5
1=
1?
b00000000 @
b00001000 A
b000001000 B
#605000
0#
00
0=
#610000
1#
0%
b111000001 )
10
02
b111000001 6
1=
0?
b111000001 C
#615000
0#
00
0=
#620000
1#
10
1=
#625000
0#
00
0=
#630000
1#
1%
b00011100 &
b00010101 '
b000110001 (
10
12
b00011100 3
b00010101 4
b000110001 5
1=
1?
b00011100 @
b00010101 A
b000110001 B
#635000
0#
00
0=
#640000
1#
0%
b111010110 )
10
02
b111010110 6
1=
0?
b111010110 C
#645000
0#
00
0=
#650000
1#
10
1=
#655000
0#
00
0=
#660000
1#
1%
b00100011 &
b00111110 '
b001100001 (
10
12
b00100011 3
b00111110 4
b001100001 5
1=
1?
b00100011 @
b00111110 A
b001100001 B
#665000
0#
00
0=
#670000
1#
0%
b000010100 )
10
02
b000010100 6
1=
0?
b000010100 C
#675000
0#
00
0=
#680000
1#
10
1=
#685000
0#
00
0=
#690000
1#
1%
b01100111 &
b01001011 '
b010110010 (
10
12
b01100111 3
b01001011 4
b010110010 5
1=
1?
b01100111 @
b01001011 A
b010110010 B
#695000
0#
00
0=
#700000
1#
0%
b001011111 )
10
02
b001011111 6
1=
0?
b001011111 C
#705000
0#
00
0=
#710000
1#
10
1=
#715000
0#
00
0=
#720000
1#
1%
b11011101 &
b10000000 '
b101011101 (
10
12
b11011101 3
b10000000 4
b101011101 5
1=
1?
b11011101 @
b10000000 A
b101011101 B
#725000
0#
00
0=
#730000
1#
0%
b011011111 )
10
02
b011011111 6
1=
0?
b011011111 C
#735000
0#
00
0=
#740000
1#
10
1=
#745000
0#
00
0=
#750000
1#
1%
b00001010 &
b00000101 '
b000001111 (
10
12
b00001010 3
b00000101 4
b000001111 5
1=
1?
b00001010 @
b00000101 A
b000001111 B
#755000
0#
00
0=
#760000
1#
0%
b011100100 )
10
02
b011100100 6
1=
0?
b011100100 C
#765000
0#
00
0=
#770000
1#
10
1=
#775000
0#
00
0=
#780000
1#
1%
b00010100 &
b00011111 '
b000110011 (
10
12
b00010100 3
b00011111 4
b000110011 5
1=
1?
b00010100 @
b00011111 A
b000110011 B
#785000
0#
00
0=
#790000
1#
0%
b100000011 )
10
02
b100000011 6
1=
0?
b100000011 C
#795000
0#
00
0=
#800000
1#
10
1=
#805000
0#
00
0=
#810000
1#
1%
b00101000 &
b00111101 '
b001100101 (
10
12
b00101000 3
b00111101 4
b001100101 5
1=
1?
b00101000 @
b00111101 A
b001100101 B
#815000
0#
00
0=
#820000
1#
0%
b101000000 )
10
02
b101000000 6
1=
0?
b101000000 C
#825000
0#
00
0=
#830000
1#
10
1=
#835000
0#
00
0=
#840000
1#
1%
b01100110 &
b01000000 '
b010100110 (
10
12
b01100110 3
b01000000 4
b010100110 5
1=
1?
b01100110 @
b01000000 A
b010100110 B
#845000
0#
00
0=
#850000
1#
0%
b110000000 )
10
02
b110000000 6
1=
0?
b110000000 C
#855000
0#
00
0=
#860000
1#
10
1=
#865000
0#
00
0=
#870000
1#
1%
b10101010 &
b11110101 '
b110011111 (
10
12
b10101010 3
b11110101 4
b110011111 5
1=
1?
b10101010 @
b11110101 A
b110011111 B
#875000
0#
00
0=
#880000
1#
0%
b001110101 )
10
02
b001110101 6
1=
0?
b001110101 C
#885000
0#
00
0=
#890000
1#
10
1=
#895000
0#
00
0=
#900000
1#
1%
b00000011 &
b00001000 '
b000001011 (
10
12
b00000011 3
b00001000 4
b000001011 5
1=
1?
b00000011 @
b00001000 A
b000001011 B
#905000
0#
00
0=
#910000
1#
0%
b001111101 )
10
02
b001111101 6
1=
0?
b001111101 C
#915000
0#
00
0=
#920000
1#
10
1=
#925000
0#
00
0=
#930000
1#
1%
b00010010 &
b00010100 '
b000100110 (
10
12
b00010010 3
b00010100 4
b000100110 5
1=
1?
b00010010 @
b00010100 A
b000100110 B
#935000
0#
00
0=
#940000
1#
0%
b010010001 )
10
02
b010010001 6
1=
0?
b010010001 C
#945000
0#
00
0=
#950000
1#
10
1=
#955000
0#
00
0=
#960000
1#
1%
b00100101 &
b00110000 '
b001010101 (
10
12
b00100101 3
b00110000 4
b001010101 5
1=
1?
b00100101 @
b00110000 A
b001010101 B
#965000
0#
00
0=
#970000
1#
0%
b011000001 )
10
02
b011000001 6
1=
0?
b011000001 C
#975000
0#
00
0=
#980000
1#
10
1=
#985000
0#
00
0=
#990000
1#
1%
b01010001 &
b01110110 '
b011000111 (
10
12
b01010001 3
b01110110 4
b011000111 5
1=
1?
b01010001 @
b01110110 A
b011000111 B
#995000
0#
00
0=
#1000000
1#
0%
b100110111 )
10
02
b100110111 6
1=
0?
b100110111 C
#1005000
0#
00
0=
#1010000
1#
10
1=
#1015000
0#
00
0=
#1020000
1#
1%
b11110000 &
b11011011 '
b111001011 (
10
12
b11110000 3
b11011011 4
b111001011 5
1=
1?
b11110000 @
b11011011 A
b111001011 B
#1025000
0#
00
0=
#1030000
1#
0%
b000010010 )
10
02
b000010010 6
1=
0?
b000010010 C
#1035000
0#
00
0=
#1040000
1#
10
1=
#1045000
0#
00
0=
#1050000
1#
1%
b00000111 &
b00000000 '
b000000111 (
10
12
b00000111 3
b00000000 4
b000000111 5
1=
1?
b00000111 @
b00000000 A
b000000111 B
#1055000
0#
00
0=
#1060000
1#
0%
10
02
1=
0?
#1065000
0#
00
0=
#1070000
1#
10
1=
#1075000
0#
00
0=
#1080000
1#
1%
b00011100 &
b00010111 '
b000110011 (
10
12
b00011100 3
b00010111 4
b000110011 5
1=
1?
b00011100 @
b00010111 A
b000110011 B
#1085000
0#
00
0=
#1090000
1#
0%
b000101001 )
10
02
b000101001 6
1=
0?
b000101001 C
#1095000
0#
00
0=
#1100000
1#
10
1=
#1105000
0#
00
0=
#1110000
1#
1%
b00111011 &
b00110010 '
b001101101 (
10
12
b00111011 3
b00110010 4
b001101101 5
1=
1?
b00111011 @
b00110010 A
b001101101 B
#1115000
0#
00
0=
#1120000
1#
0%
b001011011 )
10
02
b001011011 6
1=
0?
b001011011 C
#1125000
0#
00
0=
#1130000
1#
10
1=
#1135000
0#
00
0=
#1140000
1#
1%
b01010001 &
b01000010 '
b010010011 (
10
12
b01010001 3
b01000010 4
b010010011 5
1=
1?
b01010001 @
b01000010 A
b010010011 B
#1145000
0#
00
0=
#1150000
1#
0%
b010011101 )
10
02
b010011101 6
1=
0?
b010011101 C
#1155000
0#
00
0=
#1160000
1#
10
1=
#1165000
0#
00
0=
#1170000
1#
1%
b10001111 &
b11010110 '
b101100101 (
10
12
b10001111 3
b11010110 4
b101100101 5
1=
1?
b10001111 @
b11010110 A
b101100101 B
#1175000
0#
00
0=
#1180000
1#
0%
b101110011 )
10
02
b101110011 6
1=
0?
b101110011 C
#1185000
0#
00
0=
#1190000
1#
10
1=
#1195000
0#
00
0=
#1200000
1#
1%
b00001101 &
b00000011 '
b000010000 (
10
12
b00001101 3
b00000011 4
b000010000 5
1=
1?
b00001101 @
b00000011 A
b000010000 B
#1205000
0#
00
0=
#1210000
1#
0%
b101110110 )
10
02
b101110110 6
1=
0?
b101110110 C
#1215000
0#
00
0=
#1220000
1#
10
1=
#1225000
0#
00
0=
#1230000
1#
1%
b00010011 &
b00010011 '
b000100110 (
10
12
b00010011 3
b00010011 4
b000100110 5
1=
1?
b00010011 @
b00010011 A
b000100110 B
#1235000
0#
00
0=
#1240000
1#
0%
b110001001 )
10
02
b110001001 6
1=
0?
b110001001 C
#1245000
0#
00
0=
#1250000
1#
10
1=
#1255000
0#
00
0=
#1260000
1#
1%
b00111111 &
b00101111 '
b001101110 (
10
12
b00111111 3
b00101111 4
b001101110 5
1=
1?
b00111111 @
b00101111 A
b001101110 B
#1265000
0#
00
0=
#1270000
1#
0%
b110111000 )
10
02
b110111000 6
1=
0?
b110111000 C
#1275000
0#
00
0=
#1280000
1#
10
1=
#1285000
0#
00
0=
#1290000
1#
1%
b01100100 &
b01011010 '
b010111110 (
10
12
b01100100 3
b01011010 4
b010111110 5
1=
1?
b01100100 @
b01011010 A
b010111110 B
#1295000
0#
00
0=
#1300000
1#
0%
b000010010 )
10
02
b000010010 6
1=
0?
b000010010 C
#1305000
0#
00
0=
#1310000
1#
10
1=
#1315000
0#
00
0=
#1320000
1#
1%
b11011100 &
b11110111 '
b111010011 (
10
12
b11011100 3
b11110111 4
b111010011 5
1=
1?
b11011100 @
b11110111 A
b111010011 B
#1325000
0#
00
0=
#1330000
1#
0%
b100001001 )
10
02
b100001001 6
1=
0?
b100001001 C
#1335000
0#
00
0=
#1340000
1#
10
1=
#1345000
0#
00
0=
#1350000
1#
1%
b00000010 &
b00000001 '
b000000011 (
10
12
b00000010 3
b00000001 4
b000000011 5
1=
1?
b00000010 @
b00000001 A
b000000011 B
#1355000
0#
00
0=
#1360000
1#
0%
b100001010 )
10
02
b100001010 6
1=
0?
b100001010 C
#1365000
0#
00
0=
#1370000
1#
10
1=
#1375000
0#
00
0=
#1380000
1#
1%
b00011010 &
b00011001 '
b000110011 (
10
12
b00011010 3
b00011001 4
b000110011 5
1=
1?
b00011010 @
b00011001 A
b000110011 B
#1385000
0#
00
0=
#1390000
1#
0%
b100100011 )
10
02
b100100011 6
1=
0?
b100100011 C
#1395000
0#
00
0=
#1400000
1#
10
1=
#1405000
0#
00
0=
#1410000
1#
1%
b00101101 &
b00101110 '
b001011011 (
10
12
b00101101 3
b00101110 4
b001011011 5
1=
1?
b00101101 @
b00101110 A
b001011011 B
#1415000
0#
00
0=
#1420000
1#
0%
b101010001 )
10
02
b101010001 6
1=
0?
b101010001 C
#1425000
0#
00
0=
#1430000
1#
10
1=
#1435000
0#
00
0=
#1440000
1#
1%
b01011111 &
b01000100 '
b010100011 (
10
12
b01011111 3
b01000100 4
b010100011 5
1=
1?
b01011111 @
b01000100 A
b010100011 B
#1445000
0#
00
0=
#1450000
1#
0%
b110010101 )
10
02
b110010101 6
1=
0?
b110010101 C
#1455000
0#
00
0=
#1460000
1#
10
1=
#1465000
0#
00
0=
#1470000
1#
1%
b10100001 &
b11110000 '
b110010001 (
10
12
b10100001 3
b11110000 4
b110010001 5
1=
1?
b10100001 @
b11110000 A
b110010001 B
#1475000
0#
00
0=
#1480000
1#
0%
b010000101 )
10
02
b010000101 6
1=
0?
b010000101 C
#1485000
0#
00
0=
#1490000
1#
10
1=
#1495000
0#
00
0=
#1500000
1#
1%
b00001011 &
b00000100 '
b000001111 (
10
12
b00001011 3
b00000100 4
b000001111 5
1=
1?
b00001011 @
b00000100 A
b000001111 B
#1505000
0#
00
0=
#1510000
1#
0%
b010001001 )
10
02
b010001001 6
1=
0?
b010001001 C
#1515000
0#
00
0=
#1520000
1#
10
1=
#1525000
0#
00
0=
#1530000
1#
1%
b00010001 &
b00011101 '
b000101110 (
10
12
b00010001 3
b00011101 4
b000101110 5
1=
1?
b00010001 @
b00011101 A
b000101110 B
#1535000
0#
00
0=
#1540000
1#
0%
b010100110 )
10
02
b010100110 6
1=
0?
b010100110 C
#1545000
0#
00
0=
#1550000
1#
10
1=
#1555000
0#
00
0=
#1560000
1#
1%
b00100000 &
b00100010 '
b001000010 (
10
12
b00100000 3
b00100010 4
b001000010 5
1=
1?
b00100000 @
b00100010 A
b001000010 B
#1565000
0#
00
0=
#1570000
1#
0%
b011001000 )
10
02
b011001000 6
1=
0?
b011001000 C
#1575000
0#
00
0=
#1580000
1#
10
1=
#1585000
0#
00
0=
#1590000
1#
1%
b01000111 &
b01111110 '
b011000101 (
10
12
b01000111 3
b01111110 4
b011000101 5
1=
1?
b01000111 @
b01111110 A
b011000101 B
#1595000
0#
00
0=
#1600000
1#
0%
b101000110 )
10
02
b101000110 6
1=
0?
b101000110 C
#1605000
0#
00
0=
#1610000
1#
10
1=
#1615000
0#
00
0=
#1620000
1#
1%
b10100000 &
b10010001 '
b100110001 (
10
12
b10100000 3
b10010001 4
b100110001 5
1=
1?
b10100000 @
b10010001 A
b100110001 B
#1625000
0#
00
0=
#1630000
1#
0%
b111010111 )
10
02
b111010111 6
1=
0?
b111010111 C
#1635000
0#
00
0=
#1640000
1#
10
1=
#1645000
0#
00
0=
#1650000
1#
1%
b00001110 &
b00000100 '
b000010010 (
10
12
b00001110 3
b00000100 4
b000010010 5
1=
1?
b00001110 @
b00000100 A
b000010010 B
#1655000
0#
00
0=
#1660000
1#
0%
b111011011 )
10
02
b111011011 6
1=
0?
b111011011 C
#1665000
0#
00
0=
#1670000
1#
10
1=
#1675000
0#
00
0=
#1680000
1#
1%
b00010101 &
b00011011 '
b000110000 (
10
12
b00010101 3
b00011011 4
b000110000 5
1=
1?
b00010101 @
b00011011 A
b000110000 B
#1685000
0#
00
0=
#1690000
1#
0%
b111110110 )
10
02
b111110110 6
1=
0?
b111110110 C
#1695000
0#
00
0=
#1700000
1#
10
1=
#1705000
0#
00
0=
#1710000
1#
1%
b00101100 &
b00110100 '
b001100000 (
10
12
b00101100 3
b00110100 4
b001100000 5
1=
1?
b00101100 @
b00110100 A
b001100000 B
#1715000
0#
00
0=
#1720000
1#
0%
b000101010 )
10
02
b000101010 6
1=
0?
b000101010 C
#1725000
0#
00
0=
#1730000
1#
10
1=
#1735000
0#
00
0=
#1740000
1#
1%
b01110101 &
b01100101 '
b011011010 (
10
12
b01110101 3
b01100101 4
b011011010 5
1=
1?
b01110101 @
b01100101 A
b011011010 B
#1745000
0#
00
0=
#1750000
1#
0%
b010001111 )
10
02
b010001111 6
1=
0?
b010001111 C
#1755000
0#
00
0=
#1760000
1#
10
1=
#1765000
0#
00
0=
#1770000
1#
1%
b11110011 &
b10110100 '
b110100111 (
10
12
b11110011 3
b10110100 4
b110100111 5
1=
1?
b11110011 @
b10110100 A
b110100111 B
#1775000
0#
00
0=
#1780000
1#
0%
b101000011 )
10
02
b101000011 6
1=
0?
b101000011 C
#1785000
0#
00
0=
#1790000
1#
10
1=
#1795000
0#
00
0=
#1800000
1#
1%
b00001111 &
b00000100 '
b000010011 (
10
12
b00001111 3
b00000100 4
b000010011 5
1=
1?
b00001111 @
b00000100 A
b000010011 B
#1805000
0#
00
0=
#1810000
1#
0%
b101000111 )
10
02
b101000111 6
1=
0?
b101000111 C
#1815000
0#
00
0=
#1820000
1#
10
1=
#1825000
0#
00
0=
#1830000
1#
1%
b00011000 &
b00010111 '
b000101111 (
10
12
b00011000 3
b00010111 4
b000101111 5
1=
1?
b00011000 @
b00010111 A
b000101111 B
#1835000
0#
00
0=
#1840000
1#
0%
b101011110 )
10
02
b101011110 6
1=
0?
b101011110 C
#1845000
0#
00
0=
#1850000
1#
10
1=
#1855000
0#
00
0=
#1860000
1#
1%
b00110010 &
b00110100 '
b001100110 (
10
12
b00110010 3
b00110100 4
b001100110 5
1=
1?
b00110010 @
b00110100 A
b001100110 B
#1865000
0#
00
0=
#1870000
1#
0%
b110010010 )
10
02
b110010010 6
1=
0?
b110010010 C
#1875000
0#
00
0=
#1880000
1#
10
1=
#1885000
0#
00
0=
#1890000
1#
1%
b01011011 &
b01011010 '
b010110101 (
10
12
b01011011 3
b01011010 4
b010110101 5
1=
1?
b01011011 @
b01011010 A
b010110101 B
#1895000
0#
00
0=
#1900000
1#
0%
b111101100 )
10
02
b111101100 6
1=
0?
b111101100 C
#1905000
0#
00
0=
#1910000
1#
10
1=
#1915000
0#
00
0=
#1920000
1#
1%
b10011001 &
b11111111 '
b110011000 (
10
12
b10011001 3
b11111111 4
b110011000 5
1=
1?
b10011001 @
b11111111 A
b110011000 B
#1925000
0#
00
0=
#1930000
1#
0%
b011101011 )
10
02
b011101011 6
1=
0?
b011101011 C
#1935000
0#
00
0=
#1940000
1#
10
1=
#1945000
0#
00
0=
#1950000
1#
1%
b00000111 &
b00000011 '
b000001010 (
10
12
b00000111 3
b00000011 4
b000001010 5
1=
1?
b00000111 @
b00000011 A
b000001010 B
#1955000
0#
00
0=
#1960000
1#
0%
b011101110 )
10
02
b011101110 6
1=
0?
b011101110 C
#1965000
0#
00
0=
#1970000
1#
10
1=
#1975000
0#
00
0=
#1980000
1#
1%
b00010100 &
b00011001 '
b000101101 (
10
12
b00010100 3
b00011001 4
b000101101 5
1=
1?
b00010100 @
b00011001 A
b000101101 B
#1985000
0#
00
0=
#1990000
1#
0%
b100000111 )
10
02
b100000111 6
1=
0?
b100000111 C
#1995000
0#
00
0=
#2000000
1#
10
1=
#2005000
0#
00
0=
#2010000
1#
1%
b00110100 &
b00111000 '
b001101100 (
10
12
b00110100 3
b00111000 4
b001101100 5
1=
1?
b00110100 @
b00111000 A
b001101100 B
#2015000
0#
00
0=
#2020000
1#
0%
b100111111 )
10
02
b100111111 6
1=
0?
b100111111 C
#2025000
0#
00
0=
#2030000
1#
10
1=
#2035000
0#
00
0=
#2040000
1#
1%
b01110110 &
b01101110 '
b011100100 (
10
12
b01110110 3
b01101110 4
b011100100 5
1=
1?
b01110110 @
b01101110 A
b011100100 B
