rtl/top_level.sv


module top_level (
    input  logic       clk,

    // Channel A
    input  logic       rst_A,
    input  logic       valid_in_A,
    input  logic [7:0] a_A,
    input  logic [7:0] b_A,
    output logic [8:0] sum_async_A,
    output logic [8:0] sum_sync_A,

    // Channel B
    input  logic       rst_B,
    input  logic       valid_in_B,
    input  logic [7:0] a_B,
    input  logic [7:0] b_B,
    output logic [8:0] sum_async_B,
    output logic [8:0] sum_sync_B
);

    // Channel A synchronous accumulator
    always_ff @(posedge clk) begin
        if (rst_A)
            sum_sync_A <= '0;
        else if (valid_in_A)
            sum_sync_A <= sum_sync_A + b_A;
    end

    assign sum_async_A = a_A + b_A;

    // Channel B synchronous accumulator
    always_ff @(posedge clk) begin
        if (rst_B)
            sum_sync_B <= '0;
        else if (valid_in_B)
            sum_sync_B <= sum_sync_B + b_B;
    end

    assign sum_async_B = a_B + b_B;

    initial begin
        $display("Time | rst_A| valid_in_A | a_A | b_A |sum_async_A | sum_sync_A |rst_B | valid_in_B| a_B | b_B  | sum_async_B | sum_sync_B   ");
        $monitor("%4t  |  %b  |  %b        | %0d | %0d |    %0d     |   %0d      | %b   |    %b     | %0d | %0d  |    %0d      |   %0d ",
                 $time, rst_A, valid_in_A, a_A, b_A, sum_async_A,sum_sync_A, rst_B, valid_in_B, a_B, b_B, sum_async_B, sum_sync_B);
    end

    initial begin
        $dumpfile("dump.vcd");
        $dumpvars(1, top_level.sv);
    end

endmodule

rtl/dut_wrapper.sv
module dut_wrapper (
    input  logic       clk,

    // Channel A – cocotb drives these
    input  logic       rst_A,
    input  logic       valid_in_A,
    input  logic [7:0] a_A,
    input  logic [7:0] b_A,

    // DUT drives these
    output logic [8:0] sum_async_A,
    output logic [8:0] sum_sync_A,

    // Channel B (if needed)
    input  logic       rst_B,
    input  logic       valid_in_B,
    input  logic [7:0] a_B,
    input  logic [7:0] b_B,
    output logic [8:0] sum_async_B,
    output logic [8:0] sum_sync_B
);

    top_level u_top_level (
        .clk(clk),

        // Channel A
        .rst_A(rst_A),
        .valid_in_A(valid_in_A),
        .a_A(a_A),
        .b_A(b_A),
        .sum_async_A(sum_async_A),
        .sum_sync_A(sum_sync_A),

        // Channel B
        .rst_B(rst_B),
        .valid_in_B(valid_in_B),
        .a_B(a_B),
        .b_B(b_B),
        .sum_async_B(sum_async_B),
        .sum_sync_B(sum_sync_B)
    );

endmodule



// module dut_wrapper (
//     input  logic       clk,

//     // Channel A – exposed directly for cocotb
//     output logic       rst_A,
//     output logic       valid_in_A,
//     output logic [7:0] a_A,
//     output logic [7:0] b_A,
//     output logic [8:0] sum_async_A,
//     output logic [8:0] sum_sync_A,

//     // Channel B – exposed directly for cocotb
//     output logic       rst_B,
//     output logic       valid_in_B,
//     output logic [7:0] a_B,
//     output logic [7:0] b_B,
//     output logic [8:0] sum_async_B,
//     output logic [8:0] sum_sync_B
// );

//     // Internal wires driven by cocotb (use these as DUT inputs)
//     logic rst_A_int;
//     logic valid_in_A_int;
//     logic [7:0] a_A_int;
//     logic [7:0] b_A_int;

//     logic rst_B_int;
//     logic valid_in_B_int;
//     logic [7:0] a_B_int;
//     logic [7:0] b_B_int;

//     // Connect exposed ports to internal wires so cocotb can drive them
//     assign rst_A       = rst_A_int;
//     assign valid_in_A  = valid_in_A_int;
//     assign a_A         = a_A_int;
//     assign b_A         = b_A_int;

//     assign rst_B       = rst_B_int;
//     assign valid_in_B  = valid_in_B_int;
//     assign a_B         = a_B_int;
//     assign b_B         = b_B_int;

//     // DUT instance
//     top_level u_top_level (
//         .clk          (clk),

//         // Channel A
//         .rst_A        (rst_A_int),
//         .valid_in_A   (valid_in_A_int),
//         .a_A          (a_A_int),
//         .b_A          (b_A_int),
//         .sum_async_A  (sum_async_A),
//         .sum_sync_A   (sum_sync_A),

//         // Channel B
//         .rst_B        (rst_B_int),
//         .valid_in_B   (valid_in_B_int),
//         .a_B          (a_B_int),
//         .b_B          (b_B_int),
//         .sum_async_B  (sum_async_B),
//         .sum_sync_B   (sum_sync_B)
//     );

// endmodule

regression_results/waves_9.vcd
$version Generated by VerilatedVcd $end
$timescale 1ps $end
 $scope module $rootio $end
  $var wire 1 # clk $end
  $var wire 1 $ rst_A $end
  $var wire 1 % valid_in_A $end
  $var wire 8 & a_A [7:0] $end
  $var wire 8 ' b_A [7:0] $end
  $var wire 9 ( sum_async_A [8:0] $end
  $var wire 9 ) sum_sync_A [8:0] $end
  $var wire 1 * rst_B $end
  $var wire 1 + valid_in_B $end
  $var wire 8 , a_B [7:0] $end
  $var wire 8 - b_B [7:0] $end
  $var wire 9 . sum_async_B [8:0] $end
  $var wire 9 / sum_sync_B [8:0] $end
 $upscope $end
 $scope module dut_wrapper $end
  $var wire 1 0 clk $end
  $var wire 1 1 rst_A $end
  $var wire 1 2 valid_in_A $end
  $var wire 8 3 a_A [7:0] $end
  $var wire 8 4 b_A [7:0] $end
  $var wire 9 5 sum_async_A [8:0] $end
  $var wire 9 6 sum_sync_A [8:0] $end
  $var wire 1 7 rst_B $end
  $var wire 1 8 valid_in_B $end
  $var wire 8 9 a_B [7:0] $end
  $var wire 8 : b_B [7:0] $end
  $var wire 9 ; sum_async_B [8:0] $end
  $var wire 9 < sum_sync_B [8:0] $end
  $scope module u_top_level $end
   $var wire 1 = clk $end
   $var wire 1 > rst_A $end
   $var wire 1 ? valid_in_A $end
   $var wire 8 @ a_A [7:0] $end
   $var wire 8 A b_A [7:0] $end
   $var wire 9 B sum_async_A [8:0] $end
   $var wire 9 C sum_sync_A [8:0] $end
   $var wire 1 D rst_B $end
   $var wire 1 E valid_in_B $end
   $var wire 8 F a_B [7:0] $end
   $var wire 8 G b_B [7:0] $end
   $var wire 9 H sum_async_B [8:0] $end
   $var wire 9 I sum_sync_B [8:0] $end
  $upscope $end
 $upscope $end
$enddefinitions $end


#0
1#
1$
0%
b00000000 &
b00000000 '
b000000000 (
b000000000 )
1*
0+
b00000000 ,
b00000000 -
b000000000 .
b000000000 /
10
11
02
b00000000 3
b00000000 4
b000000000 5
b000000000 6
17
08
b00000000 9
b00000000 :
b000000000 ;
b000000000 <
1=
1>
0?
b00000000 @
b00000000 A
b000000000 B
b000000000 C
1D
0E
b00000000 F
b00000000 G
b000000000 H
b000000000 I
#2021000
00
0=
#5000
1#
10
1=
#7500
0#
00
0=
#10000
1#
10
1=
#12500
0#
00
0=
#15000
1#
10
1=
#17500
0#
00
0=
#20000
1#
0$
1%
b10111001 &
b00011100 '
b011010101 (
0*
10
01
12
b10111001 3
b00011100 4
b011010101 5
07
1=
0>
1?
b10111001 @
b00011100 A
b011010101 B
0D
#22500
0#
00
0=
#25000
1#
b000011100 )
10
b000011100 6
1=
b000011100 C
#26000
0%
1+
b11110010 ,
b11101010 -
b111011100 .
02
18
b11110010 9
b11101010 :
b111011100 ;
0?
1E
b11110010 F
b11101010 G
b111011100 H
#27500
0#
00
0=
#30000
1#
b011101010 /
10
b011101010 <
1=
b011101010 I
#31000
0+
08
0E
#32000
1%
b01011010 &
b00000001 '
b001011011 (
12
b01011010 3
b00000001 4
b001011011 5
1?
b01011010 @
b00000001 A
b001011011 B
#32500
0#
00
0=
#35000
1#
b000011101 )
10
b000011101 6
1=
b000011101 C
#36000
0%
1+
b11111100 ,
b00111100 -
b100111000 .
02
18
b11111100 9
b00111100 :
b100111000 ;
0?
1E
b11111100 F
b00111100 G
b100111000 H
#37500
0#
00
0=
#40000
1#
b100100110 /
10
b100100110 <
1=
b100100110 I
#41000
0+
08
0E
#42000
1%
b10000101 &
b10111100 '
b101000001 (
12
b10000101 3
b10111100 4
b101000001 5
1?
b10000101 @
b10111100 A
b101000001 B
#42500
0#
00
0=
#45000
1#
b011011001 )
10
b011011001 6
1=
b011011001 C
#46000
0%
1+
b11100000 ,
b10111111 -
b110011111 .
02
18
b11100000 9
b10111111 :
b110011111 ;
0?
1E
b11100000 F
b10111111 G
b110011111 H
#47500
0#
00
0=
#50000
1#
b111100101 /
10
b111100101 <
1=
b111100101 I
#51000
0+
08
0E
#52000
1%
b10101111 &
b00101111 '
b011011110 (
12
b10101111 3
b00101111 4
b011011110 5
1?
b10101111 @
b00101111 A
b011011110 B
#52500
0#
00
0=
#55000
1#
b100001000 )
10
b100001000 6
1=
b100001000 C
#56000
0%
1+
b11100111 ,
b11010000 -
b110110111 .
02
18
b11100111 9
b11010000 :
b110110111 ;
0?
1E
b11100111 F
b11010000 G
b110110111 H
#57500
0#
00
0=
#60000
1#
b010110101 /
10
b010110101 <
1=
b010110101 I
#61000
0+
08
0E
#62000
1%
b10101001 &
b01001100 '
b011110101 (
12
b10101001 3
b01001100 4
b011110101 5
1?
b10101001 @
b01001100 A
b011110101 B
#62500
0#
00
0=
#65000
1#
b101010100 )
10
b101010100 6
1=
b101010100 C
#66000
0%
1+
b11000101 ,
b01001011 -
b100010000 .
02
18
b11000101 9
b01001011 :
b100010000 ;
0?
1E
b11000101 F
b01001011 G
b100010000 H
#67500
0#
00
0=
#70000
1#
b100000000 /
10
b100000000 <
1=
b100000000 I
#71000
0+
08
0E
#72000
1%
b00111101 &
b00100000 '
b001011101 (
12
b00111101 3
b00100000 4
b001011101 5
1?
b00111101 @
b00100000 A
b001011101 B
#72500
0#
00
0=
#75000
1#
b101110100 )
10
b101110100 6
1=
b101110100 C
#76000
0%
1+
b00010110 ,
b10110110 -
b011001100 .
02
18
b00010110 9
b10110110 :
b011001100 ;
0?
1E
b00010110 F
b10110110 G
b011001100 H
#77500
0#
00
0=
#80000
1#
b110110110 /
10
b110110110 <
1=
b110110110 I
#81000
0+
08
0E
#82000
1%
b10010111 &
b10111111 '
b101010110 (
12
b10010111 3
b10111111 4
b101010110 5
1?
b10010111 @
b10111111 A
b101010110 B
#82500
0#
00
0=
#85000
1#
b000110011 )
10
b000110011 6
1=
b000110011 C
#86000
0%
1+
b01010011 ,
b10100101 -
b011111000 .
02
18
b01010011 9
b10100101 :
b011111000 ;
0?
1E
b01010011 F
b10100101 G
b011111000 H
#87500
0#
00
0=
#90000
1#
b001011011 /
10
b001011011 <
1=
b001011011 I
#91000
0+
08
0E
#92000
1%
b10000000 &
b00110000 '
b010110000 (
12
b10000000 3
b00110000 4
b010110000 5
1?
b10000000 @
b00110000 A
b010110000 B
#92500
0#
00
0=
#95000
1#
b001100011 )
10
b001100011 6
1=
b001100011 C
#96000
0%
1+
b11010111 ,
b11010100 -
b110101011 .
02
18
b11010111 9
b11010100 :
b110101011 ;
0?
1E
b11010111 F
b11010100 G
b110101011 H
#97500
0#
00
0=
#100000
1#
b100101111 /
10
b100101111 <
1=
b100101111 I
#101000
0+
08
0E
#102000
1%
b10101001 &
b01100111 '
b100010000 (
12
b10101001 3
b01100111 4
b100010000 5
1?
b10101001 @
b01100111 A
b100010000 B
#102500
0#
00
0=
#105000
1#
b011001010 )
10
b011001010 6
1=
b011001010 C
#106000
0%
1+
b01111011 ,
b10110101 -
b100110000 .
02
18
b01111011 9
b10110101 :
b100110000 ;
0?
1E
b01111011 F
b10110101 G
b100110000 H
#107500
0#
00
0=
#110000
1#
b111100100 /
10
b111100100 <
1=
b111100100 I
#111000
0+
08
0E
#112000
1%
b00110000 &
b01101010 '
b010011010 (
12
b00110000 3
b01101010 4
b010011010 5
1?
b00110000 @
b01101010 A
b010011010 B
#112500
0#
00
0=
#115000
1#
b100110100 )
10
b100110100 6
1=
b100110100 C
#116000
0%
1+
b01111111 ,
b00110010 -
b010110001 .
02
18
b01111111 9
b00110010 :
b010110001 ;
0?
1E
b01111111 F
b00110010 G
b010110001 H
#117500
0#
00
0=
#120000
1#
b000010110 /
10
b000010110 <
1=
b000010110 I
#121000
0+
08
0E
#122000
1%
b00010110 &
b00111000 '
b001001110 (
12
b00010110 3
b00111000 4
b001001110 5
1?
b00010110 @
b00111000 A
b001001110 B
#122500
0#
00
0=
#125000
1#
b101101100 )
10
b101101100 6
1=
b101101100 C
#126000
0%
1+
b00011010 ,
b00001000 -
b000100010 .
02
18
b00011010 9
b00001000 :
b000100010 ;
0?
1E
b00011010 F
b00001000 G
b000100010 H
#127500
0#
00
0=
#130000
1#
b000011110 /
10
b000011110 <
1=
b000011110 I
#131000
0+
08
0E
#132000
1%
b00100100 &
b01101100 '
b010010000 (
12
b00100100 3
b01101100 4
b010010000 5
1?
b00100100 @
b01101100 A
b010010000 B
#132500
0#
00
0=
#135000
1#
b111011000 )
10
b111011000 6
1=
b111011000 C
#136000
0%
1+
b00000001 ,
b10000100 -
b010000101 .
02
18
b00000001 9
b10000100 :
b010000101 ;
0?
1E
b00000001 F
b10000100 G
b010000101 H
#137500
0#
00
0=
#140000
1#
b010100010 /
10
b010100010 <
1=
b010100010 I
#141000
0+
08
0E
#142000
1%
b00010011 &
b01001001 '
b001011100 (
12
b00010011 3
b01001001 4
b001011100 5
1?
b00010011 @
b01001001 A
b001011100 B
#142500
0#
00
0=
#145000
1#
b000100001 )
10
b000100001 6
1=
b000100001 C
#146000
0%
1+
b00111111 ,
b10110110 -
b011110101 .
02
18
b00111111 9
b10110110 :
b011110101 ;
0?
1E
b00111111 F
b10110110 G
b011110101 H
#147500
0#
00
0=
#150000
1#
b101011000 /
10
b101011000 <
1=
b101011000 I
#151000
0+
08
0E
#152000
1%
b10100101 &
b01111011 '
b100100000 (
12
b10100101 3
b01111011 4
b100100000 5
1?
b10100101 @
b01111011 A
b100100000 B
#152500
0#
00
0=
#155000
1#
b010011100 )
10
b010011100 6
1=
b010011100 C
#156000
0%
1+
b10010000 ,
b00000000 -
b010010000 .
02
18
b10010000 9
b00000000 :
b010010000 ;
0?
1E
b10010000 F
b00000000 G
b010010000 H
#157500
0#
00
0=
#160000
1#
10
1=
#161000
0+
08
0E
#162000
1%
b00100001 &
b11010110 '
b011110111 (
12
b00100001 3
b11010110 4
b011110111 5
1?
b00100001 @
b11010110 A
b011110111 B
#162500
0#
00
0=
#165000
1#
b101110010 )
10
b101110010 6
1=
b101110010 C
#166000
0%
1+
b11011010 ,
b01010100 -
b100101110 .
02
18
b11011010 9
b01010100 :
b100101110 ;
0?
1E
b11011010 F
b01010100 G
b100101110 H
#167500
0#
00
0=
#170000
1#
b110101100 /
10
b110101100 <
1=
b110101100 I
#171000
0+
08
0E
#172000
1%
b11001100 &
b10100100 '
b101110000 (
12
b11001100 3
b10100100 4
b101110000 5
1?
b11001100 @
b10100100 A
b101110000 B
#172500
0#
00
0=
#175000
1#
b000010110 )
10
b000010110 6
1=
b000010110 C
#176000
0%
1+
b11001111 ,
b01001100 -
b100011011 .
02
18
b11001111 9
b01001100 :
b100011011 ;
0?
1E
b11001111 F
b01001100 G
b100011011 H
#177500
0#
00
0=
#180000
1#
b111111000 /
10
b111111000 <
1=
b111111000 I
#181000
0+
08
0E
#182000
1%
b01111100 &
b10011010 '
b100010110 (
12
b01111100 3
b10011010 4
b100010110 5
1?
b01111100 @
b10011010 A
b100010110 B
#182500
0#
00
0=
#185000
1#
b010110000 )
10
b010110000 6
1=
b010110000 C
#186000
0%
1+
b10000010 ,
b10010100 -
b100010110 .
02
18
b10000010 9
b10010100 :
b100010110 ;
0?
1E
b10000010 F
b10010100 G
b100010110 H
#187500
0#
00
0=
#190000
1#
b010001100 /
10
b010001100 <
1=
b010001100 I
#191000
0+
08
0E
#192000
1%
b00010010 &
b11010110 '
b011101000 (
12
b00010010 3
b11010110 4
b011101000 5
1?
b00010010 @
b11010110 A
b011101000 B
#192500
0#
00
0=
#195000
1#
b110000110 )
10
b110000110 6
1=
b110000110 C
#196000
0%
1+
b10111111 ,
b11101010 -
b110101001 .
02
18
b10111111 9
b11101010 :
b110101001 ;
0?
1E
b10111111 F
b11101010 G
b110101001 H
#197500
0#
00
0=
#200000
1#
b101110110 /
10
b101110110 <
1=
b101110110 I
#201000
0+
08
0E
#202000
1%
b01000111 &
b11001010 '
b100010001 (
12
b01000111 3
b11001010 4
b100010001 5
1?
b01000111 @
b11001010 A
b100010001 B
#202500
0#
00
0=
#205000
1#
b001010000 )
10
b001010000 6
1=
b001010000 C
#206000
0%
1+
b01101111 ,
b00101101 -
b010011100 .
02
18
b01101111 9
b00101101 :
b010011100 ;
0?
1E
b01101111 F
b00101101 G
b010011100 H
#207500
0#
00
0=
#210000
1#
b110100011 /
10
b110100011 <
1=
b110100011 I
#211000
0+
08
0E
#212000
1%
b00000100 &
b00010110 '
b000011010 (
12
b00000100 3
b00010110 4
b000011010 5
1?
b00000100 @
b00010110 A
b000011010 B
#212500
0#
00
0=
#215000
1#
b001100110 )
10
b001100110 6
1=
b001100110 C
#216000
0%
1+
b10001001 ,
b11011101 -
b101100110 .
02
18
b10001001 9
b11011101 :
b101100110 ;
0?
1E
b10001001 F
b11011101 G
b101100110 H
#217500
0#
00
0=
#220000
1#
b010000000 /
10
b010000000 <
1=
b010000000 I
#221000
0+
08
0E
#222000
1%
b01110011 &
b00111001 '
b010101100 (
12
b01110011 3
b00111001 4
b010101100 5
1?
b01110011 @
b00111001 A
b010101100 B
#222500
0#
00
0=
#225000
1#
b010011111 )
10
b010011111 6
1=
b010011111 C
#226000
0%
1+
b00000000 ,
b01010000 -
b001010000 .
02
18
b00000000 9
b01010000 :
b001010000 ;
0?
1E
b00000000 F
b01010000 G
b001010000 H
#227500
0#
00
0=
#230000
1#
b011010000 /
10
b011010000 <
1=
b011010000 I
#231000
0+
08
0E
#232000
1%
b11001010 &
b10101010 '
b101110100 (
12
b11001010 3
b10101010 4
b101110100 5
1?
b11001010 @
b10101010 A
b101110100 B
#232500
0#
00
0=
#235000
1#
b101001001 )
10
b101001001 6
1=
b101001001 C
#236000
0%
1+
b10110000 ,
b11110011 -
b110100011 .
02
18
b10110000 9
b11110011 :
b110100011 ;
0?
1E
b10110000 F
b11110011 G
b110100011 H
#237500
0#
00
0=
#240000
1#
b111000011 /
10
b111000011 <
1=
b111000011 I
#241000
0+
08
0E
#242000
1%
b11110000 &
b00010011 '
b100000011 (
12
b11110000 3
b00010011 4
b100000011 5
1?
b11110000 @
b00010011 A
b100000011 B
#242500
0#
00
0=
#245000
1#
b101011100 )
10
b101011100 6
1=
b101011100 C
#246000
0%
1+
b00110000 ,
b100100011 .
02
18
b00110000 9
b100100011 ;
0?
1E
b00110000 F
b100100011 H
#247500
0#
00
0=
#250000
1#
b010110110 /
10
b010110110 <
1=
b010110110 I
#251000
0+
08
0E
#252000
1%
b11011011 &
b00110000 '
b100001011 (
12
b11011011 3
b00110000 4
b100001011 5
1?
b11011011 @
b00110000 A
b100001011 B
#252500
0#
00
0=
#255000
1#
b110001100 )
10
b110001100 6
1=
b110001100 C
#256000
0%
1+
b01001011 ,
b11000000 -
b100001011 .
02
18
b01001011 9
b11000000 :
b100001011 ;
0?
1E
b01001011 F
b11000000 G
b100001011 H
#257500
0#
00
0=
#260000
1#
b101110110 /
10
b101110110 <
1=
b101110110 I
#261000
0+
08
0E
#262000
1%
b01100110 &
b00110111 '
b010011101 (
12
b01100110 3
b00110111 4
b010011101 5
1?
b01100110 @
b00110111 A
b010011101 B
#262500
0#
00
0=
#265000
1#
b111000011 )
10
b111000011 6
1=
b111000011 C
#266000
0%
1+
b00110010 ,
b00111011 -
b001101101 .
02
18
b00110010 9
b00111011 :
b001101101 ;
0?
1E
b00110010 F
b00111011 G
b001101101 H
#267500
0#
00
0=
#270000
1#
b110110001 /
10
b110110001 <
1=
b110110001 I
#271000
0+
08
0E
#272000
1%
b01001011 &
b11111011 '
b101000110 (
12
b01001011 3
b11111011 4
b101000110 5
1?
b01001011 @
b11111011 A
b101000110 B
#272500
0#
00
0=
#275000
1#
b010111110 )
10
b010111110 6
1=
b010111110 C
#276000
0%
1+
b10100010 ,
b00011101 -
b010111111 .
02
18
b10100010 9
b00011101 :
b010111111 ;
0?
1E
b10100010 F
b00011101 G
b010111111 H
#277500
0#
00
0=
#280000
1#
b111001110 /
10
b111001110 <
1=
b111001110 I
#281000
0+
08
0E
#282000
1%
b00001110 &
b10111000 '
b011000110 (
12
b00001110 3
b10111000 4
b011000110 5
1?
b00001110 @
b10111000 A
b011000110 B
#282500
0#
00
0=
#285000
1#
b101110110 )
10
b101110110 6
1=
b101110110 C
#286000
0%
1+
b10110100 ,
b01110100 -
b100101000 .
02
18
b10110100 9
b01110100 :
b100101000 ;
0?
1E
b10110100 F
b01110100 G
b100101000 H
#287500
0#
00
0=
#290000
1#
b001000010 /
10
b001000010 <
1=
b001000010 I
#291000
0+
08
0E
#292000
1%
b11001001 &
b11001001 '
b110010010 (
12
b11001001 3
b11001001 4
b110010010 5
1?
b11001001 @
b11001001 A
b110010010 B
#292500
0#
00
0=
#295000
1#
b000111111 )
10
b000111111 6
1=
b000111111 C
#296000
0%
1+
b01111011 ,
b11101111 -
b101101010 .
02
18
b01111011 9
b11101111 :
b101101010 ;
0?
1E
b01111011 F
b11101111 G
b101101010 H
#297500
0#
00
0=
#300000
1#
b100110001 /
10
b100110001 <
1=
b100110001 I
#301000
0+
08
0E
#302000
1%
b01100000 &
b00110101 '
b010010101 (
12
b01100000 3
b00110101 4
b010010101 5
1?
b01100000 @
b00110101 A
b010010101 B
#302500
0#
00
0=
#305000
1#
b001110100 )
10
b001110100 6
1=
b001110100 C
#306000
0%
1+
b01101000 ,
b11100111 -
b101001111 .
02
18
b01101000 9
b11100111 :
b101001111 ;
0?
1E
b01101000 F
b11100111 G
b101001111 H
#307500
0#
00
0=
#310000
1#
b000011000 /
10
b000011000 <
1=
b000011000 I
#311000
0+
08
0E
#312000
1%
b00000101 &
b11110000 '
b011110101 (
12
b00000101 3
b11110000 4
b011110101 5
1?
b00000101 @
b11110000 A
b011110101 B
#312500
0#
00
0=
#315000
1#
b101100100 )
10
b101100100 6
1=
b101100100 C
#316000
0%
1+
b01011100 ,
b11010100 -
b100110000 .
02
18
b01011100 9
b11010100 :
b100110000 ;
0?
1E
b01011100 F
b11010100 G
b100110000 H
#317500
0#
00
0=
#320000
1#
b011101100 /
10
b011101100 <
1=
b011101100 I
#321000
0+
08
0E
#322000
1%
b00101010 &
b10010111 '
b011000001 (
12
b00101010 3
b10010111 4
b011000001 5
1?
b00101010 @
b10010111 A
b011000001 B
#322500
0#
00
0=
#325000
1#
b111111011 )
10
b111111011 6
1=
b111111011 C
#326000
0%
1+
b11001000 ,
b00010011 -
b011011011 .
02
18
b11001000 9
b00010011 :
b011011011 ;
0?
1E
b11001000 F
b00010011 G
b011011011 H
#327500
0#
00
0=
#330000
1#
b011111111 /
10
b011111111 <
1=
b011111111 I
#331000
0+
08
0E
#332000
1%
b00000101 &
b11001110 '
b011010011 (
12
b00000101 3
b11001110 4
b011010011 5
1?
b00000101 @
b11001110 A
b011010011 B
#332500
0#
00
0=
#335000
1#
b011001001 )
10
b011001001 6
1=
b011001001 C
#336000
0%
1+
b11000101 ,
b11110000 -
b110110101 .
02
18
b11000101 9
b11110000 :
b110110101 ;
0?
1E
b11000101 F
b11110000 G
b110110101 H
#337500
0#
00
0=
#340000
1#
b111101111 /
10
b111101111 <
1=
b111101111 I
#341000
0+
08
0E
#342000
1%
b11000011 &
b10011011 '
b101011110 (
12
b11000011 3
b10011011 4
b101011110 5
1?
b11000011 @
b10011011 A
b101011110 B
#342500
0#
00
0=
#345000
1#
b101100100 )
10
b101100100 6
1=
b101100100 C
#346000
0%
1+
b10110000 ,
b10011010 -
b101001010 .
02
18
b10110000 9
b10011010 :
b101001010 ;
0?
1E
b10110000 F
b10011010 G
b101001010 H
#347500
0#
00
0=
#350000
1#
b010001001 /
10
b010001001 <
1=
b010001001 I
#351000
0+
08
0E
#352000
1%
b00110100 &
b11010111 '
b100001011 (
12
b00110100 3
b11010111 4
b100001011 5
1?
b00110100 @
b11010111 A
b100001011 B
#352500
0#
00
0=
#355000
1#
b000111011 )
10
b000111011 6
1=
b000111011 C
#356000
0%
1+
b11110011 ,
b00100101 -
b100011000 .
02
18
b11110011 9
b00100101 :
b100011000 ;
0?
1E
b11110011 F
b00100101 G
b100011000 H
#357500
0#
00
0=
#360000
1#
b010101110 /
10
b010101110 <
1=
b010101110 I
#361000
0+
08
0E
#362000
1%
b10110010 &
b00010110 '
b011001000 (
12
b10110010 3
b00010110 4
b011001000 5
1?
b10110010 @
b00010110 A
b011001000 B
#362500
0#
00
0=
#365000
1#
b001010001 )
10
b001010001 6
1=
b001010001 C
#366000
0%
1+
b11001100 ,
b11110000 -
b110111100 .
02
18
b11001100 9
b11110000 :
b110111100 ;
0?
1E
b11001100 F
b11110000 G
b110111100 H
#367500
0#
00
0=
#370000
1#
b110011110 /
10
b110011110 <
1=
b110011110 I
#371000
0+
08
0E
#372000
1%
b10011111 &
b10001010 '
b100101001 (
12
b10011111 3
b10001010 4
b100101001 5
1?
b10011111 @
b10001010 A
b100101001 B
#372500
0#
00
0=
#375000
1#
b011011011 )
10
b011011011 6
1=
b011011011 C
#376000
0%
1+
b11101010 ,
b00101101 -
b100010111 .
02
18
b11101010 9
b00101101 :
b100010111 ;
0?
1E
b11101010 F
b00101101 G
b100010111 H
#377500
0#
00
0=
#380000
1#
b111001011 /
10
b111001011 <
1=
b111001011 I
#381000
0+
08
0E
#382000
1%
b11111100 &
b10011101 '
b110011001 (
12
b11111100 3
b10011101 4
b110011001 5
1?
b11111100 @
b10011101 A
b110011001 B
#382500
0#
00
0=
#385000
1#
b101111000 )
10
b101111000 6
1=
b101111000 C
#386000
0%
1+
b00111100 ,
b01011010 -
b010010110 .
02
18
b00111100 9
b01011010 :
b010010110 ;
0?
1E
b00111100 F
b01011010 G
b010010110 H
#387500
0#
00
0=
#390000
1#
b000100101 /
10
b000100101 <
1=
b000100101 I
#391000
0+
08
0E
#392000
1%
b01101111 &
b11111101 '
b101101100 (
12
b01101111 3
b11111101 4
b101101100 5
1?
b01101111 @
b11111101 A
b101101100 B
#392500
0#
00
0=
#395000
1#
b001110101 )
10
b001110101 6
1=
b001110101 C
#396000
0%
1+
b01010001 ,
b10111111 -
b100010000 .
02
18
b01010001 9
b10111111 :
b100010000 ;
0?
1E
b01010001 F
b10111111 G
b100010000 H
#397500
0#
00
0=
#400000
1#
b011100100 /
10
b011100100 <
1=
b011100100 I
#401000
0+
08
0E
#402000
1%
b10101011 &
b01110100 '
b100011111 (
12
b10101011 3
b01110100 4
b100011111 5
1?
b10101011 @
b01110100 A
b100011111 B
#402500
0#
00
0=
#405000
1#
b011101001 )
10
b011101001 6
1=
b011101001 C
#406000
0%
1+
b01110100 ,
b11001111 -
b101000011 .
02
18
b01110100 9
b11001111 :
b101000011 ;
0?
1E
b01110100 F
b11001111 G
b101000011 H
#407500
0#
00
0=
#410000
1#
b110110011 /
10
b110110011 <
1=
b110110011 I
#411000
0+
08
0E
#412000
1%
b11010111 &
b10010100 '
b101101011 (
12
b11010111 3
b10010100 4
b101101011 5
1?
b11010111 @
b10010100 A
b101101011 B
#412500
0#
00
0=
#415000
1#
b101111101 )
10
b101111101 6
1=
b101111101 C
#416000
0%
1+
b01011110 ,
b10101100 -
b100001010 .
02
18
b01011110 9
b10101100 :
b100001010 ;
0?
1E
b01011110 F
b10101100 G
b100001010 H
#417500
0#
00
0=
#420000
1#
b001011111 /
10
b001011111 <
1=
b001011111 I
#421000
0+
08
0E
#422000
1%
b11101010 &
b00100101 '
b100001111 (
12
b11101010 3
b00100101 4
b100001111 5
1?
b11101010 @
b00100101 A
b100001111 B
#422500
0#
00
0=
#425000
1#
b110100010 )
10
b110100010 6
1=
b110100010 C
#426000
0%
1+
b11101001 ,
b10000110 -
b101101111 .
02
18
b11101001 9
b10000110 :
b101101111 ;
0?
1E
b11101001 F
b10000110 G
b101101111 H
#427500
0#
00
0=
#430000
1#
b011100101 /
10
b011100101 <
1=
b011100101 I
#431000
0+
08
0E
#432000
1%
b11101100 &
b11001010 '
b110110110 (
12
b11101100 3
b11001010 4
b110110110 5
1?
b11101100 @
b11001010 A
b110110110 B
#432500
0#
00
0=
#435000
1#
b001101100 )
10
b001101100 6
1=
b001101100 C
#436000
0%
1+
b00001100 ,
b01001110 -
b001011010 .
02
18
b00001100 9
b01001110 :
b001011010 ;
0?
1E
b00001100 F
b01001110 G
b001011010 H
#437500
0#
00
0=
#440000
1#
b100110011 /
10
b100110011 <
1=
b100110011 I
#441000
0+
08
0E
#442000
1%
b01011011 &
b01111001 '
b011010100 (
12
b01011011 3
b01111001 4
b011010100 5
1?
b01011011 @
b01111001 A
b011010100 B
#442500
0#
00
0=
#445000
1#
b011100101 )
10
b011100101 6
1=
b011100101 C
#446000
0%
1+
b10111101 ,
b01111101 -
b100111010 .
02
18
b10111101 9
b01111101 :
b100111010 ;
0?
1E
b10111101 F
b01111101 G
b100111010 H
#447500
0#
00
0=
#450000
1#
b110110000 /
10
b110110000 <
1=
b110110000 I
#451000
0+
08
0E
#452000
1%
b11110000 &
b00111000 '
b100101000 (
12
b11110000 3
b00111000 4
b100101000 5
1?
b11110000 @
b00111000 A
b100101000 B
#452500
0#
00
0=
#455000
1#
b100011101 )
10
b100011101 6
1=
b100011101 C
#456000
0%
1+
b01000101 ,
b00101001 -
b001101110 .
02
18
b01000101 9
b00101001 :
b001101110 ;
0?
1E
b01000101 F
b00101001 G
b001101110 H
#457500
0#
00
0=
#460000
1#
b111011001 /
10
b111011001 <
1=
b111011001 I
#461000
0+
08
0E
#462000
1%
b10110011 &
b01010111 '
b100001010 (
12
b10110011 3
b01010111 4
b100001010 5
1?
b10110011 @
b01010111 A
b100001010 B
#462500
0#
00
0=
#465000
1#
b101110100 )
10
b101110100 6
1=
b101110100 C
#466000
0%
1+
b01110111 ,
b00001001 -
b010000000 .
02
18
b01110111 9
b00001001 :
b010000000 ;
0?
1E
b01110111 F
b00001001 G
b010000000 H
#467500
0#
00
0=
#470000
1#
b111100010 /
10
b111100010 <
1=
b111100010 I
