rtl/top_level.sv


module top_level (
    input  logic       clk,

    // Channel A
    input  logic       rst_A,
    input  logic       valid_in_A,
    input  logic [7:0] a_A,
    input  logic [7:0] b_A,
    output logic [8:0] sum_async_A,
    output logic [8:0] sum_sync_A,

    // Channel B
    input  logic       rst_B,
    input  logic       valid_in_B,
    input  logic [7:0] a_B,
    input  logic [7:0] b_B,
    output logic [8:0] sum_async_B,
    output logic [8:0] sum_sync_B
);

    // Channel A synchronous accumulator
    always_ff @(posedge clk) begin
        if (rst_A)
            sum_sync_A <= '0;
        else if (valid_in_A)
            sum_sync_A <= sum_sync_A + b_A;
    end

    assign sum_async_A = a_A + b_A;

    // Channel B synchronous accumulator
    always_ff @(posedge clk) begin
        if (rst_B)
            sum_sync_B <= '0;
        else if (valid_in_B)
            sum_sync_B <= sum_sync_B + b_B;
    end

    assign sum_async_B = a_B + b_B;

    initial begin
        $display("Time | rst_A| valid_in_A | a_A | b_A |sum_async_A | sum_sync_A |rst_B | valid_in_B| a_B | b_B  | sum_async_B | sum_sync_B   ");
        $monitor("%4t  |  %b  |  %b        | %0d | %0d |    %0d     |   %0d      | %b   |    %b     | %0d | %0d  |    %0d      |   %0d ",
                 $time, rst_A, valid_in_A, a_A, b_A, sum_async_A,sum_sync_A, rst_B, valid_in_B, a_B, b_B, sum_async_B, sum_sync_B);
    end

    initial begin
        $dumpfile("dump.vcd");
        $dumpvars(1, top_level.sv);
    end

endmodule

rtl/dut_wrapper.sv
module dut_wrapper (
    input  logic       clk,

    // Channel A – cocotb drives these
    input  logic       rst_A,
    input  logic       valid_in_A,
    input  logic [7:0] a_A,
    input  logic [7:0] b_A,

    // DUT drives these
    output logic [8:0] sum_async_A,
    output logic [8:0] sum_sync_A,

    // Channel B (if needed)
    input  logic       rst_B,
    input  logic       valid_in_B,
    input  logic [7:0] a_B,
    input  logic [7:0] b_B,
    output logic [8:0] sum_async_B,
    output logic [8:0] sum_sync_B
);

    top_level u_top_level (
        .clk(clk),

        // Channel A
        .rst_A(rst_A),
        .valid_in_A(valid_in_A),
        .a_A(a_A),
        .b_A(b_A),
        .sum_async_A(sum_async_A),
        .sum_sync_A(sum_sync_A),

        // Channel B
        .rst_B(rst_B),
        .valid_in_B(valid_in_B),
        .a_B(a_B),
        .b_B(b_B),
        .sum_async_B(sum_async_B),
        .sum_sync_B(sum_sync_B)
    );

endmodule



// module dut_wrapper (
//     input  logic       clk,

//     // Channel A – exposed directly for cocotb
//     output logic       rst_A,
//     output logic       valid_in_A,
//     output logic [7:0] a_A,
//     output logic [7:0] b_A,
//     output logic [8:0] sum_async_A,
//     output logic [8:0] sum_sync_A,

//     // Channel B – exposed directly for cocotb
//     output logic       rst_B,
//     output logic       valid_in_B,
//     output logic [7:0] a_B,
//     output logic [7:0] b_B,
//     output logic [8:0] sum_async_B,
//     output logic [8:0] sum_sync_B
// );

//     // Internal wires driven by cocotb (use these as DUT inputs)
//     logic rst_A_int;
//     logic valid_in_A_int;
//     logic [7:0] a_A_int;
//     logic [7:0] b_A_int;

//     logic rst_B_int;
//     logic valid_in_B_int;
//     logic [7:0] a_B_int;
//     logic [7:0] b_B_int;

//     // Connect exposed ports to internal wires so cocotb can drive them
//     assign rst_A       = rst_A_int;
//     assign valid_in_A  = valid_in_A_int;
//     assign a_A         = a_A_int;
//     assign b_A         = b_A_int;

//     assign rst_B       = rst_B_int;
//     assign valid_in_B  = valid_in_B_int;
//     assign a_B         = a_B_int;
//     assign b_B         = b_B_int;

//     // DUT instance
//     top_level u_top_level (
//         .clk          (clk),

//         // Channel A
//         .rst_A        (rst_A_int),
//         .valid_in_A   (valid_in_A_int),
//         .a_A          (a_A_int),
//         .b_A          (b_A_int),
//         .sum_async_A  (sum_async_A),
//         .sum_sync_A   (sum_sync_A),

//         // Channel B
//         .rst_B        (rst_B_int),
//         .valid_in_B   (valid_in_B_int),
//         .a_B          (a_B_int),
//         .b_B          (b_B_int),
//         .sum_async_B  (sum_async_B),
//         .sum_sync_B   (sum_sync_B)
//     );

// endmodule

regression_results/waves_10.vcd
$version Generated by VerilatedVcd $end
$timescale 1ps $end
 $scope module $rootio $end
  $var wire 1 # clk $end
  $var wire 1 $ rst_A $end
  $var wire 1 % valid_in_A $end
  $var wire 8 & a_A [7:0] $end
  $var wire 8 ' b_A [7:0] $end
  $var wire 9 ( sum_async_A [8:0] $end
  $var wire 9 ) sum_sync_A [8:0] $end
  $var wire 1 * rst_B $end
  $var wire 1 + valid_in_B $end
  $var wire 8 , a_B [7:0] $end
  $var wire 8 - b_B [7:0] $end
  $var wire 9 . sum_async_B [8:0] $end
  $var wire 9 / sum_sync_B [8:0] $end
 $upscope $end
 $scope module dut_wrapper $end
  $var wire 1 0 clk $end
  $var wire 1 1 rst_A $end
  $var wire 1 2 valid_in_A $end
  $var wire 8 3 a_A [7:0] $end
  $var wire 8 4 b_A [7:0] $end
  $var wire 9 5 sum_async_A [8:0] $end
  $var wire 9 6 sum_sync_A [8:0] $end
  $var wire 1 7 rst_B $end
  $var wire 1 8 valid_in_B $end
  $var wire 8 9 a_B [7:0] $end
  $var wire 8 : b_B [7:0] $end
  $var wire 9 ; sum_async_B [8:0] $end
  $var wire 9 < sum_sync_B [8:0] $end
  $scope module u_top_level $end
   $var wire 1 = clk $end
   $var wire 1 > rst_A $end
   $var wire 1 ? valid_in_A $end
   $var wire 8 @ a_A [7:0] $end
   $var wire 8 A b_A [7:0] $end
   $var wire 9 B sum_async_A [8:0] $end
   $var wire 9 C sum_sync_A [8:0] $end
   $var wire 1 D rst_B $end
   $var wire 1 E valid_in_B $end
   $var wire 8 F a_B [7:0] $end
   $var wire 8 G b_B [7:0] $end
   $var wire 9 H sum_async_B [8:0] $end
   $var wire 9 I sum_sync_B [8:0] $end
  $upscope $end
 $upscope $end
$enddefinitions $end


#0
1#
0$
0%
b00000000 &
b00000000 '
b000000000 (
b000000000 )
1*
0+
b00000000 ,
b00000000 -
b000000000 .
b000000000 /
10
01
02
b00000000 3
b00000000 4
b000000000 5
b000000000 6
17
08
b00000000 9
b00000000 :
b000000000 ;
b000000000 <
1=
0>
0?
b00000000 @
b00000000 A
b000000000 B
b000000000 C
1D
0E
b00000000 F
b00000000 G
b000000000 H
b000000000 I
#10350000
0
0=
#10000
1#
0*
10
07
1=
0D
#15000
0#
00
0=
#20000
1#
10
1=
#25000
0#
00
0=
#30000
1#
10
1=
#32000
b00100011 &
b01111010 '
b010011101 (
b00100011 3
b01111010 4
b010011101 5
b00100011 @
b01111010 A
b010011101 B
#35000
0#
00
0=
#40000
1#
10
1=
#41000
1+
b10101010 ,
b00111100 -
b011100110 .
18
b10101010 9
b00111100 :
b011100110 ;
1E
b10101010 F
b00111100 G
b011100110 H
#45000
0#
00
0=
#50000
1#
b000111100 /
10
b000111100 <
1=
b000111100 I
#51000
0+
08
0E
#52000
1%
b01011100 &
b01011001 '
b010110101 (
12
b01011100 3
b01011001 4
b010110101 5
1?
b01011100 @
b01011001 A
b010110101 B
#55000
0#
00
0=
#60000
1#
b001011001 )
10
b001011001 6
1=
b001011001 C
#61000
0%
b10111100 ,
b11001000 -
b110000100 .
02
b10111100 9
b11001000 :
b110000100 ;
0?
b10111100 F
b11001000 G
b110000100 H
#65000
0#
00
0=
#70000
1#
10
1=
#72000
1%
b00100000 &
b10111010 '
b011011010 (
12
b00100000 3
b10111010 4
b011011010 5
1?
b00100000 @
b10111010 A
b011011010 B
#75000
0#
00
0=
#80000
1#
b100010011 )
10
b100010011 6
1=
b100010011 C
#81000
0%
1+
b11110000 ,
b10111101 -
b110101101 .
02
18
b11110000 9
b10111101 :
b110101101 ;
0?
1E
b11110000 F
b10111101 G
b110101101 H
#85000
0#
00
0=
#90000
1#
b011111001 /
10
b011111001 <
1=
b011111001 I
#91000
0+
08
0E
#92000
1%
b11111110 &
b01001011 '
b101001001 (
12
b11111110 3
b01001011 4
b101001001 5
1?
b11111110 @
b01001011 A
b101001001 B
#95000
0#
00
0=
#100000
1#
b101011110 )
10
b101011110 6
1=
b101011110 C
#101000
0%
b11010011 ,
b11110101 -
b111001000 .
02
b11010011 9
b11110101 :
b111001000 ;
0?
b11010011 F
b11110101 G
b111001000 H
#105000
0#
00
0=
#110000
1#
10
1=
#112000
b00111101 &
b11111111 '
b100111100 (
b00111101 3
b11111111 4
b100111100 5
b00111101 @
b11111111 A
b100111100 B
#115000
0#
00
0=
#120000
1#
10
1=
#121000
b10111010 ,
b11010000 -
b110001010 .
b10111010 9
b11010000 :
b110001010 ;
b10111010 F
b11010000 G
b110001010 H
#125000
0#
00
0=
#130000
1#
10
1=
#132000
b10111010 &
b01011111 '
b100011001 (
b10111010 3
b01011111 4
b100011001 5
b10111010 @
b01011111 A
b100011001 B
#135000
0#
00
0=
#140000
1#
10
1=
#141000
1+
b10001111 ,
b10001111 -
b100011110 .
18
b10001111 9
b10001111 :
b100011110 ;
1E
b10001111 F
b10001111 G
b100011110 H
#145000
0#
00
0=
#150000
1#
b110001000 /
10
b110001000 <
1=
b110001000 I
#151000
0+
08
0E
#152000
1%
b00100001 &
b01001101 '
b001101110 (
12
b00100001 3
b01001101 4
b001101110 5
1?
b00100001 @
b01001101 A
b001101110 B
#155000
0#
00
0=
#160000
1#
b110101011 )
10
b110101011 6
1=
b110101011 C
#161000
0%
b00001110 ,
b00110001 -
b000111111 .
02
b00001110 9
b00110001 :
b000111111 ;
0?
b00001110 F
b00110001 G
b000111111 H
#165000
0#
00
0=
#170000
1#
10
1=
#172000
b01110000 &
b10011110 '
b100001110 (
b01110000 3
b10011110 4
b100001110 5
b01110000 @
b10011110 A
b100001110 B
#175000
0#
00
0=
#180000
1#
10
1=
#181000
b00010000 ,
b10111000 -
b011001000 .
b00010000 9
b10111000 :
b011001000 ;
b00010000 F
b10111000 G
b011001000 H
#185000
0#
00
0=
#190000
1#
10
1=
#192000
1%
b00010000 &
b10101011 '
b010111011 (
12
b00010000 3
b10101011 4
b010111011 5
1?
b00010000 @
b10101011 A
b010111011 B
#195000
0#
00
0=
#200000
1#
b001010110 )
10
b001010110 6
1=
b001010110 C
#201000
0%
b01110010 ,
b11101001 -
b101011011 .
02
b01110010 9
b11101001 :
b101011011 ;
0?
b01110010 F
b11101001 G
b101011011 H
#205000
0#
00
0=
#210000
1#
10
1=
#212000
1%
b01000101 &
b10100111 '
b011101100 (
12
b01000101 3
b10100111 4
b011101100 5
1?
b01000101 @
b10100111 A
b011101100 B
#215000
0#
00
0=
#220000
1#
b011111101 )
10
b011111101 6
1=
b011111101 C
#221000
0%
1+
b01010010 ,
b01110100 -
b011000110 .
02
18
b01010010 9
b01110100 :
b011000110 ;
0?
1E
b01010010 F
b01110100 G
b011000110 H
#225000
0#
00
0=
#230000
1#
b111111100 /
10
b111111100 <
1=
b111111100 I
#231000
0+
08
0E
#232000
1%
b11000011 &
b01010101 '
b100011000 (
12
b11000011 3
b01010101 4
b100011000 5
1?
b11000011 @
b01010101 A
b100011000 B
#235000
0#
00
0=
#240000
1#
b101010010 )
10
b101010010 6
1=
b101010010 C
#241000
0%
b10101111 ,
b01001011 -
b011111010 .
02
b10101111 9
b01001011 :
b011111010 ;
0?
b10101111 F
b01001011 G
b011111010 H
#245000
0#
00
0=
#250000
1#
10
1=
#252000
1%
b01100110 &
b10111001 '
b100011111 (
12
b01100110 3
b10111001 4
b100011111 5
1?
b01100110 @
b10111001 A
b100011111 B
#255000
0#
00
0=
#260000
1#
b000001011 )
10
b000001011 6
1=
b000001011 C
#261000
0%
b01010010 ,
b00100111 -
b001111001 .
02
b01010010 9
b00100111 :
b001111001 ;
0?
b01010010 F
b00100111 G
b001111001 H
#265000
0#
00
0=
#270000
1#
10
1=
#272000
b01000110 &
b00011011 '
b001100001 (
b01000110 3
b00011011 4
b001100001 5
b01000110 @
b00011011 A
b001100001 B
#275000
0#
00
0=
#280000
1#
10
1=
#281000
1+
b10011100 ,
b11001101 -
b101101001 .
18
b10011100 9
b11001101 :
b101101001 ;
1E
b10011100 F
b11001101 G
b101101001 H
#285000
0#
00
0=
#290000
1#
b011001001 /
10
b011001001 <
1=
b011001001 I
#291000
0+
08
0E
#292000
1%
b00111100 &
b11010111 '
b100010011 (
12
b00111100 3
b11010111 4
b100010011 5
1?
b00111100 @
b11010111 A
b100010011 B
#295000
0#
00
0=
#300000
1#
b011100010 )
10
b011100010 6
1=
b011100010 C
#301000
0%
b01110101 ,
b10010011 -
b100001000 .
02
b01110101 9
b10010011 :
b100001000 ;
0?
b01110101 F
b10010011 G
b100001000 H
#305000
0#
00
0=
#310000
1#
10
1=
#312000
1%
b00110001 &
b11100100 '
b100010101 (
12
b00110001 3
b11100100 4
b100010101 5
1?
b00110001 @
b11100100 A
b100010101 B
#315000
0#
00
0=
#320000
1#
b111000110 )
10
b111000110 6
1=
b111000110 C
#321000
0%
b10100111 ,
b00110101 -
b011011100 .
02
b10100111 9
b00110101 :
b011011100 ;
0?
b10100111 F
b00110101 G
b011011100 H
#325000
0#
00
0=
#330000
1#
10
1=
#332000
b01001101 &
b01011000 '
b010100101 (
b01001101 3
b01011000 4
b010100101 5
b01001101 @
b01011000 A
b010100101 B
#335000
0#
00
0=
#340000
1#
10
1=
#341000
1+
b11010101 ,
b11000100 -
b110011001 .
18
b11010101 9
b11000100 :
b110011001 ;
1E
b11010101 F
b11000100 G
b110011001 H
#345000
0#
00
0=
#350000
1#
b110001101 /
10
b110001101 <
1=
b110001101 I
#351000
0+
08
0E
#352000
1%
b01000001 &
b10101110 '
b011101111 (
12
b01000001 3
b10101110 4
b011101111 5
1?
b01000001 @
b10101110 A
b011101111 B
#355000
0#
00
0=
#360000
1#
b001110100 )
10
b001110100 6
1=
b001110100 C
#361000
0%
b00101011 ,
b01011110 -
b010001001 .
02
b00101011 9
b01011110 :
b010001001 ;
0?
b00101011 F
b01011110 G
b010001001 H
#365000
0#
00
0=
#370000
1#
10
1=
#372000
b01011111 &
b01111000 '
b011010111 (
b01011111 3
b01111000 4
b011010111 5
b01011111 @
b01111000 A
b011010111 B
#375000
0#
00
0=
#380000
1#
10
1=
#381000
1+
b00000010 ,
b01001101 -
b001001111 .
18
b00000010 9
b01001101 :
b001001111 ;
1E
b00000010 F
b01001101 G
b001001111 H
#385000
0#
00
0=
#390000
1#
b111011010 /
10
b111011010 <
1=
b111011010 I
#391000
0+
08
0E
#392000
b01011010 &
b10001111 '
b011101001 (
b01011010 3
b10001111 4
b011101001 5
b01011010 @
b10001111 A
b011101001 B
#395000
0#
00
0=
#400000
1#
10
1=
#401000
b11100100 ,
b11111001 -
b111011101 .
b11100100 9
b11111001 :
b111011101 ;
b11100100 F
b11111001 G
b111011101 H
#405000
0#
00
0=
#410000
1#
10
1=
#412000
b00000001 &
b10110010 '
b010110011 (
b00000001 3
b10110010 4
b010110011 5
b00000001 @
b10110010 A
b010110011 B
#415000
0#
00
0=
#420000
1#
10
1=
#421000
1+
b10010110 ,
b11010111 -
b101101101 .
18
b10010110 9
b11010111 :
b101101101 ;
1E
b10010110 F
b11010111 G
b101101101 H
#425000
0#
00
0=
#430000
1#
b010110001 /
10
b010110001 <
1=
b010110001 I
#431000
0+
08
0E
#432000
1%
b11010001 &
b10111010 '
b110001011 (
12
b11010001 3
b10111010 4
b110001011 5
1?
b11010001 @
b10111010 A
b110001011 B
#435000
0#
00
0=
#440000
1#
b100101110 )
10
b100101110 6
1=
b100101110 C
#441000
0%
b11011010 ,
b01100010 -
b100111100 .
02
b11011010 9
b01100010 :
b100111100 ;
0?
b11011010 F
b01100010 G
b100111100 H
#445000
0#
00
0=
#450000
1#
10
1=
#452000
b10000000 &
b10111101 '
b100111101 (
b10000000 3
b10111101 4
b100111101 5
b10000000 @
b10111101 A
b100111101 B
#455000
0#
00
0=
#460000
1#
10
1=
#461000
1+
b11110101 ,
b10101001 -
b110011110 .
18
b11110101 9
b10101001 :
b110011110 ;
1E
b11110101 F
b10101001 G
b110011110 H
#465000
0#
00
0=
#470000
1#
b101011010 /
10
b101011010 <
1=
b101011010 I
#471000
0+
08
0E
#472000
b01010110 &
b00010000 '
b001100110 (
b01010110 3
b00010000 4
b001100110 5
b01010110 @
b00010000 A
b001100110 B
#475000
0#
00
0=
#480000
1#
10
1=
#481000
1+
b11100010 ,
b11001100 -
b110101110 .
18
b11100010 9
b11001100 :
b110101110 ;
1E
b11100010 F
b11001100 G
b110101110 H
#485000
0#
00
0=
#490000
1#
b000100110 /
10
b000100110 <
1=
b000100110 I
#491000
0+
08
0E
#492000
b10100000 &
b11101011 '
b110001011 (
b10100000 3
b11101011 4
b110001011 5
b10100000 @
b11101011 A
b110001011 B
#495000
0#
00
0=
#500000
1#
10
1=
#501000
b00011000 ,
b10001100 -
b010100100 .
b00011000 9
b10001100 :
b010100100 ;
b00011000 F
b10001100 G
b010100100 H
#505000
0#
00
0=
#510000
1#
10
1=
#512000
1%
b00000101 &
b11101000 '
b011101101 (
12
b00000101 3
b11101000 4
b011101101 5
1?
b00000101 @
b11101000 A
b011101101 B
#515000
0#
00
0=
#520000
1#
b000010110 )
10
b000010110 6
1=
b000010110 C
#521000
0%
1+
b00011011 ,
b01111110 -
b010011001 .
02
18
b00011011 9
b01111110 :
b010011001 ;
0?
1E
b00011011 F
b01111110 G
b010011001 H
#525000
0#
00
0=
#530000
1#
b010100100 /
10
b010100100 <
1=
b010100100 I
#531000
0+
08
0E
#532000
1%
b10100011 &
b11110111 '
b110011010 (
12
b10100011 3
b11110111 4
b110011010 5
1?
b10100011 @
b11110111 A
b110011010 B
#535000
0#
00
0=
#540000
1#
b100001101 )
10
b100001101 6
1=
b100001101 C
#541000
0%
1+
b10001001 ,
b11010000 -
b101011001 .
02
18
b10001001 9
b11010000 :
b101011001 ;
0?
1E
b10001001 F
b11010000 G
b101011001 H
#545000
0#
00
0=
#550000
1#
b101110100 /
10
b101110100 <
1=
b101110100 I
#551000
0+
08
0E
#552000
1%
b00101011 &
b00000010 '
b000101101 (
12
b00101011 3
b00000010 4
b000101101 5
1?
b00101011 @
b00000010 A
b000101101 B
#555000
0#
00
0=
#560000
1#
b100001111 )
10
b100001111 6
1=
b100001111 C
#561000
0%
1+
b01001000 ,
b10101001 -
b011110001 .
02
18
b01001000 9
b10101001 :
b011110001 ;
0?
1E
b01001000 F
b10101001 G
b011110001 H
#565000
0#
00
0=
#570000
1#
b000011101 /
10
b000011101 <
1=
b000011101 I
#571000
0+
08
0E
#572000
b10111111 &
b01011011 '
b100011010 (
b10111111 3
b01011011 4
b100011010 5
b10111111 @
b01011011 A
b100011010 B
#575000
0#
00
0=
#580000
1#
10
1=
#581000
1+
b01010010 ,
b01010101 -
b010100111 .
18
b01010010 9
b01010101 :
b010100111 ;
1E
b01010010 F
b01010101 G
b010100111 H
#585000
0#
00
0=
#590000
1#
b001110010 /
10
b001110010 <
1=
b001110010 I
#591000
0+
08
0E
#592000
b01001000 &
b11001000 '
b100010000 (
b01001000 3
b11001000 4
b100010000 5
b01001000 @
b11001000 A
b100010000 B
#595000
0#
00
0=
#600000
1#
10
1=
#601000
1+
b00011101 ,
b11101111 -
b100001100 .
18
b00011101 9
b11101111 :
b100001100 ;
1E
b00011101 F
b11101111 G
b100001100 H
#605000
0#
00
0=
#610000
1#
b101100001 /
10
b101100001 <
1=
b101100001 I
#611000
0+
08
0E
#612000
b11001110 &
b10101100 '
b101111010 (
b11001110 3
b10101100 4
b101111010 5
b11001110 @
b10101100 A
b101111010 B
#615000
0#
00
0=
#620000
1#
10
1=
#621000
1+
b10011110 ,
b10001010 -
b100101000 .
18
b10011110 9
b10001010 :
b100101000 ;
1E
b10011110 F
b10001010 G
b100101000 H
#625000
0#
00
0=
#630000
1#
b111101011 /
10
b111101011 <
1=
b111101011 I
#631000
0+
08
0E
#632000
b11101010 &
b00101000 '
b100010010 (
b11101010 3
b00101000 4
b100010010 5
b11101010 @
b00101000 A
b100010010 B
#635000
0#
00
0=
#640000
1#
10
1=
#641000
1+
b10001000 ,
b10011111 -
b100100111 .
18
b10001000 9
b10011111 :
b100100111 ;
1E
b10001000 F
b10011111 G
b100100111 H
#645000
0#
00
0=
#650000
1#
b010001010 /
10
b010001010 <
1=
b010001010 I
#651000
0+
08
0E
#652000
1%
b00100111 &
b11111010 '
b100100001 (
12
b00100111 3
b11111010 4
b100100001 5
1?
b00100111 @
b11111010 A
b100100001 B
#655000
0#
00
0=
#660000
1#
b000001001 )
10
b000001001 6
1=
b000001001 C
#661000
0%
1+
b00101011 ,
b01111110 -
b010101001 .
02
18
b00101011 9
b01111110 :
b010101001 ;
0?
1E
b00101011 F
b01111110 G
b010101001 H
#665000
0#
00
0=
#670000
1#
b100001000 /
10
b100001000 <
1=
b100001000 I
#671000
0+
08
0E
#672000
1%
b10100111 &
b10011101 '
b101000100 (
12
b10100111 3
b10011101 4
b101000100 5
1?
b10100111 @
b10011101 A
b101000100 B
#675000
0#
00
0=
#680000
1#
b010100110 )
10
b010100110 6
1=
b010100110 C
#681000
0%
1+
b10001110 ,
b01110111 -
b100000101 .
02
18
b10001110 9
b01110111 :
b100000101 ;
0?
1E
b10001110 F
b01110111 G
b100000101 H
#685000
0#
00
0=
#690000
1#
b101111111 /
10
b101111111 <
1=
b101111111 I
#691000
0+
08
0E
#692000
b00100110 &
b00000111 '
b000101101 (
b00100110 3
b00000111 4
b000101101 5
b00100110 @
b00000111 A
b000101101 B
#695000
0#
00
0=
#700000
1#
10
1=
#701000
b10000000 ,
b01001000 -
b011001000 .
b10000000 9
b01001000 :
b011001000 ;
b10000000 F
b01001000 G
b011001000 H
#705000
0#
00
0=
#710000
1#
10
1=
#712000
1%
b00101011 &
b00110010 '
b001011101 (
12
b00101011 3
b00110010 4
b001011101 5
1?
b00101011 @
b00110010 A
b001011101 B
#715000
0#
00
0=
#720000
1#
b011011000 )
10
b011011000 6
1=
b011011000 C
#721000
0%
b10010100 ,
b11001011 -
b101011111 .
02
b10010100 9
b11001011 :
b101011111 ;
0?
b10010100 F
b11001011 G
b101011111 H
#725000
0#
00
0=
#730000
1#
10
1=
#732000
1%
b00010010 &
b10010111 '
b010101001 (
12
b00010010 3
b10010111 4
b010101001 5
1?
b00010010 @
b10010111 A
b010101001 B
#735000
0#
00
0=
#740000
1#
b101101111 )
10
b101101111 6
1=
b101101111 C
#741000
0%
1+
b11101001 ,
b11001110 -
b110110111 .
02
18
b11101001 9
b11001110 :
b110110111 ;
0?
1E
b11101001 F
b11001110 G
b110110111 H
#745000
0#
00
0=
#750000
1#
b001001101 /
10
b001001101 <
1=
b001001101 I
#751000
0+
08
0E
#752000
b10001111 &
b00011101 '
b010101100 (
b10001111 3
b00011101 4
b010101100 5
b10001111 @
b00011101 A
b010101100 B
#755000
0#
00
0=
#760000
1#
10
1=
#761000
b01001011 ,
b00010100 -
b001011111 .
b01001011 9
b00010100 :
b001011111 ;
b01001011 F
b00010100 G
b001011111 H
#765000
0#
00
0=
#770000
1#
10
1=
#772000
b01111001 &
b11010011 '
b101001100 (
b01111001 3
b11010011 4
b101001100 5
b01111001 @
b11010011 A
b101001100 B
#775000
0#
00
0=
#780000
1#
10
1=
#781000
1+
b11010100 ,
b10001010 -
b101011110 .
18
b11010100 9
b10001010 :
b101011110 ;
1E
b11010100 F
b10001010 G
b101011110 H
#785000
0#
00
0=
#790000
1#
b011010111 /
10
b011010111 <
1=
b011010111 I
#791000
0+
08
0E
#792000
1%
b11010010 &
b10001101 '
b101011111 (
12
b11010010 3
b10001101 4
b101011111 5
1?
b11010010 @
b10001101 A
b101011111 B
#795000
0#
00
0=
#800000
1#
b111111100 )
10
b111111100 6
1=
b111111100 C
#801000
0%
b10101001 ,
b10110000 -
b101011001 .
02
b10101001 9
b10110000 :
b101011001 ;
0?
b10101001 F
b10110000 G
b101011001 H
#805000
0#
00
0=
#810000
1#
10
1=
#812000
b11110010 &
b10000001 '
b101110011 (
b11110010 3
b10000001 4
b101110011 5
b11110010 @
b10000001 A
b101110011 B
#815000
0#
00
0=
#820000
1#
10
1=
#821000
b00010001 ,
b01100110 -
b001110111 .
b00010001 9
b01100110 :
b001110111 ;
b00010001 F
b01100110 G
b001110111 H
#825000
0#
00
0=
#830000
1#
10
1=
#831000
1*
b00000000 ,
b00000000 -
b000000000 .
17
b00000000 9
b00000000 :
b000000000 ;
1D
b00000000 F
b00000000 G
b000000000 H
#835000
0#
00
0=
#840000
1#
0*
b000000000 /
10
07
b000000000 <
1=
0D
b000000000 I
#841000
b01110110 &
b01001100 '
b011000010 (
b01110110 3
b01001100 4
b011000010 5
b01110110 @
b01001100 A
b011000010 B
#845000
0#
00
0=
#850000
1#
10
1=
#851000
1+
b00000100 ,
b11100111 -
b011101011 .
18
b00000100 9
b11100111 :
b011101011 ;
1E
b00000100 F
b11100111 G
b011101011 H
#855000
0#
00
0=
#860000
1#
b011100111 /
10
b011100111 <
1=
b011100111 I
#861000
0+
08
0E
#862000
b11110101 &
b11011011 '
b111010000 (
b11110101 3
b11011011 4
b111010000 5
b11110101 @
b11011011 A
b111010000 B
#865000
0#
00
0=
#870000
1#
10
1=
#871000
1+
b01011110 ,
b01110010 -
b011010000 .
18
b01011110 9
b01110010 :
b011010000 ;
1E
b01011110 F
b01110010 G
b011010000 H
#875000
0#
00
0=
#880000
1#
b101011001 /
10
b101011001 <
1=
b101011001 I
#881000
0+
08
0E
#882000
1%
b11001011 &
b01010011 '
b100011110 (
12
b11001011 3
b01010011 4
b100011110 5
1?
b11001011 @
b01010011 A
b100011110 B
#885000
0#
00
0=
#890000
1#
b001001111 )
10
b001001111 6
1=
b001001111 C
#891000
0%
1+
b10000111 ,
b11001111 -
b101010110 .
02
18
b10000111 9
b11001111 :
b101010110 ;
0?
1E
b10000111 F
b11001111 G
b101010110 H
#895000
0#
00
0=
#900000
1#
b000101000 /
10
b000101000 <
1=
b000101000 I
#901000
0+
08
0E
#902000
b01000001 &
b10000100 '
b011000101 (
b01000001 3
b10000100 4
b011000101 5
b01000001 @
b10000100 A
b011000101 B
#905000
0#
00
0=
#910000
1#
10
1=
#911000
b11110110 ,
b00100000 -
b100010110 .
b11110110 9
b00100000 :
b100010110 ;
b11110110 F
b00100000 G
b100010110 H
#915000
0#
00
0=
#920000
1#
10
1=
#922000
1%
b10000100 &
b11011011 '
b101011111 (
12
b10000100 3
b11011011 4
b101011111 5
1?
b10000100 @
b11011011 A
b101011111 B
#925000
0#
00
0=
#930000
1#
b100101010 )
10
b100101010 6
1=
b100101010 C
#931000
0%
1+
b10101100 ,
b11011110 -
b110001010 .
02
18
b10101100 9
b11011110 :
b110001010 ;
0?
1E
b10101100 F
b11011110 G
b110001010 H
#935000
0#
00
0=
#940000
1#
b100000110 /
10
b100000110 <
1=
b100000110 I
#941000
0+
08
0E
#942000
1%
b01101100 &
b11001000 '
b100110100 (
12
b01101100 3
b11001000 4
b100110100 5
1?
b01101100 @
b11001000 A
b100110100 B
#945000
0#
00
0=
#950000
1#
b111110010 )
10
b111110010 6
1=
b111110010 C
#951000
0%
1+
b10000011 ,
b01110011 -
b011110110 .
02
18
b10000011 9
b01110011 :
b011110110 ;
0?
1E
b10000011 F
b01110011 G
b011110110 H
#955000
0#
00
0=
#960000
1#
b101111001 /
10
b101111001 <
1=
b101111001 I
#961000
0+
08
0E
#962000
b00000111 &
b00101111 '
b000110110 (
b00000111 3
b00101111 4
b000110110 5
b00000111 @
b00101111 A
b000110110 B
#965000
0#
00
0=
#970000
1#
10
1=
#971000
b00000001 ,
b10111010 -
b010111011 .
b00000001 9
b10111010 :
b010111011 ;
b00000001 F
b10111010 G
b010111011 H
#975000
0#
00
0=
#980000
1#
10
1=
#982000
b01110011 &
b10000100 '
b011110111 (
b01110011 3
b10000100 4
b011110111 5
b01110011 @
b10000100 A
b011110111 B
#985000
0#
00
0=
#990000
1#
10
1=
#991000
1+
b00111101 ,
b10010101 -
b011010010 .
18
b00111101 9
b10010101 :
b011010010 ;
1E
b00111101 F
b10010101 G
b011010010 H
#995000
0#
00
0=
#1000000
1#
b000001110 /
10
b000001110 <
1=
b000001110 I
#1001000
0+
08
0E
#1002000
b01111101 &
b01001011 '
b011001000 (
b01111101 3
b01001011 4
b011001000 5
b01111101 @
b01001011 A
b011001000 B
#1005000
0#
00
0=
#1010000
1#
10
1=
#1011000
1+
b10010000 ,
b11110101 -
b110000101 .
18
b10010000 9
b11110101 :
b110000101 ;
1E
b10010000 F
b11110101 G
b110000101 H
#1015000
0#
00
0=
#1020000
1#
b100000011 /
10
b100000011 <
1=
b100000011 I
#1021000
0+
08
0E
#1022000
1%
b00111010 &
b11111000 '
b100110010 (
12
b00111010 3
b11111000 4
b100110010 5
1?
b00111010 @
b11111000 A
b100110010 B
#1025000
0#
00
0=
#1030000
1#
b011101010 )
10
b011101010 6
1=
b011101010 C
#1031000
0%
b11000001 ,
b00110000 -
b011110001 .
02
b11000001 9
b00110000 :
b011110001 ;
0?
b11000001 F
b00110000 G
b011110001 H
#1035000
0#
00
0=
#1040000
1#
10
1=
#1042000
b10010111 &
b01010101 '
b011101100 (
b10010111 3
b01010101 4
b011101100 5
b10010111 @
b01010101 A
b011101100 B
#1045000
0#
00
0=
#1050000
1#
10
1=
#1051000
1+
b11100101 ,
b10001101 -
b101110010 .
18
b11100101 9
b10001101 :
b101110010 ;
1E
b11100101 F
b10001101 G
b101110010 H
#1055000
0#
00
0=
#1060000
1#
b110010000 /
10
b110010000 <
1=
b110010000 I
#1061000
0+
08
0E
#1062000
1%
b00110110 &
b00000100 '
b000111010 (
12
b00110110 3
b00000100 4
b000111010 5
1?
b00110110 @
b00000100 A
b000111010 B
#1065000
0#
00
0=
#1070000
1#
b011101110 )
10
b011101110 6
1=
b011101110 C
