rtl/top_level.sv


module top_level (
    input  logic       clk,

    // Channel A
    input  logic       rst_A,
    input  logic       valid_in_A,
    input  logic [7:0] a_A,
    input  logic [7:0] b_A,
    output logic [8:0] sum_async_A,
    output logic [8:0] sum_sync_A,

    // Channel B
    input  logic       rst_B,
    input  logic       valid_in_B,
    input  logic [7:0] a_B,
    input  logic [7:0] b_B,
    output logic [8:0] sum_async_B,
    output logic [8:0] sum_sync_B
);

    // Channel A synchronous accumulator
    always_ff @(posedge clk) begin
        if (rst_A)
            sum_sync_A <= '0;
        else if (valid_in_A)
            sum_sync_A <= sum_sync_A + b_A;
    end

    assign sum_async_A = a_A + b_A;

    // Channel B synchronous accumulator
    always_ff @(posedge clk) begin
        if (rst_B)
            sum_sync_B <= '0;
        else if (valid_in_B)
            sum_sync_B <= sum_sync_B + b_B;
    end

    assign sum_async_B = a_B + b_B;

    initial begin
        $display("Time | rst_A| valid_in_A | a_A | b_A |sum_async_A | sum_sync_A |rst_B | valid_in_B| a_B | b_B  | sum_async_B | sum_sync_B   ");
        $monitor("%4t  |  %b  |  %b        | %0d | %0d |    %0d     |   %0d      | %b   |    %b     | %0d | %0d  |    %0d      |   %0d ",
                 $time, rst_A, valid_in_A, a_A, b_A, sum_async_A,sum_sync_A, rst_B, valid_in_B, a_B, b_B, sum_async_B, sum_sync_B);
    end

    initial begin
        $dumpfile("dump.vcd");
        $dumpvars(1, top_level.sv);
    end

endmodule

rtl/dut_wrapper.sv
module dut_wrapper (
    input  logic       clk,

    // Channel A – cocotb drives these
    input  logic       rst_A,
    input  logic       valid_in_A,
    input  logic [7:0] a_A,
    input  logic [7:0] b_A,

    // DUT drives these
    output logic [8:0] sum_async_A,
    output logic [8:0] sum_sync_A,

    // Channel B (if needed)
    input  logic       rst_B,
    input  logic       valid_in_B,
    input  logic [7:0] a_B,
    input  logic [7:0] b_B,
    output logic [8:0] sum_async_B,
    output logic [8:0] sum_sync_B
);

    top_level u_top_level (
        .clk(clk),

        // Channel A
        .rst_A(rst_A),
        .valid_in_A(valid_in_A),
        .a_A(a_A),
        .b_A(b_A),
        .sum_async_A(sum_async_A),
        .sum_sync_A(sum_sync_A),

        // Channel B
        .rst_B(rst_B),
        .valid_in_B(valid_in_B),
        .a_B(a_B),
        .b_B(b_B),
        .sum_async_B(sum_async_B),
        .sum_sync_B(sum_sync_B)
    );

endmodule



// module dut_wrapper (
//     input  logic       clk,

//     // Channel A – exposed directly for cocotb
//     output logic       rst_A,
//     output logic       valid_in_A,
//     output logic [7:0] a_A,
//     output logic [7:0] b_A,
//     output logic [8:0] sum_async_A,
//     output logic [8:0] sum_sync_A,

//     // Channel B – exposed directly for cocotb
//     output logic       rst_B,
//     output logic       valid_in_B,
//     output logic [7:0] a_B,
//     output logic [7:0] b_B,
//     output logic [8:0] sum_async_B,
//     output logic [8:0] sum_sync_B
// );

//     // Internal wires driven by cocotb (use these as DUT inputs)
//     logic rst_A_int;
//     logic valid_in_A_int;
//     logic [7:0] a_A_int;
//     logic [7:0] b_A_int;

//     logic rst_B_int;
//     logic valid_in_B_int;
//     logic [7:0] a_B_int;
//     logic [7:0] b_B_int;

//     // Connect exposed ports to internal wires so cocotb can drive them
//     assign rst_A       = rst_A_int;
//     assign valid_in_A  = valid_in_A_int;
//     assign a_A         = a_A_int;
//     assign b_A         = b_A_int;

//     assign rst_B       = rst_B_int;
//     assign valid_in_B  = valid_in_B_int;
//     assign a_B         = a_B_int;
//     assign b_B         = b_B_int;

//     // DUT instance
//     top_level u_top_level (
//         .clk          (clk),

//         // Channel A
//         .rst_A        (rst_A_int),
//         .valid_in_A   (valid_in_A_int),
//         .a_A          (a_A_int),
//         .b_A          (b_A_int),
//         .sum_async_A  (sum_async_A),
//         .sum_sync_A   (sum_sync_A),

//         // Channel B
//         .rst_B        (rst_B_int),
//         .valid_in_B   (valid_in_B_int),
//         .a_B          (a_B_int),
//         .b_B          (b_B_int),
//         .sum_async_B  (sum_async_B),
//         .sum_sync_B   (sum_sync_B)
//     );

// endmodule

regression_results/waves_8.vcd
$version Generated by VerilatedVcd $end
$timescale 1ps $end
 $scope module $rootio $end
  $var wire 1 # clk $end
  $var wire 1 $ rst_A $end
  $var wire 1 % valid_in_A $end
  $var wire 8 & a_A [7:0] $end
  $var wire 8 ' b_A [7:0] $end
  $var wire 9 ( sum_async_A [8:0] $end
  $var wire 9 ) sum_sync_A [8:0] $end
  $var wire 1 * rst_B $end
  $var wire 1 + valid_in_B $end
  $var wire 8 , a_B [7:0] $end
  $var wire 8 - b_B [7:0] $end
  $var wire 9 . sum_async_B [8:0] $end
  $var wire 9 / sum_sync_B [8:0] $end
 $upscope $end
 $scope module dut_wrapper $end
  $var wire 1 0 clk $end
  $var wire 1 1 rst_A $end
  $var wire 1 2 valid_in_A $end
  $var wire 8 3 a_A [7:0] $end
  $var wire 8 4 b_A [7:0] $end
  $var wire 9 5 sum_async_A [8:0] $end
  $var wire 9 6 sum_sync_A [8:0] $end
  $var wire 1 7 rst_B $end
  $var wire 1 8 valid_in_B $end
  $var wire 8 9 a_B [7:0] $end
  $var wire 8 : b_B [7:0] $end
  $var wire 9 ; sum_async_B [8:0] $end
  $var wire 9 < sum_sync_B [8:0] $end
  $scope module u_top_level $end
   $var wire 1 = clk $end
   $var wire 1 > rst_A $end
   $var wire 1 ? valid_in_A $end
   $var wire 8 @ a_A [7:0] $end
   $var wire 8 A b_A [7:0] $end
   $var wire 9 B sum_async_A [8:0] $end
   $var wire 9 C sum_sync_A [8:0] $end
   $var wire 1 D rst_B $end
   $var wire 1 E valid_in_B $end
   $var wire 8 F a_B [7:0] $end
   $var wire 8 G b_B [7:0] $end
   $var wire 9 H sum_async_B [8:0] $end
   $var wire 9 I sum_sync_B [8:0] $end
  $upscope $end
 $upscope $end
$enddefinitions $end


#0
1#
1$
0%
b00000000 &
b00000000 '
b000000000 (
b000000000 )
1*
0+
b00000000 ,
b00000000 -
b000000000 .
b000000000 /
10
11
02
b00000000 3
b00000000 4
b000000000 5
b000000000 6
17
08
b00000000 9
b00000000 :
b000000000 ;
b000000000 <
1=
1>
0?
b00000000 @
b00000000 A
b000000000 B
b000000000 C
1D
0E
b00000000 F
b00000000 G
b000000000 H
b000000000 I
#5000
0#
00
0=
#10000
1#
10
1=
#15000
0#
00
0=
#20000
1#
0$
1%
b00001101 &
b00110111 '
b001000100 (
0*
10
01
12
b00001101 3
b00110111 4
b001000100 5
07
1=
0>
1?
b00001101 @
b00110111 A
b001000100 B
0D
#25000
0#
00
0=
#30000
1#
b000110111 )
10
b000110111 6
1=
b000110111 C
#31000
0%
1+
b11110110 ,
b10000100 -
b101111010 .
02
18
b11110110 9
b10000100 :
b101111010 ;
0?
1E
b11110110 F
b10000100 G
b101111010 H
#35000
0#
00
0=
#40000
1#
b010000100 /
10
b010000100 <
1=
b010000100 I
#41000
0+
08
0E
#42000
1%
b10010100 &
b00011010 '
b010101110 (
12
b10010100 3
b00011010 4
b010101110 5
1?
b10010100 @
b00011010 A
b010101110 B
#45000
0#
00
0=
#50000
1#
b001010001 )
10
b001010001 6
1=
b001010001 C
#51000
0%
1+
b01101111 ,
b01100011 -
b011010010 .
02
18
b01101111 9
b01100011 :
b011010010 ;
0?
1E
b01101111 F
b01100011 G
b011010010 H
#55000
0#
00
0=
#60000
1#
b011100111 /
10
b011100111 <
1=
b011100111 I
#61000
0+
08
0E
#62000
1%
b11000001 &
b11000000 '
b110000001 (
12
b11000001 3
b11000000 4
b110000001 5
1?
b11000001 @
b11000000 A
b110000001 B
#65000
0#
00
0=
#70000
1#
b100010001 )
10
b100010001 6
1=
b100010001 C
#71000
0%
1+
b11001111 ,
b00010110 -
b011100101 .
02
18
b11001111 9
b00010110 :
b011100101 ;
0?
1E
b11001111 F
b00010110 G
b011100101 H
#75000
0#
00
0=
#80000
1#
b011111101 /
10
b011111101 <
1=
b011111101 I
#81000
0+
08
0E
#82000
1%
b10100000 &
b11111101 '
b110011101 (
12
b10100000 3
b11111101 4
b110011101 5
1?
b10100000 @
b11111101 A
b110011101 B
#85000
0#
00
0=
#90000
1#
b000001110 )
10
b000001110 6
1=
b000001110 C
#91000
0%
1+
b10110000 ,
b00100011 -
b011010011 .
02
18
b10110000 9
b00100011 :
b011010011 ;
0?
1E
b10110000 F
b00100011 G
b011010011 H
#95000
0#
00
0=
#100000
1#
b100100000 /
10
b100100000 <
1=
b100100000 I
#101000
0+
08
0E
#102000
1%
b00000001 &
b10100011 '
b010100100 (
12
b00000001 3
b10100011 4
b010100100 5
1?
b00000001 @
b10100011 A
b010100100 B
#105000
0#
00
0=
#110000
1#
b010110001 )
10
b010110001 6
1=
b010110001 C
#111000
0%
1+
b10111010 ,
b10101011 -
b101100101 .
02
18
b10111010 9
b10101011 :
b101100101 ;
0?
1E
b10111010 F
b10101011 G
b101100101 H
#115000
0#
00
0=
#120000
1#
b111001011 /
10
b111001011 <
1=
b111001011 I
#121000
0+
08
0E
#122000
1%
b11100011 &
b01101001 '
b101001100 (
12
b11100011 3
b01101001 4
b101001100 5
1?
b11100011 @
b01101001 A
b101001100 B
#125000
0#
00
0=
#130000
1#
b100011010 )
10
b100011010 6
1=
b100011010 C
#131000
0%
1+
b00110111 ,
b11001110 -
b100000101 .
02
18
b00110111 9
b11001110 :
b100000101 ;
0?
1E
b00110111 F
b11001110 G
b100000101 H
#135000
0#
00
0=
#140000
1#
b010011001 /
10
b010011001 <
1=
b010011001 I
#141000
0+
08
0E
#142000
1%
b01101100 &
b10100101 '
b100010001 (
12
b01101100 3
b10100101 4
b100010001 5
1?
b01101100 @
b10100101 A
b100010001 B
#145000
0#
00
0=
#150000
1#
b110111111 )
10
b110111111 6
1=
b110111111 C
#151000
0%
1+
b01100101 ,
b00110000 -
b010010101 .
02
18
b01100101 9
b00110000 :
b010010101 ;
0?
1E
b01100101 F
b00110000 G
b010010101 H
#155000
0#
00
0=
#160000
1#
b011001001 /
10
b011001001 <
1=
b011001001 I
#161000
0+
08
0E
#162000
1%
b11111010 &
b10001001 '
b110000011 (
12
b11111010 3
b10001001 4
b110000011 5
1?
b11111010 @
b10001001 A
b110000011 B
#165000
0#
00
0=
#170000
1#
b001001000 )
10
b001001000 6
1=
b001001000 C
#171000
0%
1+
b11000001 ,
b01010110 -
b100010111 .
02
18
b11000001 9
b01010110 :
b100010111 ;
0?
1E
b11000001 F
b01010110 G
b100010111 H
#175000
0#
00
0=
#180000
1#
b100011111 /
10
b100011111 <
1=
b100011111 I
#181000
0+
08
0E
#182000
1%
b10100000 &
b10100010 '
b101000010 (
12
b10100000 3
b10100010 4
b101000010 5
1?
b10100000 @
b10100010 A
b101000010 B
#185000
0#
00
0=
#190000
1#
b011101010 )
10
b011101010 6
1=
b011101010 C
#191000
0%
1+
b01111010 ,
b00100001 -
b010011011 .
02
18
b01111010 9
b00100001 :
b010011011 ;
0?
1E
b01111010 F
b00100001 G
b010011011 H
#195000
0#
00
0=
#200000
1#
b101000000 /
10
b101000000 <
1=
b101000000 I
#201000
0+
08
0E
#202000
1%
b01110001 &
b01001110 '
b010111111 (
12
b01110001 3
b01001110 4
b010111111 5
1?
b01110001 @
b01001110 A
b010111111 B
#205000
0#
00
0=
#210000
1#
b100111000 )
10
b100111000 6
1=
b100111000 C
#211000
0%
1+
b11111001 ,
b11111010 -
b111110011 .
02
18
b11111001 9
b11111010 :
b111110011 ;
0?
1E
b11111001 F
b11111010 G
b111110011 H
#215000
0#
00
0=
#220000
1#
b000111010 /
10
b000111010 <
1=
b000111010 I
#221000
0+
08
0E
#222000
1%
b10111101 &
b10111100 '
b101111001 (
12
b10111101 3
b10111100 4
b101111001 5
1?
b10111101 @
b10111100 A
b101111001 B
#225000
0#
00
0=
#230000
1#
b111110100 )
10
b111110100 6
1=
b111110100 C
#231000
0%
1+
b00110000 ,
b00000010 -
b000110010 .
02
18
b00110000 9
b00000010 :
b000110010 ;
0?
1E
b00110000 F
b00000010 G
b000110010 H
#235000
0#
00
0=
#240000
1#
b000111100 /
10
b000111100 <
1=
b000111100 I
#241000
0+
08
0E
#242000
1%
b11011111 &
b00010100 '
b011110011 (
12
b11011111 3
b00010100 4
b011110011 5
1?
b11011111 @
b00010100 A
b011110011 B
#245000
0#
00
0=
#250000
1#
b000001000 )
10
b000001000 6
1=
b000001000 C
#251000
0%
1+
b00110011 ,
b10000101 -
b010111000 .
02
18
b00110011 9
b10000101 :
b010111000 ;
0?
1E
b00110011 F
b10000101 G
b010111000 H
#255000
0#
00
0=
#260000
1#
b011000001 /
10
b011000001 <
1=
b011000001 I
#261000
0+
08
0E
#262000
1%
b00001110 &
b00111000 '
b001000110 (
12
b00001110 3
b00111000 4
b001000110 5
1?
b00001110 @
b00111000 A
b001000110 B
#265000
0#
00
0=
#270000
1#
b001000000 )
10
b001000000 6
1=
b001000000 C
#271000
0%
1+
b01001110 ,
b01110010 -
b011000000 .
02
18
b01001110 9
b01110010 :
b011000000 ;
0?
1E
b01001110 F
b01110010 G
b011000000 H
#275000
0#
00
0=
#280000
1#
b100110011 /
10
b100110011 <
1=
b100110011 I
#281000
0+
08
0E
#282000
1%
b00111100 &
b11111001 '
b100110101 (
12
b00111100 3
b11111001 4
b100110101 5
1?
b00111100 @
b11111001 A
b100110101 B
#285000
0#
00
0=
#290000
1#
b100111001 )
10
b100111001 6
1=
b100111001 C
#291000
0%
1+
b00110001 ,
b01111100 -
b010101101 .
02
18
b00110001 9
b01111100 :
b010101101 ;
0?
1E
b00110001 F
b01111100 G
b010101101 H
#295000
0#
00
0=
#300000
1#
b110101111 /
10
b110101111 <
1=
b110101111 I
#301000
0+
08
0E
#302000
1%
b00110110 &
b01011000 '
b010001110 (
12
b00110110 3
b01011000 4
b010001110 5
1?
b00110110 @
b01011000 A
b010001110 B
#305000
0#
00
0=
#310000
1#
b110010001 )
10
b110010001 6
1=
b110010001 C
#311000
0%
1+
b11010001 ,
b00110000 -
b100000001 .
02
18
b11010001 9
b00110000 :
b100000001 ;
0?
1E
b11010001 F
b00110000 G
b100000001 H
#315000
0#
00
0=
#320000
1#
b111011111 /
10
b111011111 <
1=
b111011111 I
#321000
0+
08
0E
#322000
1%
b00000100 &
b00100011 '
b000100111 (
12
b00000100 3
b00100011 4
b000100111 5
1?
b00000100 @
b00100011 A
b000100111 B
#325000
0#
00
0=
#330000
1#
b110110100 )
10
b110110100 6
1=
b110110100 C
#331000
0%
1+
b00100011 ,
b00000011 -
b000100110 .
02
18
b00100011 9
b00000011 :
b000100110 ;
0?
1E
b00100011 F
b00000011 G
b000100110 H
#335000
0#
00
0=
#340000
1#
b111100010 /
10
b111100010 <
1=
b111100010 I
#341000
0+
08
0E
#342000
1%
b11101011 &
b11011011 '
b111000110 (
12
b11101011 3
b11011011 4
b111000110 5
1?
b11101011 @
b11011011 A
b111000110 B
#345000
0#
00
0=
#350000
1#
b010001111 )
10
b010001111 6
1=
b010001111 C
#351000
0%
1+
b00000011 ,
b10100101 -
b010101000 .
02
18
b00000011 9
b10100101 :
b010101000 ;
0?
1E
b00000011 F
b10100101 G
b010101000 H
#355000
0#
00
0=
#360000
1#
b010000111 /
10
b010000111 <
1=
b010000111 I
#361000
0+
08
0E
#362000
1%
b11100001 &
b00111110 '
b100011111 (
12
b11100001 3
b00111110 4
b100011111 5
1?
b11100001 @
b00111110 A
b100011111 B
#365000
0#
00
0=
#370000
1#
b011001101 )
10
b011001101 6
1=
b011001101 C
#371000
0%
1+
b01000111 ,
b01000111 -
b010001110 .
02
18
b01000111 9
b01000111 :
b010001110 ;
0?
1E
b01000111 F
b01000111 G
b010001110 H
#375000
0#
00
0=
#380000
1#
b011001110 /
10
b011001110 <
1=
b011001110 I
#381000
0+
08
0E
#382000
1%
b00111010 &
b10100110 '
b011100000 (
12
b00111010 3
b10100110 4
b011100000 5
1?
b00111010 @
b10100110 A
b011100000 B
#385000
0#
00
0=
#390000
1#
b101110011 )
10
b101110011 6
1=
b101110011 C
#391000
0%
1+
b10001000 ,
b01011100 -
b011100100 .
02
18
b10001000 9
b01011100 :
b011100100 ;
0?
1E
b10001000 F
b01011100 G
b011100100 H
#395000
0#
00
0=
#400000
1#
b100101010 /
10
b100101010 <
1=
b100101010 I
#401000
0+
08
0E
#402000
1%
b11001010 &
b01001111 '
b100011001 (
12
b11001010 3
b01001111 4
b100011001 5
1?
b11001010 @
b01001111 A
b100011001 B
#405000
0#
00
0=
#410000
1#
b111000010 )
10
b111000010 6
1=
b111000010 C
#411000
0%
1+
b00110001 ,
b10001110 -
b010111111 .
02
18
b00110001 9
b10001110 :
b010111111 ;
0?
1E
b00110001 F
b10001110 G
b010111111 H
#415000
0#
00
0=
#420000
1#
b110111000 /
10
b110111000 <
1=
b110111000 I
#421000
0+
08
0E
#422000
1%
b10101111 &
b10011001 '
b101001000 (
12
b10101111 3
b10011001 4
b101001000 5
1?
b10101111 @
b10011001 A
b101001000 B
#425000
0#
00
0=
#430000
1#
b001011011 )
10
b001011011 6
1=
b001011011 C
#431000
0%
1+
b01001101 ,
b00110100 -
b010000001 .
02
18
b01001101 9
b00110100 :
b010000001 ;
0?
1E
b01001101 F
b00110100 G
b010000001 H
#435000
0#
00
0=
#440000
1#
b111101100 /
10
b111101100 <
1=
b111101100 I
#441000
0+
08
0E
#442000
1%
b01100011 &
b10000110 '
b011101001 (
12
b01100011 3
b10000110 4
b011101001 5
1?
b01100011 @
b10000110 A
b011101001 B
#445000
0#
00
0=
#450000
1#
b011100001 )
10
b011100001 6
1=
b011100001 C
#451000
0%
1+
b10001101 ,
b00100001 -
b010101110 .
02
18
b10001101 9
b00100001 :
b010101110 ;
0?
1E
b10001101 F
b00100001 G
b010101110 H
#455000
0#
00
0=
#460000
1#
b000001101 /
10
b000001101 <
1=
b000001101 I
#461000
0+
08
0E
#462000
1%
b01100000 &
b10100110 '
b100000110 (
12
b01100000 3
b10100110 4
b100000110 5
1?
b01100000 @
b10100110 A
b100000110 B
#465000
0#
00
0=
#470000
1#
b110000111 )
10
b110000111 6
1=
b110000111 C
#471000
0%
1+
b10011010 ,
b01110110 -
b100010000 .
02
18
b10011010 9
b01110110 :
b100010000 ;
0?
1E
b10011010 F
b01110110 G
b100010000 H
#475000
0#
00
0=
#480000
1#
b010000011 /
10
b010000011 <
1=
b010000011 I
#481000
0+
08
0E
#482000
1%
b10111100 &
b00111000 '
b011110100 (
12
b10111100 3
b00111000 4
b011110100 5
1?
b10111100 @
b00111000 A
b011110100 B
#485000
0#
00
0=
#490000
1#
b110111111 )
10
b110111111 6
1=
b110111111 C
#491000
0%
1+
b10001000 ,
b01000101 -
b011001101 .
02
18
b10001000 9
b01000101 :
b011001101 ;
0?
1E
b10001000 F
b01000101 G
b011001101 H
#495000
0#
00
0=
#500000
1#
b011001000 /
10
b011001000 <
1=
b011001000 I
#501000
0+
08
0E
#502000
1%
b11001011 &
b11110011 '
b110111110 (
12
b11001011 3
b11110011 4
b110111110 5
1?
b11001011 @
b11110011 A
b110111110 B
#505000
0#
00
0=
#510000
1#
b010110010 )
10
b010110010 6
1=
b010110010 C
#511000
0%
1+
b10111101 ,
b10111001 -
b101110110 .
02
18
b10111101 9
b10111001 :
b101110110 ;
0?
1E
b10111101 F
b10111001 G
b101110110 H
#515000
0#
00
0=
#520000
1#
b110000001 /
10
b110000001 <
1=
b110000001 I
#521000
0+
08
0E
#522000
1%
b01010000 &
b11011011 '
b100101011 (
12
b01010000 3
b11011011 4
b100101011 5
1?
b01010000 @
b11011011 A
b100101011 B
#525000
0#
00
0=
#530000
1#
b110001101 )
10
b110001101 6
1=
b110001101 C
#531000
0%
1+
b11100010 ,
b00110010 -
b100010100 .
02
18
b11100010 9
b00110010 :
b100010100 ;
0?
1E
b11100010 F
b00110010 G
b100010100 H
#535000
0#
00
0=
#540000
1#
b110110011 /
10
b110110011 <
1=
b110110011 I
#541000
0+
08
0E
#542000
1%
b00011100 &
b10101100 '
b011001000 (
12
b00011100 3
b10101100 4
b011001000 5
1?
b00011100 @
b10101100 A
b011001000 B
#545000
0#
00
0=
#550000
1#
b000111001 )
10
b000111001 6
1=
b000111001 C
#551000
0%
1+
b01101010 ,
b11000110 -
b100110000 .
02
18
b01101010 9
b11000110 :
b100110000 ;
0?
1E
b01101010 F
b11000110 G
b100110000 H
#555000
0#
00
0=
#560000
1#
b001111001 /
10
b001111001 <
1=
b001111001 I
#561000
0+
08
0E
#562000
1%
b11101000 &
b11010110 '
b110111110 (
12
b11101000 3
b11010110 4
b110111110 5
1?
b11101000 @
b11010110 A
b110111110 B
#565000
0#
00
0=
#570000
1#
b100001111 )
10
b100001111 6
1=
b100001111 C
#571000
0%
1+
b00000100 ,
b10000000 -
b010000100 .
02
18
b00000100 9
b10000000 :
b010000100 ;
0?
1E
b00000100 F
b10000000 G
b010000100 H
#575000
0#
00
0=
#580000
1#
b011111001 /
10
b011111001 <
1=
b011111001 I
#581000
0+
08
0E
#582000
1%
b01111000 &
b11110111 '
b101101111 (
12
b01111000 3
b11110111 4
b101101111 5
1?
b01111000 @
b11110111 A
b101101111 B
#585000
0#
00
0=
#590000
1#
b000000110 )
10
b000000110 6
1=
b000000110 C
#591000
0%
1+
b11000010 ,
b00111110 -
b100000000 .
02
18
b11000010 9
b00111110 :
b100000000 ;
0?
1E
b11000010 F
b00111110 G
b100000000 H
#595000
0#
00
0=
#600000
1#
b100110111 /
10
b100110111 <
1=
b100110111 I
#601000
0+
08
0E
#602000
1%
b00100001 &
b11001100 '
b011101101 (
12
b00100001 3
b11001100 4
b011101101 5
1?
b00100001 @
b11001100 A
b011101101 B
#605000
0#
00
0=
#610000
1#
b011010010 )
10
b011010010 6
1=
b011010010 C
#611000
0%
1+
b00000011 ,
b01001011 -
b001001110 .
02
18
b00000011 9
b01001011 :
b001001110 ;
0?
1E
b00000011 F
b01001011 G
b001001110 H
#615000
0#
00
0=
#620000
1#
b110000010 /
10
b110000010 <
1=
b110000010 I
#621000
0+
08
0E
#622000
1%
b00010010 &
b11000011 '
b011010101 (
12
b00010010 3
b11000011 4
b011010101 5
1?
b00010010 @
b11000011 A
b011010101 B
#625000
0#
00
0=
#630000
1#
b110010101 )
10
b110010101 6
1=
b110010101 C
#631000
0%
1+
b10010010 ,
b01110000 -
b100000010 .
02
18
b10010010 9
b01110000 :
b100000010 ;
0?
1E
b10010010 F
b01110000 G
b100000010 H
#635000
0#
00
0=
#640000
1#
b111110010 /
10
b111110010 <
1=
b111110010 I
#641000
0+
08
0E
#642000
1%
b00011100 &
b00000010 '
b000011110 (
12
b00011100 3
b00000010 4
b000011110 5
1?
b00011100 @
b00000010 A
b000011110 B
#645000
0#
00
0=
#650000
1#
b110010111 )
10
b110010111 6
1=
b110010111 C
#651000
0%
1+
b11000000 ,
b10010110 -
b101010110 .
02
18
b11000000 9
b10010110 :
b101010110 ;
0?
1E
b11000000 F
b10010110 G
b101010110 H
#655000
0#
00
0=
#660000
1#
b010001000 /
10
b010001000 <
1=
b010001000 I
#661000
0+
08
0E
#662000
1%
b11100000 &
b11011001 '
b110111001 (
12
b11100000 3
b11011001 4
b110111001 5
1?
b11100000 @
b11011001 A
b110111001 B
#665000
0#
00
0=
#670000
1#
b001110000 )
10
b001110000 6
1=
b001110000 C
#671000
0%
1+
b11001001 ,
b01010010 -
b100011011 .
02
18
b11001001 9
b01010010 :
b100011011 ;
0?
1E
b11001001 F
b01010010 G
b100011011 H
#675000
0#
00
0=
#680000
1#
b011011010 /
10
b011011010 <
1=
b011011010 I
#681000
0+
08
0E
#682000
1%
b01110000 &
b11010011 '
b101000011 (
12
b01110000 3
b11010011 4
b101000011 5
1?
b01110000 @
b11010011 A
b101000011 B
#685000
0#
00
0=
#690000
1#
b101000011 )
10
b101000011 6
1=
b101000011 C
#691000
0%
1+
b00110011 ,
b00110001 -
b001100100 .
02
18
b00110011 9
b00110001 :
b001100100 ;
0?
1E
b00110011 F
b00110001 G
b001100100 H
#695000
0#
00
0=
#700000
1#
b100001011 /
10
b100001011 <
1=
b100001011 I
#701000
0+
08
0E
#702000
1%
b11100001 &
b00110101 '
b100010110 (
12
b11100001 3
b00110101 4
b100010110 5
1?
b11100001 @
b00110101 A
b100010110 B
#705000
0#
00
0=
#710000
1#
b101111000 )
10
b101111000 6
1=
b101111000 C
#711000
0%
1+
b11111010 ,
b11100011 -
b111011101 .
02
18
b11111010 9
b11100011 :
b111011101 ;
0?
1E
b11111010 F
b11100011 G
b111011101 H
#715000
0#
00
0=
#720000
1#
b111101110 /
10
b111101110 <
1=
b111101110 I
#721000
0+
08
0E
#722000
1%
b10000010 &
b01110110 '
b011111000 (
12
b10000010 3
b01110110 4
b011111000 5
1?
b10000010 @
b01110110 A
b011111000 B
#725000
0#
00
0=
#730000
1#
b111101110 )
10
b111101110 6
1=
b111101110 C
#731000
0%
1+
b11100100 ,
b01111001 -
b101011101 .
02
18
b11100100 9
b01111001 :
b101011101 ;
0?
1E
b11100100 F
b01111001 G
b101011101 H
#735000
0#
00
0=
#740000
1#
b001100111 /
10
b001100111 <
1=
b001100111 I
#741000
0+
08
0E
#742000
1%
b11101001 &
b01000101 '
b100101110 (
12
b11101001 3
b01000101 4
b100101110 5
1?
b11101001 @
b01000101 A
b100101110 B
#745000
0#
00
0=
#750000
1#
b000110011 )
10
b000110011 6
1=
b000110011 C
#751000
0%
1+
b11000001 ,
b00111101 -
b011111110 .
02
18
b11000001 9
b00111101 :
b011111110 ;
0?
1E
b11000001 F
b00111101 G
b011111110 H
#755000
0#
00
0=
#760000
1#
b010100100 /
10
b010100100 <
1=
b010100100 I
#761000
0+
08
0E
#762000
1%
b01001101 &
b01010100 '
b010100001 (
12
b01001101 3
b01010100 4
b010100001 5
1?
b01001101 @
b01010100 A
b010100001 B
#765000
0#
00
0=
#770000
1#
b010000111 )
10
b010000111 6
1=
b010000111 C
#771000
0%
1+
b00110010 ,
b11111011 -
b100101101 .
02
18
b00110010 9
b11111011 :
b100101101 ;
0?
1E
b00110010 F
b11111011 G
b100101101 H
#775000
0#
00
0=
#780000
1#
b110011111 /
10
b110011111 <
1=
b110011111 I
#781000
0+
08
0E
#782000
1%
b11111010 &
b11001010 '
b111000100 (
12
b11111010 3
b11001010 4
b111000100 5
1?
b11111010 @
b11001010 A
b111000100 B
#785000
0#
00
0=
#790000
1#
b101010001 )
10
b101010001 6
1=
b101010001 C
#791000
0%
1+
b10111000 ,
b11101100 -
b110100100 .
02
18
b10111000 9
b11101100 :
b110100100 ;
0?
1E
b10111000 F
b11101100 G
b110100100 H
#795000
0#
00
0=
#800000
1#
b010001011 /
10
b010001011 <
1=
b010001011 I
#801000
0+
08
0E
#802000
1%
b00110100 &
b10100000 '
b011010100 (
12
b00110100 3
b10100000 4
b011010100 5
1?
b00110100 @
b10100000 A
b011010100 B
#805000
0#
00
0=
#810000
1#
b111110001 )
10
b111110001 6
1=
b111110001 C
#811000
0%
1+
b11001000 ,
b11111111 -
b111000111 .
02
18
b11001000 9
b11111111 :
b111000111 ;
0?
1E
b11001000 F
b11111111 G
b111000111 H
#815000
0#
00
0=
#820000
1#
b110001010 /
10
b110001010 <
1=
b110001010 I
#821000
0+
08
0E
#822000
1%
b01110000 &
b10000001 '
b011110001 (
12
b01110000 3
b10000001 4
b011110001 5
1?
b01110000 @
b10000001 A
b011110001 B
#825000
0#
00
0=
#830000
1#
b001110010 )
10
b001110010 6
1=
b001110010 C
#831000
0%
1+
b11111001 -
b111000001 .
02
18
b11111001 :
b111000001 ;
0?
1E
b11111001 G
b111000001 H
#835000
0#
00
0=
#840000
1#
b010000011 /
10
b010000011 <
1=
b010000011 I
#841000
0+
08
0E
#842000
1%
b01011111 &
b11111101 '
b101011100 (
12
b01011111 3
b11111101 4
b101011100 5
1?
b01011111 @
b11111101 A
b101011100 B
#845000
0#
00
0=
#850000
1#
b101101111 )
10
b101101111 6
1=
b101101111 C
#851000
0%
1+
b01011011 ,
b00101011 -
b010000110 .
02
18
b01011011 9
b00101011 :
b010000110 ;
0?
1E
b01011011 F
b00101011 G
b010000110 H
#855000
0#
00
0=
#860000
1#
b010101110 /
10
b010101110 <
1=
b010101110 I
#861000
0+
08
0E
#862000
1%
b11101110 &
b11111100 '
b111101010 (
12
b11101110 3
b11111100 4
b111101010 5
1?
b11101110 @
b11111100 A
b111101010 B
#865000
0#
00
0=
#870000
1#
b001101011 )
10
b001101011 6
1=
b001101011 C
#871000
0%
1+
b01110110 ,
b01011001 -
b011001111 .
02
18
b01110110 9
b01011001 :
b011001111 ;
0?
1E
b01110110 F
b01011001 G
b011001111 H
#875000
0#
00
0=
#880000
1#
b100000111 /
10
b100000111 <
1=
b100000111 I
#881000
0+
08
0E
#882000
1%
b00010001 &
b11010000 '
b011100001 (
12
b00010001 3
b11010000 4
b011100001 5
1?
b00010001 @
b11010000 A
b011100001 B
#885000
0#
00
0=
#890000
1#
b100111011 )
10
b100111011 6
1=
b100111011 C
#891000
0%
1+
b00101000 ,
b00101001 -
b001010001 .
02
18
b00101000 9
b00101001 :
b001010001 ;
0?
1E
b00101000 F
b00101001 G
b001010001 H
#895000
0#
00
0=
#900000
1#
b100110000 /
10
b100110000 <
1=
b100110000 I
#901000
0+
08
0E
#902000
1%
b11100011 &
b10110100 '
b110010111 (
12
b11100011 3
b10110100 4
b110010111 5
1?
b11100011 @
b10110100 A
b110010111 B
#905000
0#
00
0=
#910000
1#
b111101111 )
10
b111101111 6
1=
b111101111 C
#911000
0%
1+
b00100010 ,
b10110011 -
b011010101 .
02
18
b00100010 9
b10110011 :
b011010101 ;
0?
1E
b00100010 F
b10110011 G
b011010101 H
#915000
0#
00
0=
#920000
1#
b111100011 /
10
b111100011 <
1=
b111100011 I
#921000
0+
08
0E
