rtl/top_level.sv


module top_level (
    input  logic       clk,

    // Channel A
    input  logic       rst_A,
    input  logic       valid_in_A,
    input  logic [7:0] a_A,
    input  logic [7:0] b_A,
    output logic [8:0] sum_async_A,
    output logic [8:0] sum_sync_A,

    // Channel B
    input  logic       rst_B,
    input  logic       valid_in_B,
    input  logic [7:0] a_B,
    input  logic [7:0] b_B,
    output logic [8:0] sum_async_B,
    output logic [8:0] sum_sync_B
);

    // Channel A synchronous accumulator
    always_ff @(posedge clk) begin
        if (rst_A)
            sum_sync_A <= '0;
        else if (valid_in_A)
            sum_sync_A <= sum_sync_A + b_A;
    end

    assign sum_async_A = a_A + b_A;

    // Channel B synchronous accumulator
    always_ff @(posedge clk) begin
        if (rst_B)
            sum_sync_B <= '0;
        else if (valid_in_B)
            sum_sync_B <= sum_sync_B + b_B;
    end

    assign sum_async_B = a_B + b_B;

    initial begin
        $display("Time | rst_A| valid_in_A | a_A | b_A |sum_async_A | sum_sync_A |rst_B | valid_in_B| a_B | b_B  | sum_async_B | sum_sync_B   ");
        $monitor("%4t  |  %b  |  %b        | %0d | %0d |    %0d     |   %0d      | %b   |    %b     | %0d | %0d  |    %0d      |   %0d ",
                 $time, rst_A, valid_in_A, a_A, b_A, sum_async_A,sum_sync_A, rst_B, valid_in_B, a_B, b_B, sum_async_B, sum_sync_B);
    end

    initial begin
        $dumpfile("dump.vcd");
        $dumpvars(1, top_level.sv);
    end

endmodule

rtl/dut_wrapper.sv
module dut_wrapper (
    input  logic       clk,

    // Channel A – cocotb drives these
    input  logic       rst_A,
    input  logic       valid_in_A,
    input  logic [7:0] a_A,
    input  logic [7:0] b_A,

    // DUT drives these
    output logic [8:0] sum_async_A,
    output logic [8:0] sum_sync_A,

    // Channel B (if needed)
    input  logic       rst_B,
    input  logic       valid_in_B,
    input  logic [7:0] a_B,
    input  logic [7:0] b_B,
    output logic [8:0] sum_async_B,
    output logic [8:0] sum_sync_B
);

    top_level u_top_level (
        .clk(clk),

        // Channel A
        .rst_A(rst_A),
        .valid_in_A(valid_in_A),
        .a_A(a_A),
        .b_A(b_A),
        .sum_async_A(sum_async_A),
        .sum_sync_A(sum_sync_A),

        // Channel B
        .rst_B(rst_B),
        .valid_in_B(valid_in_B),
        .a_B(a_B),
        .b_B(b_B),
        .sum_async_B(sum_async_B),
        .sum_sync_B(sum_sync_B)
    );

endmodule



// module dut_wrapper (
//     input  logic       clk,

//     // Channel A – exposed directly for cocotb
//     output logic       rst_A,
//     output logic       valid_in_A,
//     output logic [7:0] a_A,
//     output logic [7:0] b_A,
//     output logic [8:0] sum_async_A,
//     output logic [8:0] sum_sync_A,

//     // Channel B – exposed directly for cocotb
//     output logic       rst_B,
//     output logic       valid_in_B,
//     output logic [7:0] a_B,
//     output logic [7:0] b_B,
//     output logic [8:0] sum_async_B,
//     output logic [8:0] sum_sync_B
// );

//     // Internal wires driven by cocotb (use these as DUT inputs)
//     logic rst_A_int;
//     logic valid_in_A_int;
//     logic [7:0] a_A_int;
//     logic [7:0] b_A_int;

//     logic rst_B_int;
//     logic valid_in_B_int;
//     logic [7:0] a_B_int;
//     logic [7:0] b_B_int;

//     // Connect exposed ports to internal wires so cocotb can drive them
//     assign rst_A       = rst_A_int;
//     assign valid_in_A  = valid_in_A_int;
//     assign a_A         = a_A_int;
//     assign b_A         = b_A_int;

//     assign rst_B       = rst_B_int;
//     assign valid_in_B  = valid_in_B_int;
//     assign a_B         = a_B_int;
//     assign b_B         = b_B_int;

//     // DUT instance
//     top_level u_top_level (
//         .clk          (clk),

//         // Channel A
//         .rst_A        (rst_A_int),
//         .valid_in_A   (valid_in_A_int),
//         .a_A          (a_A_int),
//         .b_A          (b_A_int),
//         .sum_async_A  (sum_async_A),
//         .sum_sync_A   (sum_sync_A),

//         // Channel B
//         .rst_B        (rst_B_int),
//         .valid_in_B   (valid_in_B_int),
//         .a_B          (a_B_int),
//         .b_B          (b_B_int),
//         .sum_async_B  (sum_async_B),
//         .sum_sync_B   (sum_sync_B)
//     );

// endmodule

regression_results/waves_8.vcd
$version Generated by VerilatedVcd $end
$timescale 1ps $end
 $scope module $rootio $end
  $var wire 1 # clk $end
  $var wire 1 $ rst_A $end
  $var wire 1 % valid_in_A $end
  $var wire 8 & a_A [7:0] $end
  $var wire 8 ' b_A [7:0] $end
  $var wire 9 ( sum_async_A [8:0] $end
  $var wire 9 ) sum_sync_A [8:0] $end
  $var wire 1 * rst_B $end
  $var wire 1 + valid_in_B $end
  $var wire 8 , a_B [7:0] $end
  $var wire 8 - b_B [7:0] $end
  $var wire 9 . sum_async_B [8:0] $end
  $var wire 9 / sum_sync_B [8:0] $end
 $upscope $end
 $scope module dut_wrapper $end
  $var wire 1 0 clk $end
  $var wire 1 1 rst_A $end
  $var wire 1 2 valid_in_A $end
  $var wire 8 3 a_A [7:0] $end
  $var wire 8 4 b_A [7:0] $end
  $var wire 9 5 sum_async_A [8:0] $end
  $var wire 9 6 sum_sync_A [8:0] $end
  $var wire 1 7 rst_B $end
  $var wire 1 8 valid_in_B $end
  $var wire 8 9 a_B [7:0] $end
  $var wire 8 : b_B [7:0] $end
  $var wire 9 ; sum_async_B [8:0] $end
  $var wire 9 < sum_sync_B [8:0] $end
  $scope module u_top_level $end
   $var wire 1 = clk $end
   $var wire 1 > rst_A $end
   $var wire 1 ? valid_in_A $end
   $var wire 8 @ a_A [7:0] $end
   $var wire 8 A b_A [7:0] $end
   $var wire 9 B sum_async_A [8:0] $end
   $var wire 9 C sum_sync_A [8:0] $end
   $var wire 1 D rst_B $end
   $var wire 1 E valid_in_B $end
   $var wire 8 F a_B [7:0] $end
   $var wire 8 G b_B [7:0] $end
   $var wire 9 H sum_async_B [8:0] $end
   $var wire 9 I sum_sync_B [8:0] $end
  $upscope $end
 $upscope $end
$enddefinitions $end


#0
1#
1$
0%
b00000000 &
b00000000 '
b000000000 (
b000000000 )
1*
0+
b00000000 ,
b00000000 -
b000000000 .
b000000000 /
10
11
02
b00000000 3
b00000000 4
b000000000 5
b000000000 6
17
08
b00000000 9
b00000000 :
b000000000 ;
b000000000 <
1=
1>
0?
b00000000 @
b00000000 A
b000000000 B
b000000000 C
1D
0E
b00000000 F
b00000000 G
b000000000 H
b000000000 I
#5000
0#
00
0=
#10000
1#
10
1=
#15000
0#
00
0=
#20000
1#
0$
1%
b10010101 &
b01000000 '
b011010101 (
0*
10
01
12
b10010101 3
b01000000 4
b011010101 5
07
1=
0>
1?
b10010101 @
b01000000 A
b011010101 B
0D
#25000
0#
00
0=
#30000
1#
b001000000 )
10
b001000000 6
1=
b001000000 C
#31000
0%
1+
b01101001 ,
b11110000 -
b101011001 .
02
18
b01101001 9
b11110000 :
b101011001 ;
0?
1E
b01101001 F
b11110000 G
b101011001 H
#35000
0#
00
0=
#40000
1#
b011110000 /
10
b011110000 <
1=
b011110000 I
#41000
0+
08
0E
#42000
1%
b01111100 &
b00111100 '
b010111000 (
12
b01111100 3
b00111100 4
b010111000 5
1?
b01111100 @
b00111100 A
b010111000 B
#45000
0#
00
0=
#50000
1#
b001111100 )
10
b001111100 6
1=
b001111100 C
#51000
0%
1+
b11000110 ,
b01110110 -
b100111100 .
02
18
b11000110 9
b01110110 :
b100111100 ;
0?
1E
b11000110 F
b01110110 G
b100111100 H
#55000
0#
00
0=
#60000
1#
b101100110 /
10
b101100110 <
1=
b101100110 I
#61000
0+
08
0E
#62000
1%
b10111100 &
b10100101 '
b101100001 (
12
b10111100 3
b10100101 4
b101100001 5
1?
b10111100 @
b10100101 A
b101100001 B
#65000
0#
00
0=
#70000
1#
b100100001 )
10
b100100001 6
1=
b100100001 C
#71000
0%
1+
b10011111 -
b101100101 .
02
18
b10011111 :
b101100101 ;
0?
1E
b10011111 G
b101100101 H
#75000
0#
00
0=
#80000
1#
b000000101 /
10
b000000101 <
1=
b000000101 I
#81000
0+
08
0E
#82000
1%
b10110001 &
b11000111 '
b101111000 (
12
b10110001 3
b11000111 4
b101111000 5
1?
b10110001 @
b11000111 A
b101111000 B
#85000
0#
00
0=
#90000
1#
b111101000 )
10
b111101000 6
1=
b111101000 C
#91000
0%
1+
b11010011 ,
b01111111 -
b101010010 .
02
18
b11010011 9
b01111111 :
b101010010 ;
0?
1E
b11010011 F
b01111111 G
b101010010 H
#95000
0#
00
0=
#100000
1#
b010000100 /
10
b010000100 <
1=
b010000100 I
#101000
0+
08
0E
#102000
1%
b11000100 &
b10011010 '
b101011110 (
12
b11000100 3
b10011010 4
b101011110 5
1?
b11000100 @
b10011010 A
b101011110 B
#105000
0#
00
0=
#110000
1#
b010000010 )
10
b010000010 6
1=
b010000010 C
#111000
0%
1+
b10011101 ,
b01011000 -
b011110101 .
02
18
b10011101 9
b01011000 :
b011110101 ;
0?
1E
b10011101 F
b01011000 G
b011110101 H
#115000
0#
00
0=
#120000
1#
b011011100 /
10
b011011100 <
1=
b011011100 I
#121000
0+
08
0E
#122000
1%
b10001110 &
b10110100 '
b101000010 (
12
b10001110 3
b10110100 4
b101000010 5
1?
b10001110 @
b10110100 A
b101000010 B
#125000
0#
00
0=
#130000
1#
b100110110 )
10
b100110110 6
1=
b100110110 C
#131000
0%
1+
b11100001 ,
b00101111 -
b100010000 .
02
18
b11100001 9
b00101111 :
b100010000 ;
0?
1E
b11100001 F
b00101111 G
b100010000 H
#135000
0#
00
0=
#140000
1#
b100001011 /
10
b100001011 <
1=
b100001011 I
#141000
0+
08
0E
#142000
1%
b10101111 &
b11111001 '
b110101000 (
12
b10101111 3
b11111001 4
b110101000 5
1?
b10101111 @
b11111001 A
b110101000 B
#145000
0#
00
0=
#150000
1#
b000101111 )
10
b000101111 6
1=
b000101111 C
#151000
0%
1+
b11111011 ,
b11110111 -
b111110010 .
02
18
b11111011 9
b11110111 :
b111110010 ;
0?
1E
b11111011 F
b11110111 G
b111110010 H
#155000
0#
00
0=
#160000
1#
b000000010 /
10
b000000010 <
1=
b000000010 I
#161000
0+
08
0E
#162000
1%
b10010010 &
b01010000 '
b011100010 (
12
b10010010 3
b01010000 4
b011100010 5
1?
b10010010 @
b01010000 A
b011100010 B
#165000
0#
00
0=
#170000
1#
b001111111 )
10
b001111111 6
1=
b001111111 C
#171000
0%
1+
b11010010 ,
b00100010 -
b011110100 .
02
18
b11010010 9
b00100010 :
b011110100 ;
0?
1E
b11010010 F
b00100010 G
b011110100 H
#175000
0#
00
0=
#180000
1#
b000100100 /
10
b000100100 <
1=
b000100100 I
#181000
0+
08
0E
#182000
1%
b01110110 &
b11001011 '
b101000001 (
12
b01110110 3
b11001011 4
b101000001 5
1?
b01110110 @
b11001011 A
b101000001 B
#185000
0#
00
0=
#190000
1#
b101001010 )
10
b101001010 6
1=
b101001010 C
#191000
0%
1+
b10110011 ,
b11000101 -
b101111000 .
02
18
b10110011 9
b11000101 :
b101111000 ;
0?
1E
b10110011 F
b11000101 G
b101111000 H
#195000
0#
00
0=
#200000
1#
b011101001 /
10
b011101001 <
1=
b011101001 I
#201000
0+
08
0E
#202000
1%
b01000100 &
b10011010 '
b011011110 (
12
b01000100 3
b10011010 4
b011011110 5
1?
b01000100 @
b10011010 A
b011011110 B
#205000
0#
00
0=
#210000
1#
b111100100 )
10
b111100100 6
1=
b111100100 C
#211000
0%
1+
b11000011 ,
b10000001 -
b101000100 .
02
18
b11000011 9
b10000001 :
b101000100 ;
0?
1E
b11000011 F
b10000001 G
b101000100 H
#215000
0#
00
0=
#220000
1#
b101101010 /
10
b101101010 <
1=
b101101010 I
#221000
0+
08
0E
#222000
1%
b01111010 &
b10100001 '
b100011011 (
12
b01111010 3
b10100001 4
b100011011 5
1?
b01111010 @
b10100001 A
b100011011 B
#225000
0#
00
0=
#230000
1#
b010000101 )
10
b010000101 6
1=
b010000101 C
#231000
0%
1+
b10101111 ,
b11110101 -
b110100100 .
02
18
b10101111 9
b11110101 :
b110100100 ;
0?
1E
b10101111 F
b11110101 G
b110100100 H
#235000
0#
00
0=
#240000
1#
b001011111 /
10
b001011111 <
1=
b001011111 I
#241000
0+
08
0E
#242000
1%
b11100100 &
b00001111 '
b011110011 (
12
b11100100 3
b00001111 4
b011110011 5
1?
b11100100 @
b00001111 A
b011110011 B
#245000
0#
00
0=
#250000
1#
b010010100 )
10
b010010100 6
1=
b010010100 C
#251000
0%
1+
b01100100 ,
b01101110 -
b011010010 .
02
18
b01100100 9
b01101110 :
b011010010 ;
0?
1E
b01100100 F
b01101110 G
b011010010 H
#255000
0#
00
0=
#260000
1#
b011001101 /
10
b011001101 <
1=
b011001101 I
#261000
0+
08
0E
#262000
1%
b11010110 &
b10001010 '
b101100000 (
12
b11010110 3
b10001010 4
b101100000 5
1?
b11010110 @
b10001010 A
b101100000 B
#265000
0#
00
0=
#270000
1#
b100011110 )
10
b100011110 6
1=
b100011110 C
#271000
0%
1+
b00000011 ,
b11011010 -
b011011101 .
02
18
b00000011 9
b11011010 :
b011011101 ;
0?
1E
b00000011 F
b11011010 G
b011011101 H
#275000
0#
00
0=
#280000
1#
b110100111 /
10
b110100111 <
1=
b110100111 I
#281000
0+
08
0E
#282000
1%
b10001110 &
b10111011 '
b101001001 (
12
b10001110 3
b10111011 4
b101001001 5
1?
b10001110 @
b10111011 A
b101001001 B
#285000
0#
00
0=
#290000
1#
b111011001 )
10
b111011001 6
1=
b111011001 C
#291000
0%
1+
b01011011 ,
b01111110 -
b011011001 .
02
18
b01011011 9
b01111110 :
b011011001 ;
0?
1E
b01011011 F
b01111110 G
b011011001 H
#295000
0#
00
0=
#300000
1#
b000100101 /
10
b000100101 <
1=
b000100101 I
#301000
0+
08
0E
#302000
1%
b11011101 &
b11011000 '
b110110101 (
12
b11011101 3
b11011000 4
b110110101 5
1?
b11011101 @
b11011000 A
b110110101 B
#305000
0#
00
0=
#310000
1#
b010110001 )
10
b010110001 6
1=
b010110001 C
#311000
0%
1+
b00110111 ,
b00100000 -
b001010111 .
02
18
b00110111 9
b00100000 :
b001010111 ;
0?
1E
b00110111 F
b00100000 G
b001010111 H
#315000
0#
00
0=
#320000
1#
b001000101 /
10
b001000101 <
1=
b001000101 I
#321000
0+
08
0E
#322000
1%
b01000110 &
b10000110 '
b011001100 (
12
b01000110 3
b10000110 4
b011001100 5
1?
b01000110 @
b10000110 A
b011001100 B
#325000
0#
00
0=
#330000
1#
b100110111 )
10
b100110111 6
1=
b100110111 C
#331000
0%
1+
b00110101 ,
b00111010 -
b001101111 .
02
18
b00110101 9
b00111010 :
b001101111 ;
0?
1E
b00110101 F
b00111010 G
b001101111 H
#335000
0#
00
0=
#340000
1#
b001111111 /
10
b001111111 <
1=
b001111111 I
#341000
0+
08
0E
#342000
1%
b11110110 &
b01101100 '
b101100010 (
12
b11110110 3
b01101100 4
b101100010 5
1?
b11110110 @
b01101100 A
b101100010 B
#345000
0#
00
0=
#350000
1#
b110100011 )
10
b110100011 6
1=
b110100011 C
#351000
0%
1+
b01010101 ,
b11011000 -
b100101101 .
02
18
b01010101 9
b11011000 :
b100101101 ;
0?
1E
b01010101 F
b11011000 G
b100101101 H
#355000
0#
00
0=
#360000
1#
b101010111 /
10
b101010111 <
1=
b101010111 I
#361000
0+
08
0E
#362000
1%
b11011000 &
b10101110 '
b110000110 (
12
b11011000 3
b10101110 4
b110000110 5
1?
b11011000 @
b10101110 A
b110000110 B
#365000
0#
00
0=
#370000
1#
b001010001 )
10
b001010001 6
1=
b001010001 C
#371000
0%
1+
b00001110 ,
b01110111 -
b010000101 .
02
18
b00001110 9
b01110111 :
b010000101 ;
0?
1E
b00001110 F
b01110111 G
b010000101 H
#375000
0#
00
0=
#380000
1#
b111001110 /
10
b111001110 <
1=
b111001110 I
#381000
0+
08
0E
#382000
1%
b11110010 &
b01001100 '
b100111110 (
12
b11110010 3
b01001100 4
b100111110 5
1?
b11110010 @
b01001100 A
b100111110 B
#385000
0#
00
0=
#390000
1#
b010011101 )
10
b010011101 6
1=
b010011101 C
#391000
0%
1+
b00101101 ,
b10110011 -
b011100000 .
02
18
b00101101 9
b10110011 :
b011100000 ;
0?
1E
b00101101 F
b10110011 G
b011100000 H
#395000
0#
00
0=
#400000
1#
b010000001 /
10
b010000001 <
1=
b010000001 I
#401000
0+
08
0E
#402000
1%
b01110100 &
b10110100 '
b100101000 (
12
b01110100 3
b10110100 4
b100101000 5
1?
b01110100 @
b10110100 A
b100101000 B
#405000
0#
00
0=
#410000
1#
b101010001 )
10
b101010001 6
1=
b101010001 C
#411000
0%
1+
b11011100 ,
b00011010 -
b011110110 .
02
18
b11011100 9
b00011010 :
b011110110 ;
0?
1E
b11011100 F
b00011010 G
b011110110 H
#415000
0#
00
0=
#420000
1#
b010011011 /
10
b010011011 <
1=
b010011011 I
#421000
0+
08
0E
#422000
1%
b01111101 &
b10101110 '
b100101011 (
12
b01111101 3
b10101110 4
b100101011 5
1?
b01111101 @
b10101110 A
b100101011 B
#425000
0#
00
0=
#430000
1#
b111111111 )
10
b111111111 6
1=
b111111111 C
#431000
0%
1+
b11010100 ,
b11101011 -
b110111111 .
02
18
b11010100 9
b11101011 :
b110111111 ;
0?
1E
b11010100 F
b11101011 G
b110111111 H
#435000
0#
00
0=
#440000
1#
b110000110 /
10
b110000110 <
1=
b110000110 I
#441000
0+
08
0E
#442000
1%
b10000101 &
b10100010 '
b100100111 (
12
b10000101 3
b10100010 4
b100100111 5
1?
b10000101 @
b10100010 A
b100100111 B
#445000
0#
00
0=
#450000
1#
b010100001 )
10
b010100001 6
1=
b010100001 C
#451000
0%
1+
b01000011 ,
b00000010 -
b001000101 .
02
18
b01000011 9
b00000010 :
b001000101 ;
0?
1E
b01000011 F
b00000010 G
b001000101 H
#455000
0#
00
0=
#460000
1#
b110001000 /
10
b110001000 <
1=
b110001000 I
#461000
0+
08
0E
#462000
1%
b10111000 &
b00100000 '
b011011000 (
12
b10111000 3
b00100000 4
b011011000 5
1?
b10111000 @
b00100000 A
b011011000 B
#465000
0#
00
0=
#470000
1#
b011000001 )
10
b011000001 6
1=
b011000001 C
#471000
0%
1+
b01110000 ,
b00001110 -
b001111110 .
02
18
b01110000 9
b00001110 :
b001111110 ;
0?
1E
b01110000 F
b00001110 G
b001111110 H
#475000
0#
00
0=
#480000
1#
b110010110 /
10
b110010110 <
1=
b110010110 I
#481000
0+
08
0E
#482000
1%
b01110101 &
b11001111 '
b101000100 (
12
b01110101 3
b11001111 4
b101000100 5
1?
b01110101 @
b11001111 A
b101000100 B
#485000
0#
00
0=
#490000
1#
b110010000 )
10
b110010000 6
1=
b110010000 C
#491000
0%
1+
b10100000 ,
b10011011 -
b100111011 .
02
18
b10100000 9
b10011011 :
b100111011 ;
0?
1E
b10100000 F
b10011011 G
b100111011 H
#495000
0#
00
0=
#500000
1#
b000110001 /
10
b000110001 <
1=
b000110001 I
#501000
0+
08
0E
#502000
1%
b11101001 &
b00011110 '
b100000111 (
12
b11101001 3
b00011110 4
b100000111 5
1?
b11101001 @
b00011110 A
b100000111 B
#505000
0#
00
0=
#510000
1#
b110101110 )
10
b110101110 6
1=
b110101110 C
#511000
0%
1+
b01000011 ,
b11011000 -
b100011011 .
02
18
b01000011 9
b11011000 :
b100011011 ;
0?
1E
b01000011 F
b11011000 G
b100011011 H
#515000
0#
00
0=
#520000
1#
b100001001 /
10
b100001001 <
1=
b100001001 I
#521000
0+
08
0E
#522000
1%
b11111001 &
b10011110 '
b110010111 (
12
b11111001 3
b10011110 4
b110010111 5
1?
b11111001 @
b10011110 A
b110010111 B
#525000
0#
00
0=
#530000
1#
b001001100 )
10
b001001100 6
1=
b001001100 C
#531000
0%
1+
b01101111 ,
b10000101 -
b011110100 .
02
18
b01101111 9
b10000101 :
b011110100 ;
0?
1E
b01101111 F
b10000101 G
b011110100 H
#535000
0#
00
0=
#540000
1#
b110001110 /
10
b110001110 <
1=
b110001110 I
#541000
0+
08
0E
#542000
1%
b00001111 &
b01011111 '
b001101110 (
12
b00001111 3
b01011111 4
b001101110 5
1?
b00001111 @
b01011111 A
b001101110 B
#545000
0#
00
0=
#550000
1#
b010101011 )
10
b010101011 6
1=
b010101011 C
#551000
0%
1+
b00111000 ,
b10111010 -
b011110010 .
02
18
b00111000 9
b10111010 :
b011110010 ;
0?
1E
b00111000 F
b10111010 G
b011110010 H
#555000
0#
00
0=
#560000
1#
b001001000 /
10
b001001000 <
1=
b001001000 I
#561000
0+
08
0E
#562000
1%
b10100100 &
b10000111 '
b100101011 (
12
b10100100 3
b10000111 4
b100101011 5
1?
b10100100 @
b10000111 A
b100101011 B
#565000
0#
00
0=
#570000
1#
b100110010 )
10
b100110010 6
1=
b100110010 C
#571000
0%
1+
b10101011 ,
b11000100 -
b101101111 .
02
18
b10101011 9
b11000100 :
b101101111 ;
0?
1E
b10101011 F
b11000100 G
b101101111 H
#575000
0#
00
0=
#580000
1#
b100001100 /
10
b100001100 <
1=
b100001100 I
#581000
0+
08
0E
#582000
1%
b10011000 &
b10010010 '
b100101010 (
12
b10011000 3
b10010010 4
b100101010 5
1?
b10011000 @
b10010010 A
b100101010 B
#585000
0#
00
0=
#590000
1#
b111000100 )
10
b111000100 6
1=
b111000100 C
#591000
0%
1+
b01010001 ,
b10100111 -
b011111000 .
02
18
b01010001 9
b10100111 :
b011111000 ;
0?
1E
b01010001 F
b10100111 G
b011111000 H
#595000
0#
00
0=
#600000
1#
b110110011 /
10
b110110011 <
1=
b110110011 I
#601000
0+
08
0E
#602000
1%
b01101001 &
b10111010 '
b100100011 (
12
b01101001 3
b10111010 4
b100100011 5
1?
b01101001 @
b10111010 A
b100100011 B
#605000
0#
00
0=
#610000
1#
b001111110 )
10
b001111110 6
1=
b001111110 C
#611000
0%
1+
b01111100 ,
b10100110 -
b100100010 .
02
18
b01111100 9
b10100110 :
b100100010 ;
0?
1E
b01111100 F
b10100110 G
b100100010 H
#615000
0#
00
0=
#620000
1#
b001011001 /
10
b001011001 <
1=
b001011001 I
#621000
0+
08
0E
#622000
1%
b10110010 &
b10010010 '
b101000100 (
12
b10110010 3
b10010010 4
b101000100 5
1?
b10110010 @
b10010010 A
b101000100 B
#625000
0#
00
0=
#630000
1#
b100010000 )
10
b100010000 6
1=
b100010000 C
#631000
0%
1+
b01111101 ,
b01010111 -
b011010100 .
02
18
b01111101 9
b01010111 :
b011010100 ;
0?
1E
b01111101 F
b01010111 G
b011010100 H
#635000
0#
00
0=
#640000
1#
b010110000 /
10
b010110000 <
1=
b010110000 I
#641000
0+
08
0E
#642000
1%
b01110001 &
b10000110 '
b011110111 (
12
b01110001 3
b10000110 4
b011110111 5
1?
b01110001 @
b10000110 A
b011110111 B
#645000
0#
00
0=
#650000
1#
b110010110 )
10
b110010110 6
1=
b110010110 C
#651000
0%
1+
b11101111 ,
b10101010 -
b110011001 .
02
18
b11101111 9
b10101010 :
b110011001 ;
0?
1E
b11101111 F
b10101010 G
b110011001 H
#655000
0#
00
0=
#660000
1#
b101011010 /
10
b101011010 <
1=
b101011010 I
#661000
0+
08
0E
#662000
1%
b11000001 &
b10000011 '
b101000100 (
12
b11000001 3
b10000011 4
b101000100 5
1?
b11000001 @
b10000011 A
b101000100 B
#665000
0#
00
0=
#670000
1#
b000011001 )
10
b000011001 6
1=
b000011001 C
#671000
0%
1+
b11001010 ,
b00010101 -
b011011111 .
02
18
b11001010 9
b00010101 :
b011011111 ;
0?
1E
b11001010 F
b00010101 G
b011011111 H
#675000
0#
00
0=
#680000
1#
b101101111 /
10
b101101111 <
1=
b101101111 I
#681000
0+
08
0E
#682000
1%
b11100011 &
b10100110 '
b110001001 (
12
b11100011 3
b10100110 4
b110001001 5
1?
b11100011 @
b10100110 A
b110001001 B
#685000
0#
00
0=
#690000
1#
b010111111 )
10
b010111111 6
1=
b010111111 C
#691000
0%
1+
b00110100 ,
b00111101 -
b001110001 .
02
18
b00110100 9
b00111101 :
b001110001 ;
0?
1E
b00110100 F
b00111101 G
b001110001 H
#695000
0#
00
0=
#700000
1#
b110101100 /
10
b110101100 <
1=
b110101100 I
#701000
0+
08
0E
#702000
1%
b00100000 &
b11010111 '
b011110111 (
12
b00100000 3
b11010111 4
b011110111 5
1?
b00100000 @
b11010111 A
b011110111 B
#705000
0#
00
0=
#710000
1#
b110010110 )
10
b110010110 6
1=
b110010110 C
#711000
0%
1+
b00101111 ,
b11010110 -
b100000101 .
02
18
b00101111 9
b11010110 :
b100000101 ;
0?
1E
b00101111 F
b11010110 G
b100000101 H
#715000
0#
00
0=
#720000
1#
b010000010 /
10
b010000010 <
1=
b010000010 I
#721000
0+
08
0E
#722000
1%
b10111101 &
b10101101 '
b101101010 (
12
b10111101 3
b10101101 4
b101101010 5
1?
b10111101 @
b10101101 A
b101101010 B
#725000
0#
00
0=
#730000
1#
b001000011 )
10
b001000011 6
1=
b001000011 C
#731000
0%
1+
b01111000 ,
b00100001 -
b010011001 .
02
18
b01111000 9
b00100001 :
b010011001 ;
0?
1E
b01111000 F
b00100001 G
b010011001 H
#735000
0#
00
0=
#740000
1#
b010100011 /
10
b010100011 <
1=
b010100011 I
#741000
0+
08
0E
#742000
1%
b10100011 &
b11000101 '
b101101000 (
12
b10100011 3
b11000101 4
b101101000 5
1?
b10100011 @
b11000101 A
b101101000 B
#745000
0#
00
0=
#750000
1#
b100001000 )
10
b100001000 6
1=
b100001000 C
#751000
0%
1+
b10110111 ,
b11111111 -
b110110110 .
02
18
b10110111 9
b11111111 :
b110110110 ;
0?
1E
b10110111 F
b11111111 G
b110110110 H
#755000
0#
00
0=
#760000
1#
b110100010 /
10
b110100010 <
1=
b110100010 I
#761000
0+
08
0E
#762000
1%
b11011101 &
b10100010 '
b101111111 (
12
b11011101 3
b10100010 4
b101111111 5
1?
b11011101 @
b10100010 A
b101111111 B
#765000
0#
00
0=
#770000
1#
b110101010 )
10
b110101010 6
1=
b110101010 C
#771000
0%
1+
b01011110 ,
b00110101 -
b010010011 .
02
18
b01011110 9
b00110101 :
b010010011 ;
0?
1E
b01011110 F
b00110101 G
b010010011 H
#775000
0#
00
0=
#780000
1#
b111010111 /
10
b111010111 <
1=
b111010111 I
#781000
0+
08
0E
#782000
1%
b11111111 &
b10001011 '
b110001010 (
12
b11111111 3
b10001011 4
b110001010 5
1?
b11111111 @
b10001011 A
b110001010 B
#785000
0#
00
0=
#790000
1#
b000110101 )
10
b000110101 6
1=
b000110101 C
#791000
0%
1+
b10100001 ,
b00011000 -
b010111001 .
02
18
b10100001 9
b00011000 :
b010111001 ;
0?
1E
b10100001 F
b00011000 G
b010111001 H
#795000
0#
00
0=
#800000
1#
b111101111 /
10
b111101111 <
1=
b111101111 I
#801000
0+
08
0E
#802000
1%
b00001010 &
b11001100 '
b011010110 (
12
b00001010 3
b11001100 4
b011010110 5
1?
b00001010 @
b11001100 A
b011010110 B
#805000
0#
00
0=
#810000
1#
b100000001 )
10
b100000001 6
1=
b100000001 C
#811000
0%
1+
b00111111 ,
b10100110 -
b011100101 .
02
18
b00111111 9
b10100110 :
b011100101 ;
0?
1E
b00111111 F
b10100110 G
b011100101 H
#815000
0#
00
0=
#820000
1#
b010010101 /
10
b010010101 <
1=
b010010101 I
#821000
0+
08
0E
#822000
1%
b11001111 &
b10010100 '
b101100011 (
12
b11001111 3
b10010100 4
b101100011 5
1?
b11001111 @
b10010100 A
b101100011 B
#825000
0#
00
0=
#830000
1#
b110010101 )
10
b110010101 6
1=
b110010101 C
#831000
0%
1+
b10110010 ,
b00100011 -
b011010101 .
02
18
b10110010 9
b00100011 :
b011010101 ;
0?
1E
b10110010 F
b00100011 G
b011010101 H
#835000
0#
00
0=
#840000
1#
b010111000 /
10
b010111000 <
1=
b010111000 I
#841000
0+
08
0E
#842000
1%
b10011101 &
b01101000 '
b100000101 (
12
b10011101 3
b01101000 4
b100000101 5
1?
b10011101 @
b01101000 A
b100000101 B
#845000
0#
00
0=
#850000
1#
b111111101 )
10
b111111101 6
1=
b111111101 C
#851000
0%
1+
b11010000 ,
b01110001 -
b101000001 .
02
18
b11010000 9
b01110001 :
b101000001 ;
0?
1E
b11010000 F
b01110001 G
b101000001 H
#855000
0#
00
0=
#860000
1#
b100101001 /
10
b100101001 <
1=
b100101001 I
#861000
0+
08
0E
#862000
1%
b01000111 &
b00000101 '
b001001100 (
12
b01000111 3
b00000101 4
b001001100 5
1?
b01000111 @
b00000101 A
b001001100 B
#865000
0#
00
0=
#870000
1#
b000000010 )
10
b000000010 6
1=
b000000010 C
#871000
0%
1+
b00001110 ,
b00111100 -
b001001010 .
02
18
b00001110 9
b00111100 :
b001001010 ;
0?
1E
b00001110 F
b00111100 G
b001001010 H
#875000
0#
00
0=
#880000
1#
b101100101 /
10
b101100101 <
1=
b101100101 I
#881000
0+
08
0E
#882000
1%
b10110110 &
b10001000 '
b100111110 (
12
b10110110 3
b10001000 4
b100111110 5
1?
b10110110 @
b10001000 A
b100111110 B
#885000
0#
00
0=
#890000
1#
b010001010 )
10
b010001010 6
1=
b010001010 C
#891000
0%
1+
b10110011 ,
b11101101 -
b110100000 .
02
18
b10110011 9
b11101101 :
b110100000 ;
0?
1E
b10110011 F
b11101101 G
b110100000 H
#895000
0#
00
0=
#900000
1#
b001010010 /
10
b001010010 <
1=
b001010010 I
#901000
0+
08
0E
#902000
1%
b00101110 &
b00111111 '
b001101101 (
12
b00101110 3
b00111111 4
b001101101 5
1?
b00101110 @
b00111111 A
b001101101 B
#905000
0#
00
0=
#910000
1#
b011001001 )
10
b011001001 6
1=
b011001001 C
#911000
0%
1+
b00011010 ,
b01011101 -
b001110111 .
02
18
b00011010 9
b01011101 :
b001110111 ;
0?
1E
b00011010 F
b01011101 G
b001110111 H
#915000
0#
00
0=
#920000
1#
b010101111 /
10
b010101111 <
1=
b010101111 I
#921000
0+
08
0E
