rtl/top_level.sv


module top_level (
    input  logic       clk,

    // Channel A
    input  logic       rst_A,
    input  logic       valid_in_A,
    input  logic [7:0] a_A,
    input  logic [7:0] b_A,
    output logic [8:0] sum_async_A,
    output logic [8:0] sum_sync_A,

    // Channel B
    input  logic       rst_B,
    input  logic       valid_in_B,
    input  logic [7:0] a_B,
    input  logic [7:0] b_B,
    output logic [8:0] sum_async_B,
    output logic [8:0] sum_sync_B
);

    // Channel A synchronous accumulator
    always_ff @(posedge clk) begin
        if (rst_A)
            sum_sync_A <= '0;
        else if (valid_in_A)
            sum_sync_A <= sum_sync_A + b_A;
    end

    assign sum_async_A = a_A + b_A;

    // Channel B synchronous accumulator
    always_ff @(posedge clk) begin
        if (rst_B)
            sum_sync_B <= '0;
        else if (valid_in_B)
            sum_sync_B <= sum_sync_B + b_B;
    end

    assign sum_async_B = a_B + b_B;

    initial begin
        $display("Time | rst_A| valid_in_A | a_A | b_A |sum_async_A | sum_sync_A |rst_B | valid_in_B| a_B | b_B  | sum_async_B | sum_sync_B   ");
        $monitor("%4t  |  %b  |  %b        | %0d | %0d |    %0d     |   %0d      | %b   |    %b     | %0d | %0d  |    %0d      |   %0d ",
                 $time, rst_A, valid_in_A, a_A, b_A, sum_async_A,sum_sync_A, rst_B, valid_in_B, a_B, b_B, sum_async_B, sum_sync_B);
    end

    initial begin
        $dumpfile("dump.vcd");
        $dumpvars(1, top_level.sv);
    end

endmodule

rtl/dut_wrapper.sv
module dut_wrapper (
    input  logic       clk,

    // Channel A – cocotb drives these
    input  logic       rst_A,
    input  logic       valid_in_A,
    input  logic [7:0] a_A,
    input  logic [7:0] b_A,

    // DUT drives these
    output logic [8:0] sum_async_A,
    output logic [8:0] sum_sync_A,

    // Channel B (if needed)
    input  logic       rst_B,
    input  logic       valid_in_B,
    input  logic [7:0] a_B,
    input  logic [7:0] b_B,
    output logic [8:0] sum_async_B,
    output logic [8:0] sum_sync_B
);

    top_level u_top_level (
        .clk(clk),

        // Channel A
        .rst_A(rst_A),
        .valid_in_A(valid_in_A),
        .a_A(a_A),
        .b_A(b_A),
        .sum_async_A(sum_async_A),
        .sum_sync_A(sum_sync_A),

        // Channel B
        .rst_B(rst_B),
        .valid_in_B(valid_in_B),
        .a_B(a_B),
        .b_B(b_B),
        .sum_async_B(sum_async_B),
        .sum_sync_B(sum_sync_B)
    );

endmodule



// module dut_wrapper (
//     input  logic       clk,

//     // Channel A – exposed directly for cocotb
//     output logic       rst_A,
//     output logic       valid_in_A,
//     output logic [7:0] a_A,
//     output logic [7:0] b_A,
//     output logic [8:0] sum_async_A,
//     output logic [8:0] sum_sync_A,

//     // Channel B – exposed directly for cocotb
//     output logic       rst_B,
//     output logic       valid_in_B,
//     output logic [7:0] a_B,
//     output logic [7:0] b_B,
//     output logic [8:0] sum_async_B,
//     output logic [8:0] sum_sync_B
// );

//     // Internal wires driven by cocotb (use these as DUT inputs)
//     logic rst_A_int;
//     logic valid_in_A_int;
//     logic [7:0] a_A_int;
//     logic [7:0] b_A_int;

//     logic rst_B_int;
//     logic valid_in_B_int;
//     logic [7:0] a_B_int;
//     logic [7:0] b_B_int;

//     // Connect exposed ports to internal wires so cocotb can drive them
//     assign rst_A       = rst_A_int;
//     assign valid_in_A  = valid_in_A_int;
//     assign a_A         = a_A_int;
//     assign b_A         = b_A_int;

//     assign rst_B       = rst_B_int;
//     assign valid_in_B  = valid_in_B_int;
//     assign a_B         = a_B_int;
//     assign b_B         = b_B_int;

//     // DUT instance
//     top_level u_top_level (
//         .clk          (clk),

//         // Channel A
//         .rst_A        (rst_A_int),
//         .valid_in_A   (valid_in_A_int),
//         .a_A          (a_A_int),
//         .b_A          (b_A_int),
//         .sum_async_A  (sum_async_A),
//         .sum_sync_A   (sum_sync_A),

//         // Channel B
//         .rst_B        (rst_B_int),
//         .valid_in_B   (valid_in_B_int),
//         .a_B          (a_B_int),
//         .b_B          (b_B_int),
//         .sum_async_B  (sum_async_B),
//         .sum_sync_B   (sum_sync_B)
//     );

// endmodule

regression_results/waves_4.vcd
$version Generated by VerilatedVcd $end
$timescale 1ps $end
 $scope module $rootio $end
  $var wire 1 # clk $end
  $var wire 1 $ rst_A $end
  $var wire 1 % valid_in_A $end
  $var wire 8 & a_A [7:0] $end
  $var wire 8 ' b_A [7:0] $end
  $var wire 9 ( sum_async_A [8:0] $end
  $var wire 9 ) sum_sync_A [8:0] $end
  $var wire 1 * rst_B $end
  $var wire 1 + valid_in_B $end
  $var wire 8 , a_B [7:0] $end
  $var wire 8 - b_B [7:0] $end
  $var wire 9 . sum_async_B [8:0] $end
  $var wire 9 / sum_sync_B [8:0] $end
 $upscope $end
 $scope module dut_wrapper $end
  $var wire 1 0 clk $end
  $var wire 1 1 rst_A $end
  $var wire 1 2 valid_in_A $end
  $var wire 8 3 a_A [7:0] $end
  $var wire 8 4 b_A [7:0] $end
  $var wire 9 5 sum_async_A [8:0] $end
  $var wire 9 6 sum_sync_A [8:0] $end
  $var wire 1 7 rst_B $end
  $var wire 1 8 valid_in_B $end
  $var wire 8 9 a_B [7:0] $end
  $var wire 8 : b_B [7:0] $end
  $var wire 9 ; sum_async_B [8:0] $end
  $var wire 9 < sum_sync_B [8:0] $end
  $scope module u_top_level $end
   $var wire 1 = clk $end
   $var wire 1 > rst_A $end
   $var wire 1 ? valid_in_A $end
   $var wire 8 @ a_A [7:0] $end
   $var wire 8 A b_A [7:0] $end
   $var wire 9 B sum_async_A [8:0] $end
   $var wire 9 C sum_sync_A [8:0] $end
   $var wire 1 D rst_B $end
   $var wire 1 E valid_in_B $end
   $var wire 8 F a_B [7:0] $end
   $var wire 8 G b_B [7:0] $end
   $var wire 9 H sum_async_B [8:0] $end
   $var wire 9 I sum_sync_B [8:0] $end
  $upscope $end
 $upscope $end
$enddefinitions $end


#0
1#
1$
0%
b00000000 &
b00000000 '
b000000000 (
b000000000 )
1*
0+
b00000000 ,
b00000000 -
b000000000 .
b000000000 /
10
11
02
b00000000 3
b00000000 4
b000000000 5
b000000000 6
17
08
b00000000 9
b00000000 :
b000000000 ;
b000000000 <
1=
1>
0?
b00000000 @
b00000000 A
b000000000 B
b000000000 C
1D
0E
b00000000 F
b00000000 G
b000000000 H
b000000000 I
#5030000
00
0=
#10000
1#
10
1=
#15000
0#
00
0=
#20000
1#
10
1=
#25000
0#
0$
0*
00
01
07
0=
0>
0D
#30000
1#
1%
b00000100 &
b11111011 '
b011111111 (
1+
b00010010 ,
b00100110 -
b000111000 .
10
12
b00000100 3
b11111011 4
b011111111 5
18
b00010010 9
b00100110 :
b000111000 ;
1=
1?
b00000100 @
b11111011 A
b011111111 B
1E
b00010010 F
b00100110 G
b000111000 H
#35000
0#
00
0=
#40000
1#
b011111011 )
b000100110 /
10
b011111011 6
b000100110 <
1=
b011111011 C
b000100110 I
#41000
b00000001 &
b011111100 (
b00010000 ,
b00100111 -
b000110111 .
b00000001 3
b011111100 5
b00010000 9
b00100111 :
b000110111 ;
b00000001 @
b011111100 B
b00010000 F
b00100111 G
b000110111 H
#45000
0#
00
0=
#50000
1#
b111110110 )
b001001101 /
10
b111110110 6
b001001101 <
1=
b111110110 C
b001001101 I
#51000
b11111111 '
b100000000 (
b00010010 ,
b00101000 -
b000111010 .
b11111111 4
b100000000 5
b00010010 9
b00101000 :
b000111010 ;
b11111111 A
b100000000 B
b00010010 F
b00101000 G
b000111010 H
#55000
0#
00
0=
#60000
1#
b011110101 )
b001110101 /
10
b011110101 6
b001110101 <
1=
b011110101 C
b001110101 I
#61000
b00001110 ,
b000110110 .
b00001110 9
b000110110 ;
b00001110 F
b000110110 H
#65000
0#
00
0=
#70000
1#
b111110100 )
b010011101 /
10
b111110100 6
b010011101 <
1=
b111110100 C
b010011101 I
#71000
b00000100 &
b11111011 '
b011111111 (
b00010010 ,
b00100110 -
b000111000 .
b00000100 3
b11111011 4
b011111111 5
b00010010 9
b00100110 :
b000111000 ;
b00000100 @
b11111011 A
b011111111 B
b00010010 F
b00100110 G
b000111000 H
#75000
0#
00
0=
#80000
1#
b011101111 )
b011000011 /
10
b011101111 6
b011000011 <
1=
b011101111 C
b011000011 I
#81000
b00000011 &
b11111101 '
b100000000 (
b00001100 ,
b00100011 -
b000101111 .
b00000011 3
b11111101 4
b100000000 5
b00001100 9
b00100011 :
b000101111 ;
b00000011 @
b11111101 A
b100000000 B
b00001100 F
b00100011 G
b000101111 H
#85000
0#
00
0=
#90000
1#
b111101100 )
b011100110 /
10
b111101100 6
b011100110 <
1=
b111101100 C
b011100110 I
#91000
b00000010 &
b011111111 (
b00010011 ,
b00100100 -
b000110111 .
b00000010 3
b011111111 5
b00010011 9
b00100100 :
b000110111 ;
b00000010 @
b011111111 B
b00010011 F
b00100100 G
b000110111 H
#95000
0#
00
0=
#100000
1#
b011101001 )
b100001010 /
10
b011101001 6
b100001010 <
1=
b011101001 C
b100001010 I
#101000
b00000100 &
b11111110 '
b100000010 (
b00001011 ,
b00100000 -
b000101011 .
b00000100 3
b11111110 4
b100000010 5
b00001011 9
b00100000 :
b000101011 ;
b00000100 @
b11111110 A
b100000010 B
b00001011 F
b00100000 G
b000101011 H
#105000
0#
00
0=
#110000
1#
b111100111 )
b100101010 /
10
b111100111 6
b100101010 <
1=
b111100111 C
b100101010 I
#111000
b00000011 &
b11111011 '
b011111110 (
b00010011 ,
b00011111 -
b000110010 .
b00000011 3
b11111011 4
b011111110 5
b00010011 9
b00011111 :
b000110010 ;
b00000011 @
b11111011 A
b011111110 B
b00010011 F
b00011111 G
b000110010 H
#115000
0#
00
0=
#120000
1#
b011100010 )
b101001001 /
10
b011100010 6
b101001001 <
1=
b011100010 C
b101001001 I
#121000
b00000100 &
b11111111 '
b100000011 (
b00010001 ,
b00100110 -
b000110111 .
b00000100 3
b11111111 4
b100000011 5
b00010001 9
b00100110 :
b000110111 ;
b00000100 @
b11111111 A
b100000011 B
b00010001 F
b00100110 G
b000110111 H
#125000
0#
00
0=
#130000
1#
b111100001 )
b101101111 /
10
b111100001 6
b101101111 <
1=
b111100001 C
b101101111 I
#131000
b00000000 &
b11111011 '
b011111011 (
b00001110 ,
b00011111 -
b000101101 .
b00000000 3
b11111011 4
b011111011 5
b00001110 9
b00011111 :
b000101101 ;
b00000000 @
b11111011 A
b011111011 B
b00001110 F
b00011111 G
b000101101 H
#135000
0#
00
0=
#140000
1#
b011011100 )
b110001110 /
10
b011011100 6
b110001110 <
1=
b011011100 C
b110001110 I
#141000
b00000101 &
b11111100 '
b100000001 (
b00001111 ,
b00100111 -
b000110110 .
b00000101 3
b11111100 4
b100000001 5
b00001111 9
b00100111 :
b000110110 ;
b00000101 @
b11111100 A
b100000001 B
b00001111 F
b00100111 G
b000110110 H
#145000
0#
00
0=
#150000
1#
b111011000 )
b110110101 /
10
b111011000 6
b110110101 <
1=
b111011000 C
b110110101 I
#151000
b00000011 &
b11111011 '
b011111110 (
b00010010 ,
b00100100 -
b00000011 3
b11111011 4
b011111110 5
b00010010 9
b00100100 :
b00000011 @
b11111011 A
b011111110 B
b00010010 F
b00100100 G
#155000
0#
00
0=
#160000
1#
b011010011 )
b111011001 /
10
b011010011 6
b111011001 <
1=
b011010011 C
b111011001 I
#161000
b00000010 &
b11111101 '
b011111111 (
b00001100 ,
b00100110 -
b000110010 .
b00000010 3
b11111101 4
b011111111 5
b00001100 9
b00100110 :
b000110010 ;
b00000010 @
b11111101 A
b011111111 B
b00001100 F
b00100110 G
b000110010 H
#165000
0#
00
0=
#170000
1#
b111010000 )
b111111111 /
10
b111010000 6
b111111111 <
1=
b111010000 C
b111111111 I
#171000
b00000001 &
b011111110 (
b00001101 ,
b00011110 -
b000101011 .
b00000001 3
b011111110 5
b00001101 9
b00011110 :
b000101011 ;
b00000001 @
b011111110 B
b00001101 F
b00011110 G
b000101011 H
#175000
0#
00
0=
#180000
1#
b011001101 )
b000011101 /
10
b011001101 6
b000011101 <
1=
b011001101 C
b000011101 I
#181000
b00000000 &
b11111010 '
b011111010 (
b00010010 ,
b00100111 -
b000111001 .
b00000000 3
b11111010 4
b011111010 5
b00010010 9
b00100111 :
b000111001 ;
b00000000 @
b11111010 A
b011111010 B
b00010010 F
b00100111 G
b000111001 H
#185000
0#
00
0=
#190000
1#
b111000111 )
b001000100 /
10
b111000111 6
b001000100 <
1=
b111000111 C
b001000100 I
#191000
b11111011 '
b011111011 (
b00001110 ,
b00011110 -
b000101100 .
b11111011 4
b011111011 5
b00001110 9
b00011110 :
b000101100 ;
b11111011 A
b011111011 B
b00001110 F
b00011110 G
b000101100 H
#195000
0#
00
0=
#200000
1#
b011000010 )
b001100010 /
10
b011000010 6
b001100010 <
1=
b011000010 C
b001100010 I
#201000
b11111110 '
b011111110 (
b00010000 ,
b00100110 -
b000110110 .
b11111110 4
b011111110 5
b00010000 9
b00100110 :
b000110110 ;
b11111110 A
b011111110 B
b00010000 F
b00100110 G
b000110110 H
#205000
0#
00
0=
#210000
1#
b111000000 )
b010001000 /
10
b111000000 6
b010001000 <
1=
b111000000 C
b010001000 I
#211000
b00000011 &
b11111101 '
b100000000 (
b00010001 ,
b00100101 -
b00000011 3
b11111101 4
b100000000 5
b00010001 9
b00100101 :
b00000011 @
b11111101 A
b100000000 B
b00010001 F
b00100101 G
#215000
0#
00
0=
#220000
1#
b010111101 )
b010101101 /
10
b010111101 6
b010101101 <
1=
b010111101 C
b010101101 I
#221000
b11111111 '
b100000010 (
b00001111 ,
b00100111 -
b11111111 4
b100000010 5
b00001111 9
b00100111 :
b11111111 A
b100000010 B
b00001111 F
b00100111 G
#225000
0#
00
0=
#230000
1#
b110111100 )
b011010100 /
10
b110111100 6
b011010100 <
1=
b110111100 C
b011010100 I
#231000
b00000010 &
b11111110 '
b100000000 (
b00010001 ,
b00011111 -
b000110000 .
b00000010 3
b11111110 4
b100000000 5
b00010001 9
b00011111 :
b000110000 ;
b00000010 @
b11111110 A
b100000000 B
b00010001 F
b00011111 G
b000110000 H
#235000
0#
00
0=
#240000
1#
b010111010 )
b011110011 /
10
b010111010 6
b011110011 <
1=
b010111010 C
b011110011 I
#241000
b00000011 &
b11111111 '
b100000010 (
b00001110 ,
b00101000 -
b000110110 .
b00000011 3
b11111111 4
b100000010 5
b00001110 9
b00101000 :
b000110110 ;
b00000011 @
b11111111 A
b100000010 B
b00001110 F
b00101000 G
b000110110 H
#245000
0#
00
0=
#250000
1#
b110111001 )
b100011011 /
10
b110111001 6
b100011011 <
1=
b110111001 C
b100011011 I
#251000
b00001100 ,
b00100111 -
b000110011 .
b00001100 9
b00100111 :
b000110011 ;
b00001100 F
b00100111 G
b000110011 H
#255000
0#
00
0=
#260000
1#
b010111000 )
b101000010 /
10
b010111000 6
b101000010 <
1=
b010111000 C
b101000010 I
#261000
b00000100 &
b11111011 '
b011111111 (
b00010100 ,
b00100101 -
b000111001 .
b00000100 3
b11111011 4
b011111111 5
b00010100 9
b00100101 :
b000111001 ;
b00000100 @
b11111011 A
b011111111 B
b00010100 F
b00100101 G
b000111001 H
#265000
0#
00
0=
#270000
1#
b110110011 )
b101100111 /
10
b110110011 6
b101100111 <
1=
b110110011 C
b101100111 I
#271000
b00000001 &
b11111110 '
b00001100 ,
b00011110 -
b000101010 .
b00000001 3
b11111110 4
b00001100 9
b00011110 :
b000101010 ;
b00000001 @
b11111110 A
b00001100 F
b00011110 G
b000101010 H
#275000
0#
00
0=
#280000
1#
b010110001 )
b110000101 /
10
b010110001 6
b110000101 <
1=
b010110001 C
b110000101 I
#281000
b00000100 &
b11111010 '
b011111110 (
b00001111 ,
b00100100 -
b000110011 .
b00000100 3
b11111010 4
b011111110 5
b00001111 9
b00100100 :
b000110011 ;
b00000100 @
b11111010 A
b011111110 B
b00001111 F
b00100100 G
b000110011 H
#285000
0#
00
0=
#290000
1#
b110101011 )
b110101001 /
10
b110101011 6
b110101001 <
1=
b110101011 C
b110101001 I
#291000
b00000011 &
b11111011 '
b00001100 ,
b00100011 -
b000101111 .
b00000011 3
b11111011 4
b00001100 9
b00100011 :
b000101111 ;
b00000011 @
b11111011 A
b00001100 F
b00100011 G
b000101111 H
#295000
0#
00
0=
#300000
1#
b010100110 )
b111001100 /
10
b010100110 6
b111001100 <
1=
b010100110 C
b111001100 I
#301000
b00000010 &
b11111111 '
b100000001 (
b00001011 ,
b00100001 -
b000101100 .
b00000010 3
b11111111 4
b100000001 5
b00001011 9
b00100001 :
b000101100 ;
b00000010 @
b11111111 A
b100000001 B
b00001011 F
b00100001 G
b000101100 H
#305000
0#
00
0=
#310000
1#
b110100101 )
b111101101 /
10
b110100101 6
b111101101 <
1=
b110100101 C
b111101101 I
#311000
b00000001 &
b11111010 '
b011111011 (
b00001100 ,
b00100101 -
b000110001 .
b00000001 3
b11111010 4
b011111011 5
b00001100 9
b00100101 :
b000110001 ;
b00000001 @
b11111010 A
b011111011 B
b00001100 F
b00100101 G
b000110001 H
#315000
0#
00
0=
#320000
1#
b010011111 )
b000010010 /
10
b010011111 6
b000010010 <
1=
b010011111 C
b000010010 I
#321000
b00000000 &
b11111101 '
b011111101 (
b00010100 ,
b00101000 -
b000111100 .
b00000000 3
b11111101 4
b011111101 5
b00010100 9
b00101000 :
b000111100 ;
b00000000 @
b11111101 A
b011111101 B
b00010100 F
b00101000 G
b000111100 H
#325000
0#
00
0=
#330000
1#
b110011100 )
b000111010 /
10
b110011100 6
b000111010 <
1=
b110011100 C
b000111010 I
#331000
b00000100 &
b11111011 '
b011111111 (
b00001101 ,
b00100111 -
b000110100 .
b00000100 3
b11111011 4
b011111111 5
b00001101 9
b00100111 :
b000110100 ;
b00000100 @
b11111011 A
b011111111 B
b00001101 F
b00100111 G
b000110100 H
#335000
0#
00
0=
#340000
1#
b010010111 )
b001100001 /
10
b010010111 6
b001100001 <
1=
b010010111 C
b001100001 I
#341000
b00000010 &
b011111101 (
b00001111 ,
b00100010 -
b000110001 .
b00000010 3
b011111101 5
b00001111 9
b00100010 :
b000110001 ;
b00000010 @
b011111101 B
b00001111 F
b00100010 G
b000110001 H
#345000
0#
00
0=
#350000
1#
b110010010 )
b010000011 /
10
b110010010 6
b010000011 <
1=
b110010010 C
b010000011 I
#351000
b00000000 &
b011111011 (
b00010001 ,
b00101000 -
b000111001 .
b00000000 3
b011111011 5
b00010001 9
b00101000 :
b000111001 ;
b00000000 @
b011111011 B
b00010001 F
b00101000 G
b000111001 H
#355000
0#
00
0=
#360000
1#
b010001101 )
b010101011 /
10
b010001101 6
b010101011 <
1=
b010001101 C
b010101011 I
#361000
b00000100 &
b11111100 '
b100000000 (
b00001100 ,
b000110100 .
b00000100 3
b11111100 4
b100000000 5
b00001100 9
b000110100 ;
b00000100 @
b11111100 A
b100000000 B
b00001100 F
b000110100 H
#365000
0#
00
0=
#370000
1#
b110001001 )
b011010011 /
10
b110001001 6
b011010011 <
1=
b110001001 C
b011010011 I
#371000
b00000001 &
b011111101 (
b00010011 ,
b00100110 -
b000111001 .
b00000001 3
b011111101 5
b00010011 9
b00100110 :
b000111001 ;
b00000001 @
b011111101 B
b00010011 F
b00100110 G
b000111001 H
#375000
0#
00
0=
#380000
1#
b010000101 )
b011111001 /
10
b010000101 6
b011111001 <
1=
b010000101 C
b011111001 I
#381000
b00000010 &
b11111011 '
b00001110 ,
b00100101 -
b000110011 .
b00000010 3
b11111011 4
b00001110 9
b00100101 :
b000110011 ;
b00000010 @
b11111011 A
b00001110 F
b00100101 G
b000110011 H
#385000
0#
00
0=
#390000
1#
b110000000 )
b100011110 /
10
b110000000 6
b100011110 <
1=
b110000000 C
b100011110 I
#391000
b00000011 &
b011111110 (
b00001011 ,
b00100010 -
b000101101 .
b00000011 3
b011111110 5
b00001011 9
b00100010 :
b000101101 ;
b00000011 @
b011111110 B
b00001011 F
b00100010 G
b000101101 H
#395000
0#
00
0=
#400000
1#
b001111011 )
b101000000 /
10
b001111011 6
b101000000 <
1=
b001111011 C
b101000000 I
#401000
b00000001 &
b11111101 '
b00001111 ,
b00100000 -
b000101111 .
b00000001 3
b11111101 4
b00001111 9
b00100000 :
b000101111 ;
b00000001 @
b11111101 A
b00001111 F
b00100000 G
b000101111 H
#405000
0#
00
0=
#410000
1#
b101111000 )
b101100000 /
10
b101111000 6
b101100000 <
1=
b101111000 C
b101100000 I
#411000
b11111010 '
b011111011 (
b00011110 -
b000101101 .
b11111010 4
b011111011 5
b00011110 :
b000101101 ;
b11111010 A
b011111011 B
b00011110 G
b000101101 H
#415000
0#
00
0=
#420000
1#
b001110010 )
b101111110 /
10
b001110010 6
b101111110 <
1=
b001110010 C
b101111110 I
#421000
b00000010 &
b11111110 '
b100000000 (
b00001110 ,
b00011111 -
b00000010 3
b11111110 4
b100000000 5
b00001110 9
b00011111 :
b00000010 @
b11111110 A
b100000000 B
b00001110 F
b00011111 G
#425000
0#
00
0=
#430000
1#
b101110000 )
b110011101 /
10
b101110000 6
b110011101 <
1=
b101110000 C
b110011101 I
#431000
b00000100 &
b100000010 (
b00001100 ,
b00100111 -
b000110011 .
b00000100 3
b100000010 5
b00001100 9
b00100111 :
b000110011 ;
b00000100 @
b100000010 B
b00001100 F
b00100111 G
b000110011 H
#435000
0#
00
0=
#440000
1#
b001101110 )
b111000100 /
10
b001101110 6
b111000100 <
1=
b001101110 C
b111000100 I
#441000
b00000101 &
b11111111 '
b100000100 (
b00001101 ,
b00011110 -
b000101011 .
b00000101 3
b11111111 4
b100000100 5
b00001101 9
b00011110 :
b000101011 ;
b00000101 @
b11111111 A
b100000100 B
b00001101 F
b00011110 G
b000101011 H
#445000
0#
00
0=
#450000
1#
b101101101 )
b111100010 /
10
b101101101 6
b111100010 <
1=
b101101101 C
b111100010 I
#451000
b00000000 &
b11111010 '
b011111010 (
b00001100 ,
b00100111 -
b000110011 .
b00000000 3
b11111010 4
b011111010 5
b00001100 9
b00100111 :
b000110011 ;
b00000000 @
b11111010 A
b011111010 B
b00001100 F
b00100111 G
b000110011 H
#455000
0#
00
0=
#460000
1#
b001100111 )
b000001001 /
10
b001100111 6
b000001001 <
1=
b001100111 C
b000001001 I
#461000
b00000001 &
b11111101 '
b011111110 (
b00001110 ,
b00100100 -
b000110010 .
b00000001 3
b11111101 4
b011111110 5
b00001110 9
b00100100 :
b000110010 ;
b00000001 @
b11111101 A
b011111110 B
b00001110 F
b00100100 G
b000110010 H
#465000
0#
00
0=
#470000
1#
b101100100 )
b000101101 /
10
b101100100 6
b000101101 <
1=
b101100100 C
b000101101 I
#471000
b00000101 &
b11111110 '
b100000011 (
b00001011 ,
b000101111 .
b00000101 3
b11111110 4
b100000011 5
b00001011 9
b000101111 ;
b00000101 @
b11111110 A
b100000011 B
b00001011 F
b000101111 H
#475000
0#
00
0=
#480000
1#
b001100010 )
b001010001 /
10
b001100010 6
b001010001 <
1=
b001100010 C
b001010001 I
#481000
b00000011 &
b11111101 '
b100000000 (
b00010100 ,
b000111000 .
b00000011 3
b11111101 4
b100000000 5
b00010100 9
b000111000 ;
b00000011 @
b11111101 A
b100000000 B
b00010100 F
b000111000 H
#485000
0#
00
0=
#490000
1#
b101011111 )
b001110101 /
10
b101011111 6
b001110101 <
1=
b101011111 C
b001110101 I
#491000
b00000101 &
b11111111 '
b100000100 (
b00001011 ,
b00100101 -
b000110000 .
b00000101 3
b11111111 4
b100000100 5
b00001011 9
b00100101 :
b000110000 ;
b00000101 @
b11111111 A
b100000100 B
b00001011 F
b00100101 G
b000110000 H
#495000
0#
00
0=
#500000
1#
b001011110 )
b010011010 /
10
b001011110 6
b010011010 <
1=
b001011110 C
b010011010 I
#501000
b00000011 &
b11111101 '
b100000000 (
b00010000 ,
b00011111 -
b000101111 .
b00000011 3
b11111101 4
b100000000 5
b00010000 9
b00011111 :
b000101111 ;
b00000011 @
b11111101 A
b100000000 B
b00010000 F
b00011111 G
b000101111 H
#505000
0#
00
0=
#510000
1#
b101011011 )
b010111001 /
10
b101011011 6
b010111001 <
1=
b101011011 C
b010111001 I
#511000
b00000000 &
b11111011 '
b011111011 (
b00010011 ,
b00100111 -
b000111010 .
b00000000 3
b11111011 4
b011111011 5
b00010011 9
b00100111 :
b000111010 ;
b00000000 @
b11111011 A
b011111011 B
b00010011 F
b00100111 G
b000111010 H
#515000
0#
00
0=
#520000
1#
b001010110 )
b011100000 /
10
b001010110 6
b011100000 <
1=
b001010110 C
b011100000 I
#521000
b00000101 &
b11111110 '
b100000011 (
b00010100 ,
b00100100 -
b000111000 .
b00000101 3
b11111110 4
b100000011 5
b00010100 9
b00100100 :
b000111000 ;
b00000101 @
b11111110 A
b100000011 B
b00010100 F
b00100100 G
b000111000 H
#525000
0#
00
0=
#530000
1#
b101010100 )
b100000100 /
10
b101010100 6
b100000100 <
1=
b101010100 C
b100000100 I
#531000
b00000100 &
b11111100 '
b100000000 (
b00010001 ,
b00011111 -
b000110000 .
b00000100 3
b11111100 4
b100000000 5
b00010001 9
b00011111 :
b000110000 ;
b00000100 @
b11111100 A
b100000000 B
b00010001 F
b00011111 G
b000110000 H
#535000
0#
00
0=
#540000
1#
b001010000 )
b100100011 /
10
b001010000 6
b100100011 <
1=
b001010000 C
b100100011 I
#541000
b00000000 &
b11111011 '
b011111011 (
b00010010 ,
b00100000 -
b000110010 .
b00000000 3
b11111011 4
b011111011 5
b00010010 9
b00100000 :
b000110010 ;
b00000000 @
b11111011 A
b011111011 B
b00010010 F
b00100000 G
b000110010 H
#545000
0#
00
0=
#550000
1#
b101001011 )
b101000011 /
10
b101001011 6
b101000011 <
1=
b101001011 C
b101000011 I
#551000
b00000101 &
b11111101 '
b100000010 (
b00010100 ,
b00100101 -
b000111001 .
b00000101 3
b11111101 4
b100000010 5
b00010100 9
b00100101 :
b000111001 ;
b00000101 @
b11111101 A
b100000010 B
b00010100 F
b00100101 G
b000111001 H
#555000
0#
00
0=
#560000
1#
b001001000 )
b101101000 /
10
b001001000 6
b101101000 <
1=
b001001000 C
b101101000 I
#561000
b00000000 &
b11111110 '
b011111110 (
b00001110 ,
b00100110 -
b000110100 .
b00000000 3
b11111110 4
b011111110 5
b00001110 9
b00100110 :
b000110100 ;
b00000000 @
b11111110 A
b011111110 B
b00001110 F
b00100110 G
b000110100 H
#565000
0#
00
0=
#570000
1#
b101000110 )
b110001110 /
10
b101000110 6
b110001110 <
1=
b101000110 C
b110001110 I
#571000
b00000001 &
b11111111 '
b100000000 (
b00001111 ,
b00101000 -
b000110111 .
b00000001 3
b11111111 4
b100000000 5
b00001111 9
b00101000 :
b000110111 ;
b00000001 @
b11111111 A
b100000000 B
b00001111 F
b00101000 G
b000110111 H
#575000
0#
00
0=
#580000
1#
b001000101 )
b110110110 /
10
b001000101 6
b110110110 <
1=
b001000101 C
b110110110 I
#581000
b00000011 &
b11111010 '
b011111101 (
b00010011 ,
b00100111 -
b000111010 .
b00000011 3
b11111010 4
b011111101 5
b00010011 9
b00100111 :
b000111010 ;
b00000011 @
b11111010 A
b011111101 B
b00010011 F
b00100111 G
b000111010 H
#585000
0#
00
0=
#590000
1#
b100111111 )
b111011101 /
10
b100111111 6
b111011101 <
1=
b100111111 C
b111011101 I
#591000
b00000001 &
b11111110 '
b011111111 (
b00001011 ,
b00011111 -
b000101010 .
b00000001 3
b11111110 4
b011111111 5
b00001011 9
b00011111 :
b000101010 ;
b00000001 @
b11111110 A
b011111111 B
b00001011 F
b00011111 G
b000101010 H
#595000
0#
00
0=
#600000
1#
b000111101 )
b111111100 /
10
b000111101 6
b111111100 <
1=
b000111101 C
b111111100 I
#601000
b00000011 &
b100000001 (
b00010001 ,
b00100101 -
b000110110 .
b00000011 3
b100000001 5
b00010001 9
b00100101 :
b000110110 ;
b00000011 @
b100000001 B
b00010001 F
b00100101 G
b000110110 H
#605000
0#
00
0=
#610000
1#
b100111011 )
b000100001 /
10
b100111011 6
b000100001 <
1=
b100111011 C
b000100001 I
#611000
b00000101 &
b11111101 '
b100000010 (
b00010100 ,
b00011111 -
b000110011 .
b00000101 3
b11111101 4
b100000010 5
b00010100 9
b00011111 :
b000110011 ;
b00000101 @
b11111101 A
b100000010 B
b00010100 F
b00011111 G
b000110011 H
#615000
0#
00
0=
#620000
1#
b000111000 )
b001000000 /
10
b000111000 6
b001000000 <
1=
b000111000 C
b001000000 I
#621000
b00000011 &
b11111100 '
b011111111 (
b00010011 ,
b00011110 -
b000110001 .
b00000011 3
b11111100 4
b011111111 5
b00010011 9
b00011110 :
b000110001 ;
b00000011 @
b11111100 A
b011111111 B
b00010011 F
b00011110 G
b000110001 H
#625000
0#
00
0=
#630000
1#
b100110100 )
b001011110 /
10
b100110100 6
b001011110 <
1=
b100110100 C
b001011110 I
#631000
b00000100 &
b11111011 '
b00001100 ,
b00100001 -
b000101101 .
b00000100 3
b11111011 4
b00001100 9
b00100001 :
b000101101 ;
b00000100 @
b11111011 A
b00001100 F
b00100001 G
b000101101 H
#635000
0#
00
0=
#640000
1#
b000101111 )
b001111111 /
10
b000101111 6
b001111111 <
1=
b000101111 C
b001111111 I
#641000
b00000001 &
b11111100 '
b011111101 (
b00001011 ,
b00100111 -
b000110010 .
b00000001 3
b11111100 4
b011111101 5
b00001011 9
b00100111 :
b000110010 ;
b00000001 @
b11111100 A
b011111101 B
b00001011 F
b00100111 G
b000110010 H
#645000
0#
00
0=
#650000
1#
b100101011 )
b010100110 /
10
b100101011 6
b010100110 <
1=
b100101011 C
b010100110 I
#651000
b11111111 '
b100000000 (
b00001010 ,
b00100100 -
b000101110 .
b11111111 4
b100000000 5
b00001010 9
b00100100 :
b000101110 ;
b11111111 A
b100000000 B
b00001010 F
b00100100 G
b000101110 H
#655000
0#
00
0=
#660000
1#
b000101010 )
b011001010 /
10
b000101010 6
b011001010 <
1=
b000101010 C
b011001010 I
