rtl/top_level.sv


module top_level (
    input  logic       clk,

    // Channel A
    input  logic       rst_A,
    input  logic       valid_in_A,
    input  logic [7:0] a_A,
    input  logic [7:0] b_A,
    output logic [8:0] sum_async_A,
    output logic [8:0] sum_sync_A,

    // Channel B
    input  logic       rst_B,
    input  logic       valid_in_B,
    input  logic [7:0] a_B,
    input  logic [7:0] b_B,
    output logic [8:0] sum_async_B,
    output logic [8:0] sum_sync_B
);

    // Channel A synchronous accumulator
    always_ff @(posedge clk) begin
        if (rst_A)
            sum_sync_A <= '0;
        else if (valid_in_A)
            sum_sync_A <= sum_sync_A + b_A;
    end

    assign sum_async_A = a_A + b_A;

    // Channel B synchronous accumulator
    always_ff @(posedge clk) begin
        if (rst_B)
            sum_sync_B <= '0;
        else if (valid_in_B)
            sum_sync_B <= sum_sync_B + b_B;
    end

    assign sum_async_B = a_B + b_B;

    initial begin
        $display("Time | rst_A| valid_in_A | a_A | b_A |sum_async_A | sum_sync_A |rst_B | valid_in_B| a_B | b_B  | sum_async_B | sum_sync_B   ");
        $monitor("%4t  |  %b  |  %b        | %0d | %0d |    %0d     |   %0d      | %b   |    %b     | %0d | %0d  |    %0d      |   %0d ",
                 $time, rst_A, valid_in_A, a_A, b_A, sum_async_A,sum_sync_A, rst_B, valid_in_B, a_B, b_B, sum_async_B, sum_sync_B);
    end

    initial begin
        $dumpfile("dump.vcd");
        $dumpvars(1, top_level.sv);
    end

endmodule

rtl/dut_wrapper.sv
module dut_wrapper (
    input  logic       clk,

    // Channel A – cocotb drives these
    input  logic       rst_A,
    input  logic       valid_in_A,
    input  logic [7:0] a_A,
    input  logic [7:0] b_A,

    // DUT drives these
    output logic [8:0] sum_async_A,
    output logic [8:0] sum_sync_A,

    // Channel B (if needed)
    input  logic       rst_B,
    input  logic       valid_in_B,
    input  logic [7:0] a_B,
    input  logic [7:0] b_B,
    output logic [8:0] sum_async_B,
    output logic [8:0] sum_sync_B
);

    top_level u_top_level (
        .clk(clk),

        // Channel A
        .rst_A(rst_A),
        .valid_in_A(valid_in_A),
        .a_A(a_A),
        .b_A(b_A),
        .sum_async_A(sum_async_A),
        .sum_sync_A(sum_sync_A),

        // Channel B
        .rst_B(rst_B),
        .valid_in_B(valid_in_B),
        .a_B(a_B),
        .b_B(b_B),
        .sum_async_B(sum_async_B),
        .sum_sync_B(sum_sync_B)
    );

endmodule



// module dut_wrapper (
//     input  logic       clk,

//     // Channel A – exposed directly for cocotb
//     output logic       rst_A,
//     output logic       valid_in_A,
//     output logic [7:0] a_A,
//     output logic [7:0] b_A,
//     output logic [8:0] sum_async_A,
//     output logic [8:0] sum_sync_A,

//     // Channel B – exposed directly for cocotb
//     output logic       rst_B,
//     output logic       valid_in_B,
//     output logic [7:0] a_B,
//     output logic [7:0] b_B,
//     output logic [8:0] sum_async_B,
//     output logic [8:0] sum_sync_B
// );

//     // Internal wires driven by cocotb (use these as DUT inputs)
//     logic rst_A_int;
//     logic valid_in_A_int;
//     logic [7:0] a_A_int;
//     logic [7:0] b_A_int;

//     logic rst_B_int;
//     logic valid_in_B_int;
//     logic [7:0] a_B_int;
//     logic [7:0] b_B_int;

//     // Connect exposed ports to internal wires so cocotb can drive them
//     assign rst_A       = rst_A_int;
//     assign valid_in_A  = valid_in_A_int;
//     assign a_A         = a_A_int;
//     assign b_A         = b_A_int;

//     assign rst_B       = rst_B_int;
//     assign valid_in_B  = valid_in_B_int;
//     assign a_B         = a_B_int;
//     assign b_B         = b_B_int;

//     // DUT instance
//     top_level u_top_level (
//         .clk          (clk),

//         // Channel A
//         .rst_A        (rst_A_int),
//         .valid_in_A   (valid_in_A_int),
//         .a_A          (a_A_int),
//         .b_A          (b_A_int),
//         .sum_async_A  (sum_async_A),
//         .sum_sync_A   (sum_sync_A),

//         // Channel B
//         .rst_B        (rst_B_int),
//         .valid_in_B   (valid_in_B_int),
//         .a_B          (a_B_int),
//         .b_B          (b_B_int),
//         .sum_async_B  (sum_async_B),
//         .sum_sync_B   (sum_sync_B)
//     );

// endmodule

regression_results/waves_9.vcd
$version Generated by VerilatedVcd $end
$timescale 1ps $end
 $scope module $rootio $end
  $var wire 1 # clk $end
  $var wire 1 $ rst_A $end
  $var wire 1 % valid_in_A $end
  $var wire 8 & a_A [7:0] $end
  $var wire 8 ' b_A [7:0] $end
  $var wire 9 ( sum_async_A [8:0] $end
  $var wire 9 ) sum_sync_A [8:0] $end
  $var wire 1 * rst_B $end
  $var wire 1 + valid_in_B $end
  $var wire 8 , a_B [7:0] $end
  $var wire 8 - b_B [7:0] $end
  $var wire 9 . sum_async_B [8:0] $end
  $var wire 9 / sum_sync_B [8:0] $end
 $upscope $end
 $scope module dut_wrapper $end
  $var wire 1 0 clk $end
  $var wire 1 1 rst_A $end
  $var wire 1 2 valid_in_A $end
  $var wire 8 3 a_A [7:0] $end
  $var wire 8 4 b_A [7:0] $end
  $var wire 9 5 sum_async_A [8:0] $end
  $var wire 9 6 sum_sync_A [8:0] $end
  $var wire 1 7 rst_B $end
  $var wire 1 8 valid_in_B $end
  $var wire 8 9 a_B [7:0] $end
  $var wire 8 : b_B [7:0] $end
  $var wire 9 ; sum_async_B [8:0] $end
  $var wire 9 < sum_sync_B [8:0] $end
  $scope module u_top_level $end
   $var wire 1 = clk $end
   $var wire 1 > rst_A $end
   $var wire 1 ? valid_in_A $end
   $var wire 8 @ a_A [7:0] $end
   $var wire 8 A b_A [7:0] $end
   $var wire 9 B sum_async_A [8:0] $end
   $var wire 9 C sum_sync_A [8:0] $end
   $var wire 1 D rst_B $end
   $var wire 1 E valid_in_B $end
   $var wire 8 F a_B [7:0] $end
   $var wire 8 G b_B [7:0] $end
   $var wire 9 H sum_async_B [8:0] $end
   $var wire 9 I sum_sync_B [8:0] $end
  $upscope $end
 $upscope $end
$enddefinitions $end


#0
1#
1$
0%
b00000000 &
b00000000 '
b000000000 (
b000000000 )
1*
0+
b00000000 ,
b00000000 -
b000000000 .
b000000000 /
10
11
02
b00000000 3
b00000000 4
b000000000 5
b000000000 6
17
08
b00000000 9
b00000000 :
b000000000 ;
b000000000 <
1=
1>
0?
b00000000 @
b00000000 A
b000000000 B
b000000000 C
1D
0E
b00000000 F
b00000000 G
b000000000 H
b000000000 I
#2021000
00
0=
#5000
1#
10
1=
#7500
0#
00
0=
#10000
1#
10
1=
#12500
0#
00
0=
#15000
1#
10
1=
#17500
0#
00
0=
#20000
1#
0$
1%
b11110110 &
b00100111 '
b100011101 (
0*
10
01
12
b11110110 3
b00100111 4
b100011101 5
07
1=
0>
1?
b11110110 @
b00100111 A
b100011101 B
0D
#22500
0#
00
0=
#25000
1#
b000100111 )
10
b000100111 6
1=
b000100111 C
#26000
0%
1+
b00101101 ,
b01100000 -
b010001101 .
02
18
b00101101 9
b01100000 :
b010001101 ;
0?
1E
b00101101 F
b01100000 G
b010001101 H
#27500
0#
00
0=
#30000
1#
b001100000 /
10
b001100000 <
1=
b001100000 I
#31000
0+
08
0E
#32000
1%
b11010001 &
b00001100 '
b011011101 (
12
b11010001 3
b00001100 4
b011011101 5
1?
b11010001 @
b00001100 A
b011011101 B
#32500
0#
00
0=
#35000
1#
b000110011 )
10
b000110011 6
1=
b000110011 C
#36000
0%
1+
b10100111 ,
b01101110 -
b100010101 .
02
18
b10100111 9
b01101110 :
b100010101 ;
0?
1E
b10100111 F
b01101110 G
b100010101 H
#37500
0#
00
0=
#40000
1#
b011001110 /
10
b011001110 <
1=
b011001110 I
#41000
0+
08
0E
#42000
1%
b11110011 &
b11011100 '
b111001111 (
12
b11110011 3
b11011100 4
b111001111 5
1?
b11110011 @
b11011100 A
b111001111 B
#42500
0#
00
0=
#45000
1#
b100001111 )
10
b100001111 6
1=
b100001111 C
#46000
0%
1+
b00100010 ,
b00000000 -
b000100010 .
02
18
b00100010 9
b00000000 :
b000100010 ;
0?
1E
b00100010 F
b00000000 G
b000100010 H
#47500
0#
00
0=
#50000
1#
10
1=
#51000
0+
08
0E
#52000
1%
b11001001 &
b01111010 '
b101000011 (
12
b11001001 3
b01111010 4
b101000011 5
1?
b11001001 @
b01111010 A
b101000011 B
#52500
0#
00
0=
#55000
1#
b110001001 )
10
b110001001 6
1=
b110001001 C
#56000
0%
1+
b00101000 ,
b11001000 -
b011110000 .
02
18
b00101000 9
b11001000 :
b011110000 ;
0?
1E
b00101000 F
b11001000 G
b011110000 H
#57500
0#
00
0=
#60000
1#
b110010110 /
10
b110010110 <
1=
b110010110 I
#61000
0+
08
0E
#62000
1%
b01111101 &
b01111011 '
b011111000 (
12
b01111101 3
b01111011 4
b011111000 5
1?
b01111101 @
b01111011 A
b011111000 B
#62500
0#
00
0=
#65000
1#
b000000100 )
10
b000000100 6
1=
b000000100 C
#66000
0%
1+
b00010000 ,
b10110011 -
b011000011 .
02
18
b00010000 9
b10110011 :
b011000011 ;
0?
1E
b00010000 F
b10110011 G
b011000011 H
#67500
0#
00
0=
#70000
1#
b001001001 /
10
b001001001 <
1=
b001001001 I
#71000
0+
08
0E
#72000
1%
b00110100 &
b01111101 '
b010110001 (
12
b00110100 3
b01111101 4
b010110001 5
1?
b00110100 @
b01111101 A
b010110001 B
#72500
0#
00
0=
#75000
1#
b010000001 )
10
b010000001 6
1=
b010000001 C
#76000
0%
1+
b11101101 ,
b01011001 -
b101000110 .
02
18
b11101101 9
b01011001 :
b101000110 ;
0?
1E
b11101101 F
b01011001 G
b101000110 H
#77500
0#
00
0=
#80000
1#
b010100010 /
10
b010100010 <
1=
b010100010 I
#81000
0+
08
0E
#82000
1%
b10110111 &
b10011001 '
b101010000 (
12
b10110111 3
b10011001 4
b101010000 5
1?
b10110111 @
b10011001 A
b101010000 B
#82500
0#
00
0=
#85000
1#
b100011010 )
10
b100011010 6
1=
b100011010 C
#86000
0%
1+
b10101000 ,
b01101101 -
b100010101 .
02
18
b10101000 9
b01101101 :
b100010101 ;
0?
1E
b10101000 F
b01101101 G
b100010101 H
#87500
0#
00
0=
#90000
1#
b100001111 /
10
b100001111 <
1=
b100001111 I
#91000
0+
08
0E
#92000
1%
b11101010 &
b10110101 '
b110011111 (
12
b11101010 3
b10110101 4
b110011111 5
1?
b11101010 @
b10110101 A
b110011111 B
#92500
0#
00
0=
#95000
1#
b111001111 )
10
b111001111 6
1=
b111001111 C
#96000
0%
1+
b11100011 ,
b11001111 -
b110110010 .
02
18
b11100011 9
b11001111 :
b110110010 ;
0?
1E
b11100011 F
b11001111 G
b110110010 H
#97500
0#
00
0=
#100000
1#
b111011110 /
10
b111011110 <
1=
b111011110 I
#101000
0+
08
0E
#102000
1%
b11111001 &
b00010100 '
b100001101 (
12
b11111001 3
b00010100 4
b100001101 5
1?
b11111001 @
b00010100 A
b100001101 B
#102500
0#
00
0=
#105000
1#
b111100011 )
10
b111100011 6
1=
b111100011 C
#106000
0%
1+
b00110110 ,
b00101100 -
b001100010 .
02
18
b00110110 9
b00101100 :
b001100010 ;
0?
1E
b00110110 F
b00101100 G
b001100010 H
#107500
0#
00
0=
#110000
1#
b000001010 /
10
b000001010 <
1=
b000001010 I
#111000
0+
08
0E
#112000
1%
b00000101 &
b11011100 '
b011100001 (
12
b00000101 3
b11011100 4
b011100001 5
1?
b00000101 @
b11011100 A
b011100001 B
#112500
0#
00
0=
#115000
1#
b010111111 )
10
b010111111 6
1=
b010111111 C
#116000
0%
1+
b11010101 ,
b11101101 -
b111000010 .
02
18
b11010101 9
b11101101 :
b111000010 ;
0?
1E
b11010101 F
b11101101 G
b111000010 H
#117500
0#
00
0=
#120000
1#
b011110111 /
10
b011110111 <
1=
b011110111 I
#121000
0+
08
0E
#122000
1%
b00011000 &
b01101100 '
b010000100 (
12
b00011000 3
b01101100 4
b010000100 5
1?
b00011000 @
b01101100 A
b010000100 B
#122500
0#
00
0=
#125000
1#
b100101011 )
10
b100101011 6
1=
b100101011 C
#126000
0%
1+
b10101011 ,
b10100011 -
b101001110 .
02
18
b10101011 9
b10100011 :
b101001110 ;
0?
1E
b10101011 F
b10100011 G
b101001110 H
#127500
0#
00
0=
#130000
1#
b110011010 /
10
b110011010 <
1=
b110011010 I
#131000
0+
08
0E
#132000
1%
b11111101 &
b11001000 '
b111000101 (
12
b11111101 3
b11001000 4
b111000101 5
1?
b11111101 @
b11001000 A
b111000101 B
#132500
0#
00
0=
#135000
1#
b111110011 )
10
b111110011 6
1=
b111110011 C
#136000
0%
1+
b00000111 ,
b00100111 -
b000101110 .
02
18
b00000111 9
b00100111 :
b000101110 ;
0?
1E
b00000111 F
b00100111 G
b000101110 H
#137500
0#
00
0=
#140000
1#
b111000001 /
10
b111000001 <
1=
b111000001 I
#141000
0+
08
0E
#142000
1%
b01111011 &
b01111000 '
b011110011 (
12
b01111011 3
b01111000 4
b011110011 5
1?
b01111011 @
b01111000 A
b011110011 B
#142500
0#
00
0=
#145000
1#
b001101011 )
10
b001101011 6
1=
b001101011 C
#146000
0%
1+
b11001111 ,
b10000010 -
b101010001 .
02
18
b11001111 9
b10000010 :
b101010001 ;
0?
1E
b11001111 F
b10000010 G
b101010001 H
#147500
0#
00
0=
#150000
1#
b001000011 /
10
b001000011 <
1=
b001000011 I
#151000
0+
08
0E
#152000
1%
b01010101 &
b00111011 '
b010010000 (
12
b01010101 3
b00111011 4
b010010000 5
1?
b01010101 @
b00111011 A
b010010000 B
#152500
0#
00
0=
#155000
1#
b010100110 )
10
b010100110 6
1=
b010100110 C
#156000
0%
1+
b01110001 ,
b01011001 -
b011001010 .
02
18
b01110001 9
b01011001 :
b011001010 ;
0?
1E
b01110001 F
b01011001 G
b011001010 H
#157500
0#
00
0=
#160000
1#
b010011100 /
10
b010011100 <
1=
b010011100 I
#161000
0+
08
0E
#162000
1%
b00001100 &
b10001011 '
b010010111 (
12
b00001100 3
b10001011 4
b010010111 5
1?
b00001100 @
b10001011 A
b010010111 B
#162500
0#
00
0=
#165000
1#
b100110001 )
10
b100110001 6
1=
b100110001 C
#166000
0%
1+
b11101100 ,
b11101011 -
b111010111 .
02
18
b11101100 9
b11101011 :
b111010111 ;
0?
1E
b11101100 F
b11101011 G
b111010111 H
#167500
0#
00
0=
#170000
1#
b110000111 /
10
b110000111 <
1=
b110000111 I
#171000
0+
08
0E
#172000
1%
b11110000 &
b00011111 '
b100001111 (
12
b11110000 3
b00011111 4
b100001111 5
1?
b11110000 @
b00011111 A
b100001111 B
#172500
0#
00
0=
#175000
1#
b101010000 )
10
b101010000 6
1=
b101010000 C
#176000
0%
1+
b11010010 ,
b00011011 -
b011101101 .
02
18
b11010010 9
b00011011 :
b011101101 ;
0?
1E
b11010010 F
b00011011 G
b011101101 H
#177500
0#
00
0=
#180000
1#
b110100010 /
10
b110100010 <
1=
b110100010 I
#181000
0+
08
0E
#182000
1%
b11011111 &
b11001010 '
b110101001 (
12
b11011111 3
b11001010 4
b110101001 5
1?
b11011111 @
b11001010 A
b110101001 B
#182500
0#
00
0=
#185000
1#
b000011010 )
10
b000011010 6
1=
b000011010 C
#186000
0%
1+
b00010111 ,
b01010100 -
b001101011 .
02
18
b00010111 9
b01010100 :
b001101011 ;
0?
1E
b00010111 F
b01010100 G
b001101011 H
#187500
0#
00
0=
#190000
1#
b111110110 /
10
b111110110 <
1=
b111110110 I
#191000
0+
08
0E
#192000
1%
b01000111 &
b00010000 '
b001010111 (
12
b01000111 3
b00010000 4
b001010111 5
1?
b01000111 @
b00010000 A
b001010111 B
#192500
0#
00
0=
#195000
1#
b000101010 )
10
b000101010 6
1=
b000101010 C
#196000
0%
1+
b01100010 ,
b10101101 -
b100001111 .
02
18
b01100010 9
b10101101 :
b100001111 ;
0?
1E
b01100010 F
b10101101 G
b100001111 H
#197500
0#
00
0=
#200000
1#
b010100011 /
10
b010100011 <
1=
b010100011 I
#201000
0+
08
0E
#202000
1%
b00111110 &
b10101111 '
b011101101 (
12
b00111110 3
b10101111 4
b011101101 5
1?
b00111110 @
b10101111 A
b011101101 B
#202500
0#
00
0=
#205000
1#
b011011001 )
10
b011011001 6
1=
b011011001 C
#206000
0%
1+
b00110110 ,
b01011101 -
b010010011 .
02
18
b00110110 9
b01011101 :
b010010011 ;
0?
1E
b00110110 F
b01011101 G
b010010011 H
#207500
0#
00
0=
#210000
1#
b100000000 /
10
b100000000 <
1=
b100000000 I
#211000
0+
08
0E
#212000
1%
b00011100 &
b00001101 '
b000101001 (
12
b00011100 3
b00001101 4
b000101001 5
1?
b00011100 @
b00001101 A
b000101001 B
#212500
0#
00
0=
#215000
1#
b011100110 )
10
b011100110 6
1=
b011100110 C
#216000
0%
1+
b10100000 ,
b10101111 -
b101001111 .
02
18
b10100000 9
b10101111 :
b101001111 ;
0?
1E
b10100000 F
b10101111 G
b101001111 H
#217500
0#
00
0=
#220000
1#
b110101111 /
10
b110101111 <
1=
b110101111 I
#221000
0+
08
0E
#222000
1%
b11011101 &
b00100100 '
b100000001 (
12
b11011101 3
b00100100 4
b100000001 5
1?
b11011101 @
b00100100 A
b100000001 B
#222500
0#
00
0=
#225000
1#
b100001010 )
10
b100001010 6
1=
b100001010 C
#226000
0%
1+
b01110110 ,
b00001011 -
b010000001 .
02
18
b01110110 9
b00001011 :
b010000001 ;
0?
1E
b01110110 F
b00001011 G
b010000001 H
#227500
0#
00
0=
#230000
1#
b110111010 /
10
b110111010 <
1=
b110111010 I
#231000
0+
08
0E
#232000
1%
b10101110 &
b10010011 '
b101000001 (
12
b10101110 3
b10010011 4
b101000001 5
1?
b10101110 @
b10010011 A
b101000001 B
#232500
0#
00
0=
#235000
1#
b110011101 )
10
b110011101 6
1=
b110011101 C
#236000
0%
1+
b11001011 ,
b01000011 -
b100001110 .
02
18
b11001011 9
b01000011 :
b100001110 ;
0?
1E
b11001011 F
b01000011 G
b100001110 H
#237500
0#
00
0=
#240000
1#
b111111101 /
10
b111111101 <
1=
b111111101 I
#241000
0+
08
0E
#242000
1%
b10111011 &
b10110111 '
b101110010 (
12
b10111011 3
b10110111 4
b101110010 5
1?
b10111011 @
b10110111 A
b101110010 B
#242500
0#
00
0=
#245000
1#
b001010100 )
10
b001010100 6
1=
b001010100 C
#246000
0%
1+
b01100101 ,
b10101100 -
b100010001 .
02
18
b01100101 9
b10101100 :
b100010001 ;
0?
1E
b01100101 F
b10101100 G
b100010001 H
#247500
0#
00
0=
#250000
1#
b010101001 /
10
b010101001 <
1=
b010101001 I
#251000
0+
08
0E
#252000
1%
b11000000 &
b00101110 '
b011101110 (
12
b11000000 3
b00101110 4
b011101110 5
1?
b11000000 @
b00101110 A
b011101110 B
#252500
0#
00
0=
#255000
1#
b010000010 )
10
b010000010 6
1=
b010000010 C
#256000
0%
1+
b00111000 ,
b01011100 -
b010010100 .
02
18
b00111000 9
b01011100 :
b010010100 ;
0?
1E
b00111000 F
b01011100 G
b010010100 H
#257500
0#
00
0=
#260000
1#
b100000101 /
10
b100000101 <
1=
b100000101 I
#261000
0+
08
0E
#262000
1%
b01010001 &
b01101101 '
b010111110 (
12
b01010001 3
b01101101 4
b010111110 5
1?
b01010001 @
b01101101 A
b010111110 B
#262500
0#
00
0=
#265000
1#
b011101111 )
10
b011101111 6
1=
b011101111 C
#266000
0%
1+
b00101100 ,
b00001001 -
b000110101 .
02
18
b00101100 9
b00001001 :
b000110101 ;
0?
1E
b00101100 F
b00001001 G
b000110101 H
#267500
0#
00
0=
#270000
1#
b100001110 /
10
b100001110 <
1=
b100001110 I
#271000
0+
08
0E
#272000
1%
b00101111 &
b01000111 '
b001110110 (
12
b00101111 3
b01000111 4
b001110110 5
1?
b00101111 @
b01000111 A
b001110110 B
#272500
0#
00
0=
#275000
1#
b100110110 )
10
b100110110 6
1=
b100110110 C
#276000
0%
1+
b01100100 ,
b01100110 -
b011001010 .
02
18
b01100100 9
b01100110 :
b011001010 ;
0?
1E
b01100100 F
b01100110 G
b011001010 H
#277500
0#
00
0=
#280000
1#
b101110100 /
10
b101110100 <
1=
b101110100 I
#281000
0+
08
0E
#282000
1%
b10010101 &
b10011011 '
b100110000 (
12
b10010101 3
b10011011 4
b100110000 5
1?
b10010101 @
b10011011 A
b100110000 B
#282500
0#
00
0=
#285000
1#
b111010001 )
10
b111010001 6
1=
b111010001 C
#286000
0%
1+
b01100000 ,
b00111100 -
b010011100 .
02
18
b01100000 9
b00111100 :
b010011100 ;
0?
1E
b01100000 F
b00111100 G
b010011100 H
#287500
0#
00
0=
#290000
1#
b110110000 /
10
b110110000 <
1=
b110110000 I
#291000
0+
08
0E
#292000
1%
b00111000 &
b10001000 '
b011000000 (
12
b00111000 3
b10001000 4
b011000000 5
1?
b00111000 @
b10001000 A
b011000000 B
#292500
0#
00
0=
#295000
1#
b001011001 )
10
b001011001 6
1=
b001011001 C
#296000
0%
1+
b01111111 ,
b11010101 -
b101010100 .
02
18
b01111111 9
b11010101 :
b101010100 ;
0?
1E
b01111111 F
b11010101 G
b101010100 H
#297500
0#
00
0=
#300000
1#
b010000101 /
10
b010000101 <
1=
b010000101 I
#301000
0+
08
0E
#302000
1%
b11011111 &
b00111110 '
b100011101 (
12
b11011111 3
b00111110 4
b100011101 5
1?
b11011111 @
b00111110 A
b100011101 B
#302500
0#
00
0=
#305000
1#
b010010111 )
10
b010010111 6
1=
b010010111 C
#306000
0%
1+
b01111101 ,
b01110110 -
b011110011 .
02
18
b01111101 9
b01110110 :
b011110011 ;
0?
1E
b01111101 F
b01110110 G
b011110011 H
#307500
0#
00
0=
#310000
1#
b011111011 /
10
b011111011 <
1=
b011111011 I
#311000
0+
08
0E
#312000
1%
b01011010 &
b10111111 '
b100011001 (
12
b01011010 3
b10111111 4
b100011001 5
1?
b01011010 @
b10111111 A
b100011001 B
#312500
0#
00
0=
#315000
1#
b101010110 )
10
b101010110 6
1=
b101010110 C
#316000
0%
1+
b11101011 ,
b00101000 -
b100010011 .
02
18
b11101011 9
b00101000 :
b100010011 ;
0?
1E
b11101011 F
b00101000 G
b100010011 H
#317500
0#
00
0=
#320000
1#
b100100011 /
10
b100100011 <
1=
b100100011 I
#321000
0+
08
0E
#322000
1%
b00101010 &
b00101111 '
b001011001 (
12
b00101010 3
b00101111 4
b001011001 5
1?
b00101010 @
b00101111 A
b001011001 B
#322500
0#
00
0=
#325000
1#
b110000101 )
10
b110000101 6
1=
b110000101 C
#326000
0%
1+
b11001101 ,
b11100100 -
b110110001 .
02
18
b11001101 9
b11100100 :
b110110001 ;
0?
1E
b11001101 F
b11100100 G
b110110001 H
#327500
0#
00
0=
#330000
1#
b000000111 /
10
b000000111 <
1=
b000000111 I
#331000
0+
08
0E
#332000
1%
b10110101 &
b01110110 '
b100101011 (
12
b10110101 3
b01110110 4
b100101011 5
1?
b10110101 @
b01110110 A
b100101011 B
#332500
0#
00
0=
#335000
1#
b111111011 )
10
b111111011 6
1=
b111111011 C
#336000
0%
1+
b10111011 ,
b11110001 -
b110101100 .
02
18
b10111011 9
b11110001 :
b110101100 ;
0?
1E
b10111011 F
b11110001 G
b110101100 H
#337500
0#
00
0=
#340000
1#
b011111000 /
10
b011111000 <
1=
b011111000 I
#341000
0+
08
0E
#342000
1%
b11000010 &
b11011011 '
b110011101 (
12
b11000010 3
b11011011 4
b110011101 5
1?
b11000010 @
b11011011 A
b110011101 B
#342500
0#
00
0=
#345000
1#
b011010110 )
10
b011010110 6
1=
b011010110 C
#346000
0%
1+
b10010011 ,
b01100001 -
b011110100 .
02
18
b10010011 9
b01100001 :
b011110100 ;
0?
1E
b10010011 F
b01100001 G
b011110100 H
#347500
0#
00
0=
#350000
1#
b101011001 /
10
b101011001 <
1=
b101011001 I
#351000
0+
08
0E
#352000
1%
b00010001 &
b11110101 '
b100000110 (
12
b00010001 3
b11110101 4
b100000110 5
1?
b00010001 @
b11110101 A
b100000110 B
#352500
0#
00
0=
#355000
1#
b111001011 )
10
b111001011 6
1=
b111001011 C
#356000
0%
1+
b11110010 ,
b11100010 -
b111010100 .
02
18
b11110010 9
b11100010 :
b111010100 ;
0?
1E
b11110010 F
b11100010 G
b111010100 H
#357500
0#
00
0=
#360000
1#
b000111011 /
10
b000111011 <
1=
b000111011 I
#361000
0+
08
0E
#362000
1%
b10010001 &
b11111110 '
b110001111 (
12
b10010001 3
b11111110 4
b110001111 5
1?
b10010001 @
b11111110 A
b110001111 B
#362500
0#
00
0=
#365000
1#
b011001001 )
10
b011001001 6
1=
b011001001 C
#366000
0%
1+
b10000000 ,
b01000010 -
b011000010 .
02
18
b10000000 9
b01000010 :
b011000010 ;
0?
1E
b10000000 F
b01000010 G
b011000010 H
#367500
0#
00
0=
#370000
1#
b001111101 /
10
b001111101 <
1=
b001111101 I
#371000
0+
08
0E
#372000
1%
b00111110 &
b00101111 '
b001101101 (
12
b00111110 3
b00101111 4
b001101101 5
1?
b00111110 @
b00101111 A
b001101101 B
#372500
0#
00
0=
#375000
1#
b011111000 )
10
b011111000 6
1=
b011111000 C
#376000
0%
1+
b11110010 ,
b11000111 -
b110111001 .
02
18
b11110010 9
b11000111 :
b110111001 ;
0?
1E
b11110010 F
b11000111 G
b110111001 H
#377500
0#
00
0=
#380000
1#
b101000100 /
10
b101000100 <
1=
b101000100 I
#381000
0+
08
0E
#382000
1%
b10011101 &
b10111000 '
b101010101 (
12
b10011101 3
b10111000 4
b101010101 5
1?
b10011101 @
b10111000 A
b101010101 B
#382500
0#
00
0=
#385000
1#
b110110000 )
10
b110110000 6
1=
b110110000 C
#386000
0%
1+
b00101001 ,
b10100010 -
b011001011 .
02
18
b00101001 9
b10100010 :
b011001011 ;
0?
1E
b00101001 F
b10100010 G
b011001011 H
#387500
0#
00
0=
#390000
1#
b111100110 /
10
b111100110 <
1=
b111100110 I
#391000
0+
08
0E
#392000
1%
b10011010 &
b00111011 '
b011010101 (
12
b10011010 3
b00111011 4
b011010101 5
1?
b10011010 @
b00111011 A
b011010101 B
#392500
0#
00
0=
#395000
1#
b111101011 )
10
b111101011 6
1=
b111101011 C
#396000
0%
1+
b11110001 ,
b01001010 -
b100111011 .
02
18
b11110001 9
b01001010 :
b100111011 ;
0?
1E
b11110001 F
b01001010 G
b100111011 H
#397500
0#
00
0=
#400000
1#
b000110000 /
10
b000110000 <
1=
b000110000 I
#401000
0+
08
0E
#402000
1%
b10011001 &
b10101010 '
b101000011 (
12
b10011001 3
b10101010 4
b101000011 5
1?
b10011001 @
b10101010 A
b101000011 B
#402500
0#
00
0=
#405000
1#
b010010101 )
10
b010010101 6
1=
b010010101 C
#406000
0%
1+
b01010100 ,
b00100110 -
b001111010 .
02
18
b01010100 9
b00100110 :
b001111010 ;
0?
1E
b01010100 F
b00100110 G
b001111010 H
#407500
0#
00
0=
#410000
1#
b001010110 /
10
b001010110 <
1=
b001010110 I
#411000
0+
08
0E
#412000
1%
b00100010 &
b10100010 '
b011000100 (
12
b00100010 3
b10100010 4
b011000100 5
1?
b00100010 @
b10100010 A
b011000100 B
#412500
0#
00
0=
#415000
1#
b100110111 )
10
b100110111 6
1=
b100110111 C
#416000
0%
1+
b10001111 ,
b10101000 -
b100110111 .
02
18
b10001111 9
b10101000 :
b100110111 ;
0?
1E
b10001111 F
b10101000 G
b100110111 H
#417500
0#
00
0=
#420000
1#
b011111110 /
10
b011111110 <
1=
b011111110 I
#421000
0+
08
0E
#422000
1%
b11100100 &
b00001100 '
b011110000 (
12
b11100100 3
b00001100 4
b011110000 5
1?
b11100100 @
b00001100 A
b011110000 B
#422500
0#
00
0=
#425000
1#
b101000011 )
10
b101000011 6
1=
b101000011 C
#426000
0%
1+
b11111000 ,
b01000101 -
b100111101 .
02
18
b11111000 9
b01000101 :
b100111101 ;
0?
1E
b11111000 F
b01000101 G
b100111101 H
#427500
0#
00
0=
#430000
1#
b101000011 /
10
b101000011 <
1=
b101000011 I
#431000
0+
08
0E
#432000
1%
b01100010 &
b10101100 '
b100001110 (
12
b01100010 3
b10101100 4
b100001110 5
1?
b01100010 @
b10101100 A
b100001110 B
#432500
0#
00
0=
#435000
1#
b111101111 )
10
b111101111 6
1=
b111101111 C
#436000
0%
1+
b00100101 ,
b10001100 -
b010110001 .
02
18
b00100101 9
b10001100 :
b010110001 ;
0?
1E
b00100101 F
b10001100 G
b010110001 H
#437500
0#
00
0=
#440000
1#
b111001111 /
10
b111001111 <
1=
b111001111 I
#441000
0+
08
0E
#442000
1%
b10010001 &
b10011111 '
b100110000 (
12
b10010001 3
b10011111 4
b100110000 5
1?
b10010001 @
b10011111 A
b100110000 B
#442500
0#
00
0=
#445000
1#
b010001110 )
10
b010001110 6
1=
b010001110 C
#446000
0%
1+
b10010101 ,
b11010110 -
b101101011 .
02
18
b10010101 9
b11010110 :
b101101011 ;
0?
1E
b10010101 F
b11010110 G
b101101011 H
#447500
0#
00
0=
#450000
1#
b010100101 /
10
b010100101 <
1=
b010100101 I
#451000
0+
08
0E
#452000
1%
b11010010 &
b10111100 '
b110001110 (
12
b11010010 3
b10111100 4
b110001110 5
1?
b11010010 @
b10111100 A
b110001110 B
#452500
0#
00
0=
#455000
1#
b101001010 )
10
b101001010 6
1=
b101001010 C
#456000
0%
1+
b10100000 ,
b01011011 -
b011111011 .
02
18
b10100000 9
b01011011 :
b011111011 ;
0?
1E
b10100000 F
b01011011 G
b011111011 H
#457500
0#
00
0=
#460000
1#
b100000000 /
10
b100000000 <
1=
b100000000 I
#461000
0+
08
0E
#462000
1%
b11010110 &
b10111001 '
b110001111 (
12
b11010110 3
b10111001 4
b110001111 5
1?
b11010110 @
b10111001 A
b110001111 B
#462500
0#
00
0=
#465000
1#
b000000011 )
10
b000000011 6
1=
b000000011 C
#466000
0%
1+
b10000101 ,
b01110010 -
b011110111 .
02
18
b10000101 9
b01110010 :
b011110111 ;
0?
1E
b10000101 F
b01110010 G
b011110111 H
#467500
0#
00
0=
