rtl/top_level.sv


module top_level (
    input  logic       clk,

    // Channel A
    input  logic       rst_A,
    input  logic       valid_in_A,
    input  logic [7:0] a_A,
    input  logic [7:0] b_A,
    output logic [8:0] sum_async_A,
    output logic [8:0] sum_sync_A,

    // Channel B
    input  logic       rst_B,
    input  logic       valid_in_B,
    input  logic [7:0] a_B,
    input  logic [7:0] b_B,
    output logic [8:0] sum_async_B,
    output logic [8:0] sum_sync_B
);

    // Channel A synchronous accumulator
    always_ff @(posedge clk) begin
        if (rst_A)
            sum_sync_A <= '0;
        else if (valid_in_A)
            sum_sync_A <= sum_sync_A + b_A;
    end

    assign sum_async_A = a_A + b_A;

    // Channel B synchronous accumulator
    always_ff @(posedge clk) begin
        if (rst_B)
            sum_sync_B <= '0;
        else if (valid_in_B)
            sum_sync_B <= sum_sync_B + b_B;
    end

    assign sum_async_B = a_B + b_B;

    initial begin
        $display("Time | rst_A| valid_in_A | a_A | b_A |sum_async_A | sum_sync_A |rst_B | valid_in_B| a_B | b_B  | sum_async_B | sum_sync_B   ");
        $monitor("%4t  |  %b  |  %b        | %0d | %0d |    %0d     |   %0d      | %b   |    %b     | %0d | %0d  |    %0d      |   %0d ",
                 $time, rst_A, valid_in_A, a_A, b_A, sum_async_A,sum_sync_A, rst_B, valid_in_B, a_B, b_B, sum_async_B, sum_sync_B);
    end

    initial begin
        $dumpfile("dump.vcd");
        $dumpvars(1, top_level.sv);
    end

endmodule

rtl/dut_wrapper.sv
module dut_wrapper (
    input  logic       clk,

    // Channel A – cocotb drives these
    input  logic       rst_A,
    input  logic       valid_in_A,
    input  logic [7:0] a_A,
    input  logic [7:0] b_A,

    // DUT drives these
    output logic [8:0] sum_async_A,
    output logic [8:0] sum_sync_A,

    // Channel B (if needed)
    input  logic       rst_B,
    input  logic       valid_in_B,
    input  logic [7:0] a_B,
    input  logic [7:0] b_B,
    output logic [8:0] sum_async_B,
    output logic [8:0] sum_sync_B
);

    top_level u_top_level (
        .clk(clk),

        // Channel A
        .rst_A(rst_A),
        .valid_in_A(valid_in_A),
        .a_A(a_A),
        .b_A(b_A),
        .sum_async_A(sum_async_A),
        .sum_sync_A(sum_sync_A),

        // Channel B
        .rst_B(rst_B),
        .valid_in_B(valid_in_B),
        .a_B(a_B),
        .b_B(b_B),
        .sum_async_B(sum_async_B),
        .sum_sync_B(sum_sync_B)
    );

endmodule



// module dut_wrapper (
//     input  logic       clk,

//     // Channel A – exposed directly for cocotb
//     output logic       rst_A,
//     output logic       valid_in_A,
//     output logic [7:0] a_A,
//     output logic [7:0] b_A,
//     output logic [8:0] sum_async_A,
//     output logic [8:0] sum_sync_A,

//     // Channel B – exposed directly for cocotb
//     output logic       rst_B,
//     output logic       valid_in_B,
//     output logic [7:0] a_B,
//     output logic [7:0] b_B,
//     output logic [8:0] sum_async_B,
//     output logic [8:0] sum_sync_B
// );

//     // Internal wires driven by cocotb (use these as DUT inputs)
//     logic rst_A_int;
//     logic valid_in_A_int;
//     logic [7:0] a_A_int;
//     logic [7:0] b_A_int;

//     logic rst_B_int;
//     logic valid_in_B_int;
//     logic [7:0] a_B_int;
//     logic [7:0] b_B_int;

//     // Connect exposed ports to internal wires so cocotb can drive them
//     assign rst_A       = rst_A_int;
//     assign valid_in_A  = valid_in_A_int;
//     assign a_A         = a_A_int;
//     assign b_A         = b_A_int;

//     assign rst_B       = rst_B_int;
//     assign valid_in_B  = valid_in_B_int;
//     assign a_B         = a_B_int;
//     assign b_B         = b_B_int;

//     // DUT instance
//     top_level u_top_level (
//         .clk          (clk),

//         // Channel A
//         .rst_A        (rst_A_int),
//         .valid_in_A   (valid_in_A_int),
//         .a_A          (a_A_int),
//         .b_A          (b_A_int),
//         .sum_async_A  (sum_async_A),
//         .sum_sync_A   (sum_sync_A),

//         // Channel B
//         .rst_B        (rst_B_int),
//         .valid_in_B   (valid_in_B_int),
//         .a_B          (a_B_int),
//         .b_B          (b_B_int),
//         .sum_async_B  (sum_async_B),
//         .sum_sync_B   (sum_sync_B)
//     );

// endmodule

regression_results/waves_10.vcd
$version Generated by VerilatedVcd $end
$timescale 1ps $end
 $scope module $rootio $end
  $var wire 1 # clk $end
  $var wire 1 $ rst_A $end
  $var wire 1 % valid_in_A $end
  $var wire 8 & a_A [7:0] $end
  $var wire 8 ' b_A [7:0] $end
  $var wire 9 ( sum_async_A [8:0] $end
  $var wire 9 ) sum_sync_A [8:0] $end
  $var wire 1 * rst_B $end
  $var wire 1 + valid_in_B $end
  $var wire 8 , a_B [7:0] $end
  $var wire 8 - b_B [7:0] $end
  $var wire 9 . sum_async_B [8:0] $end
  $var wire 9 / sum_sync_B [8:0] $end
 $upscope $end
 $scope module dut_wrapper $end
  $var wire 1 0 clk $end
  $var wire 1 1 rst_A $end
  $var wire 1 2 valid_in_A $end
  $var wire 8 3 a_A [7:0] $end
  $var wire 8 4 b_A [7:0] $end
  $var wire 9 5 sum_async_A [8:0] $end
  $var wire 9 6 sum_sync_A [8:0] $end
  $var wire 1 7 rst_B $end
  $var wire 1 8 valid_in_B $end
  $var wire 8 9 a_B [7:0] $end
  $var wire 8 : b_B [7:0] $end
  $var wire 9 ; sum_async_B [8:0] $end
  $var wire 9 < sum_sync_B [8:0] $end
  $scope module u_top_level $end
   $var wire 1 = clk $end
   $var wire 1 > rst_A $end
   $var wire 1 ? valid_in_A $end
   $var wire 8 @ a_A [7:0] $end
   $var wire 8 A b_A [7:0] $end
   $var wire 9 B sum_async_A [8:0] $end
   $var wire 9 C sum_sync_A [8:0] $end
   $var wire 1 D rst_B $end
   $var wire 1 E valid_in_B $end
   $var wire 8 F a_B [7:0] $end
   $var wire 8 G b_B [7:0] $end
   $var wire 9 H sum_async_B [8:0] $end
   $var wire 9 I sum_sync_B [8:0] $end
  $upscope $end
 $upscope $end
$enddefinitions $end


#0
1#
0$
0%
b00000000 &
b00000000 '
b000000000 (
b000000000 )
1*
0+
b00000000 ,
b00000000 -
b000000000 .
b000000000 /
10
01
02
b00000000 3
b00000000 4
b000000000 5
b000000000 6
17
08
b00000000 9
b00000000 :
b000000000 ;
b000000000 <
1=
0>
0?
b00000000 @
b00000000 A
b000000000 B
b000000000 C
1D
0E
b00000000 F
b00000000 G
b000000000 H
b000000000 I
#40640000
0
0=
#10000
1#
0*
10
07
1=
0D
#15000
0#
00
0=
#20000
1#
10
1=
#25000
0#
00
0=
#30000
1#
10
1=
#32000
b00011011 &
b01011110 '
b001111001 (
b00011011 3
b01011110 4
b001111001 5
b00011011 @
b01011110 A
b001111001 B
#35000
0#
00
0=
#40000
1#
10
1=
#41000
1+
b01011110 ,
b01110100 -
b011010010 .
18
b01011110 9
b01110100 :
b011010010 ;
1E
b01011110 F
b01110100 G
b011010010 H
#45000
0#
00
0=
#50000
1#
b001110100 /
10
b001110100 <
1=
b001110100 I
#51000
0+
08
0E
#52000
b10010001 &
b01100110 '
b011110111 (
b10010001 3
b01100110 4
b011110111 5
b10010001 @
b01100110 A
b011110111 B
#55000
0#
00
0=
#60000
1#
10
1=
#61000
1+
b10011010 ,
b00000011 -
b010011101 .
18
b10011010 9
b00000011 :
b010011101 ;
1E
b10011010 F
b00000011 G
b010011101 H
#65000
0#
00
0=
#70000
1#
b001110111 /
10
b001110111 <
1=
b001110111 I
#71000
1*
0+
b00000000 ,
b00000000 -
b000000000 .
17
08
b00000000 9
b00000000 :
b000000000 ;
1D
0E
b00000000 F
b00000000 G
b000000000 H
#75000
0#
00
0=
#80000
1#
0*
b000000000 /
10
07
b000000000 <
1=
0D
b000000000 I
#81000
b01000100 &
b10100010 '
b011100110 (
b01000100 3
b10100010 4
b011100110 5
b01000100 @
b10100010 A
b011100110 B
#85000
0#
00
0=
#90000
1#
10
1=
#91000
1+
b01110111 ,
b11001000 -
b100111111 .
18
b01110111 9
b11001000 :
b100111111 ;
1E
b01110111 F
b11001000 G
b100111111 H
#95000
0#
00
0=
#100000
1#
b011001000 /
10
b011001000 <
1=
b011001000 I
#101000
0+
08
0E
#102000
b10010000 &
b00100110 '
b010110110 (
b10010000 3
b00100110 4
b010110110 5
b10010000 @
b00100110 A
b010110110 B
#105000
0#
00
0=
#110000
1#
10
1=
#111000
b10010101 ,
b01001111 -
b011100100 .
b10010101 9
b01001111 :
b011100100 ;
b10010101 F
b01001111 G
b011100100 H
#115000
0#
00
0=
#120000
1#
10
1=
#122000
1%
b00001101 &
b01010110 '
b001100011 (
12
b00001101 3
b01010110 4
b001100011 5
1?
b00001101 @
b01010110 A
b001100011 B
#125000
0#
00
0=
#130000
1#
b001010110 )
10
b001010110 6
1=
b001010110 C
#131000
0%
b00101010 ,
b11000111 -
b011110001 .
02
b00101010 9
b11000111 :
b011110001 ;
0?
b00101010 F
b11000111 G
b011110001 H
#135000
0#
00
0=
#140000
1#
10
1=
#142000
b11110100 &
b10101101 '
b110100001 (
b11110100 3
b10101101 4
b110100001 5
b11110100 @
b10101101 A
b110100001 B
#145000
0#
00
0=
#150000
1#
10
1=
#151000
b10111011 ,
b11011010 -
b110010101 .
b10111011 9
b11011010 :
b110010101 ;
b10111011 F
b11011010 G
b110010101 H
#155000
0#
00
0=
#160000
1#
10
1=
#162000
b10110011 &
b01101100 '
b100011111 (
b10110011 3
b01101100 4
b100011111 5
b10110011 @
b01101100 A
b100011111 B
#165000
0#
00
0=
#170000
1#
10
1=
#171000
1+
b11110100 ,
b11110100 -
b111101000 .
18
b11110100 9
b11110100 :
b111101000 ;
1E
b11110100 F
b11110100 G
b111101000 H
#175000
0#
00
0=
#180000
1#
b110111100 /
10
b110111100 <
1=
b110111100 I
#181000
0+
08
0E
#182000
b11100110 &
b10100001 '
b110000111 (
b11100110 3
b10100001 4
b110000111 5
b11100110 @
b10100001 A
b110000111 B
#185000
0#
00
0=
#190000
1#
10
1=
#191000
1+
b00010110 ,
b01110111 -
b010001101 .
18
b00010110 9
b01110111 :
b010001101 ;
1E
b00010110 F
b01110111 G
b010001101 H
#195000
0#
00
0=
#200000
1#
b000110011 /
10
b000110011 <
1=
b000110011 I
#201000
0+
08
0E
#202000
b10110110 &
b11000110 '
b101111100 (
b10110110 3
b11000110 4
b101111100 5
b10110110 @
b11000110 A
b101111100 B
#205000
0#
00
0=
#210000
1#
10
1=
#211000
b00000010 ,
b01010100 -
b001010110 .
b00000010 9
b01010100 :
b001010110 ;
b00000010 F
b01010100 G
b001010110 H
#215000
0#
00
0=
#220000
1#
10
1=
#222000
b11000100 &
b10100101 '
b101101001 (
b11000100 3
b10100101 4
b101101001 5
b11000100 @
b10100101 A
b101101001 B
#225000
0#
00
0=
#230000
1#
10
1=
#231000
b00111001 ,
b10010010 -
b011001011 .
b00111001 9
b10010010 :
b011001011 ;
b00111001 F
b10010010 G
b011001011 H
#235000
0#
00
0=
#240000
1#
10
1=
#242000
1%
b10101001 &
b10011001 '
b101000010 (
12
b10101001 3
b10011001 4
b101000010 5
1?
b10101001 @
b10011001 A
b101000010 B
#245000
0#
00
0=
#250000
1#
b011101111 )
10
b011101111 6
1=
b011101111 C
#251000
0%
b00101011 ,
b11000001 -
b011101100 .
02
b00101011 9
b11000001 :
b011101100 ;
0?
b00101011 F
b11000001 G
b011101100 H
#255000
0#
00
0=
#260000
1#
10
1=
#262000
b10110011 &
b11110001 '
b110100100 (
b10110011 3
b11110001 4
b110100100 5
b10110011 @
b11110001 A
b110100100 B
#265000
0#
00
0=
#270000
1#
10
1=
#271000
b11110101 ,
b01111111 -
b101110100 .
b11110101 9
b01111111 :
b101110100 ;
b11110101 F
b01111111 G
b101110100 H
#275000
0#
00
0=
#280000
1#
10
1=
#282000
b11010010 &
b00100111 '
b011111001 (
b11010010 3
b00100111 4
b011111001 5
b11010010 @
b00100111 A
b011111001 B
#285000
0#
00
0=
#290000
1#
10
1=
#291000
1+
b11001000 ,
b01001100 -
b100010100 .
18
b11001000 9
b01001100 :
b100010100 ;
1E
b11001000 F
b01001100 G
b100010100 H
#295000
0#
00
0=
#300000
1#
b001111111 /
10
b001111111 <
1=
b001111111 I
#301000
0+
08
0E
#302000
b11010011 &
b11100100 '
b110110111 (
b11010011 3
b11100100 4
b110110111 5
b11010011 @
b11100100 A
b110110111 B
#305000
0#
00
0=
#310000
1#
10
1=
#311000
b11110111 ,
b00110111 -
b100101110 .
b11110111 9
b00110111 :
b100101110 ;
b11110111 F
b00110111 G
b100101110 H
#315000
0#
00
0=
#320000
1#
10
1=
#322000
1%
b10001001 &
b10100111 '
b100110000 (
12
b10001001 3
b10100111 4
b100110000 5
1?
b10001001 @
b10100111 A
b100110000 B
#325000
0#
00
0=
#330000
1#
b110010110 )
10
b110010110 6
1=
b110010110 C
#331000
0%
b01010100 ,
b01010001 -
b010100101 .
02
b01010100 9
b01010001 :
b010100101 ;
0?
b01010100 F
b01010001 G
b010100101 H
#335000
0#
00
0=
#340000
1#
10
1=
#342000
1%
b10010000 &
b00110111 '
b011000111 (
12
b10010000 3
b00110111 4
b011000111 5
1?
b10010000 @
b00110111 A
b011000111 B
#345000
0#
00
0=
#350000
1#
b111001101 )
10
b111001101 6
1=
b111001101 C
#351000
0%
1+
b00100100 ,
b10111111 -
b011100011 .
02
18
b00100100 9
b10111111 :
b011100011 ;
0?
1E
b00100100 F
b10111111 G
b011100011 H
#355000
0#
00
0=
#360000
1#
b100111110 /
10
b100111110 <
1=
b100111110 I
#361000
0+
08
0E
#362000
1%
b00110100 &
b11011100 '
b100010000 (
12
b00110100 3
b11011100 4
b100010000 5
1?
b00110100 @
b11011100 A
b100010000 B
#365000
0#
00
0=
#370000
1#
b010101001 )
10
b010101001 6
1=
b010101001 C
#371000
0%
b00000111 ,
b10010001 -
b010011000 .
02
b00000111 9
b10010001 :
b010011000 ;
0?
b00000111 F
b10010001 G
b010011000 H
#375000
0#
00
0=
#380000
1#
10
1=
#382000
1%
b11010001 &
b11110011 '
b111000100 (
12
b11010001 3
b11110011 4
b111000100 5
1?
b11010001 @
b11110011 A
b111000100 B
#385000
0#
00
0=
#390000
1#
b110011100 )
10
b110011100 6
1=
b110011100 C
#391000
0%
1+
b10001100 ,
b00110011 -
b010111111 .
02
18
b10001100 9
b00110011 :
b010111111 ;
0?
1E
b10001100 F
b00110011 G
b010111111 H
#395000
0#
00
0=
#400000
1#
b101110001 /
10
b101110001 <
1=
b101110001 I
#401000
0+
08
0E
#402000
1%
b01000001 &
b01110011 '
b010110100 (
12
b01000001 3
b01110011 4
b010110100 5
1?
b01000001 @
b01110011 A
b010110100 B
#405000
0#
00
0=
#410000
1#
b000001111 )
10
b000001111 6
1=
b000001111 C
#411000
0%
b11101110 ,
b00010110 -
b100000100 .
02
b11101110 9
b00010110 :
b100000100 ;
0?
b11101110 F
b00010110 G
b100000100 H
#415000
0#
00
0=
#420000
1#
10
1=
#422000
b00100110 &
b00000111 '
b000101101 (
b00100110 3
b00000111 4
b000101101 5
b00100110 @
b00000111 A
b000101101 B
#425000
0#
00
0=
#430000
1#
10
1=
#431000
b00110010 ,
b01010100 -
b010000110 .
b00110010 9
b01010100 :
b010000110 ;
b00110010 F
b01010100 G
b010000110 H
#435000
0#
00
0=
#440000
1#
10
1=
#442000
b11011010 &
b10011010 '
b101110100 (
b11011010 3
b10011010 4
b101110100 5
b11011010 @
b10011010 A
b101110100 B
#445000
0#
00
0=
#450000
1#
10
1=
#451000
b11100110 ,
b11010011 -
b110111001 .
b11100110 9
b11010011 :
b110111001 ;
b11100110 F
b11010011 G
b110111001 H
#455000
0#
00
0=
#460000
1#
10
1=
#462000
b01110010 &
b10111010 '
b100101100 (
b01110010 3
b10111010 4
b100101100 5
b01110010 @
b10111010 A
b100101100 B
#465000
0#
00
0=
#470000
1#
10
1=
#471000
1+
b11110110 ,
b00100110 -
b100011100 .
18
b11110110 9
b00100110 :
b100011100 ;
1E
b11110110 F
b00100110 G
b100011100 H
#475000
0#
00
0=
#480000
1#
b110010111 /
10
b110010111 <
1=
b110010111 I
#481000
0+
08
0E
#482000
1%
b11011011 &
b11010101 '
b110110000 (
12
b11011011 3
b11010101 4
b110110000 5
1?
b11011011 @
b11010101 A
b110110000 B
#485000
0#
00
0=
#490000
1#
b011100100 )
10
b011100100 6
1=
b011100100 C
#491000
0%
b10011100 ,
b11001101 -
b101101001 .
02
b10011100 9
b11001101 :
b101101001 ;
0?
b10011100 F
b11001101 G
b101101001 H
#495000
0#
00
0=
#500000
1#
10
1=
#502000
1%
b11100000 &
b01000101 '
b100100101 (
12
b11100000 3
b01000101 4
b100100101 5
1?
b11100000 @
b01000101 A
b100100101 B
#505000
0#
00
0=
#510000
1#
b100101001 )
10
b100101001 6
1=
b100101001 C
#511000
0%
b10111000 ,
b10100111 -
b101011111 .
02
b10111000 9
b10100111 :
b101011111 ;
0?
b10111000 F
b10100111 G
b101011111 H
#515000
0#
00
0=
#520000
1#
10
1=
#522000
b01011000 &
b00101100 '
b010000100 (
b01011000 3
b00101100 4
b010000100 5
b01011000 @
b00101100 A
b010000100 B
#525000
0#
00
0=
#530000
1#
10
1=
#531000
1+
b11000111 ,
b10011101 -
b101100100 .
18
b11000111 9
b10011101 :
b101100100 ;
1E
b11000111 F
b10011101 G
b101100100 H
#535000
0#
00
0=
#540000
1#
b000110100 /
10
b000110100 <
1=
b000110100 I
#541000
0+
08
0E
#542000
1%
b01111110 &
b00010011 '
b010010001 (
12
b01111110 3
b00010011 4
b010010001 5
1?
b01111110 @
b00010011 A
b010010001 B
#545000
0#
00
0=
#550000
1#
b100111100 )
10
b100111100 6
1=
b100111100 C
#551000
0%
b11001001 ,
b11100110 -
b110101111 .
02
b11001001 9
b11100110 :
b110101111 ;
0?
b11001001 F
b11100110 G
b110101111 H
#555000
0#
00
0=
#560000
1#
10
1=
#562000
1%
b01111111 &
b01111010 '
b011111001 (
12
b01111111 3
b01111010 4
b011111001 5
1?
b01111111 @
b01111010 A
b011111001 B
#565000
0#
00
0=
#570000
1#
b110110110 )
10
b110110110 6
1=
b110110110 C
#571000
0%
b00000001 ,
b11111101 -
b011111110 .
02
b00000001 9
b11111101 :
b011111110 ;
0?
b00000001 F
b11111101 G
b011111110 H
#575000
0#
00
0=
#580000
1#
10
1=
#582000
b00011110 &
b10011001 '
b010110111 (
b00011110 3
b10011001 4
b010110111 5
b00011110 @
b10011001 A
b010110111 B
#585000
0#
00
0=
#590000
1#
10
1=
#591000
b10111010 ,
b10000110 -
b101000000 .
b10111010 9
b10000110 :
b101000000 ;
b10111010 F
b10000110 G
b101000000 H
#595000
0#
00
0=
#600000
1#
10
1=
#602000
1%
b11000100 &
b01100001 '
b100100101 (
12
b11000100 3
b01100001 4
b100100101 5
1?
b11000100 @
b01100001 A
b100100101 B
#605000
0#
00
0=
#610000
1#
b000010111 )
10
b000010111 6
1=
b000010111 C
#611000
0%
1+
b01101011 ,
b11011111 -
b101001010 .
02
18
b01101011 9
b11011111 :
b101001010 ;
0?
1E
b01101011 F
b11011111 G
b101001010 H
#615000
0#
00
0=
#620000
1#
b100010011 /
10
b100010011 <
1=
b100010011 I
#621000
0+
08
0E
#622000
b01010111 &
b01000000 '
b010010111 (
b01010111 3
b01000000 4
b010010111 5
b01010111 @
b01000000 A
b010010111 B
#625000
0#
00
0=
#630000
1#
10
1=
#631000
1+
b00101101 ,
b00111111 -
b001101100 .
18
b00101101 9
b00111111 :
b001101100 ;
1E
b00101101 F
b00111111 G
b001101100 H
#635000
0#
00
0=
#640000
1#
b101010010 /
10
b101010010 <
1=
b101010010 I
#641000
0+
08
0E
#642000
b01110010 &
b11001011 '
b100111101 (
b01110010 3
b11001011 4
b100111101 5
b01110010 @
b11001011 A
b100111101 B
#645000
0#
00
0=
#650000
1#
10
1=
#651000
1+
b11101011 ,
b00011110 -
b100001001 .
18
b11101011 9
b00011110 :
b100001001 ;
1E
b11101011 F
b00011110 G
b100001001 H
#655000
0#
00
0=
#660000
1#
b101110000 /
10
b101110000 <
1=
b101110000 I
#661000
0+
08
0E
#662000
1%
b01110011 &
b01011011 '
b011001110 (
12
b01110011 3
b01011011 4
b011001110 5
1?
b01110011 @
b01011011 A
b011001110 B
#665000
0#
00
0=
#670000
1#
b001110010 )
10
b001110010 6
1=
b001110010 C
#671000
0%
b10100010 ,
b00011101 -
b010111111 .
02
b10100010 9
b00011101 :
b010111111 ;
0?
b10100010 F
b00011101 G
b010111111 H
#675000
0#
00
0=
#680000
1#
10
1=
#682000
b00110100 &
b11011101 '
b100010001 (
b00110100 3
b11011101 4
b100010001 5
b00110100 @
b11011101 A
b100010001 B
#685000
0#
00
0=
#690000
1#
10
1=
#691000
b00010011 ,
b01101101 -
b010000000 .
b00010011 9
b01101101 :
b010000000 ;
b00010011 F
b01101101 G
b010000000 H
#695000
0#
00
0=
#700000
1#
10
1=
#702000
1%
b00111101 &
b10001010 '
b011000111 (
12
b00111101 3
b10001010 4
b011000111 5
1?
b00111101 @
b10001010 A
b011000111 B
#705000
0#
00
0=
#710000
1#
b011111100 )
10
b011111100 6
1=
b011111100 C
#711000
0%
b01001101 ,
b01101110 -
b010111011 .
02
b01001101 9
b01101110 :
b010111011 ;
0?
b01001101 F
b01101110 G
b010111011 H
#715000
0#
00
0=
#720000
1#
10
1=
#722000
1%
b01110001 &
b11010111 '
b101001000 (
12
b01110001 3
b11010111 4
b101001000 5
1?
b01110001 @
b11010111 A
b101001000 B
#725000
0#
00
0=
#730000
1#
b111010011 )
10
b111010011 6
1=
b111010011 C
#731000
0%
1+
b00010010 ,
b11011010 -
b011101100 .
02
18
b00010010 9
b11011010 :
b011101100 ;
0?
1E
b00010010 F
b11011010 G
b011101100 H
#735000
0#
00
0=
#740000
1#
b001001010 /
10
b001001010 <
1=
b001001010 I
#741000
0+
08
0E
#742000
1%
b10110100 &
b00100010 '
b011010110 (
12
b10110100 3
b00100010 4
b011010110 5
1?
b10110100 @
b00100010 A
b011010110 B
#745000
0#
00
0=
#750000
1#
b111110101 )
10
b111110101 6
1=
b111110101 C
#751000
0%
b01010010 ,
b10111101 -
b100001111 .
02
b01010010 9
b10111101 :
b100001111 ;
0?
b01010010 F
b10111101 G
b100001111 H
#755000
0#
00
0=
#760000
1#
10
1=
#762000
b01010100 &
b00111011 '
b010001111 (
b01010100 3
b00111011 4
b010001111 5
b01010100 @
b00111011 A
b010001111 B
#765000
0#
00
0=
#770000
1#
10
1=
#771000
b11001101 ,
b00000010 -
b011001111 .
b11001101 9
b00000010 :
b011001111 ;
b11001101 F
b00000010 G
b011001111 H
#775000
0#
00
0=
#780000
1#
10
1=
#782000
b10010001 &
b10100100 '
b100110101 (
b10010001 3
b10100100 4
b100110101 5
b10010001 @
b10100100 A
b100110101 B
#785000
0#
00
0=
#790000
1#
10
1=
#791000
b00111101 ,
b11101110 -
b100101011 .
b00111101 9
b11101110 :
b100101011 ;
b00111101 F
b11101110 G
b100101011 H
#795000
0#
00
0=
#800000
1#
10
1=
#802000
1%
b10100110 &
b01101010 '
b100010000 (
12
b10100110 3
b01101010 4
b100010000 5
1?
b10100110 @
b01101010 A
b100010000 B
#805000
0#
00
0=
#810000
1#
b001011111 )
10
b001011111 6
1=
b001011111 C
#811000
0%
b11010011 ,
b01110100 -
b101000111 .
02
b11010011 9
b01110100 :
b101000111 ;
0?
b11010011 F
b01110100 G
b101000111 H
#815000
0#
00
0=
#820000
1#
10
1=
#822000
1%
b01011100 &
b01001101 '
b010101001 (
12
b01011100 3
b01001101 4
b010101001 5
1?
b01011100 @
b01001101 A
b010101001 B
#825000
0#
00
0=
#830000
1#
b010101100 )
10
b010101100 6
1=
b010101100 C
#831000
0%
b11001101 ,
b10101100 -
b101111001 .
02
b11001101 9
b10101100 :
b101111001 ;
0?
b11001101 F
b10101100 G
b101111001 H
#835000
0#
00
0=
#840000
1#
10
1=
#842000
1%
b11001100 &
b01111111 '
b101001011 (
12
b11001100 3
b01111111 4
b101001011 5
1?
b11001100 @
b01111111 A
b101001011 B
#845000
0#
00
0=
#850000
1#
b100101011 )
10
b100101011 6
1=
b100101011 C
#851000
0%
1+
b11000000 ,
b00110101 -
b011110101 .
02
18
b11000000 9
b00110101 :
b011110101 ;
0?
1E
b11000000 F
b00110101 G
b011110101 H
#855000
0#
00
0=
#860000
1#
b001111111 /
10
b001111111 <
1=
b001111111 I
#861000
0+
08
0E
#862000
1%
b11111010 &
b00101110 '
b100101000 (
12
b11111010 3
b00101110 4
b100101000 5
1?
b11111010 @
b00101110 A
b100101000 B
#865000
0#
00
0=
#870000
1#
b101011001 )
10
b101011001 6
1=
b101011001 C
#871000
0%
1+
b11101000 ,
b00011010 -
b100000010 .
02
18
b11101000 9
b00011010 :
b100000010 ;
0?
1E
b11101000 F
b00011010 G
b100000010 H
#875000
0#
00
0=
#880000
1#
b010011001 /
10
b010011001 <
1=
b010011001 I
#881000
1*
0+
b00000000 ,
b00000000 -
b000000000 .
17
08
b00000000 9
b00000000 :
b000000000 ;
1D
0E
b00000000 F
b00000000 G
b000000000 H
#885000
0#
00
0=
#890000
1#
0*
b000000000 /
10
07
b000000000 <
1=
0D
b000000000 I
#891000
1%
b10001010 &
b11101010 '
b101110100 (
12
b10001010 3
b11101010 4
b101110100 5
1?
b10001010 @
b11101010 A
b101110100 B
#895000
0#
00
0=
#900000
1#
b001000011 )
10
b001000011 6
1=
b001000011 C
#901000
0%
b00100010 ,
b11010010 -
b011110100 .
02
b00100010 9
b11010010 :
b011110100 ;
0?
b00100010 F
b11010010 G
b011110100 H
#905000
0#
00
0=
#910000
1#
10
1=
#912000
1%
b01011000 &
b00100110 '
b001111110 (
12
b01011000 3
b00100110 4
b001111110 5
1?
b01011000 @
b00100110 A
b001111110 B
#915000
0#
00
0=
#920000
1#
b001101001 )
10
b001101001 6
1=
b001101001 C
#921000
0%
1+
b01110001 ,
b01000000 -
b010110001 .
02
18
b01110001 9
b01000000 :
b010110001 ;
0?
1E
b01110001 F
b01000000 G
b010110001 H
#925000
0#
00
0=
#930000
1#
b001000000 /
10
b001000000 <
1=
b001000000 I
#931000
0+
08
0E
#932000
1%
b11101110 &
b10010010 '
b110000000 (
12
b11101110 3
b10010010 4
b110000000 5
1?
b11101110 @
b10010010 A
b110000000 B
#935000
0#
00
0=
#940000
1#
b011111011 )
10
b011111011 6
1=
b011111011 C
#941000
0%
1+
b00110111 ,
b01110101 -
b010101100 .
02
18
b00110111 9
b01110101 :
b010101100 ;
0?
1E
b00110111 F
b01110101 G
b010101100 H
#945000
0#
00
0=
#950000
1#
b010110101 /
10
b010110101 <
1=
b010110101 I
#951000
0+
08
0E
#952000
1%
b00011001 &
b11010101 '
b011101110 (
12
b00011001 3
b11010101 4
b011101110 5
1?
b00011001 @
b11010101 A
b011101110 B
#955000
0#
00
0=
#960000
1#
b111010000 )
10
b111010000 6
1=
b111010000 C
#961000
0%
1+
b11011000 ,
b00101100 -
b100000100 .
02
18
b11011000 9
b00101100 :
b100000100 ;
0?
1E
b11011000 F
b00101100 G
b100000100 H
#965000
0#
00
0=
#970000
1#
b011100001 /
10
b011100001 <
1=
b011100001 I
#971000
0+
08
0E
#972000
1%
b00011111 &
b11010000 '
b011101111 (
12
b00011111 3
b11010000 4
b011101111 5
1?
b00011111 @
b11010000 A
b011101111 B
#975000
0#
00
0=
#980000
1#
b010100000 )
10
b010100000 6
1=
b010100000 C
#981000
0%
1+
b00110000 ,
b00110011 -
b001100011 .
02
18
b00110000 9
b00110011 :
b001100011 ;
0?
1E
b00110000 F
b00110011 G
b001100011 H
#985000
0#
00
0=
#990000
1#
b100010100 /
10
b100010100 <
1=
b100010100 I
#991000
0+
08
0E
#992000
b11011000 &
b10001110 '
b101100110 (
b11011000 3
b10001110 4
b101100110 5
b11011000 @
b10001110 A
b101100110 B
#995000
0#
00
0=
#1000000
1#
10
1=
#1001000
1+
b00011110 ,
b11000000 -
b011011110 .
18
b00011110 9
b11000000 :
b011011110 ;
1E
b00011110 F
b11000000 G
b011011110 H
#1005000
0#
00
0=
#1010000
1#
b111010100 /
10
b111010100 <
1=
b111010100 I
#1011000
0+
08
0E
#1012000
b00100100 &
b01110100 '
b010011000 (
b00100100 3
b01110100 4
b010011000 5
b00100100 @
b01110100 A
b010011000 B
#1015000
0#
00
0=
#1020000
1#
10
1=
#1021000
b00111101 ,
b11111000 -
b100110101 .
b00111101 9
b11111000 :
b100110101 ;
b00111101 F
b11111000 G
b100110101 H
#1025000
0#
00
0=
#1030000
1#
10
1=
#1032000
b01011110 &
b10000110 '
b011100100 (
b01011110 3
b10000110 4
b011100100 5
b01011110 @
b10000110 A
b011100100 B
#1035000
0#
00
0=
#1040000
1#
10
1=
#1041000
1+
b00011110 ,
b00110000 -
b001001110 .
18
b00011110 9
b00110000 :
b001001110 ;
1E
b00011110 F
b00110000 G
b001001110 H
#1045000
0#
00
0=
#1050000
1#
b000000100 /
10
b000000100 <
1=
b000000100 I
#1051000
0+
08
0E
#1052000
1%
b00001101 &
b01100010 '
b001101111 (
12
b00001101 3
b01100010 4
b001101111 5
1?
b00001101 @
b01100010 A
b001101111 B
#1055000
0#
00
0=
#1060000
1#
b100000010 )
10
b100000010 6
1=
b100000010 C
#1061000
0%
1+
b00101001 ,
b10101100 -
b011010101 .
02
18
b00101001 9
b10101100 :
b011010101 ;
0?
1E
b00101001 F
b10101100 G
b011010101 H
#1065000
0#
00
0=
#1070000
1#
b010110000 /
10
b010110000 <
1=
b010110000 I
#1071000
0+
08
0E
#1072000
1%
b00111110 &
b10010110 '
b011010100 (
12
b00111110 3
b10010110 4
b011010100 5
1?
b00111110 @
b10010110 A
b011010100 B
#1075000
0#
00
0=
#1080000
1#
b110011000 )
10
b110011000 6
1=
b110011000 C
