rtl/top_level.sv


module top_level (
    input  logic       clk,

    // Channel A
    input  logic       rst_A,
    input  logic       valid_in_A,
    input  logic [7:0] a_A,
    input  logic [7:0] b_A,
    output logic [8:0] sum_async_A,
    output logic [8:0] sum_sync_A,

    // Channel B
    input  logic       rst_B,
    input  logic       valid_in_B,
    input  logic [7:0] a_B,
    input  logic [7:0] b_B,
    output logic [8:0] sum_async_B,
    output logic [8:0] sum_sync_B
);

    // Channel A synchronous accumulator
    always_ff @(posedge clk) begin
        if (rst_A)
            sum_sync_A <= '0;
        else if (valid_in_A)
            sum_sync_A <= sum_sync_A + b_A;
    end

    assign sum_async_A = a_A + b_A;

    // Channel B synchronous accumulator
    always_ff @(posedge clk) begin
        if (rst_B)
            sum_sync_B <= '0;
        else if (valid_in_B)
            sum_sync_B <= sum_sync_B + b_B;
    end

    assign sum_async_B = a_B + b_B;

    initial begin
        $display("Time | rst_A| valid_in_A | a_A | b_A |sum_async_A | sum_sync_A |rst_B | valid_in_B| a_B | b_B  | sum_async_B | sum_sync_B   ");
        $monitor("%4t  |  %b  |  %b        | %0d | %0d |    %0d     |   %0d      | %b   |    %b     | %0d | %0d  |    %0d      |   %0d ",
                 $time, rst_A, valid_in_A, a_A, b_A, sum_async_A,sum_sync_A, rst_B, valid_in_B, a_B, b_B, sum_async_B, sum_sync_B);
    end

    initial begin
        $dumpfile("dump.vcd");
        $dumpvars(1, top_level.sv);
    end

endmodule

rtl/dut_wrapper.sv
module dut_wrapper (
    input  logic       clk,

    // Channel A – cocotb drives these
    input  logic       rst_A,
    input  logic       valid_in_A,
    input  logic [7:0] a_A,
    input  logic [7:0] b_A,

    // DUT drives these
    output logic [8:0] sum_async_A,
    output logic [8:0] sum_sync_A,

    // Channel B (if needed)
    input  logic       rst_B,
    input  logic       valid_in_B,
    input  logic [7:0] a_B,
    input  logic [7:0] b_B,
    output logic [8:0] sum_async_B,
    output logic [8:0] sum_sync_B
);

    top_level u_top_level (
        .clk(clk),

        // Channel A
        .rst_A(rst_A),
        .valid_in_A(valid_in_A),
        .a_A(a_A),
        .b_A(b_A),
        .sum_async_A(sum_async_A),
        .sum_sync_A(sum_sync_A),

        // Channel B
        .rst_B(rst_B),
        .valid_in_B(valid_in_B),
        .a_B(a_B),
        .b_B(b_B),
        .sum_async_B(sum_async_B),
        .sum_sync_B(sum_sync_B)
    );

endmodule



// module dut_wrapper (
//     input  logic       clk,

//     // Channel A – exposed directly for cocotb
//     output logic       rst_A,
//     output logic       valid_in_A,
//     output logic [7:0] a_A,
//     output logic [7:0] b_A,
//     output logic [8:0] sum_async_A,
//     output logic [8:0] sum_sync_A,

//     // Channel B – exposed directly for cocotb
//     output logic       rst_B,
//     output logic       valid_in_B,
//     output logic [7:0] a_B,
//     output logic [7:0] b_B,
//     output logic [8:0] sum_async_B,
//     output logic [8:0] sum_sync_B
// );

//     // Internal wires driven by cocotb (use these as DUT inputs)
//     logic rst_A_int;
//     logic valid_in_A_int;
//     logic [7:0] a_A_int;
//     logic [7:0] b_A_int;

//     logic rst_B_int;
//     logic valid_in_B_int;
//     logic [7:0] a_B_int;
//     logic [7:0] b_B_int;

//     // Connect exposed ports to internal wires so cocotb can drive them
//     assign rst_A       = rst_A_int;
//     assign valid_in_A  = valid_in_A_int;
//     assign a_A         = a_A_int;
//     assign b_A         = b_A_int;

//     assign rst_B       = rst_B_int;
//     assign valid_in_B  = valid_in_B_int;
//     assign a_B         = a_B_int;
//     assign b_B         = b_B_int;

//     // DUT instance
//     top_level u_top_level (
//         .clk          (clk),

//         // Channel A
//         .rst_A        (rst_A_int),
//         .valid_in_A   (valid_in_A_int),
//         .a_A          (a_A_int),
//         .b_A          (b_A_int),
//         .sum_async_A  (sum_async_A),
//         .sum_sync_A   (sum_sync_A),

//         // Channel B
//         .rst_B        (rst_B_int),
//         .valid_in_B   (valid_in_B_int),
//         .a_B          (a_B_int),
//         .b_B          (b_B_int),
//         .sum_async_B  (sum_async_B),
//         .sum_sync_B   (sum_sync_B)
//     );

// endmodule

regression_results/waves_9.vcd
$version Generated by VerilatedVcd $end
$timescale 1ps $end
 $scope module $rootio $end
  $var wire 1 # clk $end
  $var wire 1 $ rst_A $end
  $var wire 1 % valid_in_A $end
  $var wire 8 & a_A [7:0] $end
  $var wire 8 ' b_A [7:0] $end
  $var wire 9 ( sum_async_A [8:0] $end
  $var wire 9 ) sum_sync_A [8:0] $end
  $var wire 1 * rst_B $end
  $var wire 1 + valid_in_B $end
  $var wire 8 , a_B [7:0] $end
  $var wire 8 - b_B [7:0] $end
  $var wire 9 . sum_async_B [8:0] $end
  $var wire 9 / sum_sync_B [8:0] $end
 $upscope $end
 $scope module dut_wrapper $end
  $var wire 1 0 clk $end
  $var wire 1 1 rst_A $end
  $var wire 1 2 valid_in_A $end
  $var wire 8 3 a_A [7:0] $end
  $var wire 8 4 b_A [7:0] $end
  $var wire 9 5 sum_async_A [8:0] $end
  $var wire 9 6 sum_sync_A [8:0] $end
  $var wire 1 7 rst_B $end
  $var wire 1 8 valid_in_B $end
  $var wire 8 9 a_B [7:0] $end
  $var wire 8 : b_B [7:0] $end
  $var wire 9 ; sum_async_B [8:0] $end
  $var wire 9 < sum_sync_B [8:0] $end
  $scope module u_top_level $end
   $var wire 1 = clk $end
   $var wire 1 > rst_A $end
   $var wire 1 ? valid_in_A $end
   $var wire 8 @ a_A [7:0] $end
   $var wire 8 A b_A [7:0] $end
   $var wire 9 B sum_async_A [8:0] $end
   $var wire 9 C sum_sync_A [8:0] $end
   $var wire 1 D rst_B $end
   $var wire 1 E valid_in_B $end
   $var wire 8 F a_B [7:0] $end
   $var wire 8 G b_B [7:0] $end
   $var wire 9 H sum_async_B [8:0] $end
   $var wire 9 I sum_sync_B [8:0] $end
  $upscope $end
 $upscope $end
$enddefinitions $end


#0
1#
1$
0%
b00000000 &
b00000000 '
b000000000 (
b000000000 )
1*
0+
b00000000 ,
b00000000 -
b000000000 .
b000000000 /
10
11
02
b00000000 3
b00000000 4
b000000000 5
b000000000 6
17
08
b00000000 9
b00000000 :
b000000000 ;
b000000000 <
1=
1>
0?
b00000000 @
b00000000 A
b000000000 B
b000000000 C
1D
0E
b00000000 F
b00000000 G
b000000000 H
b000000000 I
#15021000
0
0=
#5000
1#
10
1=
#7500
0#
00
0=
#10000
1#
10
1=
#12500
0#
00
0=
#15000
1#
10
1=
#17500
0#
00
0=
#20000
1#
0$
1%
b00100111 &
b10100010 '
b011001001 (
0*
10
01
12
b00100111 3
b10100010 4
b011001001 5
07
1=
0>
1?
b00100111 @
b10100010 A
b011001001 B
0D
#22500
0#
00
0=
#25000
1#
b010100010 )
10
b010100010 6
1=
b010100010 C
#26000
0%
1+
b10000011 ,
b11001001 -
b101001100 .
02
18
b10000011 9
b11001001 :
b101001100 ;
0?
1E
b10000011 F
b11001001 G
b101001100 H
#27500
0#
00
0=
#30000
1#
b011001001 /
10
b011001001 <
1=
b011001001 I
#31000
0+
08
0E
#32000
1%
b11010011 &
b10100111 '
b101111010 (
12
b11010011 3
b10100111 4
b101111010 5
1?
b11010011 @
b10100111 A
b101111010 B
#32500
0#
00
0=
#35000
1#
b101001001 )
10
b101001001 6
1=
b101001001 C
#36000
0%
1+
b00110111 ,
b10001011 -
b011000010 .
02
18
b00110111 9
b10001011 :
b011000010 ;
0?
1E
b00110111 F
b10001011 G
b011000010 H
#37500
0#
00
0=
#40000
1#
b101010100 /
10
b101010100 <
1=
b101010100 I
#41000
0+
08
0E
#42000
1%
b10101100 &
b11001110 '
12
b10101100 3
b11001110 4
1?
b10101100 @
b11001110 A
#42500
0#
00
0=
#45000
1#
b000010111 )
10
b000010111 6
1=
b000010111 C
#46000
0%
1+
b10011110 ,
b10010111 -
b100110101 .
02
18
b10011110 9
b10010111 :
b100110101 ;
0?
1E
b10011110 F
b10010111 G
b100110101 H
#47500
0#
00
0=
#50000
1#
b111101011 /
10
b111101011 <
1=
b111101011 I
#51000
0+
08
0E
#52000
1%
b10100111 &
b00110100 '
b011011011 (
12
b10100111 3
b00110100 4
b011011011 5
1?
b10100111 @
b00110100 A
b011011011 B
#52500
0#
00
0=
#55000
1#
b001001011 )
10
b001001011 6
1=
b001001011 C
#56000
0%
1+
b00100011 ,
b01111011 -
b010011110 .
02
18
b00100011 9
b01111011 :
b010011110 ;
0?
1E
b00100011 F
b01111011 G
b010011110 H
#57500
0#
00
0=
#60000
1#
b001100110 /
10
b001100110 <
1=
b001100110 I
#61000
0+
08
0E
#62000
1%
b01011111 &
b10111000 '
b100010111 (
12
b01011111 3
b10111000 4
b100010111 5
1?
b01011111 @
b10111000 A
b100010111 B
#62500
0#
00
0=
#65000
1#
b100000011 )
10
b100000011 6
1=
b100000011 C
#66000
0%
1+
b10110110 ,
b10000001 -
b100110111 .
02
18
b10110110 9
b10000001 :
b100110111 ;
0?
1E
b10110110 F
b10000001 G
b100110111 H
#67500
0#
00
0=
#70000
1#
b011100111 /
10
b011100111 <
1=
b011100111 I
#71000
0+
08
0E
#72000
1%
b00110001 &
b11001101 '
b011111110 (
12
b00110001 3
b11001101 4
b011111110 5
1?
b00110001 @
b11001101 A
b011111110 B
#72500
0#
00
0=
#75000
1#
b111010000 )
10
b111010000 6
1=
b111010000 C
#76000
0%
1+
b01110111 ,
b11000011 -
b100111010 .
02
18
b01110111 9
b11000011 :
b100111010 ;
0?
1E
b01110111 F
b11000011 G
b100111010 H
#77500
0#
00
0=
#80000
1#
b110101010 /
10
b110101010 <
1=
b110101010 I
#81000
0+
08
0E
#82000
1%
b01110011 &
b00110011 '
b010100110 (
12
b01110011 3
b00110011 4
b010100110 5
1?
b01110011 @
b00110011 A
b010100110 B
#82500
0#
00
0=
#85000
1#
b000000011 )
10
b000000011 6
1=
b000000011 C
#86000
0%
1+
b11001111 ,
b00110011 -
b100000010 .
02
18
b11001111 9
b00110011 :
b100000010 ;
0?
1E
b11001111 F
b00110011 G
b100000010 H
#87500
0#
00
0=
#90000
1#
b111011101 /
10
b111011101 <
1=
b111011101 I
#91000
0+
08
0E
#92000
1%
b10010001 &
b01010011 '
b011100100 (
12
b10010001 3
b01010011 4
b011100100 5
1?
b10010001 @
b01010011 A
b011100100 B
#92500
0#
00
0=
#95000
1#
b001010110 )
10
b001010110 6
1=
b001010110 C
#96000
0%
1+
b01010100 ,
b11101001 -
b100111101 .
02
18
b01010100 9
b11101001 :
b100111101 ;
0?
1E
b01010100 F
b11101001 G
b100111101 H
#97500
0#
00
0=
#100000
1#
b011000110 /
10
b011000110 <
1=
b011000110 I
#101000
0+
08
0E
#102000
1%
b10011001 &
b01111001 '
b100010010 (
12
b10011001 3
b01111001 4
b100010010 5
1?
b10011001 @
b01111001 A
b100010010 B
#102500
0#
00
0=
#105000
1#
b011001111 )
10
b011001111 6
1=
b011001111 C
#106000
0%
1+
b01001111 ,
b00011000 -
b001100111 .
02
18
b01001111 9
b00011000 :
b001100111 ;
0?
1E
b01001111 F
b00011000 G
b001100111 H
#107500
0#
00
0=
#110000
1#
b011011110 /
10
b011011110 <
1=
b011011110 I
#111000
0+
08
0E
#112000
1%
b01011111 &
b10111100 '
b100011011 (
12
b01011111 3
b10111100 4
b100011011 5
1?
b01011111 @
b10111100 A
b100011011 B
#112500
0#
00
0=
#115000
1#
b110001011 )
10
b110001011 6
1=
b110001011 C
#116000
0%
1+
b11100010 ,
b10010000 -
b101110010 .
02
18
b11100010 9
b10010000 :
b101110010 ;
0?
1E
b11100010 F
b10010000 G
b101110010 H
#117500
0#
00
0=
#120000
1#
b101101110 /
10
b101101110 <
1=
b101101110 I
#121000
0+
08
0E
#122000
1%
b00110111 &
b01110101 '
b010101100 (
12
b00110111 3
b01110101 4
b010101100 5
1?
b00110111 @
b01110101 A
b010101100 B
#122500
0#
00
0=
#125000
1#
b000000000 )
10
b000000000 6
1=
b000000000 C
#126000
0%
1+
b00000001 ,
b00101000 -
b000101001 .
02
18
b00000001 9
b00101000 :
b000101001 ;
0?
1E
b00000001 F
b00101000 G
b000101001 H
#127500
0#
00
0=
#130000
1#
b110010110 /
10
b110010110 <
1=
b110010110 I
#131000
0+
08
0E
#132000
1%
b01010011 &
b01110001 '
b011000100 (
12
b01010011 3
b01110001 4
b011000100 5
1?
b01010011 @
b01110001 A
b011000100 B
#132500
0#
00
0=
#135000
1#
b001110001 )
10
b001110001 6
1=
b001110001 C
#136000
0%
1+
b01101111 ,
b10001110 -
b011111101 .
02
18
b01101111 9
b10001110 :
b011111101 ;
0?
1E
b01101111 F
b10001110 G
b011111101 H
#137500
0#
00
0=
#140000
1#
b000100100 /
10
b000100100 <
1=
b000100100 I
#141000
0+
08
0E
#142000
1%
b10100101 &
b00000010 '
b010100111 (
12
b10100101 3
b00000010 4
b010100111 5
1?
b10100101 @
b00000010 A
b010100111 B
#142500
0#
00
0=
#145000
1#
b001110011 )
10
b001110011 6
1=
b001110011 C
#146000
0%
1+
b10101100 ,
b11100001 -
b110001101 .
02
18
b10101100 9
b11100001 :
b110001101 ;
0?
1E
b10101100 F
b11100001 G
b110001101 H
#147500
0#
00
0=
#150000
1#
b100000101 /
10
b100000101 <
1=
b100000101 I
#151000
0+
08
0E
#152000
1%
b10101000 &
b01010111 '
b011111111 (
12
b10101000 3
b01010111 4
b011111111 5
1?
b10101000 @
b01010111 A
b011111111 B
#152500
0#
00
0=
#155000
1#
b011001010 )
10
b011001010 6
1=
b011001010 C
#156000
0%
1+
b01000100 ,
b10000100 -
b011001000 .
02
18
b01000100 9
b10000100 :
b011001000 ;
0?
1E
b01000100 F
b10000100 G
b011001000 H
#157500
0#
00
0=
#160000
1#
b110001001 /
10
b110001001 <
1=
b110001001 I
#161000
0+
08
0E
#162000
1%
b01101111 &
b01100100 '
b011010011 (
12
b01101111 3
b01100100 4
b011010011 5
1?
b01101111 @
b01100100 A
b011010011 B
#162500
0#
00
0=
#165000
1#
b100101110 )
10
b100101110 6
1=
b100101110 C
#166000
0%
1+
b01101010 ,
b10100110 -
b100010000 .
02
18
b01101010 9
b10100110 :
b100010000 ;
0?
1E
b01101010 F
b10100110 G
b100010000 H
#167500
0#
00
0=
#170000
1#
b000101111 /
10
b000101111 <
1=
b000101111 I
#171000
0+
08
0E
#172000
1%
b10111100 &
b01000001 '
b011111101 (
12
b10111100 3
b01000001 4
b011111101 5
1?
b10111100 @
b01000001 A
b011111101 B
#172500
0#
00
0=
#175000
1#
b101101111 )
10
b101101111 6
1=
b101101111 C
#176000
0%
1+
b01000010 ,
b00001001 -
b001001011 .
02
18
b01000010 9
b00001001 :
b001001011 ;
0?
1E
b01000010 F
b00001001 G
b001001011 H
#177500
0#
00
0=
#180000
1#
b000111000 /
10
b000111000 <
1=
b000111000 I
#181000
0+
08
0E
#182000
1%
b00111000 &
b00100011 '
b001011011 (
12
b00111000 3
b00100011 4
b001011011 5
1?
b00111000 @
b00100011 A
b001011011 B
#182500
0#
00
0=
#185000
1#
b110010010 )
10
b110010010 6
1=
b110010010 C
#186000
0%
1+
b11001000 ,
b01110010 -
b100111010 .
02
18
b11001000 9
b01110010 :
b100111010 ;
0?
1E
b11001000 F
b01110010 G
b100111010 H
#187500
0#
00
0=
#190000
1#
b010101010 /
10
b010101010 <
1=
b010101010 I
#191000
0+
08
0E
#192000
1%
b00010011 &
b11111100 '
b100001111 (
12
b00010011 3
b11111100 4
b100001111 5
1?
b00010011 @
b11111100 A
b100001111 B
#192500
0#
00
0=
#195000
1#
b010001110 )
10
b010001110 6
1=
b010001110 C
#196000
0%
1+
b00010011 ,
b00110001 -
b001000100 .
02
18
b00010011 9
b00110001 :
b001000100 ;
0?
1E
b00010011 F
b00110001 G
b001000100 H
#197500
0#
00
0=
#200000
1#
b011011011 /
10
b011011011 <
1=
b011011011 I
#201000
0+
08
0E
#202000
1%
b01000011 &
b01001001 '
b010001100 (
12
b01000011 3
b01001001 4
b010001100 5
1?
b01000011 @
b01001001 A
b010001100 B
#202500
0#
00
0=
#205000
1#
b011010111 )
10
b011010111 6
1=
b011010111 C
#206000
0%
1+
b01010001 ,
b11011111 -
b100110000 .
02
18
b01010001 9
b11011111 :
b100110000 ;
0?
1E
b01010001 F
b11011111 G
b100110000 H
#207500
0#
00
0=
#210000
1#
b110111010 /
10
b110111010 <
1=
b110111010 I
#211000
0+
08
0E
#212000
1%
b10110110 &
b01010110 '
b100001100 (
12
b10110110 3
b01010110 4
b100001100 5
1?
b10110110 @
b01010110 A
b100001100 B
#212500
0#
00
0=
#215000
1#
b100101101 )
10
b100101101 6
1=
b100101101 C
#216000
0%
1+
b10100111 ,
b10100000 -
b101000111 .
02
18
b10100111 9
b10100000 :
b101000111 ;
0?
1E
b10100111 F
b10100000 G
b101000111 H
#217500
0#
00
0=
#220000
1#
b001011010 /
10
b001011010 <
1=
b001011010 I
#221000
0+
08
0E
#222000
1%
b10110001 &
b00111110 '
b011101111 (
12
b10110001 3
b00111110 4
b011101111 5
1?
b10110001 @
b00111110 A
b011101111 B
#222500
0#
00
0=
#225000
1#
b101101011 )
10
b101101011 6
1=
b101101011 C
#226000
0%
1+
b10011000 ,
b11101111 -
b110000111 .
02
18
b10011000 9
b11101111 :
b110000111 ;
0?
1E
b10011000 F
b11101111 G
b110000111 H
#227500
0#
00
0=
#230000
1#
b101001001 /
10
b101001001 <
1=
b101001001 I
#231000
0+
08
0E
#232000
1%
b11100101 &
b10010110 '
b101111011 (
12
b11100101 3
b10010110 4
b101111011 5
1?
b11100101 @
b10010110 A
b101111011 B
#232500
0#
00
0=
#235000
1#
b000000001 )
10
b000000001 6
1=
b000000001 C
#236000
0%
1+
b01010000 ,
b10000100 -
b011010100 .
02
18
b01010000 9
b10000100 :
b011010100 ;
0?
1E
b01010000 F
b10000100 G
b011010100 H
#237500
0#
00
0=
#240000
1#
b111001101 /
10
b111001101 <
1=
b111001101 I
#241000
0+
08
0E
#242000
1%
b01001101 &
b00011100 '
b001101001 (
12
b01001101 3
b00011100 4
b001101001 5
1?
b01001101 @
b00011100 A
b001101001 B
#242500
0#
00
0=
#245000
1#
b000011101 )
10
b000011101 6
1=
b000011101 C
#246000
0%
1+
b00011110 ,
b11001110 -
b011101100 .
02
18
b00011110 9
b11001110 :
b011101100 ;
0?
1E
b00011110 F
b11001110 G
b011101100 H
#247500
0#
00
0=
#250000
1#
b010011011 /
10
b010011011 <
1=
b010011011 I
#251000
0+
08
0E
#252000
1%
b00100001 &
b00000100 '
b000100101 (
12
b00100001 3
b00000100 4
b000100101 5
1?
b00100001 @
b00000100 A
b000100101 B
#252500
0#
00
0=
#255000
1#
b000100001 )
10
b000100001 6
1=
b000100001 C
#256000
0%
1+
b11000010 ,
b10001100 -
b101001110 .
02
18
b11000010 9
b10001100 :
b101001110 ;
0?
1E
b11000010 F
b10001100 G
b101001110 H
#257500
0#
00
0=
#260000
1#
b100100111 /
10
b100100111 <
1=
b100100111 I
#261000
0+
08
0E
#262000
1%
b00010001 &
b01111100 '
b010001101 (
12
b00010001 3
b01111100 4
b010001101 5
1?
b00010001 @
b01111100 A
b010001101 B
#262500
0#
00
0=
#265000
1#
b010011101 )
10
b010011101 6
1=
b010011101 C
#266000
0%
1+
b01100001 ,
b01111101 -
b011011110 .
02
18
b01100001 9
b01111101 :
b011011110 ;
0?
1E
b01100001 F
b01111101 G
b011011110 H
#267500
0#
00
0=
#270000
1#
b110100100 /
10
b110100100 <
1=
b110100100 I
#271000
0+
08
0E
#272000
1%
b00001010 &
b00110100 '
b000111110 (
12
b00001010 3
b00110100 4
b000111110 5
1?
b00001010 @
b00110100 A
b000111110 B
#272500
0#
00
0=
#275000
1#
b011010001 )
10
b011010001 6
1=
b011010001 C
#276000
0%
1+
b01001011 ,
b00101011 -
b001110110 .
02
18
b01001011 9
b00101011 :
b001110110 ;
0?
1E
b01001011 F
b00101011 G
b001110110 H
#277500
0#
00
0=
#280000
1#
b111001111 /
10
b111001111 <
1=
b111001111 I
#281000
0+
08
0E
#282000
1%
b00001101 &
b01100011 '
b001110000 (
12
b00001101 3
b01100011 4
b001110000 5
1?
b00001101 @
b01100011 A
b001110000 B
#282500
0#
00
0=
#285000
1#
b100110100 )
10
b100110100 6
1=
b100110100 C
#286000
0%
1+
b00010111 ,
b00010111 -
b000101110 .
02
18
b00010111 9
b00010111 :
b000101110 ;
0?
1E
b00010111 F
b00010111 G
b000101110 H
#287500
0#
00
0=
#290000
1#
b111100110 /
10
b111100110 <
1=
b111100110 I
#291000
0+
08
0E
#292000
1%
b01001100 &
b00001101 '
b001011001 (
12
b01001100 3
b00001101 4
b001011001 5
1?
b01001100 @
b00001101 A
b001011001 B
#292500
0#
00
0=
#295000
1#
b101000001 )
10
b101000001 6
1=
b101000001 C
#296000
0%
1+
b10100011 ,
b00000001 -
b010100100 .
02
18
b10100011 9
b00000001 :
b010100100 ;
0?
1E
b10100011 F
b00000001 G
b010100100 H
#297500
0#
00
0=
#300000
1#
b111100111 /
10
b111100111 <
1=
b111100111 I
#301000
0+
08
0E
#302000
1%
b10010011 &
b10001001 '
b100011100 (
12
b10010011 3
b10001001 4
b100011100 5
1?
b10010011 @
b10001001 A
b100011100 B
#302500
0#
00
0=
#305000
1#
b111001010 )
10
b111001010 6
1=
b111001010 C
#306000
0%
1+
b01000110 ,
b11001101 -
b100010011 .
02
18
b01000110 9
b11001101 :
b100010011 ;
0?
1E
b01000110 F
b11001101 G
b100010011 H
#307500
0#
00
0=
#310000
1#
b010110100 /
10
b010110100 <
1=
b010110100 I
#311000
0+
08
0E
#312000
1%
b11011100 &
b01001100 '
b100101000 (
12
b11011100 3
b01001100 4
b100101000 5
1?
b11011100 @
b01001100 A
b100101000 B
#312500
0#
00
0=
#315000
1#
b000010110 )
10
b000010110 6
1=
b000010110 C
#316000
0%
1+
b10000010 ,
b11010111 -
b101011001 .
02
18
b10000010 9
b11010111 :
b101011001 ;
0?
1E
b10000010 F
b11010111 G
b101011001 H
#317500
0#
00
0=
#320000
1#
b110001011 /
10
b110001011 <
1=
b110001011 I
#321000
0+
08
0E
#322000
1%
b00101100 &
b11000101 '
b011110001 (
12
b00101100 3
b11000101 4
b011110001 5
1?
b00101100 @
b11000101 A
b011110001 B
#322500
0#
00
0=
#325000
1#
b011011011 )
10
b011011011 6
1=
b011011011 C
#326000
0%
1+
b10100101 ,
b11100011 -
b110001000 .
02
18
b10100101 9
b11100011 :
b110001000 ;
0?
1E
b10100101 F
b11100011 G
b110001000 H
#327500
0#
00
0=
#330000
1#
b001101110 /
10
b001101110 <
1=
b001101110 I
#331000
0+
08
0E
#332000
1%
b10101010 &
b10101100 '
b101010110 (
12
b10101010 3
b10101100 4
b101010110 5
1?
b10101010 @
b10101100 A
b101010110 B
#332500
0#
00
0=
#335000
1#
b110000111 )
10
b110000111 6
1=
b110000111 C
#336000
0%
1+
b10110010 ,
b11001111 -
b110000001 .
02
18
b10110010 9
b11001111 :
b110000001 ;
0?
1E
b10110010 F
b11001111 G
b110000001 H
#337500
0#
00
0=
#340000
1#
b100111101 /
10
b100111101 <
1=
b100111101 I
#341000
0+
08
0E
#342000
1%
b00001101 &
b11110001 '
b011111110 (
12
b00001101 3
b11110001 4
b011111110 5
1?
b00001101 @
b11110001 A
b011111110 B
#342500
0#
00
0=
#345000
1#
b001111000 )
10
b001111000 6
1=
b001111000 C
#346000
0%
1+
b10101010 ,
b01110001 -
b100011011 .
02
18
b10101010 9
b01110001 :
b100011011 ;
0?
1E
b10101010 F
b01110001 G
b100011011 H
#347500
0#
00
0=
#350000
1#
b110101110 /
10
b110101110 <
1=
b110101110 I
#351000
0+
08
0E
#352000
1%
b10010010 &
b10100010 '
b100110100 (
12
b10010010 3
b10100010 4
b100110100 5
1?
b10010010 @
b10100010 A
b100110100 B
#352500
0#
00
0=
#355000
1#
b100011010 )
10
b100011010 6
1=
b100011010 C
#356000
0%
1+
b10110100 ,
b10011001 -
b101001101 .
02
18
b10110100 9
b10011001 :
b101001101 ;
0?
1E
b10110100 F
b10011001 G
b101001101 H
#357500
0#
00
0=
#360000
1#
b001000111 /
10
b001000111 <
1=
b001000111 I
#361000
0+
08
0E
#362000
1%
b00000010 &
b00010000 '
b000010010 (
12
b00000010 3
b00010000 4
b000010010 5
1?
b00000010 @
b00010000 A
b000010010 B
#362500
0#
00
0=
#365000
1#
b100101010 )
10
b100101010 6
1=
b100101010 C
#366000
0%
1+
b01001111 ,
b11010101 -
b100100100 .
02
18
b01001111 9
b11010101 :
b100100100 ;
0?
1E
b01001111 F
b11010101 G
b100100100 H
#367500
0#
00
0=
#370000
1#
b100011100 /
10
b100011100 <
1=
b100011100 I
#371000
0+
08
0E
#372000
1%
b11010100 &
b11111100 '
b111010000 (
12
b11010100 3
b11111100 4
b111010000 5
1?
b11010100 @
b11111100 A
b111010000 B
#372500
0#
00
0=
#375000
1#
b000100110 )
10
b000100110 6
1=
b000100110 C
#376000
0%
1+
b10101100 ,
b110000001 .
02
18
b10101100 9
b110000001 ;
0?
1E
b10101100 F
b110000001 H
#377500
0#
00
0=
#380000
1#
b111110001 /
10
b111110001 <
1=
b111110001 I
#381000
0+
08
0E
#382000
1%
b11111000 &
b11001110 '
b111000110 (
12
b11111000 3
b11001110 4
b111000110 5
1?
b11111000 @
b11001110 A
b111000110 B
#382500
0#
00
0=
#385000
1#
b011110100 )
10
b011110100 6
1=
b011110100 C
#386000
0%
1+
b00000100 ,
b11100101 -
b011101001 .
02
18
b00000100 9
b11100101 :
b011101001 ;
0?
1E
b00000100 F
b11100101 G
b011101001 H
#387500
0#
00
0=
#390000
1#
b011010110 /
10
b011010110 <
1=
b011010110 I
#391000
0+
08
0E
#392000
1%
b11010110 &
b01111001 '
b101001111 (
12
b11010110 3
b01111001 4
b101001111 5
1?
b11010110 @
b01111001 A
b101001111 B
#392500
0#
00
0=
#395000
1#
b101101101 )
10
b101101101 6
1=
b101101101 C
#396000
0%
1+
b01100110 ,
b10101000 -
b100001110 .
02
18
b01100110 9
b10101000 :
b100001110 ;
0?
1E
b01100110 F
b10101000 G
b100001110 H
#397500
0#
00
0=
#400000
1#
b101111110 /
10
b101111110 <
1=
b101111110 I
#401000
0+
08
0E
#402000
1%
b00111101 &
b10101100 '
b011101001 (
12
b00111101 3
b10101100 4
b011101001 5
1?
b00111101 @
b10101100 A
b011101001 B
#402500
0#
00
0=
#405000
1#
b000011001 )
10
b000011001 6
1=
b000011001 C
#406000
0%
1+
b10011010 ,
b10001111 -
b100101001 .
02
18
b10011010 9
b10001111 :
b100101001 ;
0?
1E
b10011010 F
b10001111 G
b100101001 H
#407500
0#
00
0=
#410000
1#
b000001101 /
10
b000001101 <
1=
b000001101 I
#411000
0+
08
0E
#412000
1%
b10100110 &
b01101000 '
b100001110 (
12
b10100110 3
b01101000 4
b100001110 5
1?
b10100110 @
b01101000 A
b100001110 B
#412500
0#
00
0=
#415000
1#
b010000001 )
10
b010000001 6
1=
b010000001 C
#416000
0%
1+
b10101110 ,
b01111010 -
b100101000 .
02
18
b10101110 9
b01111010 :
b100101000 ;
0?
1E
b10101110 F
b01111010 G
b100101000 H
#417500
0#
00
0=
#420000
1#
b010000111 /
10
b010000111 <
1=
b010000111 I
#421000
0+
08
0E
#422000
1%
b11110011 &
b00111110 '
b100110001 (
12
b11110011 3
b00111110 4
b100110001 5
1?
b11110011 @
b00111110 A
b100110001 B
#422500
0#
00
0=
#425000
1#
b010111111 )
10
b010111111 6
1=
b010111111 C
#426000
0%
1+
b01100010 ,
b01011001 -
b010111011 .
02
18
b01100010 9
b01011001 :
b010111011 ;
0?
1E
b01100010 F
b01011001 G
b010111011 H
#427500
0#
00
0=
#430000
1#
b011100000 /
10
b011100000 <
1=
b011100000 I
#431000
0+
08
0E
#432000
1%
b01111100 &
b01100100 '
b011100000 (
12
b01111100 3
b01100100 4
b011100000 5
1?
b01111100 @
b01100100 A
b011100000 B
#432500
0#
00
0=
#435000
1#
b100100011 )
10
b100100011 6
1=
b100100011 C
#436000
0%
1+
b01101110 ,
b11110010 -
b101100000 .
02
18
b01101110 9
b11110010 :
b101100000 ;
0?
1E
b01101110 F
b11110010 G
b101100000 H
#437500
0#
00
0=
#440000
1#
b111010010 /
10
b111010010 <
1=
b111010010 I
#441000
0+
08
0E
#442000
1%
b10111000 &
b00110000 '
b011101000 (
12
b10111000 3
b00110000 4
b011101000 5
1?
b10111000 @
b00110000 A
b011101000 B
#442500
0#
00
0=
#445000
1#
b101010011 )
10
b101010011 6
1=
b101010011 C
#446000
0%
1+
b11111010 ,
b00010011 -
b100001101 .
02
18
b11111010 9
b00010011 :
b100001101 ;
0?
1E
b11111010 F
b00010011 G
b100001101 H
#447500
0#
00
0=
#450000
1#
b111100101 /
10
b111100101 <
1=
b111100101 I
#451000
0+
08
0E
#452000
1%
b01010001 &
b10001111 '
b011100000 (
12
b01010001 3
b10001111 4
b011100000 5
1?
b01010001 @
b10001111 A
b011100000 B
#452500
0#
00
0=
#455000
1#
b111100010 )
10
b111100010 6
1=
b111100010 C
#456000
0%
1+
b10010110 ,
b00111001 -
b011001111 .
02
18
b10010110 9
b00111001 :
b011001111 ;
0?
1E
b10010110 F
b00111001 G
b011001111 H
#457500
0#
00
0=
#460000
1#
b000011110 /
10
b000011110 <
1=
b000011110 I
#461000
0+
08
0E
#462000
1%
b11100100 &
b00010111 '
b011111011 (
12
b11100100 3
b00010111 4
b011111011 5
1?
b11100100 @
b00010111 A
b011111011 B
#462500
0#
00
0=
#465000
1#
b111111001 )
10
b111111001 6
1=
b111111001 C
#466000
0%
1+
b00110101 ,
b00000010 -
b000110111 .
02
18
b00110101 9
b00000010 :
b000110111 ;
0?
1E
b00110101 F
b00000010 G
b000110111 H
#467500
0#
00
0=
#470000
1#
b000100000 /
10
b000100000 <
1=
b000100000 I
