rtl/top_level.sv


module top_level (
    input  logic       clk,

    // Channel A
    input  logic       rst_A,
    input  logic       valid_in_A,
    input  logic [7:0] a_A,
    input  logic [7:0] b_A,
    output logic [8:0] sum_async_A,
    output logic [8:0] sum_sync_A,

    // Channel B
    input  logic       rst_B,
    input  logic       valid_in_B,
    input  logic [7:0] a_B,
    input  logic [7:0] b_B,
    output logic [8:0] sum_async_B,
    output logic [8:0] sum_sync_B
);

    // Channel A synchronous accumulator
    always_ff @(posedge clk) begin
        if (rst_A)
            sum_sync_A <= '0;
        else if (valid_in_A)
            sum_sync_A <= sum_sync_A + b_A;
    end

    assign sum_async_A = a_A + b_A;

    // Channel B synchronous accumulator
    always_ff @(posedge clk) begin
        if (rst_B)
            sum_sync_B <= '0;
        else if (valid_in_B)
            sum_sync_B <= sum_sync_B + b_B;
    end

    assign sum_async_B = a_B + b_B;

    // initial begin
    //     $display("Time | rst_A| valid_in_A | a_A | b_A |sum_async_A | sum_sync_A |rst_B | valid_in_B| a_B | b_B  | sum_async_B | sum_sync_B   ");
    //     $monitor("%9t  |  %b  |  %b        | %3d | %3d |    %3d     |   %3d      | %b   |    %b     | %3d | %3d  |    %3d      |   %3d ",
    //              $time, rst_A, valid_in_A, a_A, b_A, sum_async_A,sum_sync_A, rst_B, valid_in_B, a_B, b_B, sum_async_B, sum_sync_B);
    // end

    initial begin
        $dumpfile("dump.vcd");
        $dumpvars(1, top_level.sv);
    end

endmodule

rtl/dut_wrapper.sv
module dut_wrapper (
    input  logic       clk,

    // Channel A – cocotb drives these
    input  logic       rst_A,
    input  logic       valid_in_A,
    input  logic [7:0] a_A,
    input  logic [7:0] b_A,

    // DUT drives these
    output logic [8:0] sum_async_A,
    output logic [8:0] sum_sync_A,

    // Channel B (if needed)
    input  logic       rst_B,
    input  logic       valid_in_B,
    input  logic [7:0] a_B,
    input  logic [7:0] b_B,
    output logic [8:0] sum_async_B,
    output logic [8:0] sum_sync_B
);

    top_level u_top_level (
        .clk(clk),

        // Channel A
        .rst_A(rst_A),
        .valid_in_A(valid_in_A),
        .a_A(a_A),
        .b_A(b_A),
        .sum_async_A(sum_async_A),
        .sum_sync_A(sum_sync_A),

        // Channel B
        .rst_B(rst_B),
        .valid_in_B(valid_in_B),
        .a_B(a_B),
        .b_B(b_B),
        .sum_async_B(sum_async_B),
        .sum_sync_B(sum_sync_B)
    );

endmodule



// module dut_wrapper (
//     input  logic       clk,

//     // Channel A – exposed directly for cocotb
//     output logic       rst_A,
//     output logic       valid_in_A,
//     output logic [7:0] a_A,
//     output logic [7:0] b_A,
//     output logic [8:0] sum_async_A,
//     output logic [8:0] sum_sync_A,

//     // Channel B – exposed directly for cocotb
//     output logic       rst_B,
//     output logic       valid_in_B,
//     output logic [7:0] a_B,
//     output logic [7:0] b_B,
//     output logic [8:0] sum_async_B,
//     output logic [8:0] sum_sync_B
// );

//     // Internal wires driven by cocotb (use these as DUT inputs)
//     logic rst_A_int;
//     logic valid_in_A_int;
//     logic [7:0] a_A_int;
//     logic [7:0] b_A_int;

//     logic rst_B_int;
//     logic valid_in_B_int;
//     logic [7:0] a_B_int;
//     logic [7:0] b_B_int;

//     // Connect exposed ports to internal wires so cocotb can drive them
//     assign rst_A       = rst_A_int;
//     assign valid_in_A  = valid_in_A_int;
//     assign a_A         = a_A_int;
//     assign b_A         = b_A_int;

//     assign rst_B       = rst_B_int;
//     assign valid_in_B  = valid_in_B_int;
//     assign a_B         = a_B_int;
//     assign b_B         = b_B_int;

//     // DUT instance
//     top_level u_top_level (
//         .clk          (clk),

//         // Channel A
//         .rst_A        (rst_A_int),
//         .valid_in_A   (valid_in_A_int),
//         .a_A          (a_A_int),
//         .b_A          (b_A_int),
//         .sum_async_A  (sum_async_A),
//         .sum_sync_A   (sum_sync_A),

//         // Channel B
//         .rst_B        (rst_B_int),
//         .valid_in_B   (valid_in_B_int),
//         .a_B          (a_B_int),
//         .b_B          (b_B_int),
//         .sum_async_B  (sum_async_B),
//         .sum_sync_B   (sum_sync_B)
//     );

// endmodule

regression_results/waves_3.vcd
$version Generated by VerilatedVcd $end
$timescale 1ps $end
 $scope module $rootio $end
  $var wire 1 # clk $end
  $var wire 1 $ rst_A $end
  $var wire 1 % valid_in_A $end
  $var wire 8 & a_A [7:0] $end
  $var wire 8 ' b_A [7:0] $end
  $var wire 9 ( sum_async_A [8:0] $end
  $var wire 9 ) sum_sync_A [8:0] $end
  $var wire 1 * rst_B $end
  $var wire 1 + valid_in_B $end
  $var wire 8 , a_B [7:0] $end
  $var wire 8 - b_B [7:0] $end
  $var wire 9 . sum_async_B [8:0] $end
  $var wire 9 / sum_sync_B [8:0] $end
 $upscope $end
 $scope module dut_wrapper $end
  $var wire 1 0 clk $end
  $var wire 1 1 rst_A $end
  $var wire 1 2 valid_in_A $end
  $var wire 8 3 a_A [7:0] $end
  $var wire 8 4 b_A [7:0] $end
  $var wire 9 5 sum_async_A [8:0] $end
  $var wire 9 6 sum_sync_A [8:0] $end
  $var wire 1 7 rst_B $end
  $var wire 1 8 valid_in_B $end
  $var wire 8 9 a_B [7:0] $end
  $var wire 8 : b_B [7:0] $end
  $var wire 9 ; sum_async_B [8:0] $end
  $var wire 9 < sum_sync_B [8:0] $end
  $scope module u_top_level $end
   $var wire 1 = clk $end
   $var wire 1 > rst_A $end
   $var wire 1 ? valid_in_A $end
   $var wire 8 @ a_A [7:0] $end
   $var wire 8 A b_A [7:0] $end
   $var wire 9 B sum_async_A [8:0] $end
   $var wire 9 C sum_sync_A [8:0] $end
   $var wire 1 D rst_B $end
   $var wire 1 E valid_in_B $end
   $var wire 8 F a_B [7:0] $end
   $var wire 8 G b_B [7:0] $end
   $var wire 9 H sum_async_B [8:0] $end
   $var wire 9 I sum_sync_B [8:0] $end
  $upscope $end
 $upscope $end
$enddefinitions $end


#0
1#
1$
0%
b00000000 &
b00000000 '
b000000000 (
b000000000 )
1*
0+
b00000000 ,
b00000000 -
b000000000 .
b000000000 /
10
11
02
b00000000 3
b00000000 4
b000000000 5
b000000000 6
17
08
b00000000 9
b00000000 :
b000000000 ;
b000000000 <
1=
1>
0?
b00000000 @
b00000000 A
b000000000 B
b000000000 C
1D
0E
b00000000 F
b00000000 G
b000000000 H
b000000000 I
#5000
0#
00
0=
#10000
1#
10
1=
#15000
0#
00
0=
#20000
1#
0$
1%
b11111111 &
b011111111 (
0*
10
01
12
b11111111 3
b011111111 5
07
1=
0>
1?
b11111111 @
b011111111 B
0D
#25000
0#
00
0=
#30000
1#
10
1=
#31000
b11111111 '
b111111110 (
b11111111 4
b111111110 5
b11111111 A
b111111110 B
#35000
0#
00
0=
#40000
1#
b011111111 )
10
b011111111 6
1=
b011111111 C
#41000
1$
b00000000 &
b00000000 '
b000000000 (
11
b00000000 3
b00000000 4
b000000000 5
1>
b00000000 @
b00000000 A
b000000000 B
#45000
0#
00
0=
#50000
1#
b000000000 )
10
b000000000 6
1=
b000000000 C
#51000
b00000001 &
b00000001 '
b000000010 (
b00000001 3
b00000001 4
b000000010 5
b00000001 @
b00000001 A
b000000010 B
#55000
0#
00
0=
#60000
1#
10
1=
#61000
0$
b11111111 &
b100000000 (
01
b11111111 3
b100000000 5
0>
b11111111 @
b100000000 B
#65000
0#
00
0=
#70000
1#
b000000001 )
10
b000000001 6
1=
b000000001 C
#71000
b11001000 &
b01100100 '
b100101100 (
b11001000 3
b01100100 4
b100101100 5
b11001000 @
b01100100 A
b100101100 B
#75000
0#
00
0=
#80000
1#
b001100101 )
10
b001100101 6
1=
b001100101 C
#81000
b10000000 &
b11001000 '
b101001000 (
b10000000 3
b11001000 4
b101001000 5
b10000000 @
b11001000 A
b101001000 B
#85000
0#
00
0=
#90000
1#
b100101101 )
10
b100101101 6
1=
b100101101 C
#91000
b11111111 &
b11111111 '
b111111110 (
b11111111 3
b11111111 4
b111111110 5
b11111111 @
b11111111 A
b111111110 B
#95000
0#
00
0=
#100000
1#
b000101100 )
10
b000101100 6
1=
b000101100 C
#101000
0%
b00000000 &
b00000000 '
b000000000 (
02
b00000000 3
b00000000 4
b000000000 5
0?
b00000000 @
b00000000 A
b000000000 B
#105000
0#
00
0=
#110000
1#
10
1=
#111000
1%
b11111111 &
b011111111 (
12
b11111111 3
b011111111 5
1?
b11111111 @
b011111111 B
#115000
0#
00
0=
#120000
1#
10
1=
#121000
0%
b00000000 &
b000000000 (
02
b00000000 3
b000000000 5
0?
b00000000 @
b000000000 B
#125000
0#
00
0=
#130000
1#
10
1=
#131000
1%
b11111111 &
b11111111 '
b111111110 (
12
b11111111 3
b11111111 4
b111111110 5
1?
b11111111 @
b11111111 A
b111111110 B
#135000
0#
00
0=
#140000
1#
b100101011 )
10
b100101011 6
1=
b100101011 C
#141000
b01000100 &
b11100011 '
b100100111 (
b01000100 3
b11100011 4
b100100111 5
b01000100 @
b11100011 A
b100100111 B
#145000
0#
00
0=
#150000
1#
b000001110 )
10
b000001110 6
1=
b000001110 C
#151000
0%
1+
b11110110 ,
b11110111 -
b111101101 .
02
18
b11110110 9
b11110111 :
b111101101 ;
0?
1E
b11110110 F
b11110111 G
b111101101 H
#155000
0#
00
0=
#160000
1#
b011110111 /
10
b011110111 <
1=
b011110111 I
#161000
0+
08
0E
#162000
1%
b11111111 &
b11010100 '
b111010011 (
12
b11111111 3
b11010100 4
b111010011 5
1?
b11111111 @
b11010100 A
b111010011 B
#165000
0#
00
0=
#170000
1#
b011100010 )
10
b011100010 6
1=
b011100010 C
#171000
0%
1+
b11000110 ,
b01000110 -
b100001100 .
02
18
b11000110 9
b01000110 :
b100001100 ;
0?
1E
b11000110 F
b01000110 G
b100001100 H
#175000
0#
00
0=
#180000
1#
b100111101 /
10
b100111101 <
1=
b100111101 I
#181000
0+
08
0E
#182000
1%
b11001111 &
b11101011 '
b110111010 (
12
b11001111 3
b11101011 4
b110111010 5
1?
b11001111 @
b11101011 A
b110111010 B
#185000
0#
00
0=
#190000
1#
b111001101 )
10
b111001101 6
1=
b111001101 C
#191000
0%
1+
b01001010 ,
b00101011 -
b001110101 .
02
18
b01001010 9
b00101011 :
b001110101 ;
0?
1E
b01001010 F
b00101011 G
b001110101 H
#195000
0#
00
0=
#200000
1#
b101101000 /
10
b101101000 <
1=
b101101000 I
#201000
0+
08
0E
#202000
1%
b01111100 &
b00000101 '
b010000001 (
12
b01111100 3
b00000101 4
b010000001 5
1?
b01111100 @
b00000101 A
b010000001 B
#205000
0#
00
0=
#210000
1#
b111010010 )
10
b111010010 6
1=
b111010010 C
#211000
0%
1+
b00101111 ,
b10001000 -
b010110111 .
02
18
b00101111 9
b10001000 :
b010110111 ;
0?
1E
b00101111 F
b10001000 G
b010110111 H
#215000
0#
00
0=
#220000
1#
b111110000 /
10
b111110000 <
1=
b111110000 I
#221000
0+
08
0E
#222000
1%
b00100000 &
b10011011 '
b010111011 (
12
b00100000 3
b10011011 4
b010111011 5
1?
b00100000 @
b10011011 A
b010111011 B
#225000
0#
00
0=
#230000
1#
b001101101 )
10
b001101101 6
1=
b001101101 C
#231000
0%
1+
b01100101 ,
b00101100 -
b010010001 .
02
18
b01100101 9
b00101100 :
b010010001 ;
0?
1E
b01100101 F
b00101100 G
b010010001 H
#235000
0#
00
0=
#240000
1#
b000011100 /
10
b000011100 <
1=
b000011100 I
#241000
0+
08
0E
#242000
1%
b01010110 &
b01101111 '
b011000101 (
12
b01010110 3
b01101111 4
b011000101 5
1?
b01010110 @
b01101111 A
b011000101 B
#245000
0#
00
0=
#250000
1#
b011011100 )
10
b011011100 6
1=
b011011100 C
#251000
0%
1+
b10001001 ,
b00010101 -
b010011110 .
02
18
b10001001 9
b00010101 :
b010011110 ;
0?
1E
b10001001 F
b00010101 G
b010011110 H
#255000
0#
00
0=
#260000
1#
b000110001 /
10
b000110001 <
1=
b000110001 I
#261000
0+
08
0E
#262000
1%
b10011001 &
b01110001 '
b100001010 (
12
b10011001 3
b01110001 4
b100001010 5
1?
b10011001 @
b01110001 A
b100001010 B
#265000
0#
00
0=
#270000
1#
b101001101 )
10
b101001101 6
1=
b101001101 C
#271000
0%
1+
b11000110 ,
b11100001 -
b110100111 .
02
18
b11000110 9
b11100001 :
b110100111 ;
0?
1E
b11000110 F
b11100001 G
b110100111 H
#275000
0#
00
0=
#280000
1#
b100010010 /
10
b100010010 <
1=
b100010010 I
#281000
0+
08
0E
#282000
1%
b10000001 &
b11100010 '
b101100011 (
12
b10000001 3
b11100010 4
b101100011 5
1?
b10000001 @
b11100010 A
b101100011 B
#285000
0#
00
0=
#290000
1#
b000101111 )
10
b000101111 6
1=
b000101111 C
#291000
0%
1+
b10011001 ,
b01100101 -
b011111110 .
02
18
b10011001 9
b01100101 :
b011111110 ;
0?
1E
b10011001 F
b01100101 G
b011111110 H
#295000
0#
00
0=
#300000
1#
b101110111 /
10
b101110111 <
1=
b101110111 I
#301000
0+
08
0E
#302000
1%
b10101101 &
b11101111 '
b110011100 (
12
b10101101 3
b11101111 4
b110011100 5
1?
b10101101 @
b11101111 A
b110011100 B
#305000
0#
00
0=
#310000
1#
b100011110 )
10
b100011110 6
1=
b100011110 C
#311000
0%
1+
b01110110 ,
b11011001 -
b101001111 .
02
18
b01110110 9
b11011001 :
b101001111 ;
0?
1E
b01110110 F
b11011001 G
b101001111 H
#315000
0#
00
0=
#320000
1#
b001010000 /
10
b001010000 <
1=
b001010000 I
#321000
0+
08
0E
#322000
1%
b11111000 &
b00000001 '
b011111001 (
12
b11111000 3
b00000001 4
b011111001 5
1?
b11111000 @
b00000001 A
b011111001 B
#325000
0#
00
0=
#330000
1#
b100011111 )
10
b100011111 6
1=
b100011111 C
#331000
0%
1+
b01011110 ,
b01101001 -
b011000111 .
02
18
b01011110 9
b01101001 :
b011000111 ;
0?
1E
b01011110 F
b01101001 G
b011000111 H
#335000
0#
00
0=
#340000
1#
b010111001 /
10
b010111001 <
1=
b010111001 I
#341000
0+
08
0E
#342000
1%
b10010101 &
b01010001 '
b011100110 (
12
b10010101 3
b01010001 4
b011100110 5
1?
b10010101 @
b01010001 A
b011100110 B
#345000
0#
00
0=
#350000
1#
b101110000 )
10
b101110000 6
1=
b101110000 C
#351000
0%
1+
b11101001 ,
b11011000 -
b111000001 .
02
18
b11101001 9
b11011000 :
b111000001 ;
0?
1E
b11101001 F
b11011000 G
b111000001 H
#355000
0#
00
0=
#360000
1#
b110010001 /
10
b110010001 <
1=
b110010001 I
#361000
0+
08
0E
#362000
1%
b10011010 &
b01001111 '
b011101001 (
12
b10011010 3
b01001111 4
b011101001 5
1?
b10011010 @
b01001111 A
b011101001 B
#365000
0#
00
0=
#370000
1#
b110111111 )
10
b110111111 6
1=
b110111111 C
#371000
0%
1+
b10101111 ,
b01001010 -
b011111001 .
02
18
b10101111 9
b01001010 :
b011111001 ;
0?
1E
b10101111 F
b01001010 G
b011111001 H
#375000
0#
00
0=
#380000
1#
b111011011 /
10
b111011011 <
1=
b111011011 I
#381000
0+
08
0E
#382000
1%
b01010000 &
b11010101 '
b100100101 (
12
b01010000 3
b11010101 4
b100100101 5
1?
b01010000 @
b11010101 A
b100100101 B
#385000
0#
00
0=
#390000
1#
b010010100 )
10
b010010100 6
1=
b010010100 C
#391000
0%
1+
b01000001 ,
b10000000 -
b011000001 .
02
18
b01000001 9
b10000000 :
b011000001 ;
0?
1E
b01000001 F
b10000000 G
b011000001 H
#395000
0#
00
0=
#400000
1#
b001011011 /
10
b001011011 <
1=
b001011011 I
#401000
0+
08
0E
#402000
1%
b01001100 &
b01100101 '
b010110001 (
12
b01001100 3
b01100101 4
b010110001 5
1?
b01001100 @
b01100101 A
b010110001 B
#405000
0#
00
0=
#410000
1#
b011111001 )
10
b011111001 6
1=
b011111001 C
#411000
0%
1+
b00000110 ,
b11101111 -
b011110101 .
02
18
b00000110 9
b11101111 :
b011110101 ;
0?
1E
b00000110 F
b11101111 G
b011110101 H
#415000
0#
00
0=
#420000
1#
b101001010 /
10
b101001010 <
1=
b101001010 I
#421000
0+
08
0E
#422000
1%
b00001111 &
b00101101 '
b000111100 (
12
b00001111 3
b00101101 4
b000111100 5
1?
b00001111 @
b00101101 A
b000111100 B
#425000
0#
00
0=
#430000
1#
b100100110 )
10
b100100110 6
1=
b100100110 C
#431000
0%
1+
b10000100 ,
b11001101 -
b101010001 .
02
18
b10000100 9
b11001101 :
b101010001 ;
0?
1E
b10000100 F
b11001101 G
b101010001 H
#435000
0#
00
0=
#440000
1#
b000010111 /
10
b000010111 <
1=
b000010111 I
#441000
0+
08
0E
#442000
1%
b00000001 &
b11010101 '
b011010110 (
12
b00000001 3
b11010101 4
b011010110 5
1?
b00000001 @
b11010101 A
b011010110 B
#445000
0#
00
0=
#450000
1#
b111111011 )
10
b111111011 6
1=
b111111011 C
#451000
0%
1+
b10010110 ,
b01111001 -
b100001111 .
02
18
b10010110 9
b01111001 :
b100001111 ;
0?
1E
b10010110 F
b01111001 G
b100001111 H
#455000
0#
00
0=
#460000
1#
b010010000 /
10
b010010000 <
1=
b010010000 I
#461000
0+
08
0E
#462000
1%
b10000000 &
b10100111 '
b100100111 (
12
b10000000 3
b10100111 4
b100100111 5
1?
b10000000 @
b10100111 A
b100100111 B
#465000
0#
00
0=
#470000
1#
b010100010 )
10
b010100010 6
1=
b010100010 C
#471000
0%
1+
b01000101 ,
b00111111 -
b010000100 .
02
18
b01000101 9
b00111111 :
b010000100 ;
0?
1E
b01000101 F
b00111111 G
b010000100 H
#475000
0#
00
0=
#480000
1#
b011001111 /
10
b011001111 <
1=
b011001111 I
#481000
0+
08
0E
#482000
1%
b01111000 &
b01011001 '
b011010001 (
12
b01111000 3
b01011001 4
b011010001 5
1?
b01111000 @
b01011001 A
b011010001 B
#485000
0#
00
0=
#490000
1#
b011111011 )
10
b011111011 6
1=
b011111011 C
#491000
0%
1+
b11010110 ,
b00111110 -
b100010100 .
02
18
b11010110 9
b00111110 :
b100010100 ;
0?
1E
b11010110 F
b00111110 G
b100010100 H
#495000
0#
00
0=
#500000
1#
b100001101 /
10
b100001101 <
1=
b100001101 I
#501000
0+
08
0E
#502000
1%
b00000001 &
b01111000 '
b001111001 (
12
b00000001 3
b01111000 4
b001111001 5
1?
b00000001 @
b01111000 A
b001111001 B
#505000
0#
00
0=
#510000
1#
b101110011 )
10
b101110011 6
1=
b101110011 C
#511000
0%
1+
b01001010 ,
b00011101 -
b001100111 .
02
18
b01001010 9
b00011101 :
b001100111 ;
0?
1E
b01001010 F
b00011101 G
b001100111 H
#515000
0#
00
0=
#520000
1#
b100101010 /
10
b100101010 <
1=
b100101010 I
#521000
0+
08
0E
#522000
1%
b01011110 &
b11011010 '
b100111000 (
12
b01011110 3
b11011010 4
b100111000 5
1?
b01011110 @
b11011010 A
b100111000 B
#525000
0#
00
0=
#530000
1#
b001001101 )
10
b001001101 6
1=
b001001101 C
#531000
0%
1+
b10100010 ,
b01100111 -
b100001001 .
02
18
b10100010 9
b01100111 :
b100001001 ;
0?
1E
b10100010 F
b01100111 G
b100001001 H
#535000
0#
00
0=
#540000
1#
b110010001 /
10
b110010001 <
1=
b110010001 I
#541000
0+
08
0E
#542000
1%
b01100010 &
b10000100 '
b011100110 (
12
b01100010 3
b10000100 4
b011100110 5
1?
b01100010 @
b10000100 A
b011100110 B
#545000
0#
00
0=
#550000
1#
b011010001 )
10
b011010001 6
1=
b011010001 C
#551000
0%
1+
b10000011 ,
b11000001 -
b101000100 .
02
18
b10000011 9
b11000001 :
b101000100 ;
0?
1E
b10000011 F
b11000001 G
b101000100 H
#555000
0#
00
0=
#560000
1#
b001010010 /
10
b001010010 <
1=
b001010010 I
#561000
0+
08
0E
#562000
1%
b11111011 &
b10101011 '
b110100110 (
12
b11111011 3
b10101011 4
b110100110 5
1?
b11111011 @
b10101011 A
b110100110 B
#565000
0#
00
0=
#570000
1#
b101111100 )
10
b101111100 6
1=
b101111100 C
#571000
0%
1+
b00011100 ,
b10000111 -
b010100011 .
02
18
b00011100 9
b10000111 :
b010100011 ;
0?
1E
b00011100 F
b10000111 G
b010100011 H
#575000
0#
00
0=
#580000
1#
b011011001 /
10
b011011001 <
1=
b011011001 I
#581000
0+
08
0E
#582000
1%
b00111111 &
b11000011 '
b100000010 (
12
b00111111 3
b11000011 4
b100000010 5
1?
b00111111 @
b11000011 A
b100000010 B
#585000
0#
00
0=
#590000
1#
b000111111 )
10
b000111111 6
1=
b000111111 C
#591000
0%
1+
b00111010 ,
b11000101 -
b011111111 .
02
18
b00111010 9
b11000101 :
b011111111 ;
0?
1E
b00111010 F
b11000101 G
b011111111 H
#595000
0#
00
0=
#600000
1#
b110011110 /
10
b110011110 <
1=
b110011110 I
#601000
0+
08
0E
#602000
1%
b11010011 &
b11001001 '
b110011100 (
12
b11010011 3
b11001001 4
b110011100 5
1?
b11010011 @
b11001001 A
b110011100 B
#605000
0#
00
0=
#610000
1#
b100001000 )
10
b100001000 6
1=
b100001000 C
#611000
0%
1+
b10111101 ,
b01011011 -
b100011000 .
02
18
b10111101 9
b01011011 :
b100011000 ;
0?
1E
b10111101 F
b01011011 G
b100011000 H
#615000
0#
00
0=
#620000
1#
b111111001 /
10
b111111001 <
1=
b111111001 I
#621000
0+
08
0E
#622000
1%
b11010100 &
b11101111 '
b111000011 (
12
b11010100 3
b11101111 4
b111000011 5
1?
b11010100 @
b11101111 A
b111000011 B
#625000
0#
00
0=
#630000
1#
b111110111 )
10
b111110111 6
1=
b111110111 C
#631000
0%
1+
b10110011 ,
b00001001 -
b010111100 .
02
18
b10110011 9
b00001001 :
b010111100 ;
0?
1E
b10110011 F
b00001001 G
b010111100 H
#635000
0#
00
0=
#640000
1#
b000000010 /
10
b000000010 <
1=
b000000010 I
#641000
0+
08
0E
#642000
1%
b11011111 &
b01100011 '
b101000010 (
12
b11011111 3
b01100011 4
b101000010 5
1?
b11011111 @
b01100011 A
b101000010 B
#645000
0#
00
0=
#650000
1#
b001011010 )
10
b001011010 6
1=
b001011010 C
#651000
0%
1+
b00010100 ,
b01000010 -
b001010110 .
02
18
b00010100 9
b01000010 :
b001010110 ;
0?
1E
b00010100 F
b01000010 G
b001010110 H
#655000
0#
00
0=
#660000
1#
b001000100 /
10
b001000100 <
1=
b001000100 I
#661000
0+
08
0E
#662000
1%
b00010000 &
b11100110 '
b011110110 (
12
b00010000 3
b11100110 4
b011110110 5
1?
b00010000 @
b11100110 A
b011110110 B
#665000
0#
00
0=
#670000
1#
b101000000 )
10
b101000000 6
1=
b101000000 C
#671000
0%
1+
b11111011 ,
b10010101 -
b110010000 .
02
18
b11111011 9
b10010101 :
b110010000 ;
0?
1E
b11111011 F
b10010101 G
b110010000 H
#675000
0#
00
0=
#680000
1#
b011011001 /
10
b011011001 <
1=
b011011001 I
#681000
0+
08
0E
#682000
1%
b01011110 &
b01101010 '
b011001000 (
12
b01011110 3
b01101010 4
b011001000 5
1?
b01011110 @
b01101010 A
b011001000 B
#685000
0#
00
0=
#690000
1#
b110101010 )
10
b110101010 6
1=
b110101010 C
#691000
0%
1+
b01010101 ,
b10110011 -
b100001000 .
02
18
b01010101 9
b10110011 :
b100001000 ;
0?
1E
b01010101 F
b10110011 G
b100001000 H
#695000
0#
00
0=
#700000
1#
b110001100 /
10
b110001100 <
1=
b110001100 I
#701000
0+
08
0E
#702000
1%
b01001110 &
b00001110 '
b001011100 (
12
b01001110 3
b00001110 4
b001011100 5
1?
b01001110 @
b00001110 A
b001011100 B
#705000
0#
00
0=
#710000
1#
b110111000 )
10
b110111000 6
1=
b110111000 C
#711000
0%
1+
b01111000 ,
b10100101 -
b100011101 .
02
18
b01111000 9
b10100101 :
b100011101 ;
0?
1E
b01111000 F
b10100101 G
b100011101 H
#715000
0#
00
0=
#720000
1#
b000110001 /
10
b000110001 <
1=
b000110001 I
#721000
0+
08
0E
#722000
1%
b11001011 &
b11001111 '
b110011010 (
12
b11001011 3
b11001111 4
b110011010 5
1?
b11001011 @
b11001111 A
b110011010 B
#725000
0#
00
0=
#730000
1#
b010000111 )
10
b010000111 6
1=
b010000111 C
#731000
0%
1+
b01010110 ,
b01010111 -
b010101101 .
02
18
b01010110 9
b01010111 :
b010101101 ;
0?
1E
b01010110 F
b01010111 G
b010101101 H
#735000
0#
00
0=
#740000
1#
b010001000 /
10
b010001000 <
1=
b010001000 I
#741000
0+
08
0E
#742000
1%
b00001111 &
b10111011 '
b011001010 (
12
b00001111 3
b10111011 4
b011001010 5
1?
b00001111 @
b10111011 A
b011001010 B
#745000
0#
00
0=
#750000
1#
b101000010 )
10
b101000010 6
1=
b101000010 C
#751000
0%
1+
b01100110 ,
b10011010 -
b100000000 .
02
18
b01100110 9
b10011010 :
b100000000 ;
0?
1E
b01100110 F
b10011010 G
b100000000 H
#755000
0#
00
0=
#760000
1#
b100100010 /
10
b100100010 <
1=
b100100010 I
#761000
0+
08
0E
#762000
1%
b10011000 &
b10111000 '
b101010000 (
12
b10011000 3
b10111000 4
b101010000 5
1?
b10011000 @
b10111000 A
b101010000 B
#765000
0#
00
0=
#770000
1#
b111111010 )
10
b111111010 6
1=
b111111010 C
#771000
0%
1+
b01100101 ,
b10101111 -
b100010100 .
02
18
b01100101 9
b10101111 :
b100010100 ;
0?
1E
b01100101 F
b10101111 G
b100010100 H
#775000
0#
00
0=
#780000
1#
b111010001 /
10
b111010001 <
1=
b111010001 I
#781000
0+
08
0E
#782000
1%
b01010100 &
b11011001 '
b100101101 (
12
b01010100 3
b11011001 4
b100101101 5
1?
b01010100 @
b11011001 A
b100101101 B
#785000
0#
00
0=
#790000
1#
b011010011 )
10
b011010011 6
1=
b011010011 C
#791000
0%
1+
b11010000 ,
b10101011 -
b101111011 .
02
18
b11010000 9
b10101011 :
b101111011 ;
0?
1E
b11010000 F
b10101011 G
b101111011 H
#795000
0#
00
0=
#800000
1#
b001111100 /
10
b001111100 <
1=
b001111100 I
#801000
0+
08
0E
#802000
1%
b11001010 &
b01100110 '
b100110000 (
12
b11001010 3
b01100110 4
b100110000 5
1?
b11001010 @
b01100110 A
b100110000 B
#805000
0#
00
0=
#810000
1#
b100111001 )
10
b100111001 6
1=
b100111001 C
#811000
0%
1+
b00111101 ,
b01100001 -
b010011110 .
02
18
b00111101 9
b01100001 :
b010011110 ;
0?
1E
b00111101 F
b01100001 G
b010011110 H
#815000
0#
00
0=
#820000
1#
b011011101 /
10
b011011101 <
1=
b011011101 I
#821000
0+
08
0E
#822000
1%
b01011001 &
b10100111 '
b100000000 (
12
b01011001 3
b10100111 4
b100000000 5
1?
b01011001 @
b10100111 A
b100000000 B
#825000
0#
00
0=
#830000
1#
b111100000 )
10
b111100000 6
1=
b111100000 C
#831000
0%
1+
b11101000 ,
b01011011 -
b101000011 .
02
18
b11101000 9
b01011011 :
b101000011 ;
0?
1E
b11101000 F
b01011011 G
b101000011 H
#835000
0#
00
0=
#840000
1#
b100111000 /
10
b100111000 <
1=
b100111000 I
#841000
0+
08
0E
#842000
1%
b11000101 &
b00101101 '
b011110010 (
12
b11000101 3
b00101101 4
b011110010 5
1?
b11000101 @
b00101101 A
b011110010 B
#845000
0#
00
0=
#850000
1#
b000001101 )
10
b000001101 6
1=
b000001101 C
#851000
0%
1+
b00001111 ,
b00010111 -
b000100110 .
02
18
b00001111 9
b00010111 :
b000100110 ;
0?
1E
b00001111 F
b00010111 G
b000100110 H
#855000
0#
00
0=
#860000
1#
b101001111 /
10
b101001111 <
1=
b101001111 I
#861000
0+
08
0E
#862000
1%
b01110111 &
b01000011 '
b010111010 (
12
b01110111 3
b01000011 4
b010111010 5
1?
b01110111 @
b01000011 A
b010111010 B
#865000
0#
00
0=
#870000
1#
b001010000 )
10
b001010000 6
1=
b001010000 C
#871000
0%
1+
b11101100 ,
b00110110 -
b100100010 .
02
18
b11101100 9
b00110110 :
b100100010 ;
0?
1E
b11101100 F
b00110110 G
b100100010 H
#875000
0#
00
0=
#880000
1#
b110000101 /
10
b110000101 <
1=
b110000101 I
#881000
0+
08
0E
#882000
1%
b01110011 &
b00000100 '
b001110111 (
12
b01110011 3
b00000100 4
b001110111 5
1?
b01110011 @
b00000100 A
b001110111 B
#885000
0#
00
0=
#890000
1#
b001010100 )
10
b001010100 6
1=
b001010100 C
#891000
0%
1+
b11111100 ,
b01001111 -
b101001011 .
02
18
b11111100 9
b01001111 :
b101001011 ;
0?
1E
b11111100 F
b01001111 G
b101001011 H
#895000
0#
00
0=
#900000
1#
b111010100 /
10
b111010100 <
1=
b111010100 I
#901000
0+
08
0E
#902000
1%
b01101100 &
b11010100 '
b101000000 (
12
b01101100 3
b11010100 4
b101000000 5
1?
b01101100 @
b11010100 A
b101000000 B
#905000
0#
00
0=
#910000
1#
b100101000 )
10
b100101000 6
1=
b100101000 C
#911000
0%
1+
b10110001 ,
b11010001 -
b110000010 .
02
18
b10110001 9
b11010001 :
b110000010 ;
0?
1E
b10110001 F
b11010001 G
b110000010 H
#915000
0#
00
0=
#920000
1#
b010100101 /
10
b010100101 <
1=
b010100101 I
#921000
0+
08
0E
#922000
1%
b01010110 &
b11000001 '
b100010111 (
12
b01010110 3
b11000001 4
b100010111 5
1?
b01010110 @
b11000001 A
b100010111 B
#925000
0#
00
0=
#930000
1#
b111101001 )
10
b111101001 6
1=
b111101001 C
#931000
0%
1+
b01101100 ,
b11111010 -
b101100110 .
02
18
b01101100 9
b11111010 :
b101100110 ;
0?
1E
b01101100 F
b11111010 G
b101100110 H
#935000
0#
00
0=
#940000
1#
b110011111 /
10
b110011111 <
1=
b110011111 I
#941000
0+
08
0E
#942000
1%
b10000100 &
b01111111 '
b100000011 (
12
b10000100 3
b01111111 4
b100000011 5
1?
b10000100 @
b01111111 A
b100000011 B
#945000
0#
00
0=
