rtl/top_level.sv


module top_level (
    input  logic       clk,

    // Channel A
    input  logic       rst_A,
    input  logic       valid_in_A,
    input  logic [7:0] a_A,
    input  logic [7:0] b_A,
    output logic [8:0] sum_async_A,
    output logic [8:0] sum_sync_A,

    // Channel B
    input  logic       rst_B,
    input  logic       valid_in_B,
    input  logic [7:0] a_B,
    input  logic [7:0] b_B,
    output logic [8:0] sum_async_B,
    output logic [8:0] sum_sync_B
);

    // Channel A synchronous accumulator
    always_ff @(posedge clk) begin
        if (rst_A)
            sum_sync_A <= '0;
        else if (valid_in_A)
            sum_sync_A <= sum_sync_A + b_A;
    end

    assign sum_async_A = a_A + b_A;

    // Channel B synchronous accumulator
    always_ff @(posedge clk) begin
        if (rst_B)
            sum_sync_B <= '0;
        else if (valid_in_B)
            sum_sync_B <= sum_sync_B + b_B;
    end

    assign sum_async_B = a_B + b_B;

    initial begin
        $display("Time | rst_A| valid_in_A | a_A | b_A |sum_async_A | sum_sync_A |rst_B | valid_in_B| a_B | b_B  | sum_async_B | sum_sync_B   ");
        $monitor("%4t  |  %b  |  %b        | %0d | %0d |    %0d     |   %0d      | %b   |    %b     | %0d | %0d  |    %0d      |   %0d ",
                 $time, rst_A, valid_in_A, a_A, b_A, sum_async_A,sum_sync_A, rst_B, valid_in_B, a_B, b_B, sum_async_B, sum_sync_B);
    end

    initial begin
        $dumpfile("dump.vcd");
        $dumpvars(1, top_level.sv);
    end

endmodule

rtl/dut_wrapper.sv
module dut_wrapper (
    input  logic       clk,

    // Channel A – cocotb drives these
    input  logic       rst_A,
    input  logic       valid_in_A,
    input  logic [7:0] a_A,
    input  logic [7:0] b_A,

    // DUT drives these
    output logic [8:0] sum_async_A,
    output logic [8:0] sum_sync_A,

    // Channel B (if needed)
    input  logic       rst_B,
    input  logic       valid_in_B,
    input  logic [7:0] a_B,
    input  logic [7:0] b_B,
    output logic [8:0] sum_async_B,
    output logic [8:0] sum_sync_B
);

    top_level u_top_level (
        .clk(clk),

        // Channel A
        .rst_A(rst_A),
        .valid_in_A(valid_in_A),
        .a_A(a_A),
        .b_A(b_A),
        .sum_async_A(sum_async_A),
        .sum_sync_A(sum_sync_A),

        // Channel B
        .rst_B(rst_B),
        .valid_in_B(valid_in_B),
        .a_B(a_B),
        .b_B(b_B),
        .sum_async_B(sum_async_B),
        .sum_sync_B(sum_sync_B)
    );

endmodule



// module dut_wrapper (
//     input  logic       clk,

//     // Channel A – exposed directly for cocotb
//     output logic       rst_A,
//     output logic       valid_in_A,
//     output logic [7:0] a_A,
//     output logic [7:0] b_A,
//     output logic [8:0] sum_async_A,
//     output logic [8:0] sum_sync_A,

//     // Channel B – exposed directly for cocotb
//     output logic       rst_B,
//     output logic       valid_in_B,
//     output logic [7:0] a_B,
//     output logic [7:0] b_B,
//     output logic [8:0] sum_async_B,
//     output logic [8:0] sum_sync_B
// );

//     // Internal wires driven by cocotb (use these as DUT inputs)
//     logic rst_A_int;
//     logic valid_in_A_int;
//     logic [7:0] a_A_int;
//     logic [7:0] b_A_int;

//     logic rst_B_int;
//     logic valid_in_B_int;
//     logic [7:0] a_B_int;
//     logic [7:0] b_B_int;

//     // Connect exposed ports to internal wires so cocotb can drive them
//     assign rst_A       = rst_A_int;
//     assign valid_in_A  = valid_in_A_int;
//     assign a_A         = a_A_int;
//     assign b_A         = b_A_int;

//     assign rst_B       = rst_B_int;
//     assign valid_in_B  = valid_in_B_int;
//     assign a_B         = a_B_int;
//     assign b_B         = b_B_int;

//     // DUT instance
//     top_level u_top_level (
//         .clk          (clk),

//         // Channel A
//         .rst_A        (rst_A_int),
//         .valid_in_A   (valid_in_A_int),
//         .a_A          (a_A_int),
//         .b_A          (b_A_int),
//         .sum_async_A  (sum_async_A),
//         .sum_sync_A   (sum_sync_A),

//         // Channel B
//         .rst_B        (rst_B_int),
//         .valid_in_B   (valid_in_B_int),
//         .a_B          (a_B_int),
//         .b_B          (b_B_int),
//         .sum_async_B  (sum_async_B),
//         .sum_sync_B   (sum_sync_B)
//     );

// endmodule

regression_results/waves_9.vcd
$version Generated by VerilatedVcd $end
$timescale 1ps $end
 $scope module $rootio $end
  $var wire 1 # clk $end
  $var wire 1 $ rst_A $end
  $var wire 1 % valid_in_A $end
  $var wire 8 & a_A [7:0] $end
  $var wire 8 ' b_A [7:0] $end
  $var wire 9 ( sum_async_A [8:0] $end
  $var wire 9 ) sum_sync_A [8:0] $end
  $var wire 1 * rst_B $end
  $var wire 1 + valid_in_B $end
  $var wire 8 , a_B [7:0] $end
  $var wire 8 - b_B [7:0] $end
  $var wire 9 . sum_async_B [8:0] $end
  $var wire 9 / sum_sync_B [8:0] $end
 $upscope $end
 $scope module dut_wrapper $end
  $var wire 1 0 clk $end
  $var wire 1 1 rst_A $end
  $var wire 1 2 valid_in_A $end
  $var wire 8 3 a_A [7:0] $end
  $var wire 8 4 b_A [7:0] $end
  $var wire 9 5 sum_async_A [8:0] $end
  $var wire 9 6 sum_sync_A [8:0] $end
  $var wire 1 7 rst_B $end
  $var wire 1 8 valid_in_B $end
  $var wire 8 9 a_B [7:0] $end
  $var wire 8 : b_B [7:0] $end
  $var wire 9 ; sum_async_B [8:0] $end
  $var wire 9 < sum_sync_B [8:0] $end
  $scope module u_top_level $end
   $var wire 1 = clk $end
   $var wire 1 > rst_A $end
   $var wire 1 ? valid_in_A $end
   $var wire 8 @ a_A [7:0] $end
   $var wire 8 A b_A [7:0] $end
   $var wire 9 B sum_async_A [8:0] $end
   $var wire 9 C sum_sync_A [8:0] $end
   $var wire 1 D rst_B $end
   $var wire 1 E valid_in_B $end
   $var wire 8 F a_B [7:0] $end
   $var wire 8 G b_B [7:0] $end
   $var wire 9 H sum_async_B [8:0] $end
   $var wire 9 I sum_sync_B [8:0] $end
  $upscope $end
 $upscope $end
$enddefinitions $end


#0
1#
1$
0%
b00000000 &
b00000000 '
b000000000 (
b000000000 )
1*
0+
b00000000 ,
b00000000 -
b000000000 .
b000000000 /
10
11
02
b00000000 3
b00000000 4
b000000000 5
b000000000 6
17
08
b00000000 9
b00000000 :
b000000000 ;
b000000000 <
1=
1>
0?
b00000000 @
b00000000 A
b000000000 B
b000000000 C
1D
0E
b00000000 F
b00000000 G
b000000000 H
b000000000 I
#2021000
00
0=
#5000
1#
10
1=
#7500
0#
00
0=
#10000
1#
10
1=
#12500
0#
00
0=
#15000
1#
10
1=
#17500
0#
00
0=
#20000
1#
0$
1%
b11111001 &
b10000001 '
b101111010 (
0*
10
01
12
b11111001 3
b10000001 4
b101111010 5
07
1=
0>
1?
b11111001 @
b10000001 A
b101111010 B
0D
#22500
0#
00
0=
#25000
1#
b010000001 )
10
b010000001 6
1=
b010000001 C
#26000
0%
1+
b01001110 ,
b11100110 -
b100110100 .
02
18
b01001110 9
b11100110 :
b100110100 ;
0?
1E
b01001110 F
b11100110 G
b100110100 H
#27500
0#
00
0=
#30000
1#
b011100110 /
10
b011100110 <
1=
b011100110 I
#31000
0+
08
0E
#32000
1%
b10011011 &
b10101101 '
b101001000 (
12
b10011011 3
b10101101 4
b101001000 5
1?
b10011011 @
b10101101 A
b101001000 B
#32500
0#
00
0=
#35000
1#
b100101110 )
10
b100101110 6
1=
b100101110 C
#36000
0%
1+
b01101100 ,
b00011010 -
b010000110 .
02
18
b01101100 9
b00011010 :
b010000110 ;
0?
1E
b01101100 F
b00011010 G
b010000110 H
#37500
0#
00
0=
#40000
1#
b100000000 /
10
b100000000 <
1=
b100000000 I
#41000
0+
08
0E
#42000
1%
b10110011 &
b10100100 '
b101010111 (
12
b10110011 3
b10100100 4
b101010111 5
1?
b10110011 @
b10100100 A
b101010111 B
#42500
0#
00
0=
#45000
1#
b111010010 )
10
b111010010 6
1=
b111010010 C
#46000
0%
1+
b01011110 ,
b01001100 -
b010101010 .
02
18
b01011110 9
b01001100 :
b010101010 ;
0?
1E
b01011110 F
b01001100 G
b010101010 H
#47500
0#
00
0=
#50000
1#
b101001100 /
10
b101001100 <
1=
b101001100 I
#51000
0+
08
0E
#52000
1%
b11111101 &
b10001110 '
b110001011 (
12
b11111101 3
b10001110 4
b110001011 5
1?
b11111101 @
b10001110 A
b110001011 B
#52500
0#
00
0=
#55000
1#
b001100000 )
10
b001100000 6
1=
b001100000 C
#56000
0%
1+
b11100001 ,
b10011110 -
b101111111 .
02
18
b11100001 9
b10011110 :
b101111111 ;
0?
1E
b11100001 F
b10011110 G
b101111111 H
#57500
0#
00
0=
#60000
1#
b111101010 /
10
b111101010 <
1=
b111101010 I
#61000
0+
08
0E
#62000
1%
b11001001 &
b11001011 '
b110010100 (
12
b11001001 3
b11001011 4
b110010100 5
1?
b11001001 @
b11001011 A
b110010100 B
#62500
0#
00
0=
#65000
1#
b100101011 )
10
b100101011 6
1=
b100101011 C
#66000
0%
1+
b10011110 ,
b01101100 -
b100001010 .
02
18
b10011110 9
b01101100 :
b100001010 ;
0?
1E
b10011110 F
b01101100 G
b100001010 H
#67500
0#
00
0=
#70000
1#
b001010110 /
10
b001010110 <
1=
b001010110 I
#71000
0+
08
0E
#72000
1%
b00011101 &
b01000000 '
b001011101 (
12
b00011101 3
b01000000 4
b001011101 5
1?
b00011101 @
b01000000 A
b001011101 B
#72500
0#
00
0=
#75000
1#
b101101011 )
10
b101101011 6
1=
b101101011 C
#76000
0%
1+
b00010010 ,
b001111110 .
02
18
b00010010 9
b001111110 ;
0?
1E
b00010010 F
b001111110 H
#77500
0#
00
0=
#80000
1#
b011000010 /
10
b011000010 <
1=
b011000010 I
#81000
0+
08
0E
#82000
1%
b00111001 &
b01101101 '
b010100110 (
12
b00111001 3
b01101101 4
b010100110 5
1?
b00111001 @
b01101101 A
b010100110 B
#82500
0#
00
0=
#85000
1#
b111011000 )
10
b111011000 6
1=
b111011000 C
#86000
0%
1+
b11110011 ,
b00011101 -
b100010000 .
02
18
b11110011 9
b00011101 :
b100010000 ;
0?
1E
b11110011 F
b00011101 G
b100010000 H
#87500
0#
00
0=
#90000
1#
b011011111 /
10
b011011111 <
1=
b011011111 I
#91000
0+
08
0E
#92000
1%
b10010100 &
b00100111 '
b010111011 (
12
b10010100 3
b00100111 4
b010111011 5
1?
b10010100 @
b00100111 A
b010111011 B
#92500
0#
00
0=
#95000
1#
b111111111 )
10
b111111111 6
1=
b111111111 C
#96000
0%
1+
b10111010 ,
b11101011 -
b110100101 .
02
18
b10111010 9
b11101011 :
b110100101 ;
0?
1E
b10111010 F
b11101011 G
b110100101 H
#97500
0#
00
0=
#100000
1#
b111001010 /
10
b111001010 <
1=
b111001010 I
#101000
0+
08
0E
#102000
1%
b00100101 &
b00001100 '
b000110001 (
12
b00100101 3
b00001100 4
b000110001 5
1?
b00100101 @
b00001100 A
b000110001 B
#102500
0#
00
0=
#105000
1#
b000001011 )
10
b000001011 6
1=
b000001011 C
#106000
0%
1+
b10111100 ,
b10000010 -
b100111110 .
02
18
b10111100 9
b10000010 :
b100111110 ;
0?
1E
b10111100 F
b10000010 G
b100111110 H
#107500
0#
00
0=
#110000
1#
b001001100 /
10
b001001100 <
1=
b001001100 I
#111000
0+
08
0E
#112000
1%
b01100011 &
b10100001 '
b100000100 (
12
b01100011 3
b10100001 4
b100000100 5
1?
b01100011 @
b10100001 A
b100000100 B
#112500
0#
00
0=
#115000
1#
b010101100 )
10
b010101100 6
1=
b010101100 C
#116000
0%
1+
b01101110 ,
b00001001 -
b001110111 .
02
18
b01101110 9
b00001001 :
b001110111 ;
0?
1E
b01101110 F
b00001001 G
b001110111 H
#117500
0#
00
0=
#120000
1#
b001010101 /
10
b001010101 <
1=
b001010101 I
#121000
0+
08
0E
#122000
1%
b00000000 &
b10011101 '
b010011101 (
12
b00000000 3
b10011101 4
b010011101 5
1?
b00000000 @
b10011101 A
b010011101 B
#122500
0#
00
0=
#125000
1#
b101001001 )
10
b101001001 6
1=
b101001001 C
#126000
0%
1+
b11011000 ,
b11010110 -
b110101110 .
02
18
b11011000 9
b11010110 :
b110101110 ;
0?
1E
b11011000 F
b11010110 G
b110101110 H
#127500
0#
00
0=
#130000
1#
b100101011 /
10
b100101011 <
1=
b100101011 I
#131000
0+
08
0E
#132000
1%
b01101101 &
b11000101 '
b100110010 (
12
b01101101 3
b11000101 4
b100110010 5
1?
b01101101 @
b11000101 A
b100110010 B
#132500
0#
00
0=
#135000
1#
b000001110 )
10
b000001110 6
1=
b000001110 C
#136000
0%
1+
b11010111 ,
b11100110 -
b110111101 .
02
18
b11010111 9
b11100110 :
b110111101 ;
0?
1E
b11010111 F
b11100110 G
b110111101 H
#137500
0#
00
0=
#140000
1#
b000010001 /
10
b000010001 <
1=
b000010001 I
#141000
0+
08
0E
#142000
1%
b11100010 &
b10010010 '
b101110100 (
12
b11100010 3
b10010010 4
b101110100 5
1?
b11100010 @
b10010010 A
b101110100 B
#142500
0#
00
0=
#145000
1#
b010100000 )
10
b010100000 6
1=
b010100000 C
#146000
0%
1+
b00110011 ,
b01100110 -
b010011001 .
02
18
b00110011 9
b01100110 :
b010011001 ;
0?
1E
b00110011 F
b01100110 G
b010011001 H
#147500
0#
00
0=
#150000
1#
b001110111 /
10
b001110111 <
1=
b001110111 I
#151000
0+
08
0E
#152000
1%
b01001010 &
b00001100 '
b001010110 (
12
b01001010 3
b00001100 4
b001010110 5
1?
b01001010 @
b00001100 A
b001010110 B
#152500
0#
00
0=
#155000
1#
b010101100 )
10
b010101100 6
1=
b010101100 C
#156000
0%
1+
b11010110 ,
b10101001 -
b101111111 .
02
18
b11010110 9
b10101001 :
b101111111 ;
0?
1E
b11010110 F
b10101001 G
b101111111 H
#157500
0#
00
0=
#160000
1#
b100100000 /
10
b100100000 <
1=
b100100000 I
#161000
0+
08
0E
#162000
1%
b10011010 &
b00111111 '
b011011001 (
12
b10011010 3
b00111111 4
b011011001 5
1?
b10011010 @
b00111111 A
b011011001 B
#162500
0#
00
0=
#165000
1#
b011101011 )
10
b011101011 6
1=
b011101011 C
#166000
0%
1+
b00101101 ,
b11100000 -
b100001101 .
02
18
b00101101 9
b11100000 :
b100001101 ;
0?
1E
b00101101 F
b11100000 G
b100001101 H
#167500
0#
00
0=
#170000
1#
b000000000 /
10
b000000000 <
1=
b000000000 I
#171000
0+
08
0E
#172000
1%
b11000010 &
b11111011 '
b110111101 (
12
b11000010 3
b11111011 4
b110111101 5
1?
b11000010 @
b11111011 A
b110111101 B
#172500
0#
00
0=
#175000
1#
b111100110 )
10
b111100110 6
1=
b111100110 C
#176000
0%
1+
b10101001 ,
b01101000 -
b100010001 .
02
18
b10101001 9
b01101000 :
b100010001 ;
0?
1E
b10101001 F
b01101000 G
b100010001 H
#177500
0#
00
0=
#180000
1#
b001101000 /
10
b001101000 <
1=
b001101000 I
#181000
0+
08
0E
#182000
1%
b00001100 &
b11101011 '
b011110111 (
12
b00001100 3
b11101011 4
b011110111 5
1?
b00001100 @
b11101011 A
b011110111 B
#182500
0#
00
0=
#185000
1#
b011010001 )
10
b011010001 6
1=
b011010001 C
#186000
0%
1+
b00000100 ,
b01001001 -
b001001101 .
02
18
b00000100 9
b01001001 :
b001001101 ;
0?
1E
b00000100 F
b01001001 G
b001001101 H
#187500
0#
00
0=
#190000
1#
b010110001 /
10
b010110001 <
1=
b010110001 I
#191000
0+
08
0E
#192000
1%
b00010100 &
b10010100 '
b010101000 (
12
b00010100 3
b10010100 4
b010101000 5
1?
b00010100 @
b10010100 A
b010101000 B
#192500
0#
00
0=
#195000
1#
b101100101 )
10
b101100101 6
1=
b101100101 C
#196000
0%
1+
b11001110 ,
b11100001 -
b110101111 .
02
18
b11001110 9
b11100001 :
b110101111 ;
0?
1E
b11001110 F
b11100001 G
b110101111 H
#197500
0#
00
0=
#200000
1#
b110010010 /
10
b110010010 <
1=
b110010010 I
#201000
0+
08
0E
#202000
1%
b10011000 &
b01110100 '
b100001100 (
12
b10011000 3
b01110100 4
b100001100 5
1?
b10011000 @
b01110100 A
b100001100 B
#202500
0#
00
0=
#205000
1#
b111011001 )
10
b111011001 6
1=
b111011001 C
#206000
0%
1+
b10011101 ,
b00000010 -
b010011111 .
02
18
b10011101 9
b00000010 :
b010011111 ;
0?
1E
b10011101 F
b00000010 G
b010011111 H
#207500
0#
00
0=
#210000
1#
b110010100 /
10
b110010100 <
1=
b110010100 I
#211000
0+
08
0E
#212000
1%
b11011101 &
b10010101 '
b101110010 (
12
b11011101 3
b10010101 4
b101110010 5
1?
b11011101 @
b10010101 A
b101110010 B
#212500
0#
00
0=
#215000
1#
b001101110 )
10
b001101110 6
1=
b001101110 C
#216000
0%
1+
b00011101 ,
b01000000 -
b001011101 .
02
18
b00011101 9
b01000000 :
b001011101 ;
0?
1E
b00011101 F
b01000000 G
b001011101 H
#217500
0#
00
0=
#220000
1#
b111010100 /
10
b111010100 <
1=
b111010100 I
#221000
0+
08
0E
#222000
1%
b10001111 &
b11111000 '
b110000111 (
12
b10001111 3
b11111000 4
b110000111 5
1?
b10001111 @
b11111000 A
b110000111 B
#222500
0#
00
0=
#225000
1#
b101100110 )
10
b101100110 6
1=
b101100110 C
#226000
0%
1+
b10010010 ,
b01001011 -
b011011101 .
02
18
b10010010 9
b01001011 :
b011011101 ;
0?
1E
b10010010 F
b01001011 G
b011011101 H
#227500
0#
00
0=
#230000
1#
b000011111 /
10
b000011111 <
1=
b000011111 I
#231000
0+
08
0E
#232000
1%
b10010100 &
b01110010 '
b100000110 (
12
b10010100 3
b01110010 4
b100000110 5
1?
b10010100 @
b01110010 A
b100000110 B
#232500
0#
00
0=
#235000
1#
b111011000 )
10
b111011000 6
1=
b111011000 C
#236000
0%
1+
b00101001 ,
b10100100 -
b011001101 .
02
18
b00101001 9
b10100100 :
b011001101 ;
0?
1E
b00101001 F
b10100100 G
b011001101 H
#237500
0#
00
0=
#240000
1#
b011000011 /
10
b011000011 <
1=
b011000011 I
#241000
0+
08
0E
#242000
1%
b11110010 &
b11011101 '
b111001111 (
12
b11110010 3
b11011101 4
b111001111 5
1?
b11110010 @
b11011101 A
b111001111 B
#242500
0#
00
0=
#245000
1#
b010110101 )
10
b010110101 6
1=
b010110101 C
#246000
0%
1+
b01001110 ,
b10111011 -
b100001001 .
02
18
b01001110 9
b10111011 :
b100001001 ;
0?
1E
b01001110 F
b10111011 G
b100001001 H
#247500
0#
00
0=
#250000
1#
b101111110 /
10
b101111110 <
1=
b101111110 I
#251000
0+
08
0E
#252000
1%
b00101101 &
b10010110 '
b011000011 (
12
b00101101 3
b10010110 4
b011000011 5
1?
b00101101 @
b10010110 A
b011000011 B
#252500
0#
00
0=
#255000
1#
b101001011 )
10
b101001011 6
1=
b101001011 C
#256000
0%
1+
b00000110 ,
b10011001 -
b010011111 .
02
18
b00000110 9
b10011001 :
b010011111 ;
0?
1E
b00000110 F
b10011001 G
b010011111 H
#257500
0#
00
0=
#260000
1#
b000010111 /
10
b000010111 <
1=
b000010111 I
#261000
0+
08
0E
#262000
1%
b11110110 &
b01110010 '
b101101000 (
12
b11110110 3
b01110010 4
b101101000 5
1?
b11110110 @
b01110010 A
b101101000 B
#262500
0#
00
0=
#265000
1#
b110111101 )
10
b110111101 6
1=
b110111101 C
#266000
0%
1+
b10100101 ,
b01101100 -
b100010001 .
02
18
b10100101 9
b01101100 :
b100010001 ;
0?
1E
b10100101 F
b01101100 G
b100010001 H
#267500
0#
00
0=
#270000
1#
b010000011 /
10
b010000011 <
1=
b010000011 I
#271000
0+
08
0E
#272000
1%
b00110000 &
b00010000 '
b001000000 (
12
b00110000 3
b00010000 4
b001000000 5
1?
b00110000 @
b00010000 A
b001000000 B
#272500
0#
00
0=
#275000
1#
b111001101 )
10
b111001101 6
1=
b111001101 C
#276000
0%
1+
b10000010 ,
b10101111 -
b100110001 .
02
18
b10000010 9
b10101111 :
b100110001 ;
0?
1E
b10000010 F
b10101111 G
b100110001 H
#277500
0#
00
0=
#280000
1#
b100110010 /
10
b100110010 <
1=
b100110010 I
#281000
0+
08
0E
#282000
1%
b01010111 &
b11100001 '
b100111000 (
12
b01010111 3
b11100001 4
b100111000 5
1?
b01010111 @
b11100001 A
b100111000 B
#282500
0#
00
0=
#285000
1#
b010101110 )
10
b010101110 6
1=
b010101110 C
#286000
0%
1+
b10100110 ,
b00110001 -
b011010111 .
02
18
b10100110 9
b00110001 :
b011010111 ;
0?
1E
b10100110 F
b00110001 G
b011010111 H
#287500
0#
00
0=
#290000
1#
b101100011 /
10
b101100011 <
1=
b101100011 I
#291000
0+
08
0E
#292000
1%
b11111111 &
b00001100 '
b100001011 (
12
b11111111 3
b00001100 4
b100001011 5
1?
b11111111 @
b00001100 A
b100001011 B
#292500
0#
00
0=
#295000
1#
b010111010 )
10
b010111010 6
1=
b010111010 C
#296000
0%
1+
b00011110 ,
b11010111 -
b011110101 .
02
18
b00011110 9
b11010111 :
b011110101 ;
0?
1E
b00011110 F
b11010111 G
b011110101 H
#297500
0#
00
0=
#300000
1#
b000111010 /
10
b000111010 <
1=
b000111010 I
#301000
0+
08
0E
#302000
1%
b11001000 &
b00101010 '
b011110010 (
12
b11001000 3
b00101010 4
b011110010 5
1?
b11001000 @
b00101010 A
b011110010 B
#302500
0#
00
0=
#305000
1#
b011100100 )
10
b011100100 6
1=
b011100100 C
#306000
0%
1+
b00111010 ,
b10110011 -
b011101101 .
02
18
b00111010 9
b10110011 :
b011101101 ;
0?
1E
b00111010 F
b10110011 G
b011101101 H
#307500
0#
00
0=
#310000
1#
b011101101 /
10
b011101101 <
1=
b011101101 I
#311000
0+
08
0E
#312000
1%
b11001111 &
b01010000 '
b100011111 (
12
b11001111 3
b01010000 4
b100011111 5
1?
b11001111 @
b01010000 A
b100011111 B
#312500
0#
00
0=
#315000
1#
b100110100 )
10
b100110100 6
1=
b100110100 C
#316000
0%
1+
b11011010 ,
b11000010 -
b110011100 .
02
18
b11011010 9
b11000010 :
b110011100 ;
0?
1E
b11011010 F
b11000010 G
b110011100 H
#317500
0#
00
0=
#320000
1#
b110101111 /
10
b110101111 <
1=
b110101111 I
#321000
0+
08
0E
#322000
1%
b10101111 &
b01100111 '
b100010110 (
12
b10101111 3
b01100111 4
b100010110 5
1?
b10101111 @
b01100111 A
b100010110 B
#322500
0#
00
0=
#325000
1#
b110011011 )
10
b110011011 6
1=
b110011011 C
#326000
0%
1+
b11010110 ,
b01111011 -
b101010001 .
02
18
b11010110 9
b01111011 :
b101010001 ;
0?
1E
b11010110 F
b01111011 G
b101010001 H
#327500
0#
00
0=
#330000
1#
b000101010 /
10
b000101010 <
1=
b000101010 I
#331000
0+
08
0E
#332000
1%
b01111111 &
b01111010 '
b011111001 (
12
b01111111 3
b01111010 4
b011111001 5
1?
b01111111 @
b01111010 A
b011111001 B
#332500
0#
00
0=
#335000
1#
b000010101 )
10
b000010101 6
1=
b000010101 C
#336000
0%
1+
b10110100 ,
b01100111 -
b100011011 .
02
18
b10110100 9
b01100111 :
b100011011 ;
0?
1E
b10110100 F
b01100111 G
b100011011 H
#337500
0#
00
0=
#340000
1#
b010010001 /
10
b010010001 <
1=
b010010001 I
#341000
0+
08
0E
#342000
1%
b10011011 &
b11101011 '
b110000110 (
12
b10011011 3
b11101011 4
b110000110 5
1?
b10011011 @
b11101011 A
b110000110 B
#342500
0#
00
0=
#345000
1#
b100000000 )
10
b100000000 6
1=
b100000000 C
#346000
0%
1+
b00110100 ,
b01111001 -
b010101101 .
02
18
b00110100 9
b01111001 :
b010101101 ;
0?
1E
b00110100 F
b01111001 G
b010101101 H
#347500
0#
00
0=
#350000
1#
b100001010 /
10
b100001010 <
1=
b100001010 I
#351000
0+
08
0E
#352000
1%
b00100101 &
b01110111 '
b010011100 (
12
b00100101 3
b01110111 4
b010011100 5
1?
b00100101 @
b01110111 A
b010011100 B
#352500
0#
00
0=
#355000
1#
b101110111 )
10
b101110111 6
1=
b101110111 C
#356000
0%
1+
b10001001 ,
b00001111 -
b010011000 .
02
18
b10001001 9
b00001111 :
b010011000 ;
0?
1E
b10001001 F
b00001111 G
b010011000 H
#357500
0#
00
0=
#360000
1#
b100011001 /
10
b100011001 <
1=
b100011001 I
#361000
0+
08
0E
#362000
1%
b10110011 '
b011011000 (
12
b10110011 4
b011011000 5
1?
b10110011 A
b011011000 B
#362500
0#
00
0=
#365000
1#
b000101010 )
10
b000101010 6
1=
b000101010 C
#366000
0%
1+
b10101010 ,
b11000001 -
b101101011 .
02
18
b10101010 9
b11000001 :
b101101011 ;
0?
1E
b10101010 F
b11000001 G
b101101011 H
#367500
0#
00
0=
#370000
1#
b111011010 /
10
b111011010 <
1=
b111011010 I
#371000
0+
08
0E
#372000
1%
b10100011 &
b11000011 '
b101100110 (
12
b10100011 3
b11000011 4
b101100110 5
1?
b10100011 @
b11000011 A
b101100110 B
#372500
0#
00
0=
#375000
1#
b011101101 )
10
b011101101 6
1=
b011101101 C
#376000
0%
1+
b00011010 ,
b11001110 -
b011101000 .
02
18
b00011010 9
b11001110 :
b011101000 ;
0?
1E
b00011010 F
b11001110 G
b011101000 H
#377500
0#
00
0=
#380000
1#
b010101000 /
10
b010101000 <
1=
b010101000 I
#381000
0+
08
0E
#382000
1%
b11000001 &
b10111110 '
b101111111 (
12
b11000001 3
b10111110 4
b101111111 5
1?
b11000001 @
b10111110 A
b101111111 B
#382500
0#
00
0=
#385000
1#
b110101011 )
10
b110101011 6
1=
b110101011 C
#386000
0%
1+
b11001101 ,
b11000101 -
b110010010 .
02
18
b11001101 9
b11000101 :
b110010010 ;
0?
1E
b11001101 F
b11000101 G
b110010010 H
#387500
0#
00
0=
#390000
1#
b101101101 /
10
b101101101 <
1=
b101101101 I
#391000
0+
08
0E
#392000
1%
b01100100 &
b01111100 '
b011100000 (
12
b01100100 3
b01111100 4
b011100000 5
1?
b01100100 @
b01111100 A
b011100000 B
#392500
0#
00
0=
#395000
1#
b000100111 )
10
b000100111 6
1=
b000100111 C
#396000
0%
1+
b11111011 ,
b00101101 -
b100101000 .
02
18
b11111011 9
b00101101 :
b100101000 ;
0?
1E
b11111011 F
b00101101 G
b100101000 H
#397500
0#
00
0=
#400000
1#
b110011010 /
10
b110011010 <
1=
b110011010 I
#401000
0+
08
0E
#402000
1%
b11010101 &
b11011011 '
b110110000 (
12
b11010101 3
b11011011 4
b110110000 5
1?
b11010101 @
b11011011 A
b110110000 B
#402500
0#
00
0=
#405000
1#
b100000010 )
10
b100000010 6
1=
b100000010 C
#406000
0%
1+
b11100100 ,
b10011000 -
b101111100 .
02
18
b11100100 9
b10011000 :
b101111100 ;
0?
1E
b11100100 F
b10011000 G
b101111100 H
#407500
0#
00
0=
#410000
1#
b000110010 /
10
b000110010 <
1=
b000110010 I
#411000
0+
08
0E
#412000
1%
b00000110 &
b11010011 '
b011011001 (
12
b00000110 3
b11010011 4
b011011001 5
1?
b00000110 @
b11010011 A
b011011001 B
#412500
0#
00
0=
#415000
1#
b111010101 )
10
b111010101 6
1=
b111010101 C
#416000
0%
1+
b00011011 ,
b10011100 -
b010110111 .
02
18
b00011011 9
b10011100 :
b010110111 ;
0?
1E
b00011011 F
b10011100 G
b010110111 H
#417500
0#
00
0=
#420000
1#
b011001110 /
10
b011001110 <
1=
b011001110 I
#421000
0+
08
0E
#422000
1%
b11100111 &
b01111000 '
b101011111 (
12
b11100111 3
b01111000 4
b101011111 5
1?
b11100111 @
b01111000 A
b101011111 B
#422500
0#
00
0=
#425000
1#
b001001101 )
10
b001001101 6
1=
b001001101 C
#426000
0%
1+
b10111101 ,
b00100011 -
b011100000 .
02
18
b10111101 9
b00100011 :
b011100000 ;
0?
1E
b10111101 F
b00100011 G
b011100000 H
#427500
0#
00
0=
#430000
1#
b011110001 /
10
b011110001 <
1=
b011110001 I
#431000
0+
08
0E
#432000
1%
b10100111 &
b01101000 '
b100001111 (
12
b10100111 3
b01101000 4
b100001111 5
1?
b10100111 @
b01101000 A
b100001111 B
#432500
0#
00
0=
#435000
1#
b010110101 )
10
b010110101 6
1=
b010110101 C
#436000
0%
1+
b01010000 ,
b10101001 -
b011111001 .
02
18
b01010000 9
b10101001 :
b011111001 ;
0?
1E
b01010000 F
b10101001 G
b011111001 H
#437500
0#
00
0=
#440000
1#
b110011010 /
10
b110011010 <
1=
b110011010 I
#441000
0+
08
0E
#442000
1%
b01010110 &
b01110010 '
b011001000 (
12
b01010110 3
b01110010 4
b011001000 5
1?
b01010110 @
b01110010 A
b011001000 B
#442500
0#
00
0=
#445000
1#
b100100111 )
10
b100100111 6
1=
b100100111 C
#446000
0%
1+
b01110110 ,
b10100100 -
b100011010 .
02
18
b01110110 9
b10100100 :
b100011010 ;
0?
1E
b01110110 F
b10100100 G
b100011010 H
#447500
0#
00
0=
#450000
1#
b000111110 /
10
b000111110 <
1=
b000111110 I
#451000
0+
08
0E
#452000
1%
b00010110 &
b10010000 '
b010100110 (
12
b00010110 3
b10010000 4
b010100110 5
1?
b00010110 @
b10010000 A
b010100110 B
#452500
0#
00
0=
#455000
1#
b110110111 )
10
b110110111 6
1=
b110110111 C
#456000
0%
1+
b00100111 ,
b10101011 -
b011010010 .
02
18
b00100111 9
b10101011 :
b011010010 ;
0?
1E
b00100111 F
b10101011 G
b011010010 H
#457500
0#
00
0=
#460000
1#
b011101001 /
10
b011101001 <
1=
b011101001 I
#461000
0+
08
0E
#462000
1%
b00110101 &
b01011111 '
b010010100 (
12
b00110101 3
b01011111 4
b010010100 5
1?
b00110101 @
b01011111 A
b010010100 B
#462500
0#
00
0=
#465000
1#
b000010110 )
10
b000010110 6
1=
b000010110 C
#466000
0%
1+
b11110011 ,
b01011001 -
b101001100 .
02
18
b11110011 9
b01011001 :
b101001100 ;
0?
1E
b11110011 F
b01011001 G
b101001100 H
#467500
0#
00
0=
#470000
1#
b101000010 /
10
b101000010 <
1=
b101000010 I
