rtl/top_level.sv


module top_level (
    input  logic       clk,

    // Channel A
    input  logic       rst_A,
    input  logic       valid_in_A,
    input  logic [7:0] a_A,
    input  logic [7:0] b_A,
    output logic [8:0] sum_async_A,
    output logic [8:0] sum_sync_A,

    // Channel B
    input  logic       rst_B,
    input  logic       valid_in_B,
    input  logic [7:0] a_B,
    input  logic [7:0] b_B,
    output logic [8:0] sum_async_B,
    output logic [8:0] sum_sync_B
);

    // Channel A synchronous accumulator
    always_ff @(posedge clk) begin
        if (rst_A)
            sum_sync_A <= '0;
        else if (valid_in_A)
            sum_sync_A <= sum_sync_A + b_A;
    end

    assign sum_async_A = a_A + b_A;

    // Channel B synchronous accumulator
    always_ff @(posedge clk) begin
        if (rst_B)
            sum_sync_B <= '0;
        else if (valid_in_B)
            sum_sync_B <= sum_sync_B + b_B;
    end

    assign sum_async_B = a_B + b_B;

    initial begin
        $display("Time | rst_A| valid_in_A | a_A | b_A |sum_async_A | sum_sync_A |rst_B | valid_in_B| a_B | b_B  | sum_async_B | sum_sync_B   ");
        $monitor("%4t  |  %b  |  %b        | %0d | %0d |    %0d     |   %0d      | %b   |    %b     | %0d | %0d  |    %0d      |   %0d ",
                 $time, rst_A, valid_in_A, a_A, b_A, sum_async_A,sum_sync_A, rst_B, valid_in_B, a_B, b_B, sum_async_B, sum_sync_B);
    end

    initial begin
        $dumpfile("dump.vcd");
        $dumpvars(1, top_level.sv);
    end

endmodule

rtl/dut_wrapper.sv
module dut_wrapper (
    input  logic       clk,

    // Channel A – cocotb drives these
    input  logic       rst_A,
    input  logic       valid_in_A,
    input  logic [7:0] a_A,
    input  logic [7:0] b_A,

    // DUT drives these
    output logic [8:0] sum_async_A,
    output logic [8:0] sum_sync_A,

    // Channel B (if needed)
    input  logic       rst_B,
    input  logic       valid_in_B,
    input  logic [7:0] a_B,
    input  logic [7:0] b_B,
    output logic [8:0] sum_async_B,
    output logic [8:0] sum_sync_B
);

    top_level u_top_level (
        .clk(clk),

        // Channel A
        .rst_A(rst_A),
        .valid_in_A(valid_in_A),
        .a_A(a_A),
        .b_A(b_A),
        .sum_async_A(sum_async_A),
        .sum_sync_A(sum_sync_A),

        // Channel B
        .rst_B(rst_B),
        .valid_in_B(valid_in_B),
        .a_B(a_B),
        .b_B(b_B),
        .sum_async_B(sum_async_B),
        .sum_sync_B(sum_sync_B)
    );

endmodule



// module dut_wrapper (
//     input  logic       clk,

//     // Channel A – exposed directly for cocotb
//     output logic       rst_A,
//     output logic       valid_in_A,
//     output logic [7:0] a_A,
//     output logic [7:0] b_A,
//     output logic [8:0] sum_async_A,
//     output logic [8:0] sum_sync_A,

//     // Channel B – exposed directly for cocotb
//     output logic       rst_B,
//     output logic       valid_in_B,
//     output logic [7:0] a_B,
//     output logic [7:0] b_B,
//     output logic [8:0] sum_async_B,
//     output logic [8:0] sum_sync_B
// );

//     // Internal wires driven by cocotb (use these as DUT inputs)
//     logic rst_A_int;
//     logic valid_in_A_int;
//     logic [7:0] a_A_int;
//     logic [7:0] b_A_int;

//     logic rst_B_int;
//     logic valid_in_B_int;
//     logic [7:0] a_B_int;
//     logic [7:0] b_B_int;

//     // Connect exposed ports to internal wires so cocotb can drive them
//     assign rst_A       = rst_A_int;
//     assign valid_in_A  = valid_in_A_int;
//     assign a_A         = a_A_int;
//     assign b_A         = b_A_int;

//     assign rst_B       = rst_B_int;
//     assign valid_in_B  = valid_in_B_int;
//     assign a_B         = a_B_int;
//     assign b_B         = b_B_int;

//     // DUT instance
//     top_level u_top_level (
//         .clk          (clk),

//         // Channel A
//         .rst_A        (rst_A_int),
//         .valid_in_A   (valid_in_A_int),
//         .a_A          (a_A_int),
//         .b_A          (b_A_int),
//         .sum_async_A  (sum_async_A),
//         .sum_sync_A   (sum_sync_A),

//         // Channel B
//         .rst_B        (rst_B_int),
//         .valid_in_B   (valid_in_B_int),
//         .a_B          (a_B_int),
//         .b_B          (b_B_int),
//         .sum_async_B  (sum_async_B),
//         .sum_sync_B   (sum_sync_B)
//     );

// endmodule

regression_results/waves_4.vcd
$version Generated by VerilatedVcd $end
$timescale 1ps $end
 $scope module $rootio $end
  $var wire 1 # clk $end
  $var wire 1 $ rst_A $end
  $var wire 1 % valid_in_A $end
  $var wire 8 & a_A [7:0] $end
  $var wire 8 ' b_A [7:0] $end
  $var wire 9 ( sum_async_A [8:0] $end
  $var wire 9 ) sum_sync_A [8:0] $end
  $var wire 1 * rst_B $end
  $var wire 1 + valid_in_B $end
  $var wire 8 , a_B [7:0] $end
  $var wire 8 - b_B [7:0] $end
  $var wire 9 . sum_async_B [8:0] $end
  $var wire 9 / sum_sync_B [8:0] $end
 $upscope $end
 $scope module dut_wrapper $end
  $var wire 1 0 clk $end
  $var wire 1 1 rst_A $end
  $var wire 1 2 valid_in_A $end
  $var wire 8 3 a_A [7:0] $end
  $var wire 8 4 b_A [7:0] $end
  $var wire 9 5 sum_async_A [8:0] $end
  $var wire 9 6 sum_sync_A [8:0] $end
  $var wire 1 7 rst_B $end
  $var wire 1 8 valid_in_B $end
  $var wire 8 9 a_B [7:0] $end
  $var wire 8 : b_B [7:0] $end
  $var wire 9 ; sum_async_B [8:0] $end
  $var wire 9 < sum_sync_B [8:0] $end
  $scope module u_top_level $end
   $var wire 1 = clk $end
   $var wire 1 > rst_A $end
   $var wire 1 ? valid_in_A $end
   $var wire 8 @ a_A [7:0] $end
   $var wire 8 A b_A [7:0] $end
   $var wire 9 B sum_async_A [8:0] $end
   $var wire 9 C sum_sync_A [8:0] $end
   $var wire 1 D rst_B $end
   $var wire 1 E valid_in_B $end
   $var wire 8 F a_B [7:0] $end
   $var wire 8 G b_B [7:0] $end
   $var wire 9 H sum_async_B [8:0] $end
   $var wire 9 I sum_sync_B [8:0] $end
  $upscope $end
 $upscope $end
$enddefinitions $end


#0
1#
1$
0%
b00000000 &
b00000000 '
b000000000 (
b000000000 )
1*
0+
b00000000 ,
b00000000 -
b000000000 .
b000000000 /
10
11
02
b00000000 3
b00000000 4
b000000000 5
b000000000 6
17
08
b00000000 9
b00000000 :
b000000000 ;
b000000000 <
1=
1>
0?
b00000000 @
b00000000 A
b000000000 B
b000000000 C
1D
0E
b00000000 F
b00000000 G
b000000000 H
b000000000 I
#5000
0#
00
0=
#10000
1#
10
1=
#15000
0#
00
0=
#20000
1#
10
1=
#25000
0#
0$
0*
00
01
07
0=
0>
0D
#30000
1#
1%
b00000100 &
b11111010 '
b011111110 (
1+
b00010011 ,
b00011111 -
b000110010 .
10
12
b00000100 3
b11111010 4
b011111110 5
18
b00010011 9
b00011111 :
b000110010 ;
1=
1?
b00000100 @
b11111010 A
b011111110 B
1E
b00010011 F
b00011111 G
b000110010 H
#35000
0#
00
0=
#40000
1#
b011111010 )
b000011111 /
10
b011111010 6
b000011111 <
1=
b011111010 C
b000011111 I
#41000
b00000010 &
b11111011 '
b011111101 (
b00010010 ,
b00100111 -
b000111001 .
b00000010 3
b11111011 4
b011111101 5
b00010010 9
b00100111 :
b000111001 ;
b00000010 @
b11111011 A
b011111101 B
b00010010 F
b00100111 G
b000111001 H
#45000
0#
00
0=
#50000
1#
b111110101 )
b001000110 /
10
b111110101 6
b001000110 <
1=
b111110101 C
b001000110 I
#51000
b00000001 &
b11111111 '
b100000000 (
b00010001 ,
b00011110 -
b000101111 .
b00000001 3
b11111111 4
b100000000 5
b00010001 9
b00011110 :
b000101111 ;
b00000001 @
b11111111 A
b100000000 B
b00010001 F
b00011110 G
b000101111 H
#55000
0#
00
0=
#60000
1#
b011110100 )
b001100100 /
10
b011110100 6
b001100100 <
1=
b011110100 C
b001100100 I
#61000
b11111101 '
b011111110 (
b00001111 ,
b00101000 -
b000110111 .
b11111101 4
b011111110 5
b00001111 9
b00101000 :
b000110111 ;
b11111101 A
b011111110 B
b00001111 F
b00101000 G
b000110111 H
#65000
0#
00
0=
#70000
1#
b111110001 )
b010001100 /
10
b111110001 6
b010001100 <
1=
b111110001 C
b010001100 I
#71000
b00000101 &
b11111110 '
b100000011 (
b00010010 ,
b00100110 -
b000111000 .
b00000101 3
b11111110 4
b100000011 5
b00010010 9
b00100110 :
b000111000 ;
b00000101 @
b11111110 A
b100000011 B
b00010010 F
b00100110 G
b000111000 H
#75000
0#
00
0=
#80000
1#
b011101111 )
b010110010 /
10
b011101111 6
b010110010 <
1=
b011101111 C
b010110010 I
#81000
b00000001 &
b11111111 '
b100000000 (
b00011111 -
b000110001 .
b00000001 3
b11111111 4
b100000000 5
b00011111 :
b000110001 ;
b00000001 @
b11111111 A
b100000000 B
b00011111 G
b000110001 H
#85000
0#
00
0=
#90000
1#
b111101110 )
b011010001 /
10
b111101110 6
b011010001 <
1=
b111101110 C
b011010001 I
#91000
b00000101 &
b11111011 '
b00010001 ,
b00100011 -
b000110100 .
b00000101 3
b11111011 4
b00010001 9
b00100011 :
b000110100 ;
b00000101 @
b11111011 A
b00010001 F
b00100011 G
b000110100 H
#95000
0#
00
0=
#100000
1#
b011101001 )
b011110100 /
10
b011101001 6
b011110100 <
1=
b011101001 C
b011110100 I
#101000
b00001110 ,
b00011111 -
b000101101 .
b00001110 9
b00011111 :
b000101101 ;
b00001110 F
b00011111 G
b000101101 H
#105000
0#
00
0=
#110000
1#
b111100100 )
b100010011 /
10
b111100100 6
b100010011 <
1=
b111100100 C
b100010011 I
#111000
b11111101 '
b100000010 (
b00001101 ,
b00100010 -
b000101111 .
b11111101 4
b100000010 5
b00001101 9
b00100010 :
b000101111 ;
b11111101 A
b100000010 B
b00001101 F
b00100010 G
b000101111 H
#115000
0#
00
0=
#120000
1#
b011100001 )
b100110101 /
10
b011100001 6
b100110101 <
1=
b011100001 C
b100110101 I
#121000
b00000001 &
b011111110 (
b00010100 ,
b00100001 -
b000110101 .
b00000001 3
b011111110 5
b00010100 9
b00100001 :
b000110101 ;
b00000001 @
b011111110 B
b00010100 F
b00100001 G
b000110101 H
#125000
0#
00
0=
#130000
1#
b111011110 )
b101010110 /
10
b111011110 6
b101010110 <
1=
b111011110 C
b101010110 I
#131000
b00000000 &
b11111011 '
b011111011 (
b00001100 ,
b00101000 -
b000110100 .
b00000000 3
b11111011 4
b011111011 5
b00001100 9
b00101000 :
b000110100 ;
b00000000 @
b11111011 A
b011111011 B
b00001100 F
b00101000 G
b000110100 H
#135000
0#
00
0=
#140000
1#
b011011001 )
b101111110 /
10
b011011001 6
b101111110 <
1=
b011011001 C
b101111110 I
#141000
b00000101 &
b11111111 '
b100000100 (
b00001011 ,
b000110011 .
b00000101 3
b11111111 4
b100000100 5
b00001011 9
b000110011 ;
b00000101 @
b11111111 A
b100000100 B
b00001011 F
b000110011 H
#145000
0#
00
0=
#150000
1#
b111011000 )
b110100110 /
10
b111011000 6
b110100110 <
1=
b111011000 C
b110100110 I
#151000
b00000001 &
b11111101 '
b011111110 (
b00001100 ,
b00100110 -
b000110010 .
b00000001 3
b11111101 4
b011111110 5
b00001100 9
b00100110 :
b000110010 ;
b00000001 @
b11111101 A
b011111110 B
b00001100 F
b00100110 G
b000110010 H
#155000
0#
00
0=
#160000
1#
b011010101 )
b111001100 /
10
b011010101 6
b111001100 <
1=
b011010101 C
b111001100 I
#161000
b00000011 &
b11111100 '
b011111111 (
b00010010 ,
b00100101 -
b000110111 .
b00000011 3
b11111100 4
b011111111 5
b00010010 9
b00100101 :
b000110111 ;
b00000011 @
b11111100 A
b011111111 B
b00010010 F
b00100101 G
b000110111 H
#165000
0#
00
0=
#170000
1#
b111010001 )
b111110001 /
10
b111010001 6
b111110001 <
1=
b111010001 C
b111110001 I
#171000
b00000001 &
b11111010 '
b011111011 (
b00001100 ,
b00011110 -
b000101010 .
b00000001 3
b11111010 4
b011111011 5
b00001100 9
b00011110 :
b000101010 ;
b00000001 @
b11111010 A
b011111011 B
b00001100 F
b00011110 G
b000101010 H
#175000
0#
00
0=
#180000
1#
b011001011 )
b000001111 /
10
b011001011 6
b000001111 <
1=
b011001011 C
b000001111 I
#181000
b00000000 &
b11111100 '
b011111100 (
b00001110 ,
b00100000 -
b000101110 .
b00000000 3
b11111100 4
b011111100 5
b00001110 9
b00100000 :
b000101110 ;
b00000000 @
b11111100 A
b011111100 B
b00001110 F
b00100000 G
b000101110 H
#185000
0#
00
0=
#190000
1#
b111000111 )
b000101111 /
10
b111000111 6
b000101111 <
1=
b111000111 C
b000101111 I
#191000
b00000100 &
b11111010 '
b011111110 (
b00010001 ,
b00100100 -
b000110101 .
b00000100 3
b11111010 4
b011111110 5
b00010001 9
b00100100 :
b000110101 ;
b00000100 @
b11111010 A
b011111110 B
b00010001 F
b00100100 G
b000110101 H
#195000
0#
00
0=
#200000
1#
b011000001 )
b001010011 /
10
b011000001 6
b001010011 <
1=
b011000001 C
b001010011 I
#201000
b11111111 '
b100000011 (
b00010011 ,
b000110111 .
b11111111 4
b100000011 5
b00010011 9
b000110111 ;
b11111111 A
b100000011 B
b00010011 F
b000110111 H
#205000
0#
00
0=
#210000
1#
b111000000 )
b001110111 /
10
b111000000 6
b001110111 <
1=
b111000000 C
b001110111 I
#211000
b00000010 &
b11111011 '
b011111101 (
b00001010 ,
b00100110 -
b000110000 .
b00000010 3
b11111011 4
b011111101 5
b00001010 9
b00100110 :
b000110000 ;
b00000010 @
b11111011 A
b011111101 B
b00001010 F
b00100110 G
b000110000 H
#215000
0#
00
0=
#220000
1#
b010111011 )
b010011101 /
10
b010111011 6
b010011101 <
1=
b010111011 C
b010011101 I
#221000
b00000100 &
b011111111 (
b00001101 ,
b00100111 -
b000110100 .
b00000100 3
b011111111 5
b00001101 9
b00100111 :
b000110100 ;
b00000100 @
b011111111 B
b00001101 F
b00100111 G
b000110100 H
#225000
0#
00
0=
#230000
1#
b110110110 )
b011000100 /
10
b110110110 6
b011000100 <
1=
b110110110 C
b011000100 I
