rtl/top_level.sv


module top_level (
    input  logic       clk,

    // Channel A
    input  logic       rst_A,
    input  logic       valid_in_A,
    input  logic [7:0] a_A,
    input  logic [7:0] b_A,
    output logic [8:0] sum_async_A,
    output logic [8:0] sum_sync_A,

    // Channel B
    input  logic       rst_B,
    input  logic       valid_in_B,
    input  logic [7:0] a_B,
    input  logic [7:0] b_B,
    output logic [8:0] sum_async_B,
    output logic [8:0] sum_sync_B
);

    // Channel A synchronous accumulator
    always_ff @(posedge clk) begin
        if (rst_A)
            sum_sync_A <= '0;
        else if (valid_in_A)
            sum_sync_A <= sum_sync_A + b_A;
    end

    assign sum_async_A = a_A + b_A;

    // Channel B synchronous accumulator
    always_ff @(posedge clk) begin
        if (rst_B)
            sum_sync_B <= '0;
        else if (valid_in_B)
            sum_sync_B <= sum_sync_B + b_B;
    end

    assign sum_async_B = a_B + b_B;

    initial begin
        $display("Time | rst_A| valid_in_A | a_A | b_A |sum_async_A | sum_sync_A |rst_B | valid_in_B| a_B | b_B  | sum_async_B | sum_sync_B   ");
        $monitor("%4t  |  %b  |  %b        | %0d | %0d |    %0d     |   %0d      | %b   |    %b     | %0d | %0d  |    %0d      |   %0d ",
                 $time, rst_A, valid_in_A, a_A, b_A, sum_async_A,sum_sync_A, rst_B, valid_in_B, a_B, b_B, sum_async_B, sum_sync_B);
    end

    initial begin
        $dumpfile("dump.vcd");
        $dumpvars(1, top_level.sv);
    end

endmodule

rtl/dut_wrapper.sv
module dut_wrapper (
    input  logic       clk,

    // Channel A – cocotb drives these
    input  logic       rst_A,
    input  logic       valid_in_A,
    input  logic [7:0] a_A,
    input  logic [7:0] b_A,

    // DUT drives these
    output logic [8:0] sum_async_A,
    output logic [8:0] sum_sync_A,

    // Channel B (if needed)
    input  logic       rst_B,
    input  logic       valid_in_B,
    input  logic [7:0] a_B,
    input  logic [7:0] b_B,
    output logic [8:0] sum_async_B,
    output logic [8:0] sum_sync_B
);

    top_level u_top_level (
        .clk(clk),

        // Channel A
        .rst_A(rst_A),
        .valid_in_A(valid_in_A),
        .a_A(a_A),
        .b_A(b_A),
        .sum_async_A(sum_async_A),
        .sum_sync_A(sum_sync_A),

        // Channel B
        .rst_B(rst_B),
        .valid_in_B(valid_in_B),
        .a_B(a_B),
        .b_B(b_B),
        .sum_async_B(sum_async_B),
        .sum_sync_B(sum_sync_B)
    );

endmodule



// module dut_wrapper (
//     input  logic       clk,

//     // Channel A – exposed directly for cocotb
//     output logic       rst_A,
//     output logic       valid_in_A,
//     output logic [7:0] a_A,
//     output logic [7:0] b_A,
//     output logic [8:0] sum_async_A,
//     output logic [8:0] sum_sync_A,

//     // Channel B – exposed directly for cocotb
//     output logic       rst_B,
//     output logic       valid_in_B,
//     output logic [7:0] a_B,
//     output logic [7:0] b_B,
//     output logic [8:0] sum_async_B,
//     output logic [8:0] sum_sync_B
// );

//     // Internal wires driven by cocotb (use these as DUT inputs)
//     logic rst_A_int;
//     logic valid_in_A_int;
//     logic [7:0] a_A_int;
//     logic [7:0] b_A_int;

//     logic rst_B_int;
//     logic valid_in_B_int;
//     logic [7:0] a_B_int;
//     logic [7:0] b_B_int;

//     // Connect exposed ports to internal wires so cocotb can drive them
//     assign rst_A       = rst_A_int;
//     assign valid_in_A  = valid_in_A_int;
//     assign a_A         = a_A_int;
//     assign b_A         = b_A_int;

//     assign rst_B       = rst_B_int;
//     assign valid_in_B  = valid_in_B_int;
//     assign a_B         = a_B_int;
//     assign b_B         = b_B_int;

//     // DUT instance
//     top_level u_top_level (
//         .clk          (clk),

//         // Channel A
//         .rst_A        (rst_A_int),
//         .valid_in_A   (valid_in_A_int),
//         .a_A          (a_A_int),
//         .b_A          (b_A_int),
//         .sum_async_A  (sum_async_A),
//         .sum_sync_A   (sum_sync_A),

//         // Channel B
//         .rst_B        (rst_B_int),
//         .valid_in_B   (valid_in_B_int),
//         .a_B          (a_B_int),
//         .b_B          (b_B_int),
//         .sum_async_B  (sum_async_B),
//         .sum_sync_B   (sum_sync_B)
//     );

// endmodule

regression_results/waves_10.vcd
$version Generated by VerilatedVcd $end
$timescale 1ps $end
 $scope module $rootio $end
  $var wire 1 # clk $end
  $var wire 1 $ rst_A $end
  $var wire 1 % valid_in_A $end
  $var wire 8 & a_A [7:0] $end
  $var wire 8 ' b_A [7:0] $end
  $var wire 9 ( sum_async_A [8:0] $end
  $var wire 9 ) sum_sync_A [8:0] $end
  $var wire 1 * rst_B $end
  $var wire 1 + valid_in_B $end
  $var wire 8 , a_B [7:0] $end
  $var wire 8 - b_B [7:0] $end
  $var wire 9 . sum_async_B [8:0] $end
  $var wire 9 / sum_sync_B [8:0] $end
 $upscope $end
 $scope module dut_wrapper $end
  $var wire 1 0 clk $end
  $var wire 1 1 rst_A $end
  $var wire 1 2 valid_in_A $end
  $var wire 8 3 a_A [7:0] $end
  $var wire 8 4 b_A [7:0] $end
  $var wire 9 5 sum_async_A [8:0] $end
  $var wire 9 6 sum_sync_A [8:0] $end
  $var wire 1 7 rst_B $end
  $var wire 1 8 valid_in_B $end
  $var wire 8 9 a_B [7:0] $end
  $var wire 8 : b_B [7:0] $end
  $var wire 9 ; sum_async_B [8:0] $end
  $var wire 9 < sum_sync_B [8:0] $end
  $scope module u_top_level $end
   $var wire 1 = clk $end
   $var wire 1 > rst_A $end
   $var wire 1 ? valid_in_A $end
   $var wire 8 @ a_A [7:0] $end
   $var wire 8 A b_A [7:0] $end
   $var wire 9 B sum_async_A [8:0] $end
   $var wire 9 C sum_sync_A [8:0] $end
   $var wire 1 D rst_B $end
   $var wire 1 E valid_in_B $end
   $var wire 8 F a_B [7:0] $end
   $var wire 8 G b_B [7:0] $end
   $var wire 9 H sum_async_B [8:0] $end
   $var wire 9 I sum_sync_B [8:0] $end
  $upscope $end
 $upscope $end
$enddefinitions $end


#0
1#
0$
0%
b00000000 &
b00000000 '
b000000000 (
b000000000 )
1*
0+
b00000000 ,
b00000000 -
b000000000 .
b000000000 /
10
01
02
b00000000 3
b00000000 4
b000000000 5
b000000000 6
17
08
b00000000 9
b00000000 :
b000000000 ;
b000000000 <
1=
0>
0?
b00000000 @
b00000000 A
b000000000 B
b000000000 C
1D
0E
b00000000 F
b00000000 G
b000000000 H
b000000000 I
#40690000
0
0=
#10000
1#
0*
10
07
1=
0D
#15000
0#
00
0=
#20000
1#
10
1=
#25000
0#
00
0=
#30000
1#
10
1=
#32000
1%
b01111110 &
b11000101 '
b101000011 (
12
b01111110 3
b11000101 4
b101000011 5
1?
b01111110 @
b11000101 A
b101000011 B
#35000
0#
00
0=
#40000
1#
b011000101 )
10
b011000101 6
1=
b011000101 C
#41000
0%
1+
b11100111 ,
b01100001 -
b101001000 .
02
18
b11100111 9
b01100001 :
b101001000 ;
0?
1E
b11100111 F
b01100001 G
b101001000 H
#45000
0#
00
0=
#50000
1#
b001100001 /
10
b001100001 <
1=
b001100001 I
#51000
0+
08
0E
#52000
1%
b00101011 &
b11101101 '
b100011000 (
12
b00101011 3
b11101101 4
b100011000 5
1?
b00101011 @
b11101101 A
b100011000 B
#55000
0#
00
0=
#60000
1#
b110110010 )
10
b110110010 6
1=
b110110010 C
#61000
0%
b00111011 ,
b10100101 -
b011100000 .
02
b00111011 9
b10100101 :
b011100000 ;
0?
b00111011 F
b10100101 G
b011100000 H
#65000
0#
00
0=
#70000
1#
10
1=
#72000
1%
b10100110 &
b10111001 '
b101011111 (
12
b10100110 3
b10111001 4
b101011111 5
1?
b10100110 @
b10111001 A
b101011111 B
#75000
0#
00
0=
#80000
1#
b001101011 )
10
b001101011 6
1=
b001101011 C
#81000
0%
1+
b11101111 ,
b01001010 -
b100111001 .
02
18
b11101111 9
b01001010 :
b100111001 ;
0?
1E
b11101111 F
b01001010 G
b100111001 H
#85000
0#
00
0=
#90000
1#
b010101011 /
10
b010101011 <
1=
b010101011 I
#91000
0+
08
0E
#92000
b01111101 &
b01000010 '
b010111111 (
b01111101 3
b01000010 4
b010111111 5
b01111101 @
b01000010 A
b010111111 B
#95000
0#
00
0=
#100000
1#
10
1=
#101000
1+
b10010001 ,
b10000000 -
b100010001 .
18
b10010001 9
b10000000 :
b100010001 ;
1E
b10010001 F
b10000000 G
b100010001 H
#105000
0#
00
0=
#110000
1#
b100101011 /
10
b100101011 <
1=
b100101011 I
#111000
0+
08
0E
#112000
b11010111 &
b01111000 '
b101001111 (
b11010111 3
b01111000 4
b101001111 5
b11010111 @
b01111000 A
b101001111 B
#115000
0#
00
0=
#120000
1#
10
1=
#121000
1+
b10000001 ,
b01101001 -
b011101010 .
18
b10000001 9
b01101001 :
b011101010 ;
1E
b10000001 F
b01101001 G
b011101010 H
#125000
0#
00
0=
#130000
1#
b110010100 /
10
b110010100 <
1=
b110010100 I
#131000
0+
08
0E
#132000
1%
b11010101 &
b11110010 '
b111000111 (
12
b11010101 3
b11110010 4
b111000111 5
1?
b11010101 @
b11110010 A
b111000111 B
#135000
0#
00
0=
#140000
1#
b101011101 )
10
b101011101 6
1=
b101011101 C
#141000
0%
1+
b11110111 ,
b10000000 -
b101110111 .
02
18
b11110111 9
b10000000 :
b101110111 ;
0?
1E
b11110111 F
b10000000 G
b101110111 H
#145000
0#
00
0=
#150000
1#
b000010100 /
10
b000010100 <
1=
b000010100 I
#151000
0+
08
0E
#152000
b01110101 &
b10100010 '
b100010111 (
b01110101 3
b10100010 4
b100010111 5
b01110101 @
b10100010 A
b100010111 B
#155000
0#
00
0=
#160000
1#
10
1=
#161000
1+
b10000001 ,
b01110111 -
b011111000 .
18
b10000001 9
b01110111 :
b011111000 ;
1E
b10000001 F
b01110111 G
b011111000 H
#165000
0#
00
0=
#170000
1#
b010001011 /
10
b010001011 <
1=
b010001011 I
#171000
0+
08
0E
#172000
b00110011 &
b00110001 '
b001100100 (
b00110011 3
b00110001 4
b001100100 5
b00110011 @
b00110001 A
b001100100 B
#175000
0#
00
0=
#180000
1#
10
1=
#181000
1+
b11001110 ,
b11110101 -
b111000011 .
18
b11001110 9
b11110101 :
b111000011 ;
1E
b11001110 F
b11110101 G
b111000011 H
#185000
0#
00
0=
#190000
1#
b110000000 /
10
b110000000 <
1=
b110000000 I
#191000
0+
08
0E
#192000
1%
b00001101 &
b10101000 '
b010110101 (
12
b00001101 3
b10101000 4
b010110101 5
1?
b00001101 @
b10101000 A
b010110101 B
#195000
0#
00
0=
#200000
1#
b000000101 )
10
b000000101 6
1=
b000000101 C
#201000
0%
b11000101 ,
b11001000 -
b110001101 .
02
b11000101 9
b11001000 :
b110001101 ;
0?
b11000101 F
b11001000 G
b110001101 H
#205000
0#
00
0=
#210000
1#
10
1=
#212000
1%
b11011011 &
b11111101 '
b111011000 (
12
b11011011 3
b11111101 4
b111011000 5
1?
b11011011 @
b11111101 A
b111011000 B
#215000
0#
00
0=
#220000
1#
b100000010 )
10
b100000010 6
1=
b100000010 C
#221000
0%
1+
b01011001 ,
b00111000 -
b010010001 .
02
18
b01011001 9
b00111000 :
b010010001 ;
0?
1E
b01011001 F
b00111000 G
b010010001 H
#225000
0#
00
0=
#230000
1#
b110111000 /
10
b110111000 <
1=
b110111000 I
#231000
0+
08
0E
#232000
1%
b10000101 &
b00100011 '
b010101000 (
12
b10000101 3
b00100011 4
b010101000 5
1?
b10000101 @
b00100011 A
b010101000 B
#235000
0#
00
0=
#240000
1#
b100100101 )
10
b100100101 6
1=
b100100101 C
#241000
0%
1+
b10011010 ,
b10001001 -
b100100011 .
02
18
b10011010 9
b10001001 :
b100100011 ;
0?
1E
b10011010 F
b10001001 G
b100100011 H
#245000
0#
00
0=
#250000
1#
b001000001 /
10
b001000001 <
1=
b001000001 I
#251000
0+
08
0E
#252000
1%
b11001011 &
b10110011 '
b101111110 (
12
b11001011 3
b10110011 4
b101111110 5
1?
b11001011 @
b10110011 A
b101111110 B
#255000
0#
00
0=
#260000
1#
b111011000 )
10
b111011000 6
1=
b111011000 C
#261000
0%
b11011110 ,
b11110100 -
b111010010 .
02
b11011110 9
b11110100 :
b111010010 ;
0?
b11011110 F
b11110100 G
b111010010 H
#265000
0#
00
0=
#270000
1#
10
1=
#272000
b10110100 &
b01011111 '
b100010011 (
b10110100 3
b01011111 4
b100010011 5
b10110100 @
b01011111 A
b100010011 B
#275000
0#
00
0=
#280000
1#
10
1=
#281000
b01110000 ,
b00001111 -
b001111111 .
b01110000 9
b00001111 :
b001111111 ;
b01110000 F
b00001111 G
b001111111 H
#285000
0#
00
0=
#290000
1#
10
1=
#292000
1%
b11100000 &
b11111001 '
b111011001 (
12
b11100000 3
b11111001 4
b111011001 5
1?
b11100000 @
b11111001 A
b111011001 B
#295000
0#
00
0=
#300000
1#
b011010001 )
10
b011010001 6
1=
b011010001 C
#301000
0%
1+
b11000100 ,
b11100010 -
b110100110 .
02
18
b11000100 9
b11100010 :
b110100110 ;
0?
1E
b11000100 F
b11100010 G
b110100110 H
#305000
0#
00
0=
#310000
1#
b100100011 /
10
b100100011 <
1=
b100100011 I
#311000
0+
08
0E
#312000
b11110011 &
b01010110 '
b101001001 (
b11110011 3
b01010110 4
b101001001 5
b11110011 @
b01010110 A
b101001001 B
#315000
0#
00
0=
#320000
1#
10
1=
#321000
b11100010 ,
b11110101 -
b111010111 .
b11100010 9
b11110101 :
b111010111 ;
b11100010 F
b11110101 G
b111010111 H
#325000
0#
00
0=
#330000
1#
10
1=
#332000
b01100111 &
b00011100 '
b010000011 (
b01100111 3
b00011100 4
b010000011 5
b01100111 @
b00011100 A
b010000011 B
#335000
0#
00
0=
#340000
1#
10
1=
#341000
1+
b10101000 ,
b00010010 -
b010111010 .
18
b10101000 9
b00010010 :
b010111010 ;
1E
b10101000 F
b00010010 G
b010111010 H
#345000
0#
00
0=
#350000
1#
b100110101 /
10
b100110101 <
1=
b100110101 I
#351000
0+
08
0E
#352000
1%
b11110000 &
b10110000 '
b110100000 (
12
b11110000 3
b10110000 4
b110100000 5
1?
b11110000 @
b10110000 A
b110100000 B
#355000
0#
00
0=
#360000
1#
b110000001 )
10
b110000001 6
1=
b110000001 C
#361000
0%
b11011001 -
b110000001 .
02
b11011001 :
b110000001 ;
0?
b11011001 G
b110000001 H
#365000
0#
00
0=
#370000
1#
10
1=
#372000
b01011000 &
b10011001 '
b011110001 (
b01011000 3
b10011001 4
b011110001 5
b01011000 @
b10011001 A
b011110001 B
#375000
0#
00
0=
#380000
1#
10
1=
#381000
1+
b00000111 ,
b01010001 -
b001011000 .
18
b00000111 9
b01010001 :
b001011000 ;
1E
b00000111 F
b01010001 G
b001011000 H
#385000
0#
00
0=
#390000
1#
b110000110 /
10
b110000110 <
1=
b110000110 I
#391000
0+
08
0E
#392000
1%
b10110001 &
b01110010 '
b100100011 (
12
b10110001 3
b01110010 4
b100100011 5
1?
b10110001 @
b01110010 A
b100100011 B
#395000
0#
00
0=
#400000
1#
b111110011 )
10
b111110011 6
1=
b111110011 C
#401000
0%
b11101001 ,
b10011010 -
b110000011 .
02
b11101001 9
b10011010 :
b110000011 ;
0?
b11101001 F
b10011010 G
b110000011 H
#405000
0#
00
0=
#410000
1#
10
1=
#412000
1%
b10010110 &
b00110111 '
b011001101 (
12
b10010110 3
b00110111 4
b011001101 5
1?
b10010110 @
b00110111 A
b011001101 B
#415000
0#
00
0=
#420000
1#
b000101010 )
10
b000101010 6
1=
b000101010 C
#421000
0%
b10000100 ,
b00000001 -
b010000101 .
02
b10000100 9
b00000001 :
b010000101 ;
0?
b10000100 F
b00000001 G
b010000101 H
#425000
0#
00
0=
#430000
1#
10
1=
#432000
1%
b10110100 &
b00010110 '
b011001010 (
12
b10110100 3
b00010110 4
b011001010 5
1?
b10110100 @
b00010110 A
b011001010 B
#435000
0#
00
0=
#440000
1#
b001000000 )
10
b001000000 6
1=
b001000000 C
#441000
0%
b00111110 ,
b00010101 -
b001010011 .
02
b00111110 9
b00010101 :
b001010011 ;
0?
b00111110 F
b00010101 G
b001010011 H
#445000
0#
00
0=
#450000
1#
10
1=
#452000
1%
b00011111 &
b10100101 '
b011000100 (
12
b00011111 3
b10100101 4
b011000100 5
1?
b00011111 @
b10100101 A
b011000100 B
#455000
0#
00
0=
#460000
1#
b011100101 )
10
b011100101 6
1=
b011100101 C
#461000
0%
1+
b01000010 ,
b00000101 -
b001000111 .
02
18
b01000010 9
b00000101 :
b001000111 ;
0?
1E
b01000010 F
b00000101 G
b001000111 H
#465000
0#
00
0=
#470000
1#
b110001011 /
10
b110001011 <
1=
b110001011 I
#471000
0+
08
0E
#472000
1%
b10010111 &
b11000011 '
b101011010 (
12
b10010111 3
b11000011 4
b101011010 5
1?
b10010111 @
b11000011 A
b101011010 B
#475000
0#
00
0=
#480000
1#
b110101000 )
10
b110101000 6
1=
b110101000 C
#481000
0%
b11110101 ,
b11001101 -
b111000010 .
02
b11110101 9
b11001101 :
b111000010 ;
0?
b11110101 F
b11001101 G
b111000010 H
#485000
0#
00
0=
#490000
1#
10
1=
#492000
1%
b00000100 &
b01010000 '
b001010100 (
12
b00000100 3
b01010000 4
b001010100 5
1?
b00000100 @
b01010000 A
b001010100 B
#495000
0#
00
0=
#500000
1#
b111111000 )
10
b111111000 6
1=
b111111000 C
#501000
0%
b01110110 ,
b00001101 -
b010000011 .
02
b01110110 9
b00001101 :
b010000011 ;
0?
b01110110 F
b00001101 G
b010000011 H
#505000
0#
00
0=
#510000
1#
10
1=
#512000
b00111000 &
b10111110 '
b011110110 (
b00111000 3
b10111110 4
b011110110 5
b00111000 @
b10111110 A
b011110110 B
#515000
0#
00
0=
#520000
1#
10
1=
#521000
b10101101 ,
b10000110 -
b100110011 .
b10101101 9
b10000110 :
b100110011 ;
b10101101 F
b10000110 G
b100110011 H
#525000
0#
00
0=
#530000
1#
10
1=
#532000
1%
b01001000 &
b01000101 '
b010001101 (
12
b01001000 3
b01000101 4
b010001101 5
1?
b01001000 @
b01000101 A
b010001101 B
#535000
0#
00
0=
#540000
1#
b000111101 )
10
b000111101 6
1=
b000111101 C
#541000
0%
1+
b01000110 ,
b01010000 -
b010010110 .
02
18
b01000110 9
b01010000 :
b010010110 ;
0?
1E
b01000110 F
b01010000 G
b010010110 H
#545000
0#
00
0=
#550000
1#
b111011011 /
10
b111011011 <
1=
b111011011 I
#551000
0+
08
0E
#552000
b00011101 &
b10110110 '
b011010011 (
b00011101 3
b10110110 4
b011010011 5
b00011101 @
b10110110 A
b011010011 B
#555000
0#
00
0=
#560000
1#
10
1=
#561000
1+
b01010100 ,
b11100100 -
b100111000 .
18
b01010100 9
b11100100 :
b100111000 ;
1E
b01010100 F
b11100100 G
b100111000 H
#565000
0#
00
0=
#570000
1#
b010111111 /
10
b010111111 <
1=
b010111111 I
#571000
0+
08
0E
#572000
1%
b00101000 &
b00101110 '
b001010110 (
12
b00101000 3
b00101110 4
b001010110 5
1?
b00101000 @
b00101110 A
b001010110 B
#575000
0#
00
0=
#580000
1#
b001101011 )
10
b001101011 6
1=
b001101011 C
#581000
0%
b00110110 ,
b10010111 -
b011001101 .
02
b00110110 9
b10010111 :
b011001101 ;
0?
b00110110 F
b10010111 G
b011001101 H
#585000
0#
00
0=
#590000
1#
10
1=
#592000
1%
b01010000 &
b00010011 '
b001100011 (
12
b01010000 3
b00010011 4
b001100011 5
1?
b01010000 @
b00010011 A
b001100011 B
#595000
0#
00
0=
#600000
1#
b001111110 )
10
b001111110 6
1=
b001111110 C
#601000
0%
1+
b00101011 ,
b11101010 -
b100010101 .
02
18
b00101011 9
b11101010 :
b100010101 ;
0?
1E
b00101011 F
b11101010 G
b100010101 H
#605000
0#
00
0=
#610000
1#
b110101001 /
10
b110101001 <
1=
b110101001 I
#611000
0+
08
0E
#612000
1%
b00001011 &
b10011011 '
b010100110 (
12
b00001011 3
b10011011 4
b010100110 5
1?
b00001011 @
b10011011 A
b010100110 B
#615000
0#
00
0=
#620000
1#
b100011001 )
10
b100011001 6
1=
b100011001 C
#621000
0%
b01101000 ,
b01010111 -
b010111111 .
02
b01101000 9
b01010111 :
b010111111 ;
0?
b01101000 F
b01010111 G
b010111111 H
#625000
0#
00
0=
#630000
1#
10
1=
#632000
1%
b00100000 &
b01001100 '
b001101100 (
12
b00100000 3
b01001100 4
b001101100 5
1?
b00100000 @
b01001100 A
b001101100 B
#635000
0#
00
0=
#640000
1#
b101100101 )
10
b101100101 6
1=
b101100101 C
#641000
0%
1+
b00110110 ,
b01011101 -
b010010011 .
02
18
b00110110 9
b01011101 :
b010010011 ;
0?
1E
b00110110 F
b01011101 G
b010010011 H
#645000
0#
00
0=
#650000
1#
b000000110 /
10
b000000110 <
1=
b000000110 I
#651000
1*
0+
b00000000 ,
b00000000 -
b000000000 .
17
08
b00000000 9
b00000000 :
b000000000 ;
1D
0E
b00000000 F
b00000000 G
b000000000 H
#655000
0#
00
0=
#660000
1#
0*
b000000000 /
10
07
b000000000 <
1=
0D
b000000000 I
#661000
b11110111 &
b11000011 '
b110111010 (
b11110111 3
b11000011 4
b110111010 5
b11110111 @
b11000011 A
b110111010 B
#665000
0#
00
0=
#670000
1#
10
1=
#671000
1+
b11001011 ,
b11100000 -
b110101011 .
18
b11001011 9
b11100000 :
b110101011 ;
1E
b11001011 F
b11100000 G
b110101011 H
#675000
0#
00
0=
#680000
1#
b011100000 /
10
b011100000 <
1=
b011100000 I
#681000
0+
08
0E
#682000
1%
b11101010 &
b11001100 '
b110110110 (
12
b11101010 3
b11001100 4
b110110110 5
1?
b11101010 @
b11001100 A
b110110110 B
#685000
0#
00
0=
#690000
1#
b000110001 )
10
b000110001 6
1=
b000110001 C
#691000
0%
1+
b11001110 ,
b10011111 -
b101101101 .
02
18
b11001110 9
b10011111 :
b101101101 ;
0?
1E
b11001110 F
b10011111 G
b101101101 H
#695000
0#
00
0=
#700000
1#
b101111111 /
10
b101111111 <
1=
b101111111 I
#701000
0+
08
0E
#702000
b00100100 &
b10011110 '
b011000010 (
b00100100 3
b10011110 4
b011000010 5
b00100100 @
b10011110 A
b011000010 B
#705000
0#
00
0=
#710000
1#
10
1=
#711000
b10010101 ,
b00010110 -
b010101011 .
b10010101 9
b00010110 :
b010101011 ;
b10010101 F
b00010110 G
b010101011 H
#715000
0#
00
0=
#720000
1#
10
1=
#722000
1%
b00111100 &
b11110010 '
b100101110 (
12
b00111100 3
b11110010 4
b100101110 5
1?
b00111100 @
b11110010 A
b100101110 B
#725000
0#
00
0=
#730000
1#
b100100011 )
10
b100100011 6
1=
b100100011 C
#731000
0%
1+
b11110010 ,
b00100001 -
b100010011 .
02
18
b11110010 9
b00100001 :
b100010011 ;
0?
1E
b11110010 F
b00100001 G
b100010011 H
#735000
0#
00
0=
#740000
1#
b110100000 /
10
b110100000 <
1=
b110100000 I
#741000
0+
08
0E
#742000
1%
b10110010 &
b00000001 '
b010110011 (
12
b10110010 3
b00000001 4
b010110011 5
1?
b10110010 @
b00000001 A
b010110011 B
#745000
0#
00
0=
#750000
1#
b100100100 )
10
b100100100 6
1=
b100100100 C
#751000
0%
b10111111 ,
b10101011 -
b101101010 .
02
b10111111 9
b10101011 :
b101101010 ;
0?
b10111111 F
b10101011 G
b101101010 H
#755000
0#
00
0=
#760000
1#
10
1=
#762000
b00011011 &
b10100000 '
b010111011 (
b00011011 3
b10100000 4
b010111011 5
b00011011 @
b10100000 A
b010111011 B
#765000
0#
00
0=
#770000
1#
10
1=
#771000
1+
b00111111 ,
b10000011 -
b011000010 .
18
b00111111 9
b10000011 :
b011000010 ;
1E
b00111111 F
b10000011 G
b011000010 H
#775000
0#
00
0=
#780000
1#
b000100011 /
10
b000100011 <
1=
b000100011 I
#781000
0+
08
0E
#782000
b11111100 &
b00101111 '
b100101011 (
b11111100 3
b00101111 4
b100101011 5
b11111100 @
b00101111 A
b100101011 B
#785000
0#
00
0=
#790000
1#
10
1=
#791000
b01100101 ,
b10110100 -
b100011001 .
b01100101 9
b10110100 :
b100011001 ;
b01100101 F
b10110100 G
b100011001 H
#795000
0#
00
0=
#800000
1#
10
1=
#802000
1%
b00101011 &
b01100001 '
b010001100 (
12
b00101011 3
b01100001 4
b010001100 5
1?
b00101011 @
b01100001 A
b010001100 B
#805000
0#
00
0=
#810000
1#
b110000101 )
10
b110000101 6
1=
b110000101 C
#811000
0%
1+
b01010010 ,
b11101110 -
b101000000 .
02
18
b01010010 9
b11101110 :
b101000000 ;
0?
1E
b01010010 F
b11101110 G
b101000000 H
#815000
0#
00
0=
#820000
1#
b100010001 /
10
b100010001 <
1=
b100010001 I
#821000
0+
08
0E
#822000
b00110101 &
b10000110 '
b010111011 (
b00110101 3
b10000110 4
b010111011 5
b00110101 @
b10000110 A
b010111011 B
#825000
0#
00
0=
#830000
1#
10
1=
#831000
1+
b10111000 ,
b00001011 -
b011000011 .
18
b10111000 9
b00001011 :
b011000011 ;
1E
b10111000 F
b00001011 G
b011000011 H
#835000
0#
00
0=
#840000
1#
b100011100 /
10
b100011100 <
1=
b100011100 I
#841000
0+
08
0E
#842000
b10111100 &
b01001110 '
b100001010 (
b10111100 3
b01001110 4
b100001010 5
b10111100 @
b01001110 A
b100001010 B
#845000
0#
00
0=
#850000
1#
10
1=
#851000
b11101101 ,
b00110111 -
b100100100 .
b11101101 9
b00110111 :
b100100100 ;
b11101101 F
b00110111 G
b100100100 H
#855000
0#
00
0=
#860000
1#
10
1=
#862000
b01011100 &
b01100110 '
b011000010 (
b01011100 3
b01100110 4
b011000010 5
b01011100 @
b01100110 A
b011000010 B
#865000
0#
00
0=
#870000
1#
10
1=
#871000
1+
b10100110 ,
b01110000 -
b100010110 .
18
b10100110 9
b01110000 :
b100010110 ;
1E
b10100110 F
b01110000 G
b100010110 H
#875000
0#
00
0=
#880000
1#
b110001100 /
10
b110001100 <
1=
b110001100 I
#881000
0+
08
0E
#882000
1%
b10100111 &
b11100001 '
b110001000 (
12
b10100111 3
b11100001 4
b110001000 5
1?
b10100111 @
b11100001 A
b110001000 B
#885000
0#
00
0=
#890000
1#
b001100110 )
10
b001100110 6
1=
b001100110 C
#891000
0%
1+
b00000111 ,
b01000011 -
b001001010 .
02
18
b00000111 9
b01000011 :
b001001010 ;
0?
1E
b00000111 F
b01000011 G
b001001010 H
#895000
0#
00
0=
#900000
1#
b111001111 /
10
b111001111 <
1=
b111001111 I
#901000
0+
08
0E
#902000
b00001010 &
b11001100 '
b011010110 (
b00001010 3
b11001100 4
b011010110 5
b00001010 @
b11001100 A
b011010110 B
#905000
0#
00
0=
#910000
1#
10
1=
#911000
1+
b01010011 ,
b11011000 -
b100101011 .
18
b01010011 9
b11011000 :
b100101011 ;
1E
b01010011 F
b11011000 G
b100101011 H
#915000
0#
00
0=
#920000
1#
b010100111 /
10
b010100111 <
1=
b010100111 I
#921000
0+
08
0E
#922000
1%
b11010101 &
b01111110 '
b101010011 (
12
b11010101 3
b01111110 4
b101010011 5
1?
b11010101 @
b01111110 A
b101010011 B
#925000
0#
00
0=
#930000
1#
b011100100 )
10
b011100100 6
1=
b011100100 C
#931000
0%
b00000000 ,
b10000000 -
b010000000 .
02
b00000000 9
b10000000 :
b010000000 ;
0?
b00000000 F
b10000000 G
b010000000 H
#935000
0#
00
0=
#940000
1#
10
1=
#942000
b00110011 &
b01101111 '
b010100010 (
b00110011 3
b01101111 4
b010100010 5
b00110011 @
b01101111 A
b010100010 B
#945000
0#
00
0=
#950000
1#
10
1=
#951000
b11000110 ,
b11111111 -
b111000101 .
b11000110 9
b11111111 :
b111000101 ;
b11000110 F
b11111111 G
b111000101 H
#955000
0#
00
0=
#960000
1#
10
1=
#962000
1%
b10110010 &
b11100100 '
b110010110 (
12
b10110010 3
b11100100 4
b110010110 5
1?
b10110010 @
b11100100 A
b110010110 B
#965000
0#
00
0=
#970000
1#
b111001000 )
10
b111001000 6
1=
b111001000 C
#971000
0%
b00011001 ,
b11100110 -
b011111111 .
02
b00011001 9
b11100110 :
b011111111 ;
0?
b00011001 F
b11100110 G
b011111111 H
#975000
0#
00
0=
#980000
1#
10
1=
#982000
1%
b10110011 &
b11000010 '
b101110101 (
12
b10110011 3
b11000010 4
b101110101 5
1?
b10110011 @
b11000010 A
b101110101 B
#985000
0#
00
0=
#990000
1#
b010001010 )
10
b010001010 6
1=
b010001010 C
#991000
0%
1+
b11110100 ,
b01001111 -
b101000011 .
02
18
b11110100 9
b01001111 :
b101000011 ;
0?
1E
b11110100 F
b01001111 G
b101000011 H
#995000
0#
00
0=
#1000000
1#
b011110110 /
10
b011110110 <
1=
b011110110 I
#1001000
0+
08
0E
#1002000
1%
b00000111 &
b10111101 '
b011000100 (
12
b00000111 3
b10111101 4
b011000100 5
1?
b00000111 @
b10111101 A
b011000100 B
#1005000
0#
00
0=
#1010000
1#
b101000111 )
10
b101000111 6
1=
b101000111 C
#1011000
0%
1+
b01101110 ,
b01111000 -
b011100110 .
02
18
b01101110 9
b01111000 :
b011100110 ;
0?
1E
b01101110 F
b01111000 G
b011100110 H
#1015000
0#
00
0=
#1020000
1#
b101101110 /
10
b101101110 <
1=
b101101110 I
#1021000
0+
08
0E
#1022000
1%
b11011011 &
b01110010 '
b101001101 (
12
b11011011 3
b01110010 4
b101001101 5
1?
b11011011 @
b01110010 A
b101001101 B
#1025000
0#
00
0=
#1030000
1#
b110111001 )
10
b110111001 6
1=
b110111001 C
#1031000
0%
b00111111 -
b010101101 .
02
b00111111 :
b010101101 ;
0?
b00111111 G
b010101101 H
#1035000
0#
00
0=
#1040000
1#
10
1=
#1042000
b10111001 &
b00100010 '
b011011011 (
b10111001 3
b00100010 4
b011011011 5
b10111001 @
b00100010 A
b011011011 B
#1045000
0#
00
0=
#1050000
1#
10
1=
#1051000
b00000010 ,
b00110011 -
b000110101 .
b00000010 9
b00110011 :
b000110101 ;
b00000010 F
b00110011 G
b000110101 H
#1055000
0#
00
0=
