rtl/top_level.sv


module top_level (
    input  logic       clk,

    // Channel A
    input  logic       rst_A,
    input  logic       valid_in_A,
    input  logic [7:0] a_A,
    input  logic [7:0] b_A,
    output logic [8:0] sum_async_A,
    output logic [8:0] sum_sync_A,

    // Channel B
    input  logic       rst_B,
    input  logic       valid_in_B,
    input  logic [7:0] a_B,
    input  logic [7:0] b_B,
    output logic [8:0] sum_async_B,
    output logic [8:0] sum_sync_B
);

    // Channel A synchronous accumulator
    always_ff @(posedge clk) begin
        if (rst_A)
            sum_sync_A <= '0;
        else if (valid_in_A)
            sum_sync_A <= sum_sync_A + b_A;
    end

    assign sum_async_A = a_A + b_A;

    // Channel B synchronous accumulator
    always_ff @(posedge clk) begin
        if (rst_B)
            sum_sync_B <= '0;
        else if (valid_in_B)
            sum_sync_B <= sum_sync_B + b_B;
    end

    assign sum_async_B = a_B + b_B;

    initial begin
        $display("Time | rst_A| valid_in_A | a_A | b_A |sum_async_A | sum_sync_A |rst_B | valid_in_B| a_B | b_B  | sum_async_B | sum_sync_B   ");
        $monitor("%4t  |  %b  |  %b        | %0d | %0d |    %0d     |   %0d      | %b   |    %b     | %0d | %0d  |    %0d      |   %0d ",
                 $time, rst_A, valid_in_A, a_A, b_A, sum_async_A,sum_sync_A, rst_B, valid_in_B, a_B, b_B, sum_async_B, sum_sync_B);
    end

    initial begin
        $dumpfile("dump.vcd");
        $dumpvars(1, top_level.sv);
    end

endmodule

rtl/dut_wrapper.sv
module dut_wrapper (
    input  logic       clk,

    // Channel A – cocotb drives these
    input  logic       rst_A,
    input  logic       valid_in_A,
    input  logic [7:0] a_A,
    input  logic [7:0] b_A,

    // DUT drives these
    output logic [8:0] sum_async_A,
    output logic [8:0] sum_sync_A,

    // Channel B (if needed)
    input  logic       rst_B,
    input  logic       valid_in_B,
    input  logic [7:0] a_B,
    input  logic [7:0] b_B,
    output logic [8:0] sum_async_B,
    output logic [8:0] sum_sync_B
);

    top_level u_top_level (
        .clk(clk),

        // Channel A
        .rst_A(rst_A),
        .valid_in_A(valid_in_A),
        .a_A(a_A),
        .b_A(b_A),
        .sum_async_A(sum_async_A),
        .sum_sync_A(sum_sync_A),

        // Channel B
        .rst_B(rst_B),
        .valid_in_B(valid_in_B),
        .a_B(a_B),
        .b_B(b_B),
        .sum_async_B(sum_async_B),
        .sum_sync_B(sum_sync_B)
    );

endmodule



// module dut_wrapper (
//     input  logic       clk,

//     // Channel A – exposed directly for cocotb
//     output logic       rst_A,
//     output logic       valid_in_A,
//     output logic [7:0] a_A,
//     output logic [7:0] b_A,
//     output logic [8:0] sum_async_A,
//     output logic [8:0] sum_sync_A,

//     // Channel B – exposed directly for cocotb
//     output logic       rst_B,
//     output logic       valid_in_B,
//     output logic [7:0] a_B,
//     output logic [7:0] b_B,
//     output logic [8:0] sum_async_B,
//     output logic [8:0] sum_sync_B
// );

//     // Internal wires driven by cocotb (use these as DUT inputs)
//     logic rst_A_int;
//     logic valid_in_A_int;
//     logic [7:0] a_A_int;
//     logic [7:0] b_A_int;

//     logic rst_B_int;
//     logic valid_in_B_int;
//     logic [7:0] a_B_int;
//     logic [7:0] b_B_int;

//     // Connect exposed ports to internal wires so cocotb can drive them
//     assign rst_A       = rst_A_int;
//     assign valid_in_A  = valid_in_A_int;
//     assign a_A         = a_A_int;
//     assign b_A         = b_A_int;

//     assign rst_B       = rst_B_int;
//     assign valid_in_B  = valid_in_B_int;
//     assign a_B         = a_B_int;
//     assign b_B         = b_B_int;

//     // DUT instance
//     top_level u_top_level (
//         .clk          (clk),

//         // Channel A
//         .rst_A        (rst_A_int),
//         .valid_in_A   (valid_in_A_int),
//         .a_A          (a_A_int),
//         .b_A          (b_A_int),
//         .sum_async_A  (sum_async_A),
//         .sum_sync_A   (sum_sync_A),

//         // Channel B
//         .rst_B        (rst_B_int),
//         .valid_in_B   (valid_in_B_int),
//         .a_B          (a_B_int),
//         .b_B          (b_B_int),
//         .sum_async_B  (sum_async_B),
//         .sum_sync_B   (sum_sync_B)
//     );

// endmodule

regression_results/waves_8.vcd
$version Generated by VerilatedVcd $end
$timescale 1ps $end
 $scope module $rootio $end
  $var wire 1 # clk $end
  $var wire 1 $ rst_A $end
  $var wire 1 % valid_in_A $end
  $var wire 8 & a_A [7:0] $end
  $var wire 8 ' b_A [7:0] $end
  $var wire 9 ( sum_async_A [8:0] $end
  $var wire 9 ) sum_sync_A [8:0] $end
  $var wire 1 * rst_B $end
  $var wire 1 + valid_in_B $end
  $var wire 8 , a_B [7:0] $end
  $var wire 8 - b_B [7:0] $end
  $var wire 9 . sum_async_B [8:0] $end
  $var wire 9 / sum_sync_B [8:0] $end
 $upscope $end
 $scope module dut_wrapper $end
  $var wire 1 0 clk $end
  $var wire 1 1 rst_A $end
  $var wire 1 2 valid_in_A $end
  $var wire 8 3 a_A [7:0] $end
  $var wire 8 4 b_A [7:0] $end
  $var wire 9 5 sum_async_A [8:0] $end
  $var wire 9 6 sum_sync_A [8:0] $end
  $var wire 1 7 rst_B $end
  $var wire 1 8 valid_in_B $end
  $var wire 8 9 a_B [7:0] $end
  $var wire 8 : b_B [7:0] $end
  $var wire 9 ; sum_async_B [8:0] $end
  $var wire 9 < sum_sync_B [8:0] $end
  $scope module u_top_level $end
   $var wire 1 = clk $end
   $var wire 1 > rst_A $end
   $var wire 1 ? valid_in_A $end
   $var wire 8 @ a_A [7:0] $end
   $var wire 8 A b_A [7:0] $end
   $var wire 9 B sum_async_A [8:0] $end
   $var wire 9 C sum_sync_A [8:0] $end
   $var wire 1 D rst_B $end
   $var wire 1 E valid_in_B $end
   $var wire 8 F a_B [7:0] $end
   $var wire 8 G b_B [7:0] $end
   $var wire 9 H sum_async_B [8:0] $end
   $var wire 9 I sum_sync_B [8:0] $end
  $upscope $end
 $upscope $end
$enddefinitions $end


#0
1#
1$
0%
b00000000 &
b00000000 '
b000000000 (
b000000000 )
1*
0+
b00000000 ,
b00000000 -
b000000000 .
b000000000 /
10
11
02
b00000000 3
b00000000 4
b000000000 5
b000000000 6
17
08
b00000000 9
b00000000 :
b000000000 ;
b000000000 <
1=
1>
0?
b00000000 @
b00000000 A
b000000000 B
b000000000 C
1D
0E
b00000000 F
b00000000 G
b000000000 H
b000000000 I
#5000
0#
00
0=
#10000
1#
10
1=
#15000
0#
00
0=
#20000
1#
0$
1%
b11111011 &
b10001001 '
b110000100 (
0*
10
01
12
b11111011 3
b10001001 4
b110000100 5
07
1=
0>
1?
b11111011 @
b10001001 A
b110000100 B
0D
#25000
0#
00
0=
#30000
1#
b010001001 )
10
b010001001 6
1=
b010001001 C
#31000
0%
1+
b10011100 ,
b11110101 -
b110010001 .
02
18
b10011100 9
b11110101 :
b110010001 ;
0?
1E
b10011100 F
b11110101 G
b110010001 H
#35000
0#
00
0=
#40000
1#
b011110101 /
10
b011110101 <
1=
b011110101 I
#41000
0+
08
0E
#42000
1%
b00111101 &
b00100111 '
b001100100 (
12
b00111101 3
b00100111 4
b001100100 5
1?
b00111101 @
b00100111 A
b001100100 B
#45000
0#
00
0=
#50000
1#
b010110000 )
10
b010110000 6
1=
b010110000 C
#51000
0%
1+
b00110101 ,
b10111111 -
b011110100 .
02
18
b00110101 9
b10111111 :
b011110100 ;
0?
1E
b00110101 F
b10111111 G
b011110100 H
#55000
0#
00
0=
#60000
1#
b110110100 /
10
b110110100 <
1=
b110110100 I
#61000
0+
08
0E
#62000
1%
b00001001 &
b00011000 '
b000100001 (
12
b00001001 3
b00011000 4
b000100001 5
1?
b00001001 @
b00011000 A
b000100001 B
#65000
0#
00
0=
#70000
1#
b011001000 )
10
b011001000 6
1=
b011001000 C
#71000
0%
1+
b00110111 ,
b11111010 -
b100110001 .
02
18
b00110111 9
b11111010 :
b100110001 ;
0?
1E
b00110111 F
b11111010 G
b100110001 H
#75000
0#
00
0=
#80000
1#
b010101110 /
10
b010101110 <
1=
b010101110 I
#81000
0+
08
0E
#82000
1%
b11101110 &
b01100000 '
b101001110 (
12
b11101110 3
b01100000 4
b101001110 5
1?
b11101110 @
b01100000 A
b101001110 B
#85000
0#
00
0=
#90000
1#
b100101000 )
10
b100101000 6
1=
b100101000 C
#91000
0%
1+
b01001110 ,
b01010011 -
b010100001 .
02
18
b01001110 9
b01010011 :
b010100001 ;
0?
1E
b01001110 F
b01010011 G
b010100001 H
#95000
0#
00
0=
#100000
1#
b100000001 /
10
b100000001 <
1=
b100000001 I
#101000
0+
08
0E
#102000
1%
b11010011 &
b00111100 '
b100001111 (
12
b11010011 3
b00111100 4
b100001111 5
1?
b11010011 @
b00111100 A
b100001111 B
#105000
0#
00
0=
#110000
1#
b101100100 )
10
b101100100 6
1=
b101100100 C
#111000
0%
1+
b01000110 ,
b10011010 -
b011100000 .
02
18
b01000110 9
b10011010 :
b011100000 ;
0?
1E
b01000110 F
b10011010 G
b011100000 H
#115000
0#
00
0=
#120000
1#
b110011011 /
10
b110011011 <
1=
b110011011 I
#121000
0+
08
0E
#122000
1%
b00000011 &
b00101101 '
b000110000 (
12
b00000011 3
b00101101 4
b000110000 5
1?
b00000011 @
b00101101 A
b000110000 B
#125000
0#
00
0=
#130000
1#
b110010001 )
10
b110010001 6
1=
b110010001 C
#131000
0%
1+
b10100010 ,
b01011011 -
b011111101 .
02
18
b10100010 9
b01011011 :
b011111101 ;
0?
1E
b10100010 F
b01011011 G
b011111101 H
#135000
0#
00
0=
#140000
1#
b111110110 /
10
b111110110 <
1=
b111110110 I
#141000
0+
08
0E
#142000
1%
b00100010 &
b01001111 '
b001110001 (
12
b00100010 3
b01001111 4
b001110001 5
1?
b00100010 @
b01001111 A
b001110001 B
#145000
0#
00
0=
#150000
1#
b111100000 )
10
b111100000 6
1=
b111100000 C
#151000
0%
1+
b01000101 ,
b10011100 -
b011100001 .
02
18
b01000101 9
b10011100 :
b011100001 ;
0?
1E
b01000101 F
b10011100 G
b011100001 H
#155000
0#
00
0=
#160000
1#
b010010010 /
10
b010010010 <
1=
b010010010 I
#161000
0+
08
0E
#162000
1%
b00001000 &
b00010100 '
b000011100 (
12
b00001000 3
b00010100 4
b000011100 5
1?
b00001000 @
b00010100 A
b000011100 B
#165000
0#
00
0=
#170000
1#
b111110100 )
10
b111110100 6
1=
b111110100 C
#171000
0%
1+
b01011110 ,
b00000100 -
b001100010 .
02
18
b01011110 9
b00000100 :
b001100010 ;
0?
1E
b01011110 F
b00000100 G
b001100010 H
#175000
0#
00
0=
#180000
1#
b010010110 /
10
b010010110 <
1=
b010010110 I
#181000
0+
08
0E
#182000
1%
b10100010 &
b11110111 '
b110011001 (
12
b10100010 3
b11110111 4
b110011001 5
1?
b10100010 @
b11110111 A
b110011001 B
#185000
0#
00
0=
#190000
1#
b011101011 )
10
b011101011 6
1=
b011101011 C
#191000
0%
1+
b00001100 ,
b10100000 -
b010101100 .
02
18
b00001100 9
b10100000 :
b010101100 ;
0?
1E
b00001100 F
b10100000 G
b010101100 H
#195000
0#
00
0=
#200000
1#
b100110110 /
10
b100110110 <
1=
b100110110 I
#201000
0+
08
0E
#202000
1%
b01000010 &
b01101000 '
b010101010 (
12
b01000010 3
b01101000 4
b010101010 5
1?
b01000010 @
b01101000 A
b010101010 B
#205000
0#
00
0=
#210000
1#
b101010011 )
10
b101010011 6
1=
b101010011 C
#211000
0%
1+
b00000010 ,
b11000110 -
b011001000 .
02
18
b00000010 9
b11000110 :
b011001000 ;
0?
1E
b00000010 F
b11000110 G
b011001000 H
#215000
0#
00
0=
#220000
1#
b111111100 /
10
b111111100 <
1=
b111111100 I
#221000
0+
08
0E
#222000
1%
b01001001 &
b10110101 '
b011111110 (
12
b01001001 3
b10110101 4
b011111110 5
1?
b01001001 @
b10110101 A
b011111110 B
#225000
0#
00
0=
#230000
1#
b000001000 )
10
b000001000 6
1=
b000001000 C
#231000
0%
1+
b01110010 ,
b11010111 -
b101001001 .
02
18
b01110010 9
b11010111 :
b101001001 ;
0?
1E
b01110010 F
b11010111 G
b101001001 H
#235000
0#
00
0=
#240000
1#
b011010011 /
10
b011010011 <
1=
b011010011 I
#241000
0+
08
0E
#242000
1%
b00111010 &
b00011011 '
b001010101 (
12
b00111010 3
b00011011 4
b001010101 5
1?
b00111010 @
b00011011 A
b001010101 B
#245000
0#
00
0=
#250000
1#
b000100011 )
10
b000100011 6
1=
b000100011 C
#251000
0%
1+
b01101011 ,
b01111000 -
b011100011 .
02
18
b01101011 9
b01111000 :
b011100011 ;
0?
1E
b01101011 F
b01111000 G
b011100011 H
#255000
0#
00
0=
#260000
1#
b101001011 /
10
b101001011 <
1=
b101001011 I
#261000
0+
08
0E
#262000
1%
b01110100 &
b10100001 '
b100010101 (
12
b01110100 3
b10100001 4
b100010101 5
1?
b01110100 @
b10100001 A
b100010101 B
#265000
0#
00
0=
#270000
1#
b011000100 )
10
b011000100 6
1=
b011000100 C
#271000
0%
1+
b01001100 ,
b10110100 -
b100000000 .
02
18
b01001100 9
b10110100 :
b100000000 ;
0?
1E
b01001100 F
b10110100 G
b100000000 H
#275000
0#
00
0=
#280000
1#
b111111111 /
10
b111111111 <
1=
b111111111 I
#281000
0+
08
0E
#282000
1%
b00010011 &
b00110011 '
b001000110 (
12
b00010011 3
b00110011 4
b001000110 5
1?
b00010011 @
b00110011 A
b001000110 B
#285000
0#
00
0=
#290000
1#
b011110111 )
10
b011110111 6
1=
b011110111 C
#291000
0%
1+
b10000110 ,
b11000010 -
b101001000 .
02
18
b10000110 9
b11000010 :
b101001000 ;
0?
1E
b10000110 F
b11000010 G
b101001000 H
#295000
0#
00
0=
#300000
1#
b011000001 /
10
b011000001 <
1=
b011000001 I
#301000
0+
08
0E
#302000
1%
b10111000 &
b01100000 '
b100011000 (
12
b10111000 3
b01100000 4
b100011000 5
1?
b10111000 @
b01100000 A
b100011000 B
#305000
0#
00
0=
#310000
1#
b101010111 )
10
b101010111 6
1=
b101010111 C
#311000
0%
1+
b00000100 ,
b00110000 -
b000110100 .
02
18
b00000100 9
b00110000 :
b000110100 ;
0?
1E
b00000100 F
b00110000 G
b000110100 H
#315000
0#
00
0=
#320000
1#
b011110001 /
10
b011110001 <
1=
b011110001 I
#321000
0+
08
0E
#322000
1%
b10111001 &
b11011000 '
b110010001 (
12
b10111001 3
b11011000 4
b110010001 5
1?
b10111001 @
b11011000 A
b110010001 B
#325000
0#
00
0=
#330000
1#
b000101111 )
10
b000101111 6
1=
b000101111 C
#331000
0%
1+
b11000110 ,
b11001011 -
b110010001 .
02
18
b11000110 9
b11001011 :
b110010001 ;
0?
1E
b11000110 F
b11001011 G
b110010001 H
#335000
0#
00
0=
#340000
1#
b110111100 /
10
b110111100 <
1=
b110111100 I
#341000
0+
08
0E
#342000
1%
b10101111 &
b11111000 '
b110100111 (
12
b10101111 3
b11111000 4
b110100111 5
1?
b10101111 @
b11111000 A
b110100111 B
#345000
0#
00
0=
#350000
1#
b100100111 )
10
b100100111 6
1=
b100100111 C
#351000
0%
1+
b11001010 ,
b10000110 -
b101010000 .
02
18
b11001010 9
b10000110 :
b101010000 ;
0?
1E
b11001010 F
b10000110 G
b101010000 H
#355000
0#
00
0=
#360000
1#
b001000010 /
10
b001000010 <
1=
b001000010 I
#361000
0+
08
0E
#362000
1%
b11111011 &
b01100011 '
b101011110 (
12
b11111011 3
b01100011 4
b101011110 5
1?
b11111011 @
b01100011 A
b101011110 B
#365000
0#
00
0=
#370000
1#
b110001010 )
10
b110001010 6
1=
b110001010 C
#371000
0%
1+
b10111000 ,
b10011001 -
b101010001 .
02
18
b10111000 9
b10011001 :
b101010001 ;
0?
1E
b10111000 F
b10011001 G
b101010001 H
#375000
0#
00
0=
#380000
1#
b011011011 /
10
b011011011 <
1=
b011011011 I
#381000
0+
08
0E
#382000
1%
b01011101 &
b00111011 '
b010011000 (
12
b01011101 3
b00111011 4
b010011000 5
1?
b01011101 @
b00111011 A
b010011000 B
#385000
0#
00
0=
#390000
1#
b111000101 )
10
b111000101 6
1=
b111000101 C
#391000
0%
1+
b00110110 ,
b01010000 -
b010000110 .
02
18
b00110110 9
b01010000 :
b010000110 ;
0?
1E
b00110110 F
b01010000 G
b010000110 H
#395000
0#
00
0=
#400000
1#
b100101011 /
10
b100101011 <
1=
b100101011 I
#401000
0+
08
0E
#402000
1%
b11110010 &
b00110010 '
b100100100 (
12
b11110010 3
b00110010 4
b100100100 5
1?
b11110010 @
b00110010 A
b100100100 B
#405000
0#
00
0=
#410000
1#
b111110111 )
10
b111110111 6
1=
b111110111 C
#411000
0%
1+
b00001110 ,
b01101111 -
b001111101 .
02
18
b00001110 9
b01101111 :
b001111101 ;
0?
1E
b00001110 F
b01101111 G
b001111101 H
#415000
0#
00
0=
#420000
1#
b110011010 /
10
b110011010 <
1=
b110011010 I
#421000
0+
08
0E
#422000
1%
b00000001 &
b10101111 '
b010110000 (
12
b00000001 3
b10101111 4
b010110000 5
1?
b00000001 @
b10101111 A
b010110000 B
#425000
0#
00
0=
#430000
1#
b010100110 )
10
b010100110 6
1=
b010100110 C
#431000
0%
1+
b00100001 ,
b10000011 -
b010100100 .
02
18
b00100001 9
b10000011 :
b010100100 ;
0?
1E
b00100001 F
b10000011 G
b010100100 H
#435000
0#
00
0=
#440000
1#
b000011101 /
10
b000011101 <
1=
b000011101 I
#441000
0+
08
0E
#442000
1%
b10000110 &
b10010111 '
b100011101 (
12
b10000110 3
b10010111 4
b100011101 5
1?
b10000110 @
b10010111 A
b100011101 B
#445000
0#
00
0=
#450000
1#
b100111101 )
10
b100111101 6
1=
b100111101 C
#451000
0%
1+
b01001011 ,
b01111000 -
b011000011 .
02
18
b01001011 9
b01111000 :
b011000011 ;
0?
1E
b01001011 F
b01111000 G
b011000011 H
#455000
0#
00
0=
#460000
1#
b010010101 /
10
b010010101 <
1=
b010010101 I
#461000
0+
08
0E
#462000
1%
b10101110 &
b10100100 '
b101010010 (
12
b10101110 3
b10100100 4
b101010010 5
1?
b10101110 @
b10100100 A
b101010010 B
#465000
0#
00
0=
#470000
1#
b111100001 )
10
b111100001 6
1=
b111100001 C
#471000
0%
1+
b01001101 ,
b11001110 -
b100011011 .
02
18
b01001101 9
b11001110 :
b100011011 ;
0?
1E
b01001101 F
b11001110 G
b100011011 H
#475000
0#
00
0=
#480000
1#
b101100011 /
10
b101100011 <
1=
b101100011 I
#481000
0+
08
0E
#482000
1%
b11101001 &
b00110011 '
b100011100 (
12
b11101001 3
b00110011 4
b100011100 5
1?
b11101001 @
b00110011 A
b100011100 B
#485000
0#
00
0=
#490000
1#
b000010100 )
10
b000010100 6
1=
b000010100 C
#491000
0%
1+
b00001010 ,
b10111110 -
b011001000 .
02
18
b00001010 9
b10111110 :
b011001000 ;
0?
1E
b00001010 F
b10111110 G
b011001000 H
#495000
0#
00
0=
#500000
1#
b000100001 /
10
b000100001 <
1=
b000100001 I
#501000
0+
08
0E
#502000
1%
b00100110 &
b10101101 '
b011010011 (
12
b00100110 3
b10101101 4
b011010011 5
1?
b00100110 @
b10101101 A
b011010011 B
#505000
0#
00
0=
#510000
1#
b011000001 )
10
b011000001 6
1=
b011000001 C
#511000
0%
1+
b10000011 ,
b11011101 -
b101100000 .
02
18
b10000011 9
b11011101 :
b101100000 ;
0?
1E
b10000011 F
b11011101 G
b101100000 H
#515000
0#
00
0=
#520000
1#
b011111110 /
10
b011111110 <
1=
b011111110 I
#521000
0+
08
0E
#522000
1%
b10101000 &
b11111100 '
b110100100 (
12
b10101000 3
b11111100 4
b110100100 5
1?
b10101000 @
b11111100 A
b110100100 B
#525000
0#
00
0=
#530000
1#
b110111101 )
10
b110111101 6
1=
b110111101 C
#531000
0%
1+
b10011100 ,
b11100001 -
b101111101 .
02
18
b10011100 9
b11100001 :
b101111101 ;
0?
1E
b10011100 F
b11100001 G
b101111101 H
#535000
0#
00
0=
#540000
1#
b111011111 /
10
b111011111 <
1=
b111011111 I
#541000
0+
08
0E
#542000
1%
b10111110 &
b01110110 '
b100110100 (
12
b10111110 3
b01110110 4
b100110100 5
1?
b10111110 @
b01110110 A
b100110100 B
#545000
0#
00
0=
#550000
1#
b000110011 )
10
b000110011 6
1=
b000110011 C
#551000
0%
1+
b01011000 ,
b00000100 -
b001011100 .
02
18
b01011000 9
b00000100 :
b001011100 ;
0?
1E
b01011000 F
b00000100 G
b001011100 H
#555000
0#
00
0=
#560000
1#
b111100011 /
10
b111100011 <
1=
b111100011 I
#561000
0+
08
0E
#562000
1%
b01101000 &
b00000010 '
b001101010 (
12
b01101000 3
b00000010 4
b001101010 5
1?
b01101000 @
b00000010 A
b001101010 B
#565000
0#
00
0=
#570000
1#
b000110101 )
10
b000110101 6
1=
b000110101 C
#571000
0%
1+
b00101011 ,
b00010000 -
b000111011 .
02
18
b00101011 9
b00010000 :
b000111011 ;
0?
1E
b00101011 F
b00010000 G
b000111011 H
#575000
0#
00
0=
#580000
1#
b111110011 /
10
b111110011 <
1=
b111110011 I
#581000
0+
08
0E
#582000
1%
b10110001 &
b01100011 '
b100010100 (
12
b10110001 3
b01100011 4
b100010100 5
1?
b10110001 @
b01100011 A
b100010100 B
#585000
0#
00
0=
#590000
1#
b010011000 )
10
b010011000 6
1=
b010011000 C
#591000
0%
1+
b01010000 ,
b10001110 -
b011011110 .
02
18
b01010000 9
b10001110 :
b011011110 ;
0?
1E
b01010000 F
b10001110 G
b011011110 H
#595000
0#
00
0=
#600000
1#
b010000001 /
10
b010000001 <
1=
b010000001 I
#601000
0+
08
0E
#602000
1%
b11010011 &
b01101110 '
b101000001 (
12
b11010011 3
b01101110 4
b101000001 5
1?
b11010011 @
b01101110 A
b101000001 B
#605000
0#
00
0=
#610000
1#
b100000110 )
10
b100000110 6
1=
b100000110 C
#611000
0%
1+
b10010110 ,
b11111011 -
b110010001 .
02
18
b10010110 9
b11111011 :
b110010001 ;
0?
1E
b10010110 F
b11111011 G
b110010001 H
#615000
0#
00
0=
#620000
1#
b101111100 /
10
b101111100 <
1=
b101111100 I
#621000
0+
08
0E
#622000
1%
b01111010 &
b00100101 '
b010011111 (
12
b01111010 3
b00100101 4
b010011111 5
1?
b01111010 @
b00100101 A
b010011111 B
#625000
0#
00
0=
#630000
1#
b100101011 )
10
b100101011 6
1=
b100101011 C
#631000
0%
1+
b11101100 ,
b10110000 -
b110011100 .
02
18
b11101100 9
b10110000 :
b110011100 ;
0?
1E
b11101100 F
b10110000 G
b110011100 H
#635000
0#
00
0=
#640000
1#
b000101100 /
10
b000101100 <
1=
b000101100 I
#641000
0+
08
0E
#642000
1%
b10001101 &
b01100001 '
b011101110 (
12
b10001101 3
b01100001 4
b011101110 5
1?
b10001101 @
b01100001 A
b011101110 B
#645000
0#
00
0=
#650000
1#
b110001100 )
10
b110001100 6
1=
b110001100 C
#651000
0%
1+
b00011010 ,
b01101000 -
b010000010 .
02
18
b00011010 9
b01101000 :
b010000010 ;
0?
1E
b00011010 F
b01101000 G
b010000010 H
#655000
0#
00
0=
#660000
1#
b010010100 /
10
b010010100 <
1=
b010010100 I
#661000
0+
08
0E
#662000
1%
b00111101 &
b10010111 '
b011010100 (
12
b00111101 3
b10010111 4
b011010100 5
1?
b00111101 @
b10010111 A
b011010100 B
#665000
0#
00
0=
#670000
1#
b000100011 )
10
b000100011 6
1=
b000100011 C
#671000
0%
1+
b10111001 ,
b00101011 -
b011100100 .
02
18
b10111001 9
b00101011 :
b011100100 ;
0?
1E
b10111001 F
b00101011 G
b011100100 H
#675000
0#
00
0=
#680000
1#
b010111111 /
10
b010111111 <
1=
b010111111 I
#681000
0+
08
0E
#682000
1%
b01000111 &
b01000111 '
b010001110 (
12
b01000111 3
b01000111 4
b010001110 5
1?
b01000111 @
b01000111 A
b010001110 B
#685000
0#
00
0=
#690000
1#
b001101010 )
10
b001101010 6
1=
b001101010 C
#691000
0%
1+
b11011001 ,
b11001011 -
b110100100 .
02
18
b11011001 9
b11001011 :
b110100100 ;
0?
1E
b11011001 F
b11001011 G
b110100100 H
#695000
0#
00
0=
#700000
1#
b110001010 /
10
b110001010 <
1=
b110001010 I
#701000
0+
08
0E
#702000
1%
b10010100 &
b01000101 '
b011011001 (
12
b10010100 3
b01000101 4
b011011001 5
1?
b10010100 @
b01000101 A
b011011001 B
#705000
0#
00
0=
#710000
1#
b010101111 )
10
b010101111 6
1=
b010101111 C
#711000
0%
1+
b10001111 ,
b10101101 -
b100111100 .
02
18
b10001111 9
b10101101 :
b100111100 ;
0?
1E
b10001111 F
b10101101 G
b100111100 H
#715000
0#
00
0=
#720000
1#
b000110111 /
10
b000110111 <
1=
b000110111 I
#721000
0+
08
0E
#722000
1%
b00001011 &
b10110011 '
b010111110 (
12
b00001011 3
b10110011 4
b010111110 5
1?
b00001011 @
b10110011 A
b010111110 B
#725000
0#
00
0=
#730000
1#
b101100010 )
10
b101100010 6
1=
b101100010 C
#731000
0%
1+
b01010011 ,
b11100110 -
b100111001 .
02
18
b01010011 9
b11100110 :
b100111001 ;
0?
1E
b01010011 F
b11100110 G
b100111001 H
#735000
0#
00
0=
#740000
1#
b100011101 /
10
b100011101 <
1=
b100011101 I
#741000
0+
08
0E
#742000
1%
b01011101 &
b00011000 '
b001110101 (
12
b01011101 3
b00011000 4
b001110101 5
1?
b01011101 @
b00011000 A
b001110101 B
#745000
0#
00
0=
#750000
1#
b101111010 )
10
b101111010 6
1=
b101111010 C
#751000
0%
1+
b11000110 ,
b00010110 -
b011011100 .
02
18
b11000110 9
b00010110 :
b011011100 ;
0?
1E
b11000110 F
b00010110 G
b011011100 H
#755000
0#
00
0=
#760000
1#
b100110011 /
10
b100110011 <
1=
b100110011 I
#761000
0+
08
0E
#762000
1%
b10011101 &
b10101111 '
b101001100 (
12
b10011101 3
b10101111 4
b101001100 5
1?
b10011101 @
b10101111 A
b101001100 B
#765000
0#
00
0=
#770000
1#
b000101001 )
10
b000101001 6
1=
b000101001 C
#771000
0%
1+
b00010100 ,
b01101111 -
b010000011 .
02
18
b00010100 9
b01101111 :
b010000011 ;
0?
1E
b00010100 F
b01101111 G
b010000011 H
#775000
0#
00
0=
#780000
1#
b110100010 /
10
b110100010 <
1=
b110100010 I
#781000
0+
08
0E
#782000
1%
b01010000 &
b10100101 '
b011110101 (
12
b01010000 3
b10100101 4
b011110101 5
1?
b01010000 @
b10100101 A
b011110101 B
#785000
0#
00
0=
#790000
1#
b011001110 )
10
b011001110 6
1=
b011001110 C
#791000
0%
1+
b11101001 ,
b01101010 -
b101010011 .
02
18
b11101001 9
b01101010 :
b101010011 ;
0?
1E
b11101001 F
b01101010 G
b101010011 H
#795000
0#
00
0=
#800000
1#
b000001100 /
10
b000001100 <
1=
b000001100 I
#801000
0+
08
0E
#802000
1%
b10101010 &
b11110101 '
b110011111 (
12
b10101010 3
b11110101 4
b110011111 5
1?
b10101010 @
b11110101 A
b110011111 B
#805000
0#
00
0=
#810000
1#
b111000011 )
10
b111000011 6
1=
b111000011 C
#811000
0%
1+
b11101111 ,
b10101000 -
b110010111 .
02
18
b11101111 9
b10101000 :
b110010111 ;
0?
1E
b11101111 F
b10101000 G
b110010111 H
#815000
0#
00
0=
#820000
1#
b010110100 /
10
b010110100 <
1=
b010110100 I
#821000
0+
08
0E
#822000
1%
b01010000 &
b10001000 '
b011011000 (
12
b01010000 3
b10001000 4
b011011000 5
1?
b01010000 @
b10001000 A
b011011000 B
#825000
0#
00
0=
#830000
1#
b001001011 )
10
b001001011 6
1=
b001001011 C
#831000
0%
1+
b00100001 ,
b11101001 -
b100001010 .
02
18
b00100001 9
b11101001 :
b100001010 ;
0?
1E
b00100001 F
b11101001 G
b100001010 H
#835000
0#
00
0=
#840000
1#
b110011101 /
10
b110011101 <
1=
b110011101 I
#841000
0+
08
0E
#842000
1%
b00001001 &
b10101101 '
b010110110 (
12
b00001001 3
b10101101 4
b010110110 5
1?
b00001001 @
b10101101 A
b010110110 B
#845000
0#
00
0=
#850000
1#
b011111000 )
10
b011111000 6
1=
b011111000 C
#851000
0%
1+
b01001110 ,
b00011101 -
b001101011 .
02
18
b01001110 9
b00011101 :
b001101011 ;
0?
1E
b01001110 F
b00011101 G
b001101011 H
#855000
0#
00
0=
#860000
1#
b110111010 /
10
b110111010 <
1=
b110111010 I
#861000
0+
08
0E
#862000
1%
b01110000 &
b11101011 '
b101011011 (
12
b01110000 3
b11101011 4
b101011011 5
1?
b01110000 @
b11101011 A
b101011011 B
#865000
0#
00
0=
#870000
1#
b111100011 )
10
b111100011 6
1=
b111100011 C
#871000
0%
1+
b10110100 ,
b11010001 -
b110000101 .
02
18
b10110100 9
b11010001 :
b110000101 ;
0?
1E
b10110100 F
b11010001 G
b110000101 H
#875000
0#
00
0=
#880000
1#
b010001011 /
10
b010001011 <
1=
b010001011 I
#881000
0+
08
0E
#882000
1%
b10011111 &
b00011000 '
b010110111 (
12
b10011111 3
b00011000 4
b010110111 5
1?
b10011111 @
b00011000 A
b010110111 B
#885000
0#
00
0=
#890000
1#
b111111011 )
10
b111111011 6
1=
b111111011 C
#891000
0%
1+
b00110000 ,
b01010110 -
b010000110 .
02
18
b00110000 9
b01010110 :
b010000110 ;
0?
1E
b00110000 F
b01010110 G
b010000110 H
#895000
0#
00
0=
#900000
1#
b011100001 /
10
b011100001 <
1=
b011100001 I
#901000
0+
08
0E
#902000
1%
b00011110 &
b01011101 '
b001111011 (
12
b00011110 3
b01011101 4
b001111011 5
1?
b00011110 @
b01011101 A
b001111011 B
#905000
0#
00
0=
#910000
1#
b001011000 )
10
b001011000 6
1=
b001011000 C
#911000
0%
1+
b11000111 ,
b00001001 -
b011010000 .
02
18
b11000111 9
b00001001 :
b011010000 ;
0?
1E
b11000111 F
b00001001 G
b011010000 H
#915000
0#
00
0=
#920000
1#
b011101010 /
10
b011101010 <
1=
b011101010 I
